Workbook
Name Category_New: 'Time Plan (Lacy))'!$F$5
Name Category_New: 'Time Plan (Multiple Release)'!$F$5
Name Category_New: 'Time Plan (Partial Phani)'!$F$5
Name Category_New: 'Time Plan HY'!$F$5
Name Category_New: 'Time Plan (Single Release)'!$F$5
Name ClientList: INDEX(Table2[Client Name],0)
Name ClientList: INDEX(Table2[Client Name],0)
Name ClientList: INDEX(Table2[Client Name],0)
Name ClientList: INDEX(Table2[Client Name],0)
Name ClientList: INDEX(Table2[Client Name],0)
Name Forecast_New: 'Time Plan (Lacy))'!$C$1
Name Forecast_New: 'Time Plan (Multiple Release)'!$C$1
Name Forecast_New: 'Time Plan (Partial Phani)'!$C$1
Name Forecast_New: 'Time Plan HY'!$C$1
Name Forecast_New: 'Time Plan (Single Release)'!$C$1
Name forecastdate: #REF!
Name forecastdate_OLD: #REF!
Name Panel: #REF!
Name Panel_New: 'Time Plan (Lacy))'!$F$4
Name Panel_New: 'Time Plan (Multiple Release)'!$F$4
Name Panel_New: 'Time Plan (Partial Phani)'!$F$4
Name Panel_New: 'Time Plan HY'!$F$4
Name Panel_New: 'Time Plan (Single Release)'!$F$4
Name Panel_OLD: #REF!
Name PeopleList: INDEX(CMEMList[Names],0)
Name PeopleList: INDEX(CMEMList[Names],0)
Name PeopleList: INDEX(CMEMList[Names],0)
Name PeopleList: INDEX(CMEMList[Names],0)
Name PeopleList: INDEX(CMEMList[Names],0)
Name ResAugProject: #REF!
Name ResourceNames: CostTableLookup[Name]
Name ResourceNames: CostTableLookup[Name]
Name ResourceNames: CostTableLookup[Name]
Name ResourceNames: CostTableLookup[Name]
Name ResourceNames: CostTableLookup[Name]
Name test: "OFFSET(Plan!T4,0,MATCH(HLOOKUP(TODAY(),Plan!T1:BS1,1,TRUE),Plan!T1:BS1),1,COLUMNS(Plan!T4:BS4)-MATCH(HLOOKUP(TODAY(),Plan!T4:BS4,1,TRUE),Plan!T4:BS4))"

Sheet Coversheet
B1: REASON GROUP ENGAGEMENT JOB PLAN (template updated 25 AUG 2025) | E1: Summary of Requirement
B2: CLIENT INFORMATION | E2: The Attorney-General's Department (the department) is seeking a 12-month contract to supply, software licensing and professional services required to build a Case Management System (CMS). AGD requires a quote for both professional services to build and the software licenses required to deliver the solution (noting: unit pricing is preferred for licenses). The resulting contract will include the ability to purchase additional software licensing and additional professional services relevant to the solution as required. Date expected to place order: Monday, 03 November 2025. Expected contract duration: 12 months. Extension term: 12 months, Number of extensions: 2
B3: Client name | C3: AGD - Attorney-General's Department
B4: Client sponsor (buyer)
B5: Client sponsor email
B6: Client contact phone/mobile number
B7: End client (if different to above)
B8: Work location | C8: Canberra
B9: ENGAGEMENT INFORMATION | E9: Delivery Assumptions
B10: Engagement Code | E10: Hadas: I had a chat with Andy, the most important for this customer is to support their maturity, OCM, how to run a project and get it right etc. We will go with PSDS Pro Plus (Now Assist) on their existing instance. We will get the Servicenow response early next week. We also need to mention how we will work with the managed service provider (he doesn't know who it is yet). He also hasn't heard from Novabridge or Xmplify so maybe they aren't in.
B11: Engagement name | C11: Case Management System (CMS) Licences, Build and Development – Commonwealth Parole Board
B12: Account Manager (pre-populated from Time Plan) | C12: ='Time Plan (Single Release)'!D4 -> Aleksandar Vranesevic
B13: Engagement Manager (pre-populated from Time Plan) | C13: ='Time Plan (Single Release)'!D5 -> Hadas Yehezkel
B14: Timesheets requirement | C14: Signed I-Time
B15: Start date (pre-populated from Time Plan) | C15: ='Time Plan (Single Release)'!C2 -> 46062
B16: End date | C16: 46328
B17: FINANCIAL & ACCOUNT INFORMATION | E17: Pricing Assumptions
B18: PO/WO Number | E18: ServiceNow pricing
B19: PO/WO Amount (ex GST)
B20: Project Budget Amount (ex GST) in iTimes
B21: Variance (Project Budget to PO ex GST) | C21: =C20-C19 -> 0
B22: Variance (Project budget to total task budget ex GST) | C22: =Coversheet!C20-'Time Plan (Single Release)'!M5 -> 0
B23: Accounts Contact
B24: Accounts Email Address
B25: Invoice method
B26: Invoice Instructions (T&M/monthly; Milestones, approvals)
B27: SYSTEM SETUP REQUIREMENT | E27: Identified Risks
B28: MS Teams DEL channel & Planner required | C28: Yes
B29: -> If using existing (insert engagement code)
B31: Legend: | C31: TBC by CAS
C32: TBC by CSD
C33: TBC by OPS

Sheet Pricing
U1: Category | V1: =Category_New -> Market Rates - Solutions implementation services
B2: By Milestone/Workstream | L2: By Deliverable | U2: By Person
B3: Milestone | C3: Start Date | D3: End Date | E3: Week Number | F3: $ ex GST | G3: $ GST | H3: $ inc GST | I3: Discount | J3: Margin | L3: Deliverable | M3: Start Date | N3: End Date | O3: $ ex GST | P3: GST | Q3: $ inc GST | R3: Discount | S3: Margin | U3: Resource | V3: Position | W3: Offered Hourly Rate ($ ex-GST) | X3: Offered Hourly Rate ($ inc-GST) | Y3: Start Date | Z3: End Date | AA3: Chargeable $ ex GST | AB3: Chargeable $ inc GST | AC3: Discount % | AD3: Margin % | AE3: Forecasted Hours | AF3: Forecasted Days | AG3: Re-apportioned Hours (distribute contingency) | AH3: Re-apportioned Days (distribute contingency) | AI3: % Re-allocation of contingency | AJ3: Re-allocated $ ex GST
B4: {=IFERROR(_xlfn._xlws.SORT(_xlfn.UNIQUE(_xlfn._xlws.FILTER('Time Plan (Single Release)'!B6:B64, 'Time Plan (Single Release)'!B6:B64 <> ""))),"")} -> M1 - Discovery Completion | C4: {=IFERROR(INDEX('Time Plan (Single Release)'!$Y$3:$JN$3, 1, _xlfn.XMATCH(TRUE, _xlfn.BYCOL(('Time Plan (Single Release)'!$Y$6:$JN$64)*('Time Plan (Single Release)'!$B$6:$B$64=$B4), _xlfn.LAMBDA(_xlpm.col, SUM(_xlpm.col)>0)), 0, 1)),"")} -> 46062 | D4: {=IFERROR(INDEX('Time Plan (Single Release)'!$Y$3:$JN$3, 1, _xlfn.XMATCH(TRUE, _xlfn.BYCOL(('Time Plan (Single Release)'!$Y$6:$JN$64)*('Time Plan (Single Release)'!$B$6:$B$64=$B4), _xlfn.LAMBDA(_xlpm.col, SUM(_xlpm.col)>0)), 0,-1))+4,"")} -> 46087 | E4: =IFERROR(DATEDIF('Time Plan (Single Release)'!$Y$3,$D4+3,"d")/7,"") -> 4 | F4: {=SUM(IFERROR(('Time Plan (Single Release)'!$U$6:$U$64*('Time Plan (Single Release)'!$B$6:$B$64=Pricing!$B4)),0))} -> 28773.2 | G4: =$F4*0.1 -> 2877.32 | H4: =$F4*1.1 -> 31650.52 | I4: {=IFERROR( (SUM('Time Plan (Single Release)'!$Y$6:$JN$64*(IFERROR('Time Plan (Single Release)'!$G$6:$G$64*40,0))*('Time Plan (Single Release)'!$B$6:$B$64=Pricing!$B4)) - SUM('Time Plan (Single Release)'!$Y$6:$JN$64*(IFERROR('Time Plan (Single Release)'!$I$6:$I$64*40,0))*('Time Plan (Single Release)'!$B$6:$B$64=Pricing!$B4))) / SUM('Time Plan (Single Release)'!$Y$6:$JN$64*(IFERROR('Time Plan (Single Release)'!$G$6:$G$64*40,0))*('Time Plan (Single Release)'!$B$6:$B$64=Pricing!$B4)),"")} -> 0.41381916 | J4: {=IFERROR( (SUM('Time Plan (Single Release)'!$Y$6:$JN$64*(IFERROR('Time Plan (Single Release)'!$I$6:$I$64*40,0))*('Time Plan (Single Release)'!$B$6:$B$64=Pricing!$B4)) - SUM('Time Plan (Single Release)'!$Y$6:$JN$64*(IFERROR('Time Plan (Single Release)'!$K$6:$K$64*40,0))*('Time Plan (Single Release)'!$B$6:$B$64=Pricing!$B4))) / SUM('Time Plan (Single Release)'!$Y$6:$JN$64*(IFERROR('Time Plan (Single Release)'!$I$6:$I$64*40,0))*('Time Plan (Single Release)'!$B$6:$B$64=Pricing!$B4)),"")} -> -0.0067441646 | L4: {=IFERROR(_xlfn._xlws.SORT(_xlfn.UNIQUE(_xlfn._xlws.FILTER('Time Plan (Single Release)'!C6:C64, 'Time Plan (Single Release)'!C6:C64 <> ""))),"")} -> 1.1 Detailed requirements, business process mapping | M4: {=IFERROR(INDEX('Time Plan (Single Release)'!$Y$3:$JN$3, 1, _xlfn.XMATCH(TRUE, _xlfn.BYCOL(('Time Plan (Single Release)'!$Y$6:$JN$64)*('Time Plan (Single Release)'!$C$6:$C$64=$L4), _xlfn.LAMBDA(_xlpm.col, SUM(_xlpm.col)>0)), 0, 1)),"")} -> 46062 | N4: {=IFERROR(INDEX('Time Plan (Single Release)'!$Y$3:$JN$3, 1, _xlfn.XMATCH(TRUE, _xlfn.BYCOL(('Time Plan (Single Release)'!$Y$6:$JN$64)*('Time Plan (Single Release)'!$C$6:$C$64=$L4), _xlfn.LAMBDA(_xlpm.col, SUM(_xlpm.col)>0)), 0,-1))+4,"")} -> 46087 | O4: {=SUM(IFERROR(('Time Plan (Single Release)'!$U$6:$U$64*('Time Plan (Single Release)'!$C$6:$C$64=$L4)),0))} -> 28773.2 | P4: =IFERROR(O4*0.1,"") -> 2877.32 | Q4: =O4*1.1 -> 31650.52 | R4: {=IFERROR( (SUM('Time Plan (Single Release)'!$Y$6:$JN$64*(IFERROR('Time Plan (Single Release)'!$G$6:$G$64*40,0))*('Time Plan (Single Release)'!$C$6:$C$64=$L4)) - SUM('Time Plan (Single Release)'!$Y$6:$JN$64*(IFERROR('Time Plan (Single Release)'!$I$6:$I$64*40,0))*('Time Plan (Single Release)'!$C$6:$C$64=$L4))) / SUM('Time Plan (Single Release)'!$Y$6:$JN$64*(IFERROR('Time Plan (Single Release)'!$G$6:$G$64*40,0))*('Time Plan (Single Release)'!$C$6:$C$64=$L4)),"")} -> 0.41381916 | S4: {=IFERROR( (SUM('Time Plan (Single Release)'!$Y$6:$JN$64*(IFERROR('Time Plan (Single Release)'!$I$6:$I$64*40,0))*('Time Plan (Single Release)'!$C$6:$C$64=$L4)) - SUM('Time Plan (Single Release)'!$Y$6:$JN$64*(IFERROR('Time Plan (Single Release)'!$K$6:$K$64*40,0))*('Time Plan (Single Release)'!$C$6:$C$64=$L4))) / SUM('Time Plan (Single Release)'!$Y$6:$JN$64*(IFERROR('Time Plan (Single Release)'!$I$6:$I$64*40,0))*('Time Plan (Single Release)'!$C$6:$C$64=$L4)),"")} -> -0.0067441646 | U4: {=IFERROR(_xlfn._xlws.SORT(_xlfn.UNIQUE(_xlfn._xlws.FILTER('Time Plan (Single Release)'!D6:D64, 'Time Plan (Single Release)'!D6:D64 <> ""))),"")} -> Anil Kinagi | V4: {=IFERROR(_xlfn.XLOOKUP($U4,'Time Plan (Single Release)'!$D$6:$D$194,'Time Plan (Single Release)'!$E$6:$E$194&" - "&'Time Plan (Single Release)'!$F$6:$F$194),"")} -> Level 4 - Project Manager | W4: =IFERROR(_xlfn.XLOOKUP($U4,'Time Plan (Single Release)'!$D$6:$D$64,'Time Plan (Single Release)'!$I$6:$I$64),"") -> 207.4 | X4: =IFERROR(W4*1.1,"") -> 228.14 | Y4: {=IFERROR(INDEX('Time Plan (Single Release)'!$Y$3:$JN$3, 1, _xlfn.XMATCH(TRUE, _xlfn.BYCOL(('Time Plan (Single Release)'!$Y$6:$JN$64)*('Time Plan (Single Release)'!$D$6:$D$64=$U4), _xlfn.LAMBDA(_xlpm.col, SUM(_xlpm.col)>0)), 0, 1)),"")} -> 46062 | Z4: {=IFERROR(INDEX('Time Plan (Single Release)'!$Y$3:$JN$3, 1, _xlfn.XMATCH(TRUE, _xlfn.BYCOL(('Time Plan (Single Release)'!$Y$6:$JN$64)*('Time Plan (Single Release)'!$D$6:$D$64=$U4), _xlfn.LAMBDA(_xlpm.col, SUM(_xlpm.col)>0)), 0,-1))+4,"")} -> 46220 | AA4: {=SUM(IFERROR(('Time Plan (Single Release)'!$U$6:$U$64*('Time Plan (Single Release)'!$D$6:$D$64=$U4)),0))} -> 146839.2 | AB4: =AA4*1.1 -> 161523.12 | AC4: {=IFERROR( (SUM('Time Plan (Single Release)'!$Y$6:$JN$64*(IFERROR('Time Plan (Single Release)'!$G$6:$G$64*40,0))*('Time Plan (Single Release)'!$D$6:$D$64=$U4)) - SUM('Time Plan (Single Release)'!$Y$6:$JN$64*(IFERROR('Time Plan (Single Release)'!$I$6:$I$64*40,0))*('Time Plan (Single Release)'!$D$6:$D$64=$U4))) / SUM('Time Plan (Single Release)'!$Y$6:$JN$64*(IFERROR('Time Plan (Single Release)'!$G$6:$G$64*40,0))*('Time Plan (Single Release)'!$D$6:$D$64=$U4)),"")} -> 0.32 | AD4: {=IFERROR( (SUM('Time Plan (Single Release)'!$Y$6:$JN$64*(IFERROR('Time Plan (Single Release)'!$I$6:$I$64*40,0))*('Time Plan (Single Release)'!$D$6:$D$64=$U4)) - SUM('Time Plan (Single Release)'!$Y$6:$JN$64*(IFERROR('Time Plan (Single Release)'!$K$6:$K$64*40,0))*('Time Plan (Single Release)'!$D$6:$D$64=$U4))) / SUM('Time Plan (Single Release)'!$Y$6:$JN$64*(IFERROR('Time Plan (Single Release)'!$I$6:$I$64*40,0))*('Time Plan (Single Release)'!$D$6:$D$64=$U4)),"")} -> -0.18129219 | AE4: =SUMIF('Time Plan (Single Release)'!D$6:D$64,Pricing!U4,'Time Plan (Single Release)'!S$6:S$64) -> 708 | AF4: =AE4/8 -> 88.5
B5: M2 - Sprint 1 and 2 completion | C5: {=IFERROR(INDEX('Time Plan (Single Release)'!$Y$3:$JN$3, 1, _xlfn.XMATCH(TRUE, _xlfn.BYCOL(('Time Plan (Single Release)'!$Y$6:$JN$64)*('Time Plan (Single Release)'!$B$6:$B$64=$B5), _xlfn.LAMBDA(_xlpm.col, SUM(_xlpm.col)>0)), 0, 1)),"")} -> 46076 | D5: {=IFERROR(INDEX('Time Plan (Single Release)'!$Y$3:$JN$3, 1, _xlfn.XMATCH(TRUE, _xlfn.BYCOL(('Time Plan (Single Release)'!$Y$6:$JN$64)*('Time Plan (Single Release)'!$B$6:$B$64=$B5), _xlfn.LAMBDA(_xlpm.col, SUM(_xlpm.col)>0)), 0,-1))+4,"")} -> 46108 | E5: =IFERROR(DATEDIF('Time Plan (Single Release)'!$Y$3,$D5+3,"d")/7,"") -> 7 | F5: {=SUM(IFERROR(('Time Plan (Single Release)'!$U$6:$U$64*('Time Plan (Single Release)'!$B$6:$B$64=Pricing!$B5)),0))} -> 166496.4 | G5: =$F5*0.1 -> 16649.64 | H5: =$F5*1.1 -> 183146.04 | I5: {=IFERROR( (SUM('Time Plan (Single Release)'!$Y$6:$JN$64*(IFERROR('Time Plan (Single Release)'!$G$6:$G$64*40,0))*('Time Plan (Single Release)'!$B$6:$B$64=Pricing!$B5)) - SUM('Time Plan (Single Release)'!$Y$6:$JN$64*(IFERROR('Time Plan (Single Release)'!$I$6:$I$64*40,0))*('Time Plan (Single Release)'!$B$6:$B$64=Pricing!$B5))) / SUM('Time Plan (Single Release)'!$Y$6:$JN$64*(IFERROR('Time Plan (Single Release)'!$G$6:$G$64*40,0))*('Time Plan (Single Release)'!$B$6:$B$64=Pricing!$B5)),"")} -> 0.41922343 | J5: {=IFERROR( (SUM('Time Plan (Single Release)'!$Y$6:$JN$64*(IFERROR('Time Plan (Single Release)'!$I$6:$I$64*40,0))*('Time Plan (Single Release)'!$B$6:$B$64=Pricing!$B5)) - SUM('Time Plan (Single Release)'!$Y$6:$JN$64*(IFERROR('Time Plan (Single Release)'!$K$6:$K$64*40,0))*('Time Plan (Single Release)'!$B$6:$B$64=Pricing!$B5))) / SUM('Time Plan (Single Release)'!$Y$6:$JN$64*(IFERROR('Time Plan (Single Release)'!$I$6:$I$64*40,0))*('Time Plan (Single Release)'!$B$6:$B$64=Pricing!$B5)),"")} -> -0.045165699 | L5: 1.3 Detailed delivery plan, RACI of build/delivery meeting AGD Operating Model requirements | M5: {=IFERROR(INDEX('Time Plan (Single Release)'!$Y$3:$JN$3, 1, _xlfn.XMATCH(TRUE, _xlfn.BYCOL(('Time Plan (Single Release)'!$Y$6:$JN$64)*('Time Plan (Single Release)'!$C$6:$C$64=$L5), _xlfn.LAMBDA(_xlpm.col, SUM(_xlpm.col)>0)), 0, 1)),"")} | N5: {=IFERROR(INDEX('Time Plan (Single Release)'!$Y$3:$JN$3, 1, _xlfn.XMATCH(TRUE, _xlfn.BYCOL(('Time Plan (Single Release)'!$Y$6:$JN$64)*('Time Plan (Single Release)'!$C$6:$C$64=$L5), _xlfn.LAMBDA(_xlpm.col, SUM(_xlpm.col)>0)), 0,-1))+4,"")} | O5: {=SUM(IFERROR(('Time Plan (Single Release)'!$U$6:$U$64*('Time Plan (Single Release)'!$C$6:$C$64=$L5)),0))} -> 0 | P5: =IFERROR(O5*0.1,"") -> 0 | Q5: =O5*1.1 -> 0 | R5: {=IFERROR( (SUM('Time Plan (Single Release)'!$Y$6:$JN$64*(IFERROR('Time Plan (Single Release)'!$G$6:$G$64*40,0))*('Time Plan (Single Release)'!$C$6:$C$64=$L5)) - SUM('Time Plan (Single Release)'!$Y$6:$JN$64*(IFERROR('Time Plan (Single Release)'!$I$6:$I$64*40,0))*('Time Plan (Single Release)'!$C$6:$C$64=$L5))) / SUM('Time Plan (Single Release)'!$Y$6:$JN$64*(IFERROR('Time Plan (Single Release)'!$G$6:$G$64*40,0))*('Time Plan (Single Release)'!$C$6:$C$64=$L5)),"")} | S5: {=IFERROR( (SUM('Time Plan (Single Release)'!$Y$6:$JN$64*(IFERROR('Time Plan (Single Release)'!$I$6:$I$64*40,0))*('Time Plan (Single Release)'!$C$6:$C$64=$L5)) - SUM('Time Plan (Single Release)'!$Y$6:$JN$64*(IFERROR('Time Plan (Single Release)'!$K$6:$K$64*40,0))*('Time Plan (Single Release)'!$C$6:$C$64=$L5))) / SUM('Time Plan (Single Release)'!$Y$6:$JN$64*(IFERROR('Time Plan (Single Release)'!$I$6:$I$64*40,0))*('Time Plan (Single Release)'!$C$6:$C$64=$L5)),"")} | U5: Bradley Burge | V5: {=IFERROR(_xlfn.XLOOKUP($U5,'Time Plan (Single Release)'!$D$6:$D$194,'Time Plan (Single Release)'!$E$6:$E$194&" - "&'Time Plan (Single Release)'!$F$6:$F$194),"")} -> Level 4 - Lead ServiceNow Developer | W5: =IFERROR(_xlfn.XLOOKUP($U5,'Time Plan (Single Release)'!$D$6:$D$64,'Time Plan (Single Release)'!$I$6:$I$64),"") -> 207.4 | X5: =IFERROR(W5*1.1,"") -> 228.14 | Y5: {=IFERROR(INDEX('Time Plan (Single Release)'!$Y$3:$JN$3, 1, _xlfn.XMATCH(TRUE, _xlfn.BYCOL(('Time Plan (Single Release)'!$Y$6:$JN$64)*('Time Plan (Single Release)'!$D$6:$D$64=$U5), _xlfn.LAMBDA(_xlpm.col, SUM(_xlpm.col)>0)), 0, 1)),"")} -> 46076 | Z5: {=IFERROR(INDEX('Time Plan (Single Release)'!$Y$3:$JN$3, 1, _xlfn.XMATCH(TRUE, _xlfn.BYCOL(('Time Plan (Single Release)'!$Y$6:$JN$64)*('Time Plan (Single Release)'!$D$6:$D$64=$U5), _xlfn.LAMBDA(_xlpm.col, SUM(_xlpm.col)>0)), 0,-1))+4,"")} -> 46220 | AA5: {=SUM(IFERROR(('Time Plan (Single Release)'!$U$6:$U$64*('Time Plan (Single Release)'!$D$6:$D$64=$U5)),0))} -> 155428 | AB5: =AA5*1.1 -> 170970.8 | AC5: {=IFERROR( (SUM('Time Plan (Single Release)'!$Y$6:$JN$64*(IFERROR('Time Plan (Single Release)'!$G$6:$G$64*40,0))*('Time Plan (Single Release)'!$D$6:$D$64=$U5)) - SUM('Time Plan (Single Release)'!$Y$6:$JN$64*(IFERROR('Time Plan (Single Release)'!$I$6:$I$64*40,0))*('Time Plan (Single Release)'!$D$6:$D$64=$U5))) / SUM('Time Plan (Single Release)'!$Y$6:$JN$64*(IFERROR('Time Plan (Single Release)'!$G$6:$G$64*40,0))*('Time Plan (Single Release)'!$D$6:$D$64=$U5)),"")} -> 0.37714286 | AD5: {=IFERROR( (SUM('Time Plan (Single Release)'!$Y$6:$JN$64*(IFERROR('Time Plan (Single Release)'!$I$6:$I$64*40,0))*('Time Plan (Single Release)'!$D$6:$D$64=$U5)) - SUM('Time Plan (Single Release)'!$Y$6:$JN$64*(IFERROR('Time Plan (Single Release)'!$K$6:$K$64*40,0))*('Time Plan (Single Release)'!$D$6:$D$64=$U5))) / SUM('Time Plan (Single Release)'!$Y$6:$JN$64*(IFERROR('Time Plan (Single Release)'!$I$6:$I$64*40,0))*('Time Plan (Single Release)'!$D$6:$D$64=$U5)),"")} -> 0.20514363 | AE5: =SUMIF('Time Plan (Single Release)'!D$6:D$64,Pricing!U5,'Time Plan (Single Release)'!S$6:S$64) -> 820 | AF5: =AE5/8 -> 102.5 | AG5: =IFERROR(AE5+(AA$4*AI5/W5),"") -> 820 | AH5: =IFERROR(AG5/8,"") -> 102.5 | AI5: 0 | AJ5: =AG5*W5 -> 170068
B6: M3 - Sprint 3 and 4 completion | C6: {=IFERROR(INDEX('Time Plan (Single Release)'!$Y$3:$JN$3, 1, _xlfn.XMATCH(TRUE, _xlfn.BYCOL(('Time Plan (Single Release)'!$Y$6:$JN$64)*('Time Plan (Single Release)'!$B$6:$B$64=$B6), _xlfn.LAMBDA(_xlpm.col, SUM(_xlpm.col)>0)), 0, 1)),"")} -> 46111 | D6: {=IFERROR(INDEX('Time Plan (Single Release)'!$Y$3:$JN$3, 1, _xlfn.XMATCH(TRUE, _xlfn.BYCOL(('Time Plan (Single Release)'!$Y$6:$JN$64)*('Time Plan (Single Release)'!$B$6:$B$64=$B6), _xlfn.LAMBDA(_xlpm.col, SUM(_xlpm.col)>0)), 0,-1))+4,"")} -> 46136 | E6: =IFERROR(DATEDIF('Time Plan (Single Release)'!$Y$3,$D6+3,"d")/7,"") -> 11 | F6: {=SUM(IFERROR(('Time Plan (Single Release)'!$U$6:$U$64*('Time Plan (Single Release)'!$B$6:$B$64=Pricing!$B6)),0))} -> 202558.44 | G6: =$F6*0.1 -> 20255.844 | H6: =$F6*1.1 -> 222814.28 | I6: {=IFERROR( (SUM('Time Plan (Single Release)'!$Y$6:$JN$64*(IFERROR('Time Plan (Single Release)'!$G$6:$G$64*40,0))*('Time Plan (Single Release)'!$B$6:$B$64=Pricing!$B6)) - SUM('Time Plan (Single Release)'!$Y$6:$JN$64*(IFERROR('Time Plan (Single Release)'!$I$6:$I$64*40,0))*('Time Plan (Single Release)'!$B$6:$B$64=Pricing!$B6))) / SUM('Time Plan (Single Release)'!$Y$6:$JN$64*(IFERROR('Time Plan (Single Release)'!$G$6:$G$64*40,0))*('Time Plan (Single Release)'!$B$6:$B$64=Pricing!$B6)),"")} -> 0.37904629 | J6: {=IFERROR( (SUM('Time Plan (Single Release)'!$Y$6:$JN$64*(IFERROR('Time Plan (Single Release)'!$I$6:$I$64*40,0))*('Time Plan (Single Release)'!$B$6:$B$64=Pricing!$B6)) - SUM('Time Plan (Single Release)'!$Y$6:$JN$64*(IFERROR('Time Plan (Single Release)'!$K$6:$K$64*40,0))*('Time Plan (Single Release)'!$B$6:$B$64=Pricing!$B6))) / SUM('Time Plan (Single Release)'!$Y$6:$JN$64*(IFERROR('Time Plan (Single Release)'!$I$6:$I$64*40,0))*('Time Plan (Single Release)'!$B$6:$B$64=Pricing!$B6)),"")} -> 0.034038097 | L6: 1.4 Acceptance certificate | M6: {=IFERROR(INDEX('Time Plan (Single Release)'!$Y$3:$JN$3, 1, _xlfn.XMATCH(TRUE, _xlfn.BYCOL(('Time Plan (Single Release)'!$Y$6:$JN$64)*('Time Plan (Single Release)'!$C$6:$C$64=$L6), _xlfn.LAMBDA(_xlpm.col, SUM(_xlpm.col)>0)), 0, 1)),"")} | N6: {=IFERROR(INDEX('Time Plan (Single Release)'!$Y$3:$JN$3, 1, _xlfn.XMATCH(TRUE, _xlfn.BYCOL(('Time Plan (Single Release)'!$Y$6:$JN$64)*('Time Plan (Single Release)'!$C$6:$C$64=$L6), _xlfn.LAMBDA(_xlpm.col, SUM(_xlpm.col)>0)), 0,-1))+4,"")} | O6: {=SUM(IFERROR(('Time Plan (Single Release)'!$U$6:$U$64*('Time Plan (Single Release)'!$C$6:$C$64=$L6)),0))} -> 0 | P6: =IFERROR(O6*0.1,"") -> 0 | Q6: =O6*1.1 -> 0 | R6: {=IFERROR( (SUM('Time Plan (Single Release)'!$Y$6:$JN$64*(IFERROR('Time Plan (Single Release)'!$G$6:$G$64*40,0))*('Time Plan (Single Release)'!$C$6:$C$64=$L6)) - SUM('Time Plan (Single Release)'!$Y$6:$JN$64*(IFERROR('Time Plan (Single Release)'!$I$6:$I$64*40,0))*('Time Plan (Single Release)'!$C$6:$C$64=$L6))) / SUM('Time Plan (Single Release)'!$Y$6:$JN$64*(IFERROR('Time Plan (Single Release)'!$G$6:$G$64*40,0))*('Time Plan (Single Release)'!$C$6:$C$64=$L6)),"")} | S6: {=IFERROR( (SUM('Time Plan (Single Release)'!$Y$6:$JN$64*(IFERROR('Time Plan (Single Release)'!$I$6:$I$64*40,0))*('Time Plan (Single Release)'!$C$6:$C$64=$L6)) - SUM('Time Plan (Single Release)'!$Y$6:$JN$64*(IFERROR('Time Plan (Single Release)'!$K$6:$K$64*40,0))*('Time Plan (Single Release)'!$C$6:$C$64=$L6))) / SUM('Time Plan (Single Release)'!$Y$6:$JN$64*(IFERROR('Time Plan (Single Release)'!$I$6:$I$64*40,0))*('Time Plan (Single Release)'!$C$6:$C$64=$L6)),"")} | U6: Contingency | V6: {=IFERROR(_xlfn.XLOOKUP($U6,'Time Plan (Single Release)'!$D$6:$D$194,'Time Plan (Single Release)'!$E$6:$E$194&" - "&'Time Plan (Single Release)'!$F$6:$F$194),"")} -> - | W6: =IFERROR(_xlfn.XLOOKUP($U6,'Time Plan (Single Release)'!$D$6:$D$64,'Time Plan (Single Release)'!$I$6:$I$64),"") -> 1438.66 | X6: =IFERROR(W6*1.1,"") -> 1582.526 | Y6: {=IFERROR(INDEX('Time Plan (Single Release)'!$Y$3:$JN$3, 1, _xlfn.XMATCH(TRUE, _xlfn.BYCOL(('Time Plan (Single Release)'!$Y$6:$JN$64)*('Time Plan (Single Release)'!$D$6:$D$64=$U6), _xlfn.LAMBDA(_xlpm.col, SUM(_xlpm.col)>0)), 0, 1)),"")} -> 46069 | Z6: {=IFERROR(INDEX('Time Plan (Single Release)'!$Y$3:$JN$3, 1, _xlfn.XMATCH(TRUE, _xlfn.BYCOL(('Time Plan (Single Release)'!$Y$6:$JN$64)*('Time Plan (Single Release)'!$D$6:$D$64=$U6), _xlfn.LAMBDA(_xlpm.col, SUM(_xlpm.col)>0)), 0,-1))+4,"")} -> 46136 | AA6: {=SUM(IFERROR(('Time Plan (Single Release)'!$U$6:$U$64*('Time Plan (Single Release)'!$D$6:$D$64=$U6)),0))} -> 17574.04 | AB6: =AA6*1.1 -> 19331.444 | AC6: {=IFERROR( (SUM('Time Plan (Single Release)'!$Y$6:$JN$64*(IFERROR('Time Plan (Single Release)'!$G$6:$G$64*40,0))*('Time Plan (Single Release)'!$D$6:$D$64=$U6)) - SUM('Time Plan (Single Release)'!$Y$6:$JN$64*(IFERROR('Time Plan (Single Release)'!$I$6:$I$64*40,0))*('Time Plan (Single Release)'!$D$6:$D$64=$U6))) / SUM('Time Plan (Single Release)'!$Y$6:$JN$64*(IFERROR('Time Plan (Single Release)'!$G$6:$G$64*40,0))*('Time Plan (Single Release)'!$D$6:$D$64=$U6)),"")} | AD6: {=IFERROR( (SUM('Time Plan (Single Release)'!$Y$6:$JN$64*(IFERROR('Time Plan (Single Release)'!$I$6:$I$64*40,0))*('Time Plan (Single Release)'!$D$6:$D$64=$U6)) - SUM('Time Plan (Single Release)'!$Y$6:$JN$64*(IFERROR('Time Plan (Single Release)'!$K$6:$K$64*40,0))*('Time Plan (Single Release)'!$D$6:$D$64=$U6))) / SUM('Time Plan (Single Release)'!$Y$6:$JN$64*(IFERROR('Time Plan (Single Release)'!$I$6:$I$64*40,0))*('Time Plan (Single Release)'!$D$6:$D$64=$U6)),"")} -> 1 | AE6: =SUMIF('Time Plan (Single Release)'!D$6:D$64,Pricing!U6,'Time Plan (Single Release)'!S$6:S$64) -> 3 | AF6: =AE6/8 -> 0.375 | AG6: =IFERROR(AE6+(AA$4*AI6/W6),"") -> 3 | AH6: =IFERROR(AG6/8,"") -> 0.375 | AI6: 0 | AJ6: =AG6*W6 -> 4315.98
B7: M4 - Sprint 5 and 6 completion | C7: {=IFERROR(INDEX('Time Plan (Single Release)'!$Y$3:$JN$3, 1, _xlfn.XMATCH(TRUE, _xlfn.BYCOL(('Time Plan (Single Release)'!$Y$6:$JN$64)*('Time Plan (Single Release)'!$B$6:$B$64=$B7), _xlfn.LAMBDA(_xlpm.col, SUM(_xlpm.col)>0)), 0, 1)),"")} -> 46139 | D7: {=IFERROR(INDEX('Time Plan (Single Release)'!$Y$3:$JN$3, 1, _xlfn.XMATCH(TRUE, _xlfn.BYCOL(('Time Plan (Single Release)'!$Y$6:$JN$64)*('Time Plan (Single Release)'!$B$6:$B$64=$B7), _xlfn.LAMBDA(_xlpm.col, SUM(_xlpm.col)>0)), 0,-1))+4,"")} -> 46164 | E7: =IFERROR(DATEDIF('Time Plan (Single Release)'!$Y$3,$D7+3,"d")/7,"") -> 15 | F7: {=SUM(IFERROR(('Time Plan (Single Release)'!$U$6:$U$64*('Time Plan (Single Release)'!$B$6:$B$64=Pricing!$B7)),0))} -> 212800 | G7: =$F7*0.1 -> 21280 | H7: =$F7*1.1 -> 234080 | I7: {=IFERROR( (SUM('Time Plan (Single Release)'!$Y$6:$JN$64*(IFERROR('Time Plan (Single Release)'!$G$6:$G$64*40,0))*('Time Plan (Single Release)'!$B$6:$B$64=Pricing!$B7)) - SUM('Time Plan (Single Release)'!$Y$6:$JN$64*(IFERROR('Time Plan (Single Release)'!$I$6:$I$64*40,0))*('Time Plan (Single Release)'!$B$6:$B$64=Pricing!$B7))) / SUM('Time Plan (Single Release)'!$Y$6:$JN$64*(IFERROR('Time Plan (Single Release)'!$G$6:$G$64*40,0))*('Time Plan (Single Release)'!$B$6:$B$64=Pricing!$B7)),"")} -> 0.43101604 | J7: {=IFERROR( (SUM('Time Plan (Single Release)'!$Y$6:$JN$64*(IFERROR('Time Plan (Single Release)'!$I$6:$I$64*40,0))*('Time Plan (Single Release)'!$B$6:$B$64=Pricing!$B7)) - SUM('Time Plan (Single Release)'!$Y$6:$JN$64*(IFERROR('Time Plan (Single Release)'!$K$6:$K$64*40,0))*('Time Plan (Single Release)'!$B$6:$B$64=Pricing!$B7))) / SUM('Time Plan (Single Release)'!$Y$6:$JN$64*(IFERROR('Time Plan (Single Release)'!$I$6:$I$64*40,0))*('Time Plan (Single Release)'!$B$6:$B$64=Pricing!$B7)),"")} -> -0.06162406 | L7: 2.1 Project management and compliance documentation | M7: {=IFERROR(INDEX('Time Plan (Single Release)'!$Y$3:$JN$3, 1, _xlfn.XMATCH(TRUE, _xlfn.BYCOL(('Time Plan (Single Release)'!$Y$6:$JN$64)*('Time Plan (Single Release)'!$C$6:$C$64=$L7), _xlfn.LAMBDA(_xlpm.col, SUM(_xlpm.col)>0)), 0, 1)),"")} -> 46083 | N7: {=IFERROR(INDEX('Time Plan (Single Release)'!$Y$3:$JN$3, 1, _xlfn.XMATCH(TRUE, _xlfn.BYCOL(('Time Plan (Single Release)'!$Y$6:$JN$64)*('Time Plan (Single Release)'!$C$6:$C$64=$L7), _xlfn.LAMBDA(_xlpm.col, SUM(_xlpm.col)>0)), 0,-1))+4,"")} -> 46220 | O7: {=SUM(IFERROR(('Time Plan (Single Release)'!$U$6:$U$64*('Time Plan (Single Release)'!$C$6:$C$64=$L7)),0))} -> 227755.2 | P7: =IFERROR(O7*0.1,"") -> 22775.52 | Q7: =O7*1.1 -> 250530.72 | R7: {=IFERROR( (SUM('Time Plan (Single Release)'!$Y$6:$JN$64*(IFERROR('Time Plan (Single Release)'!$G$6:$G$64*40,0))*('Time Plan (Single Release)'!$C$6:$C$64=$L7)) - SUM('Time Plan (Single Release)'!$Y$6:$JN$64*(IFERROR('Time Plan (Single Release)'!$I$6:$I$64*40,0))*('Time Plan (Single Release)'!$C$6:$C$64=$L7))) / SUM('Time Plan (Single Release)'!$Y$6:$JN$64*(IFERROR('Time Plan (Single Release)'!$G$6:$G$64*40,0))*('Time Plan (Single Release)'!$C$6:$C$64=$L7)),"")} -> 0.34372061 | S7: {=IFERROR( (SUM('Time Plan (Single Release)'!$Y$6:$JN$64*(IFERROR('Time Plan (Single Release)'!$I$6:$I$64*40,0))*('Time Plan (Single Release)'!$C$6:$C$64=$L7)) - SUM('Time Plan (Single Release)'!$Y$6:$JN$64*(IFERROR('Time Plan (Single Release)'!$K$6:$K$64*40,0))*('Time Plan (Single Release)'!$C$6:$C$64=$L7))) / SUM('Time Plan (Single Release)'!$Y$6:$JN$64*(IFERROR('Time Plan (Single Release)'!$I$6:$I$64*40,0))*('Time Plan (Single Release)'!$C$6:$C$64=$L7)),"")} -> 0.0091115373 | U7: Contractor-Tester-Manager | V7: {=IFERROR(_xlfn.XLOOKUP($U7,'Time Plan (Single Release)'!$D$6:$D$194,'Time Plan (Single Release)'!$E$6:$E$194&" - "&'Time Plan (Single Release)'!$F$6:$F$194),"")} -> Level 3 - Senior Tester | W7: =IFERROR(_xlfn.XLOOKUP($U7,'Time Plan (Single Release)'!$D$6:$D$64,'Time Plan (Single Release)'!$I$6:$I$64),"") -> 151.9 | X7: =IFERROR(W7*1.1,"") -> 167.09 | Y7: {=IFERROR(INDEX('Time Plan (Single Release)'!$Y$3:$JN$3, 1, _xlfn.XMATCH(TRUE, _xlfn.BYCOL(('Time Plan (Single Release)'!$Y$6:$JN$64)*('Time Plan (Single Release)'!$D$6:$D$64=$U7), _xlfn.LAMBDA(_xlpm.col, SUM(_xlpm.col)>0)), 0, 1)),"")} -> 46125 | Z7: {=IFERROR(INDEX('Time Plan (Single Release)'!$Y$3:$JN$3, 1, _xlfn.XMATCH(TRUE, _xlfn.BYCOL(('Time Plan (Single Release)'!$Y$6:$JN$64)*('Time Plan (Single Release)'!$D$6:$D$64=$U7), _xlfn.LAMBDA(_xlpm.col, SUM(_xlpm.col)>0)), 0,-1))+4,"")} -> 46192 | AA7: {=SUM(IFERROR(('Time Plan (Single Release)'!$U$6:$U$64*('Time Plan (Single Release)'!$D$6:$D$64=$U7)),0))} -> 60760 | AB7: =AA7*1.1 -> 66836 | AC7: {=IFERROR( (SUM('Time Plan (Single Release)'!$Y$6:$JN$64*(IFERROR('Time Plan (Single Release)'!$G$6:$G$64*40,0))*('Time Plan (Single Release)'!$D$6:$D$64=$U7)) - SUM('Time Plan (Single Release)'!$Y$6:$JN$64*(IFERROR('Time Plan (Single Release)'!$I$6:$I$64*40,0))*('Time Plan (Single Release)'!$D$6:$D$64=$U7))) / SUM('Time Plan (Single Release)'!$Y$6:$JN$64*(IFERROR('Time Plan (Single Release)'!$G$6:$G$64*40,0))*('Time Plan (Single Release)'!$D$6:$D$64=$U7)),"")} -> 0.38 | AD7: {=IFERROR( (SUM('Time Plan (Single Release)'!$Y$6:$JN$64*(IFERROR('Time Plan (Single Release)'!$I$6:$I$64*40,0))*('Time Plan (Single Release)'!$D$6:$D$64=$U7)) - SUM('Time Plan (Single Release)'!$Y$6:$JN$64*(IFERROR('Time Plan (Single Release)'!$K$6:$K$64*40,0))*('Time Plan (Single Release)'!$D$6:$D$64=$U7))) / SUM('Time Plan (Single Release)'!$Y$6:$JN$64*(IFERROR('Time Plan (Single Release)'!$I$6:$I$64*40,0))*('Time Plan (Single Release)'!$D$6:$D$64=$U7)),"")} -> -0.059907834 | AE7: =SUMIF('Time Plan (Single Release)'!D$6:D$64,Pricing!U7,'Time Plan (Single Release)'!S$6:S$64) -> 400 | AF7: =AE7/8 -> 50 | AG7: =IFERROR(AE7+(AA$4*AI7/W7),"") -> 883.34167 | AH7: =IFERROR(AG7/8,"") -> 110.41771 | AI7: 0.5 | AJ7: =AG7*W7 -> 134179.6
B8: M5 - Test Completion & Go-live | C8: {=IFERROR(INDEX('Time Plan (Single Release)'!$Y$3:$JN$3, 1, _xlfn.XMATCH(TRUE, _xlfn.BYCOL(('Time Plan (Single Release)'!$Y$6:$JN$64)*('Time Plan (Single Release)'!$B$6:$B$64=$B8), _xlfn.LAMBDA(_xlpm.col, SUM(_xlpm.col)>0)), 0, 1)),"")} -> 46167 | D8: {=IFERROR(INDEX('Time Plan (Single Release)'!$Y$3:$JN$3, 1, _xlfn.XMATCH(TRUE, _xlfn.BYCOL(('Time Plan (Single Release)'!$Y$6:$JN$64)*('Time Plan (Single Release)'!$B$6:$B$64=$B8), _xlfn.LAMBDA(_xlpm.col, SUM(_xlpm.col)>0)), 0,-1))+4,"")} -> 46192 | E8: =IFERROR(DATEDIF('Time Plan (Single Release)'!$Y$3,$D8+3,"d")/7,"") -> 19 | F8: {=SUM(IFERROR(('Time Plan (Single Release)'!$U$6:$U$64*('Time Plan (Single Release)'!$B$6:$B$64=Pricing!$B8)),0))} -> 112048 | G8: =$F8*0.1 -> 11204.8 | H8: =$F8*1.1 -> 123252.8 | I8: {=IFERROR( (SUM('Time Plan (Single Release)'!$Y$6:$JN$64*(IFERROR('Time Plan (Single Release)'!$G$6:$G$64*40,0))*('Time Plan (Single Release)'!$B$6:$B$64=Pricing!$B8)) - SUM('Time Plan (Single Release)'!$Y$6:$JN$64*(IFERROR('Time Plan (Single Release)'!$I$6:$I$64*40,0))*('Time Plan (Single Release)'!$B$6:$B$64=Pricing!$B8))) / SUM('Time Plan (Single Release)'!$Y$6:$JN$64*(IFERROR('Time Plan (Single Release)'!$G$6:$G$64*40,0))*('Time Plan (Single Release)'!$B$6:$B$64=Pricing!$B8)),"")} -> 0.4544888 | J8: {=IFERROR( (SUM('Time Plan (Single Release)'!$Y$6:$JN$64*(IFERROR('Time Plan (Single Release)'!$I$6:$I$64*40,0))*('Time Plan (Single Release)'!$B$6:$B$64=Pricing!$B8)) - SUM('Time Plan (Single Release)'!$Y$6:$JN$64*(IFERROR('Time Plan (Single Release)'!$K$6:$K$64*40,0))*('Time Plan (Single Release)'!$B$6:$B$64=Pricing!$B8))) / SUM('Time Plan (Single Release)'!$Y$6:$JN$64*(IFERROR('Time Plan (Single Release)'!$I$6:$I$64*40,0))*('Time Plan (Single Release)'!$B$6:$B$64=Pricing!$B8)),"")} -> -0.21947737 | L8: 2.2 Build | M8: {=IFERROR(INDEX('Time Plan (Single Release)'!$Y$3:$JN$3, 1, _xlfn.XMATCH(TRUE, _xlfn.BYCOL(('Time Plan (Single Release)'!$Y$6:$JN$64)*('Time Plan (Single Release)'!$C$6:$C$64=$L8), _xlfn.LAMBDA(_xlpm.col, SUM(_xlpm.col)>0)), 0, 1)),"")} -> 46076 | N8: {=IFERROR(INDEX('Time Plan (Single Release)'!$Y$3:$JN$3, 1, _xlfn.XMATCH(TRUE, _xlfn.BYCOL(('Time Plan (Single Release)'!$Y$6:$JN$64)*('Time Plan (Single Release)'!$C$6:$C$64=$L8), _xlfn.LAMBDA(_xlpm.col, SUM(_xlpm.col)>0)), 0,-1))+4,"")} -> 46220 | O8: {=SUM(IFERROR(('Time Plan (Single Release)'!$U$6:$U$64*('Time Plan (Single Release)'!$C$6:$C$64=$L8)),0))} -> 518242.04 | P8: =IFERROR(O8*0.1,"") -> 51824.204 | Q8: =O8*1.1 -> 570066.24 | R8: {=IFERROR( (SUM('Time Plan (Single Release)'!$Y$6:$JN$64*(IFERROR('Time Plan (Single Release)'!$G$6:$G$64*40,0))*('Time Plan (Single Release)'!$C$6:$C$64=$L8)) - SUM('Time Plan (Single Release)'!$Y$6:$JN$64*(IFERROR('Time Plan (Single Release)'!$I$6:$I$64*40,0))*('Time Plan (Single Release)'!$C$6:$C$64=$L8))) / SUM('Time Plan (Single Release)'!$Y$6:$JN$64*(IFERROR('Time Plan (Single Release)'!$G$6:$G$64*40,0))*('Time Plan (Single Release)'!$C$6:$C$64=$L8)),"")} -> 0.44557628 | S8: {=IFERROR( (SUM('Time Plan (Single Release)'!$Y$6:$JN$64*(IFERROR('Time Plan (Single Release)'!$I$6:$I$64*40,0))*('Time Plan (Single Release)'!$C$6:$C$64=$L8)) - SUM('Time Plan (Single Release)'!$Y$6:$JN$64*(IFERROR('Time Plan (Single Release)'!$K$6:$K$64*40,0))*('Time Plan (Single Release)'!$C$6:$C$64=$L8))) / SUM('Time Plan (Single Release)'!$Y$6:$JN$64*(IFERROR('Time Plan (Single Release)'!$I$6:$I$64*40,0))*('Time Plan (Single Release)'!$C$6:$C$64=$L8)),"")} -> -0.084507967 | U8: Hadas Yehezkel | V8: {=IFERROR(_xlfn.XLOOKUP($U8,'Time Plan (Single Release)'!$D$6:$D$194,'Time Plan (Single Release)'!$E$6:$E$194&" - "&'Time Plan (Single Release)'!$F$6:$F$194),"")} -> Level 5 - ServiceNow Architect | W8: =IFERROR(_xlfn.XLOOKUP($U8,'Time Plan (Single Release)'!$D$6:$D$64,'Time Plan (Single Release)'!$I$6:$I$64),"") -> 237 | X8: =IFERROR(W8*1.1,"") -> 260.7 | Y8: {=IFERROR(INDEX('Time Plan (Single Release)'!$Y$3:$JN$3, 1, _xlfn.XMATCH(TRUE, _xlfn.BYCOL(('Time Plan (Single Release)'!$Y$6:$JN$64)*('Time Plan (Single Release)'!$D$6:$D$64=$U8), _xlfn.LAMBDA(_xlpm.col, SUM(_xlpm.col)>0)), 0, 1)),"")} -> 46062 | Z8: {=IFERROR(INDEX('Time Plan (Single Release)'!$Y$3:$JN$3, 1, _xlfn.XMATCH(TRUE, _xlfn.BYCOL(('Time Plan (Single Release)'!$Y$6:$JN$64)*('Time Plan (Single Release)'!$D$6:$D$64=$U8), _xlfn.LAMBDA(_xlpm.col, SUM(_xlpm.col)>0)), 0,-1))+4,"")} -> 46164 | AA8: {=SUM(IFERROR(('Time Plan (Single Release)'!$U$6:$U$64*('Time Plan (Single Release)'!$D$6:$D$64=$U8)),0))} -> 54510 | AB8: =AA8*1.1 -> 59961 | AC8: {=IFERROR( (SUM('Time Plan (Single Release)'!$Y$6:$JN$64*(IFERROR('Time Plan (Single Release)'!$G$6:$G$64*40,0))*('Time Plan (Single Release)'!$D$6:$D$64=$U8)) - SUM('Time Plan (Single Release)'!$Y$6:$JN$64*(IFERROR('Time Plan (Single Release)'!$I$6:$I$64*40,0))*('Time Plan (Single Release)'!$D$6:$D$64=$U8))) / SUM('Time Plan (Single Release)'!$Y$6:$JN$64*(IFERROR('Time Plan (Single Release)'!$G$6:$G$64*40,0))*('Time Plan (Single Release)'!$D$6:$D$64=$U8)),"")} -> 0.4 | AD8: {=IFERROR( (SUM('Time Plan (Single Release)'!$Y$6:$JN$64*(IFERROR('Time Plan (Single Release)'!$I$6:$I$64*40,0))*('Time Plan (Single Release)'!$D$6:$D$64=$U8)) - SUM('Time Plan (Single Release)'!$Y$6:$JN$64*(IFERROR('Time Plan (Single Release)'!$K$6:$K$64*40,0))*('Time Plan (Single Release)'!$D$6:$D$64=$U8))) / SUM('Time Plan (Single Release)'!$Y$6:$JN$64*(IFERROR('Time Plan (Single Release)'!$I$6:$I$64*40,0))*('Time Plan (Single Release)'!$D$6:$D$64=$U8)),"")} -> 0.16455696 | AE8: =SUMIF('Time Plan (Single Release)'!D$6:D$64,Pricing!U8,'Time Plan (Single Release)'!S$6:S$64) -> 230 | AF8: =AE8/8 -> 28.75 | AG8: =IFERROR(AE8+(AA$4*AI8/W8),"") -> 539.78734 | AH8: =IFERROR(AG8/8,"") -> 67.473418 | AI8: 0.5 | AJ8: =AG8*W8 -> 127929.6
B9: M6 - Hypercare completion | C9: {=IFERROR(INDEX('Time Plan (Single Release)'!$Y$3:$JN$3, 1, _xlfn.XMATCH(TRUE, _xlfn.BYCOL(('Time Plan (Single Release)'!$Y$6:$JN$64)*('Time Plan (Single Release)'!$B$6:$B$64=$B9), _xlfn.LAMBDA(_xlpm.col, SUM(_xlpm.col)>0)), 0, 1)),"")} -> 46195 | D9: {=IFERROR(INDEX('Time Plan (Single Release)'!$Y$3:$JN$3, 1, _xlfn.XMATCH(TRUE, _xlfn.BYCOL(('Time Plan (Single Release)'!$Y$6:$JN$64)*('Time Plan (Single Release)'!$B$6:$B$64=$B9), _xlfn.LAMBDA(_xlpm.col, SUM(_xlpm.col)>0)), 0,-1))+4,"")} -> 46220 | E9: =IFERROR(DATEDIF('Time Plan (Single Release)'!$Y$3,$D9+3,"d")/7,"") -> 23 | F9: {=SUM(IFERROR(('Time Plan (Single Release)'!$U$6:$U$64*('Time Plan (Single Release)'!$B$6:$B$64=Pricing!$B9)),0))} -> 52094.4 | G9: =$F9*0.1 -> 5209.44 | H9: =$F9*1.1 -> 57303.84 | I9: {=IFERROR( (SUM('Time Plan (Single Release)'!$Y$6:$JN$64*(IFERROR('Time Plan (Single Release)'!$G$6:$G$64*40,0))*('Time Plan (Single Release)'!$B$6:$B$64=Pricing!$B9)) - SUM('Time Plan (Single Release)'!$Y$6:$JN$64*(IFERROR('Time Plan (Single Release)'!$I$6:$I$64*40,0))*('Time Plan (Single Release)'!$B$6:$B$64=Pricing!$B9))) / SUM('Time Plan (Single Release)'!$Y$6:$JN$64*(IFERROR('Time Plan (Single Release)'!$G$6:$G$64*40,0))*('Time Plan (Single Release)'!$B$6:$B$64=Pricing!$B9)),"")} -> 0.43115964 | J9: {=IFERROR( (SUM('Time Plan (Single Release)'!$Y$6:$JN$64*(IFERROR('Time Plan (Single Release)'!$I$6:$I$64*40,0))*('Time Plan (Single Release)'!$B$6:$B$64=Pricing!$B9)) - SUM('Time Plan (Single Release)'!$Y$6:$JN$64*(IFERROR('Time Plan (Single Release)'!$K$6:$K$64*40,0))*('Time Plan (Single Release)'!$B$6:$B$64=Pricing!$B9))) / SUM('Time Plan (Single Release)'!$Y$6:$JN$64*(IFERROR('Time Plan (Single Release)'!$I$6:$I$64*40,0))*('Time Plan (Single Release)'!$B$6:$B$64=Pricing!$B9)),"")} -> -0.089176572 | M9: {=IFERROR(INDEX('Time Plan (Single Release)'!$Y$3:$JN$3, 1, _xlfn.XMATCH(TRUE, _xlfn.BYCOL(('Time Plan (Single Release)'!$Y$6:$JN$64)*('Time Plan (Single Release)'!$C$6:$C$64=$L9), _xlfn.LAMBDA(_xlpm.col, SUM(_xlpm.col)>0)), 0, 1)),"")} | N9: {=IFERROR(INDEX('Time Plan (Single Release)'!$Y$3:$JN$3, 1, _xlfn.XMATCH(TRUE, _xlfn.BYCOL(('Time Plan (Single Release)'!$Y$6:$JN$64)*('Time Plan (Single Release)'!$C$6:$C$64=$L9), _xlfn.LAMBDA(_xlpm.col, SUM(_xlpm.col)>0)), 0,-1))+4,"")} | O9: {=SUM(IFERROR(('Time Plan (Single Release)'!$U$6:$U$64*('Time Plan (Single Release)'!$C$6:$C$64=$L9)),0))} -> 0 | P9: =IFERROR(O9*0.1,"") -> 0 | Q9: =O9*1.1 -> 0 | R9: {=IFERROR( (SUM('Time Plan (Single Release)'!$Y$6:$JN$64*(IFERROR('Time Plan (Single Release)'!$G$6:$G$64*40,0))*('Time Plan (Single Release)'!$C$6:$C$64=$L9)) - SUM('Time Plan (Single Release)'!$Y$6:$JN$64*(IFERROR('Time Plan (Single Release)'!$I$6:$I$64*40,0))*('Time Plan (Single Release)'!$C$6:$C$64=$L9))) / SUM('Time Plan (Single Release)'!$Y$6:$JN$64*(IFERROR('Time Plan (Single Release)'!$G$6:$G$64*40,0))*('Time Plan (Single Release)'!$C$6:$C$64=$L9)),"")} | S9: {=IFERROR( (SUM('Time Plan (Single Release)'!$Y$6:$JN$64*(IFERROR('Time Plan (Single Release)'!$I$6:$I$64*40,0))*('Time Plan (Single Release)'!$C$6:$C$64=$L9)) - SUM('Time Plan (Single Release)'!$Y$6:$JN$64*(IFERROR('Time Plan (Single Release)'!$K$6:$K$64*40,0))*('Time Plan (Single Release)'!$C$6:$C$64=$L9))) / SUM('Time Plan (Single Release)'!$Y$6:$JN$64*(IFERROR('Time Plan (Single Release)'!$I$6:$I$64*40,0))*('Time Plan (Single Release)'!$C$6:$C$64=$L9)),"")} | U9: Kosta Walker-Laskos | V9: {=IFERROR(_xlfn.XLOOKUP($U9,'Time Plan (Single Release)'!$D$6:$D$194,'Time Plan (Single Release)'!$E$6:$E$194&" - "&'Time Plan (Single Release)'!$F$6:$F$194),"")} -> Level 3 - ServiceNow Developer | W9: =IFERROR(_xlfn.XLOOKUP($U9,'Time Plan (Single Release)'!$D$6:$D$64,'Time Plan (Single Release)'!$I$6:$I$64),"") -> 151.9 | X9: =IFERROR(W9*1.1,"") -> 167.09 | Y9: {=IFERROR(INDEX('Time Plan (Single Release)'!$Y$3:$JN$3, 1, _xlfn.XMATCH(TRUE, _xlfn.BYCOL(('Time Plan (Single Release)'!$Y$6:$JN$64)*('Time Plan (Single Release)'!$D$6:$D$64=$U9), _xlfn.LAMBDA(_xlpm.col, SUM(_xlpm.col)>0)), 0, 1)),"")} -> 46083 | Z9: {=IFERROR(INDEX('Time Plan (Single Release)'!$Y$3:$JN$3, 1, _xlfn.XMATCH(TRUE, _xlfn.BYCOL(('Time Plan (Single Release)'!$Y$6:$JN$64)*('Time Plan (Single Release)'!$D$6:$D$64=$U9), _xlfn.LAMBDA(_xlpm.col, SUM(_xlpm.col)>0)), 0,-1))+4,"")} -> 46206 | AA9: {=SUM(IFERROR(('Time Plan (Single Release)'!$U$6:$U$64*('Time Plan (Single Release)'!$D$6:$D$64=$U9)),0))} -> 91140 | AB9: =AA9*1.1 -> 100254 | AC9: {=IFERROR( (SUM('Time Plan (Single Release)'!$Y$6:$JN$64*(IFERROR('Time Plan (Single Release)'!$G$6:$G$64*40,0))*('Time Plan (Single Release)'!$D$6:$D$64=$U9)) - SUM('Time Plan (Single Release)'!$Y$6:$JN$64*(IFERROR('Time Plan (Single Release)'!$I$6:$I$64*40,0))*('Time Plan (Single Release)'!$D$6:$D$64=$U9))) / SUM('Time Plan (Single Release)'!$Y$6:$JN$64*(IFERROR('Time Plan (Single Release)'!$G$6:$G$64*40,0))*('Time Plan (Single Release)'!$D$6:$D$64=$U9)),"")} -> 0.38 | AD9: {=IFERROR( (SUM('Time Plan (Single Release)'!$Y$6:$JN$64*(IFERROR('Time Plan (Single Release)'!$I$6:$I$64*40,0))*('Time Plan (Single Release)'!$D$6:$D$64=$U9)) - SUM('Time Plan (Single Release)'!$Y$6:$JN$64*(IFERROR('Time Plan (Single Release)'!$K$6:$K$64*40,0))*('Time Plan (Single Release)'!$D$6:$D$64=$U9))) / SUM('Time Plan (Single Release)'!$Y$6:$JN$64*(IFERROR('Time Plan (Single Release)'!$I$6:$I$64*40,0))*('Time Plan (Single Release)'!$D$6:$D$64=$U9)),"")} -> 0.0059249506 | AE9: =SUMIF('Time Plan (Single Release)'!D$6:D$64,Pricing!U9,'Time Plan (Single Release)'!S$6:S$64) -> 600 | AF9: =AE9/8 -> 75 | AG9: =IFERROR(AE9+(AA$4*AI9/W9),"") -> 600 | AH9: =IFERROR(AG9/8,"") -> 75 | AI9: 0 | AJ9: =AG9*W9 -> 91140
C10: {=IFERROR(INDEX('Time Plan (Single Release)'!$Y$3:$JN$3, 1, _xlfn.XMATCH(TRUE, _xlfn.BYCOL(('Time Plan (Single Release)'!$Y$6:$JN$64)*('Time Plan (Single Release)'!$B$6:$B$64=$B10), _xlfn.LAMBDA(_xlpm.col, SUM(_xlpm.col)>0)), 0, 1)),"")} | D10: {=IFERROR(INDEX('Time Plan (Single Release)'!$Y$3:$JN$3, 1, _xlfn.XMATCH(TRUE, _xlfn.BYCOL(('Time Plan (Single Release)'!$Y$6:$JN$64)*('Time Plan (Single Release)'!$B$6:$B$64=$B10), _xlfn.LAMBDA(_xlpm.col, SUM(_xlpm.col)>0)), 0,-1))+4,"")} | E10: =IFERROR(DATEDIF('Time Plan (Single Release)'!$Y$3,$D10+3,"d")/7,"") | F10: {=SUM(IFERROR(('Time Plan (Single Release)'!$U$6:$U$64*('Time Plan (Single Release)'!$B$6:$B$64=Pricing!$B10)),0))} -> 0 | G10: =$F10*0.1 -> 0 | H10: =$F10*1.1 -> 0 | I10: {=IFERROR( (SUM('Time Plan (Single Release)'!$Y$6:$JN$64*(IFERROR('Time Plan (Single Release)'!$G$6:$G$64*40,0))*('Time Plan (Single Release)'!$B$6:$B$64=Pricing!$B10)) - SUM('Time Plan (Single Release)'!$Y$6:$JN$64*(IFERROR('Time Plan (Single Release)'!$I$6:$I$64*40,0))*('Time Plan (Single Release)'!$B$6:$B$64=Pricing!$B10))) / SUM('Time Plan (Single Release)'!$Y$6:$JN$64*(IFERROR('Time Plan (Single Release)'!$G$6:$G$64*40,0))*('Time Plan (Single Release)'!$B$6:$B$64=Pricing!$B10)),"")} | J10: {=IFERROR( (SUM('Time Plan (Single Release)'!$Y$6:$JN$64*(IFERROR('Time Plan (Single Release)'!$I$6:$I$64*40,0))*('Time Plan (Single Release)'!$B$6:$B$64=Pricing!$B10)) - SUM('Time Plan (Single Release)'!$Y$6:$JN$64*(IFERROR('Time Plan (Single Release)'!$K$6:$K$64*40,0))*('Time Plan (Single Release)'!$B$6:$B$64=Pricing!$B10))) / SUM('Time Plan (Single Release)'!$Y$6:$JN$64*(IFERROR('Time Plan (Single Release)'!$I$6:$I$64*40,0))*('Time Plan (Single Release)'!$B$6:$B$64=Pricing!$B10)),"")} | M10: {=IFERROR(INDEX('Time Plan (Single Release)'!$Y$3:$JN$3, 1, _xlfn.XMATCH(TRUE, _xlfn.BYCOL(('Time Plan (Single Release)'!$Y$6:$JN$64)*('Time Plan (Single Release)'!$C$6:$C$64=$L10), _xlfn.LAMBDA(_xlpm.col, SUM(_xlpm.col)>0)), 0, 1)),"")} | N10: {=IFERROR(INDEX('Time Plan (Single Release)'!$Y$3:$JN$3, 1, _xlfn.XMATCH(TRUE, _xlfn.BYCOL(('Time Plan (Single Release)'!$Y$6:$JN$64)*('Time Plan (Single Release)'!$C$6:$C$64=$L10), _xlfn.LAMBDA(_xlpm.col, SUM(_xlpm.col)>0)), 0,-1))+4,"")} | O10: {=SUM(IFERROR(('Time Plan (Single Release)'!$U$6:$U$64*('Time Plan (Single Release)'!$C$6:$C$64=$L10)),0))} -> 0 | P10: =IFERROR(O10*0.1,"") -> 0 | Q10: =O10*1.1 -> 0 | R10: {=IFERROR( (SUM('Time Plan (Single Release)'!$Y$6:$JN$64*(IFERROR('Time Plan (Single Release)'!$G$6:$G$64*40,0))*('Time Plan (Single Release)'!$C$6:$C$64=$L10)) - SUM('Time Plan (Single Release)'!$Y$6:$JN$64*(IFERROR('Time Plan (Single Release)'!$I$6:$I$64*40,0))*('Time Plan (Single Release)'!$C$6:$C$64=$L10))) / SUM('Time Plan (Single Release)'!$Y$6:$JN$64*(IFERROR('Time Plan (Single Release)'!$G$6:$G$64*40,0))*('Time Plan (Single Release)'!$C$6:$C$64=$L10)),"")} | S10: {=IFERROR( (SUM('Time Plan (Single Release)'!$Y$6:$JN$64*(IFERROR('Time Plan (Single Release)'!$I$6:$I$64*40,0))*('Time Plan (Single Release)'!$C$6:$C$64=$L10)) - SUM('Time Plan (Single Release)'!$Y$6:$JN$64*(IFERROR('Time Plan (Single Release)'!$K$6:$K$64*40,0))*('Time Plan (Single Release)'!$C$6:$C$64=$L10))) / SUM('Time Plan (Single Release)'!$Y$6:$JN$64*(IFERROR('Time Plan (Single Release)'!$I$6:$I$64*40,0))*('Time Plan (Single Release)'!$C$6:$C$64=$L10)),"")} | U10: Lacy Pejcinovic | V10: {=IFERROR(_xlfn.XLOOKUP($U10,'Time Plan (Single Release)'!$D$6:$D$194,'Time Plan (Single Release)'!$E$6:$E$194&" - "&'Time Plan (Single Release)'!$F$6:$F$194),"")} -> Level 3 - Business Analyst | W10: =IFERROR(_xlfn.XLOOKUP($U10,'Time Plan (Single Release)'!$D$6:$D$64,'Time Plan (Single Release)'!$I$6:$I$64),"") -> 151.9 | X10: =IFERROR(W10*1.1,"") -> 167.09 | Y10: {=IFERROR(INDEX('Time Plan (Single Release)'!$Y$3:$JN$3, 1, _xlfn.XMATCH(TRUE, _xlfn.BYCOL(('Time Plan (Single Release)'!$Y$6:$JN$64)*('Time Plan (Single Release)'!$D$6:$D$64=$U10), _xlfn.LAMBDA(_xlpm.col, SUM(_xlpm.col)>0)), 0, 1)),"")} -> 46062 | Z10: {=IFERROR(INDEX('Time Plan (Single Release)'!$Y$3:$JN$3, 1, _xlfn.XMATCH(TRUE, _xlfn.BYCOL(('Time Plan (Single Release)'!$Y$6:$JN$64)*('Time Plan (Single Release)'!$D$6:$D$64=$U10), _xlfn.LAMBDA(_xlpm.col, SUM(_xlpm.col)>0)), 0,-1))+4,"")} -> 46108 | AA10: {=SUM(IFERROR(('Time Plan (Single Release)'!$U$6:$U$64*('Time Plan (Single Release)'!$D$6:$D$64=$U10)),0))} -> 24304 | AB10: =AA10*1.1 -> 26734.4 | AC10: {=IFERROR( (SUM('Time Plan (Single Release)'!$Y$6:$JN$64*(IFERROR('Time Plan (Single Release)'!$G$6:$G$64*40,0))*('Time Plan (Single Release)'!$D$6:$D$64=$U10)) - SUM('Time Plan (Single Release)'!$Y$6:$JN$64*(IFERROR('Time Plan (Single Release)'!$I$6:$I$64*40,0))*('Time Plan (Single Release)'!$D$6:$D$64=$U10))) / SUM('Time Plan (Single Release)'!$Y$6:$JN$64*(IFERROR('Time Plan (Single Release)'!$G$6:$G$64*40,0))*('Time Plan (Single Release)'!$D$6:$D$64=$U10)),"")} -> 0.38 | AD10: {=IFERROR( (SUM('Time Plan (Single Release)'!$Y$6:$JN$64*(IFERROR('Time Plan (Single Release)'!$I$6:$I$64*40,0))*('Time Plan (Single Release)'!$D$6:$D$64=$U10)) - SUM('Time Plan (Single Release)'!$Y$6:$JN$64*(IFERROR('Time Plan (Single Release)'!$K$6:$K$64*40,0))*('Time Plan (Single Release)'!$D$6:$D$64=$U10))) / SUM('Time Plan (Single Release)'!$Y$6:$JN$64*(IFERROR('Time Plan (Single Release)'!$I$6:$I$64*40,0))*('Time Plan (Single Release)'!$D$6:$D$64=$U10)),"")} -> 0.038841343 | AE10: =SUMIF('Time Plan (Single Release)'!D$6:D$64,Pricing!U10,'Time Plan (Single Release)'!S$6:S$64) -> 160 | AF10: =AE10/8 -> 20 | AG10: =IFERROR(AE10+(AA$4*AI10/W10),"") -> 160 | AH10: =IFERROR(AG10/8,"") -> 20 | AI10: 0 | AJ10: =AG10*W10 -> 24304
C11: {=IFERROR(INDEX('Time Plan (Single Release)'!$Y$3:$JN$3, 1, _xlfn.XMATCH(TRUE, _xlfn.BYCOL(('Time Plan (Single Release)'!$Y$6:$JN$64)*('Time Plan (Single Release)'!$B$6:$B$64=$B11), _xlfn.LAMBDA(_xlpm.col, SUM(_xlpm.col)>0)), 0, 1)),"")} | D11: {=IFERROR(INDEX('Time Plan (Single Release)'!$Y$3:$JN$3, 1, _xlfn.XMATCH(TRUE, _xlfn.BYCOL(('Time Plan (Single Release)'!$Y$6:$JN$64)*('Time Plan (Single Release)'!$B$6:$B$64=$B11), _xlfn.LAMBDA(_xlpm.col, SUM(_xlpm.col)>0)), 0,-1))+4,"")} | E11: =IFERROR(DATEDIF('Time Plan (Single Release)'!$Y$3,$D11+3,"d")/7,"") | F11: {=SUM(IFERROR(('Time Plan (Single Release)'!$U$6:$U$64*('Time Plan (Single Release)'!$B$6:$B$64=Pricing!$B11)),0))} -> 0 | G11: =$F11*0.1 -> 0 | H11: =$F11*1.1 -> 0 | I11: {=IFERROR( (SUM('Time Plan (Single Release)'!$Y$6:$JN$64*(IFERROR('Time Plan (Single Release)'!$G$6:$G$64*40,0))*('Time Plan (Single Release)'!$B$6:$B$64=Pricing!$B11)) - SUM('Time Plan (Single Release)'!$Y$6:$JN$64*(IFERROR('Time Plan (Single Release)'!$I$6:$I$64*40,0))*('Time Plan (Single Release)'!$B$6:$B$64=Pricing!$B11))) / SUM('Time Plan (Single Release)'!$Y$6:$JN$64*(IFERROR('Time Plan (Single Release)'!$G$6:$G$64*40,0))*('Time Plan (Single Release)'!$B$6:$B$64=Pricing!$B11)),"")} | J11: {=IFERROR( (SUM('Time Plan (Single Release)'!$Y$6:$JN$64*(IFERROR('Time Plan (Single Release)'!$I$6:$I$64*40,0))*('Time Plan (Single Release)'!$B$6:$B$64=Pricing!$B11)) - SUM('Time Plan (Single Release)'!$Y$6:$JN$64*(IFERROR('Time Plan (Single Release)'!$K$6:$K$64*40,0))*('Time Plan (Single Release)'!$B$6:$B$64=Pricing!$B11))) / SUM('Time Plan (Single Release)'!$Y$6:$JN$64*(IFERROR('Time Plan (Single Release)'!$I$6:$I$64*40,0))*('Time Plan (Single Release)'!$B$6:$B$64=Pricing!$B11)),"")} | M11: {=IFERROR(INDEX('Time Plan (Single Release)'!$Y$3:$JN$3, 1, _xlfn.XMATCH(TRUE, _xlfn.BYCOL(('Time Plan (Single Release)'!$Y$6:$JN$64)*('Time Plan (Single Release)'!$C$6:$C$64=$L11), _xlfn.LAMBDA(_xlpm.col, SUM(_xlpm.col)>0)), 0, 1)),"")} | N11: {=IFERROR(INDEX('Time Plan (Single Release)'!$Y$3:$JN$3, 1, _xlfn.XMATCH(TRUE, _xlfn.BYCOL(('Time Plan (Single Release)'!$Y$6:$JN$64)*('Time Plan (Single Release)'!$C$6:$C$64=$L11), _xlfn.LAMBDA(_xlpm.col, SUM(_xlpm.col)>0)), 0,-1))+4,"")} | O11: {=SUM(IFERROR(('Time Plan (Single Release)'!$U$6:$U$64*('Time Plan (Single Release)'!$C$6:$C$64=$L11)),0))} -> 0 | P11: =IFERROR(O11*0.1,"") -> 0 | Q11: =O11*1.1 -> 0 | R11: {=IFERROR( (SUM('Time Plan (Single Release)'!$Y$6:$JN$64*(IFERROR('Time Plan (Single Release)'!$G$6:$G$64*40,0))*('Time Plan (Single Release)'!$C$6:$C$64=$L11)) - SUM('Time Plan (Single Release)'!$Y$6:$JN$64*(IFERROR('Time Plan (Single Release)'!$I$6:$I$64*40,0))*('Time Plan (Single Release)'!$C$6:$C$64=$L11))) / SUM('Time Plan (Single Release)'!$Y$6:$JN$64*(IFERROR('Time Plan (Single Release)'!$G$6:$G$64*40,0))*('Time Plan (Single Release)'!$C$6:$C$64=$L11)),"")} | S11: {=IFERROR( (SUM('Time Plan (Single Release)'!$Y$6:$JN$64*(IFERROR('Time Plan (Single Release)'!$I$6:$I$64*40,0))*('Time Plan (Single Release)'!$C$6:$C$64=$L11)) - SUM('Time Plan (Single Release)'!$Y$6:$JN$64*(IFERROR('Time Plan (Single Release)'!$K$6:$K$64*40,0))*('Time Plan (Single Release)'!$C$6:$C$64=$L11))) / SUM('Time Plan (Single Release)'!$Y$6:$JN$64*(IFERROR('Time Plan (Single Release)'!$I$6:$I$64*40,0))*('Time Plan (Single Release)'!$C$6:$C$64=$L11)),"")} | U11: Lynne Sutherland | V11: {=IFERROR(_xlfn.XLOOKUP($U11,'Time Plan (Single Release)'!$D$6:$D$194,'Time Plan (Single Release)'!$E$6:$E$194&" - "&'Time Plan (Single Release)'!$F$6:$F$194),"")} -> Level 3 - Business Analyst | W11: =IFERROR(_xlfn.XLOOKUP($U11,'Time Plan (Single Release)'!$D$6:$D$64,'Time Plan (Single Release)'!$I$6:$I$64),"") -> 151.9 | X11: =IFERROR(W11*1.1,"") -> 167.09 | Y11: {=IFERROR(INDEX('Time Plan (Single Release)'!$Y$3:$JN$3, 1, _xlfn.XMATCH(TRUE, _xlfn.BYCOL(('Time Plan (Single Release)'!$Y$6:$JN$64)*('Time Plan (Single Release)'!$D$6:$D$64=$U11), _xlfn.LAMBDA(_xlpm.col, SUM(_xlpm.col)>0)), 0, 1)),"")} -> 46062 | Z11: {=IFERROR(INDEX('Time Plan (Single Release)'!$Y$3:$JN$3, 1, _xlfn.XMATCH(TRUE, _xlfn.BYCOL(('Time Plan (Single Release)'!$Y$6:$JN$64)*('Time Plan (Single Release)'!$D$6:$D$64=$U11), _xlfn.LAMBDA(_xlpm.col, SUM(_xlpm.col)>0)), 0,-1))+4,"")} -> 46164 | AA11: {=SUM(IFERROR(('Time Plan (Single Release)'!$U$6:$U$64*('Time Plan (Single Release)'!$D$6:$D$64=$U11)),0))} -> 72912 | AB11: =AA11*1.1 -> 80203.2 | AC11: {=IFERROR( (SUM('Time Plan (Single Release)'!$Y$6:$JN$64*(IFERROR('Time Plan (Single Release)'!$G$6:$G$64*40,0))*('Time Plan (Single Release)'!$D$6:$D$64=$U11)) - SUM('Time Plan (Single Release)'!$Y$6:$JN$64*(IFERROR('Time Plan (Single Release)'!$I$6:$I$64*40,0))*('Time Plan (Single Release)'!$D$6:$D$64=$U11))) / SUM('Time Plan (Single Release)'!$Y$6:$JN$64*(IFERROR('Time Plan (Single Release)'!$G$6:$G$64*40,0))*('Time Plan (Single Release)'!$D$6:$D$64=$U11)),"")} -> 0.38 | AD11: {=IFERROR( (SUM('Time Plan (Single Release)'!$Y$6:$JN$64*(IFERROR('Time Plan (Single Release)'!$I$6:$I$64*40,0))*('Time Plan (Single Release)'!$D$6:$D$64=$U11)) - SUM('Time Plan (Single Release)'!$Y$6:$JN$64*(IFERROR('Time Plan (Single Release)'!$K$6:$K$64*40,0))*('Time Plan (Single Release)'!$D$6:$D$64=$U11))) / SUM('Time Plan (Single Release)'!$Y$6:$JN$64*(IFERROR('Time Plan (Single Release)'!$I$6:$I$64*40,0))*('Time Plan (Single Release)'!$D$6:$D$64=$U11)),"")} -> 0.40750494 | AE11: =SUMIF('Time Plan (Single Release)'!D$6:D$64,Pricing!U11,'Time Plan (Single Release)'!S$6:S$64) -> 480 | AF11: =AE11/8 -> 60 | AG11: =IFERROR(AE11+(AA$4*AI11/W11),"") -> 480 | AH11: =IFERROR(AG11/8,"") -> 60 | AI11: 0 | AJ11: =AG11*W11 -> 72912
C12: {=IFERROR(INDEX('Time Plan (Single Release)'!$Y$3:$JN$3, 1, _xlfn.XMATCH(TRUE, _xlfn.BYCOL(('Time Plan (Single Release)'!$Y$6:$JN$64)*('Time Plan (Single Release)'!$B$6:$B$64=$B12), _xlfn.LAMBDA(_xlpm.col, SUM(_xlpm.col)>0)), 0, 1)),"")} | D12: {=IFERROR(INDEX('Time Plan (Single Release)'!$Y$3:$JN$3, 1, _xlfn.XMATCH(TRUE, _xlfn.BYCOL(('Time Plan (Single Release)'!$Y$6:$JN$64)*('Time Plan (Single Release)'!$B$6:$B$64=$B12), _xlfn.LAMBDA(_xlpm.col, SUM(_xlpm.col)>0)), 0,-1))+4,"")} | E12: =IFERROR(DATEDIF('Time Plan (Single Release)'!$Y$3,$D12+3,"d")/7,"") | F12: {=SUM(IFERROR(('Time Plan (Single Release)'!$U$6:$U$64*('Time Plan (Single Release)'!$B$6:$B$64=Pricing!$B12)),0))} -> 0 | G12: =$F12*0.1 -> 0 | H12: =$F12*1.1 -> 0 | I12: {=IFERROR( (SUM('Time Plan (Single Release)'!$Y$6:$JN$64*(IFERROR('Time Plan (Single Release)'!$G$6:$G$64*40,0))*('Time Plan (Single Release)'!$B$6:$B$64=Pricing!$B12)) - SUM('Time Plan (Single Release)'!$Y$6:$JN$64*(IFERROR('Time Plan (Single Release)'!$I$6:$I$64*40,0))*('Time Plan (Single Release)'!$B$6:$B$64=Pricing!$B12))) / SUM('Time Plan (Single Release)'!$Y$6:$JN$64*(IFERROR('Time Plan (Single Release)'!$G$6:$G$64*40,0))*('Time Plan (Single Release)'!$B$6:$B$64=Pricing!$B12)),"")} | J12: {=IFERROR( (SUM('Time Plan (Single Release)'!$Y$6:$JN$64*(IFERROR('Time Plan (Single Release)'!$I$6:$I$64*40,0))*('Time Plan (Single Release)'!$B$6:$B$64=Pricing!$B12)) - SUM('Time Plan (Single Release)'!$Y$6:$JN$64*(IFERROR('Time Plan (Single Release)'!$K$6:$K$64*40,0))*('Time Plan (Single Release)'!$B$6:$B$64=Pricing!$B12))) / SUM('Time Plan (Single Release)'!$Y$6:$JN$64*(IFERROR('Time Plan (Single Release)'!$I$6:$I$64*40,0))*('Time Plan (Single Release)'!$B$6:$B$64=Pricing!$B12)),"")} | M12: {=IFERROR(INDEX('Time Plan (Single Release)'!$Y$3:$JN$3, 1, _xlfn.XMATCH(TRUE, _xlfn.BYCOL(('Time Plan (Single Release)'!$Y$6:$JN$64)*('Time Plan (Single Release)'!$C$6:$C$64=$L12), _xlfn.LAMBDA(_xlpm.col, SUM(_xlpm.col)>0)), 0, 1)),"")} | N12: {=IFERROR(INDEX('Time Plan (Single Release)'!$Y$3:$JN$3, 1, _xlfn.XMATCH(TRUE, _xlfn.BYCOL(('Time Plan (Single Release)'!$Y$6:$JN$64)*('Time Plan (Single Release)'!$C$6:$C$64=$L12), _xlfn.LAMBDA(_xlpm.col, SUM(_xlpm.col)>0)), 0,-1))+4,"")} | O12: {=SUM(IFERROR(('Time Plan (Single Release)'!$U$6:$U$64*('Time Plan (Single Release)'!$C$6:$C$64=$L12)),0))} -> 0 | P12: =IFERROR(O12*0.1,"") -> 0 | Q12: =O12*1.1 -> 0 | R12: {=IFERROR( (SUM('Time Plan (Single Release)'!$Y$6:$JN$64*(IFERROR('Time Plan (Single Release)'!$G$6:$G$64*40,0))*('Time Plan (Single Release)'!$C$6:$C$64=$L12)) - SUM('Time Plan (Single Release)'!$Y$6:$JN$64*(IFERROR('Time Plan (Single Release)'!$I$6:$I$64*40,0))*('Time Plan (Single Release)'!$C$6:$C$64=$L12))) / SUM('Time Plan (Single Release)'!$Y$6:$JN$64*(IFERROR('Time Plan (Single Release)'!$G$6:$G$64*40,0))*('Time Plan (Single Release)'!$C$6:$C$64=$L12)),"")} | S12: {=IFERROR( (SUM('Time Plan (Single Release)'!$Y$6:$JN$64*(IFERROR('Time Plan (Single Release)'!$I$6:$I$64*40,0))*('Time Plan (Single Release)'!$C$6:$C$64=$L12)) - SUM('Time Plan (Single Release)'!$Y$6:$JN$64*(IFERROR('Time Plan (Single Release)'!$K$6:$K$64*40,0))*('Time Plan (Single Release)'!$C$6:$C$64=$L12))) / SUM('Time Plan (Single Release)'!$Y$6:$JN$64*(IFERROR('Time Plan (Single Release)'!$I$6:$I$64*40,0))*('Time Plan (Single Release)'!$C$6:$C$64=$L12)),"")} | U12: Mahesh Vemegal | V12: {=IFERROR(_xlfn.XLOOKUP($U12,'Time Plan (Single Release)'!$D$6:$D$194,'Time Plan (Single Release)'!$E$6:$E$194&" - "&'Time Plan (Single Release)'!$F$6:$F$194),"")} -> Level 4 - Lead ServiceNow Developer | W12: =IFERROR(_xlfn.XLOOKUP($U12,'Time Plan (Single Release)'!$D$6:$D$64,'Time Plan (Single Release)'!$I$6:$I$64),"") -> 207.4 | X12: =IFERROR(W12*1.1,"") -> 228.14 | Y12: {=IFERROR(INDEX('Time Plan (Single Release)'!$Y$3:$JN$3, 1, _xlfn.XMATCH(TRUE, _xlfn.BYCOL(('Time Plan (Single Release)'!$Y$6:$JN$64)*('Time Plan (Single Release)'!$D$6:$D$64=$U12), _xlfn.LAMBDA(_xlpm.col, SUM(_xlpm.col)>0)), 0, 1)),"")} -> 46076 | Z12: {=IFERROR(INDEX('Time Plan (Single Release)'!$Y$3:$JN$3, 1, _xlfn.XMATCH(TRUE, _xlfn.BYCOL(('Time Plan (Single Release)'!$Y$6:$JN$64)*('Time Plan (Single Release)'!$D$6:$D$64=$U12), _xlfn.LAMBDA(_xlpm.col, SUM(_xlpm.col)>0)), 0,-1))+4,"")} -> 46164 | AA12: {=SUM(IFERROR(('Time Plan (Single Release)'!$U$6:$U$64*('Time Plan (Single Release)'!$D$6:$D$64=$U12)),0))} -> 95404 | AB12: =AA12*1.1 -> 104944.4 | AC12: {=IFERROR( (SUM('Time Plan (Single Release)'!$Y$6:$JN$64*(IFERROR('Time Plan (Single Release)'!$G$6:$G$64*40,0))*('Time Plan (Single Release)'!$D$6:$D$64=$U12)) - SUM('Time Plan (Single Release)'!$Y$6:$JN$64*(IFERROR('Time Plan (Single Release)'!$I$6:$I$64*40,0))*('Time Plan (Single Release)'!$D$6:$D$64=$U12))) / SUM('Time Plan (Single Release)'!$Y$6:$JN$64*(IFERROR('Time Plan (Single Release)'!$G$6:$G$64*40,0))*('Time Plan (Single Release)'!$D$6:$D$64=$U12)),"")} -> 0.32 | AD12: {=IFERROR( (SUM('Time Plan (Single Release)'!$Y$6:$JN$64*(IFERROR('Time Plan (Single Release)'!$I$6:$I$64*40,0))*('Time Plan (Single Release)'!$D$6:$D$64=$U12)) - SUM('Time Plan (Single Release)'!$Y$6:$JN$64*(IFERROR('Time Plan (Single Release)'!$K$6:$K$64*40,0))*('Time Plan (Single Release)'!$D$6:$D$64=$U12))) / SUM('Time Plan (Single Release)'!$Y$6:$JN$64*(IFERROR('Time Plan (Single Release)'!$I$6:$I$64*40,0))*('Time Plan (Single Release)'!$D$6:$D$64=$U12)),"")} -> 0.17569913 | AE12: =SUMIF('Time Plan (Single Release)'!D$6:D$64,Pricing!U12,'Time Plan (Single Release)'!S$6:S$64) -> 460 | AF12: =AE12/8 -> 57.5 | AG12: =IFERROR(AE12+(AA$8*AI12/W12),"") -> 460 | AH12: =IFERROR(AG12/8,"") -> 57.5
C13: {=IFERROR(INDEX('Time Plan (Single Release)'!$Y$3:$JN$3, 1, _xlfn.XMATCH(TRUE, _xlfn.BYCOL(('Time Plan (Single Release)'!$Y$6:$JN$64)*('Time Plan (Single Release)'!$B$6:$B$64=$B13), _xlfn.LAMBDA(_xlpm.col, SUM(_xlpm.col)>0)), 0, 1)),"")} | D13: {=IFERROR(INDEX('Time Plan (Single Release)'!$Y$3:$JN$3, 1, _xlfn.XMATCH(TRUE, _xlfn.BYCOL(('Time Plan (Single Release)'!$Y$6:$JN$64)*('Time Plan (Single Release)'!$B$6:$B$64=$B13), _xlfn.LAMBDA(_xlpm.col, SUM(_xlpm.col)>0)), 0,-1))+4,"")} | E13: =IFERROR(DATEDIF('Time Plan (Single Release)'!$Y$3,$D13+3,"d")/7,"") | F13: {=SUM(IFERROR(('Time Plan (Single Release)'!$U$6:$U$64*('Time Plan (Single Release)'!$B$6:$B$64=Pricing!$B13)),0))} -> 0 | G13: =$F13*0.1 -> 0 | H13: =$F13*1.1 -> 0 | I13: {=IFERROR( (SUM('Time Plan (Single Release)'!$Y$6:$JN$64*(IFERROR('Time Plan (Single Release)'!$G$6:$G$64*40,0))*('Time Plan (Single Release)'!$B$6:$B$64=Pricing!$B13)) - SUM('Time Plan (Single Release)'!$Y$6:$JN$64*(IFERROR('Time Plan (Single Release)'!$I$6:$I$64*40,0))*('Time Plan (Single Release)'!$B$6:$B$64=Pricing!$B13))) / SUM('Time Plan (Single Release)'!$Y$6:$JN$64*(IFERROR('Time Plan (Single Release)'!$G$6:$G$64*40,0))*('Time Plan (Single Release)'!$B$6:$B$64=Pricing!$B13)),"")} | J13: {=IFERROR( (SUM('Time Plan (Single Release)'!$Y$6:$JN$64*(IFERROR('Time Plan (Single Release)'!$I$6:$I$64*40,0))*('Time Plan (Single Release)'!$B$6:$B$64=Pricing!$B13)) - SUM('Time Plan (Single Release)'!$Y$6:$JN$64*(IFERROR('Time Plan (Single Release)'!$K$6:$K$64*40,0))*('Time Plan (Single Release)'!$B$6:$B$64=Pricing!$B13))) / SUM('Time Plan (Single Release)'!$Y$6:$JN$64*(IFERROR('Time Plan (Single Release)'!$I$6:$I$64*40,0))*('Time Plan (Single Release)'!$B$6:$B$64=Pricing!$B13)),"")} | M13: {=IFERROR(INDEX('Time Plan (Single Release)'!$Y$3:$JN$3, 1, _xlfn.XMATCH(TRUE, _xlfn.BYCOL(('Time Plan (Single Release)'!$Y$6:$JN$64)*('Time Plan (Single Release)'!$C$6:$C$64=$L13), _xlfn.LAMBDA(_xlpm.col, SUM(_xlpm.col)>0)), 0, 1)),"")} | N13: {=IFERROR(INDEX('Time Plan (Single Release)'!$Y$3:$JN$3, 1, _xlfn.XMATCH(TRUE, _xlfn.BYCOL(('Time Plan (Single Release)'!$Y$6:$JN$64)*('Time Plan (Single Release)'!$C$6:$C$64=$L13), _xlfn.LAMBDA(_xlpm.col, SUM(_xlpm.col)>0)), 0,-1))+4,"")} | O13: {=SUM(IFERROR(('Time Plan (Single Release)'!$U$6:$U$64*('Time Plan (Single Release)'!$C$6:$C$64=$L13)),0))} -> 0 | P13: =IFERROR(O13*0.1,"") -> 0 | Q13: =O13*1.1 -> 0 | R13: {=IFERROR( (SUM('Time Plan (Single Release)'!$Y$6:$JN$64*(IFERROR('Time Plan (Single Release)'!$G$6:$G$64*40,0))*('Time Plan (Single Release)'!$C$6:$C$64=$L13)) - SUM('Time Plan (Single Release)'!$Y$6:$JN$64*(IFERROR('Time Plan (Single Release)'!$I$6:$I$64*40,0))*('Time Plan (Single Release)'!$C$6:$C$64=$L13))) / SUM('Time Plan (Single Release)'!$Y$6:$JN$64*(IFERROR('Time Plan (Single Release)'!$G$6:$G$64*40,0))*('Time Plan (Single Release)'!$C$6:$C$64=$L13)),"")} | S13: {=IFERROR( (SUM('Time Plan (Single Release)'!$Y$6:$JN$64*(IFERROR('Time Plan (Single Release)'!$I$6:$I$64*40,0))*('Time Plan (Single Release)'!$C$6:$C$64=$L13)) - SUM('Time Plan (Single Release)'!$Y$6:$JN$64*(IFERROR('Time Plan (Single Release)'!$K$6:$K$64*40,0))*('Time Plan (Single Release)'!$C$6:$C$64=$L13))) / SUM('Time Plan (Single Release)'!$Y$6:$JN$64*(IFERROR('Time Plan (Single Release)'!$I$6:$I$64*40,0))*('Time Plan (Single Release)'!$C$6:$C$64=$L13)),"")} | U13: Michelle Chant | V13: {=IFERROR(_xlfn.XLOOKUP($U13,'Time Plan (Single Release)'!$D$6:$D$194,'Time Plan (Single Release)'!$E$6:$E$194&" - "&'Time Plan (Single Release)'!$F$6:$F$194),"")} -> Level 3 - Change Manager | W13: =IFERROR(_xlfn.XLOOKUP($U13,'Time Plan (Single Release)'!$D$6:$D$64,'Time Plan (Single Release)'!$I$6:$I$64),"") -> 151.9 | X13: =IFERROR(W13*1.1,"") -> 167.09 | Y13: {=IFERROR(INDEX('Time Plan (Single Release)'!$Y$3:$JN$3, 1, _xlfn.XMATCH(TRUE, _xlfn.BYCOL(('Time Plan (Single Release)'!$Y$6:$JN$64)*('Time Plan (Single Release)'!$D$6:$D$64=$U13), _xlfn.LAMBDA(_xlpm.col, SUM(_xlpm.col)>0)), 0, 1)),"")} -> 46062 | Z13: {=IFERROR(INDEX('Time Plan (Single Release)'!$Y$3:$JN$3, 1, _xlfn.XMATCH(TRUE, _xlfn.BYCOL(('Time Plan (Single Release)'!$Y$6:$JN$64)*('Time Plan (Single Release)'!$D$6:$D$64=$U13), _xlfn.LAMBDA(_xlpm.col, SUM(_xlpm.col)>0)), 0,-1))+4,"")} -> 46192 | AA13: {=SUM(IFERROR(('Time Plan (Single Release)'!$U$6:$U$64*('Time Plan (Single Release)'!$D$6:$D$64=$U13)),0))} -> 55899.2 | AB13: =AA13*1.1 -> 61489.12 | AC13: {=IFERROR( (SUM('Time Plan (Single Release)'!$Y$6:$JN$64*(IFERROR('Time Plan (Single Release)'!$G$6:$G$64*40,0))*('Time Plan (Single Release)'!$D$6:$D$64=$U13)) - SUM('Time Plan (Single Release)'!$Y$6:$JN$64*(IFERROR('Time Plan (Single Release)'!$I$6:$I$64*40,0))*('Time Plan (Single Release)'!$D$6:$D$64=$U13))) / SUM('Time Plan (Single Release)'!$Y$6:$JN$64*(IFERROR('Time Plan (Single Release)'!$G$6:$G$64*40,0))*('Time Plan (Single Release)'!$D$6:$D$64=$U13)),"")} -> 0.38 | AD13: {=IFERROR( (SUM('Time Plan (Single Release)'!$Y$6:$JN$64*(IFERROR('Time Plan (Single Release)'!$I$6:$I$64*40,0))*('Time Plan (Single Release)'!$D$6:$D$64=$U13)) - SUM('Time Plan (Single Release)'!$Y$6:$JN$64*(IFERROR('Time Plan (Single Release)'!$K$6:$K$64*40,0))*('Time Plan (Single Release)'!$D$6:$D$64=$U13))) / SUM('Time Plan (Single Release)'!$Y$6:$JN$64*(IFERROR('Time Plan (Single Release)'!$I$6:$I$64*40,0))*('Time Plan (Single Release)'!$D$6:$D$64=$U13)),"")} -> 0.038841343 | AE13: =SUMIF('Time Plan (Single Release)'!D$6:D$64,Pricing!U13,'Time Plan (Single Release)'!S$6:S$64) -> 368 | AF13: =AE13/8 -> 46 | AG13: =IFERROR(AE13+(AA$8*AI13/W13),"") -> 368 | AH13: =IFERROR(AG13/8,"") -> 46
C14: {=IFERROR(INDEX('Time Plan (Single Release)'!$Y$3:$JN$3, 1, _xlfn.XMATCH(TRUE, _xlfn.BYCOL(('Time Plan (Single Release)'!$Y$6:$JN$64)*('Time Plan (Single Release)'!$B$6:$B$64=$B14), _xlfn.LAMBDA(_xlpm.col, SUM(_xlpm.col)>0)), 0, 1)),"")} | D14: {=IFERROR(INDEX('Time Plan (Single Release)'!$Y$3:$JN$3, 1, _xlfn.XMATCH(TRUE, _xlfn.BYCOL(('Time Plan (Single Release)'!$Y$6:$JN$64)*('Time Plan (Single Release)'!$B$6:$B$64=$B14), _xlfn.LAMBDA(_xlpm.col, SUM(_xlpm.col)>0)), 0,-1))+4,"")} | E14: =IFERROR(DATEDIF('Time Plan (Single Release)'!$Y$3,$D14+3,"d")/7,"") | F14: {=SUM(IFERROR(('Time Plan (Single Release)'!$U$6:$U$64*('Time Plan (Single Release)'!$B$6:$B$64=Pricing!$B14)),0))} -> 0 | G14: =$F14*0.1 -> 0 | H14: =$F14*1.1 -> 0 | I14: {=IFERROR( (SUM('Time Plan (Single Release)'!$Y$6:$JN$64*(IFERROR('Time Plan (Single Release)'!$G$6:$G$64*40,0))*('Time Plan (Single Release)'!$B$6:$B$64=Pricing!$B14)) - SUM('Time Plan (Single Release)'!$Y$6:$JN$64*(IFERROR('Time Plan (Single Release)'!$I$6:$I$64*40,0))*('Time Plan (Single Release)'!$B$6:$B$64=Pricing!$B14))) / SUM('Time Plan (Single Release)'!$Y$6:$JN$64*(IFERROR('Time Plan (Single Release)'!$G$6:$G$64*40,0))*('Time Plan (Single Release)'!$B$6:$B$64=Pricing!$B14)),"")} | J14: {=IFERROR( (SUM('Time Plan (Single Release)'!$Y$6:$JN$64*(IFERROR('Time Plan (Single Release)'!$I$6:$I$64*40,0))*('Time Plan (Single Release)'!$B$6:$B$64=Pricing!$B14)) - SUM('Time Plan (Single Release)'!$Y$6:$JN$64*(IFERROR('Time Plan (Single Release)'!$K$6:$K$64*40,0))*('Time Plan (Single Release)'!$B$6:$B$64=Pricing!$B14))) / SUM('Time Plan (Single Release)'!$Y$6:$JN$64*(IFERROR('Time Plan (Single Release)'!$I$6:$I$64*40,0))*('Time Plan (Single Release)'!$B$6:$B$64=Pricing!$B14)),"")} | M14: {=IFERROR(INDEX('Time Plan (Single Release)'!$Y$3:$JN$3, 1, _xlfn.XMATCH(TRUE, _xlfn.BYCOL(('Time Plan (Single Release)'!$Y$6:$JN$64)*('Time Plan (Single Release)'!$C$6:$C$64=$L14), _xlfn.LAMBDA(_xlpm.col, SUM(_xlpm.col)>0)), 0, 1)),"")} | N14: {=IFERROR(INDEX('Time Plan (Single Release)'!$Y$3:$JN$3, 1, _xlfn.XMATCH(TRUE, _xlfn.BYCOL(('Time Plan (Single Release)'!$Y$6:$JN$64)*('Time Plan (Single Release)'!$C$6:$C$64=$L14), _xlfn.LAMBDA(_xlpm.col, SUM(_xlpm.col)>0)), 0,-1))+4,"")} | O14: {=SUM(IFERROR(('Time Plan (Single Release)'!$U$6:$U$64*('Time Plan (Single Release)'!$C$6:$C$64=$L14)),0))} -> 0 | P14: =IFERROR(O14*0.1,"") -> 0 | Q14: =O14*1.1 -> 0 | R14: {=IFERROR( (SUM('Time Plan (Single Release)'!$Y$6:$JN$64*(IFERROR('Time Plan (Single Release)'!$G$6:$G$64*40,0))*('Time Plan (Single Release)'!$C$6:$C$64=$L14)) - SUM('Time Plan (Single Release)'!$Y$6:$JN$64*(IFERROR('Time Plan (Single Release)'!$I$6:$I$64*40,0))*('Time Plan (Single Release)'!$C$6:$C$64=$L14))) / SUM('Time Plan (Single Release)'!$Y$6:$JN$64*(IFERROR('Time Plan (Single Release)'!$G$6:$G$64*40,0))*('Time Plan (Single Release)'!$C$6:$C$64=$L14)),"")} | S14: {=IFERROR( (SUM('Time Plan (Single Release)'!$Y$6:$JN$64*(IFERROR('Time Plan (Single Release)'!$I$6:$I$64*40,0))*('Time Plan (Single Release)'!$C$6:$C$64=$L14)) - SUM('Time Plan (Single Release)'!$Y$6:$JN$64*(IFERROR('Time Plan (Single Release)'!$K$6:$K$64*40,0))*('Time Plan (Single Release)'!$C$6:$C$64=$L14))) / SUM('Time Plan (Single Release)'!$Y$6:$JN$64*(IFERROR('Time Plan (Single Release)'!$I$6:$I$64*40,0))*('Time Plan (Single Release)'!$C$6:$C$64=$L14)),"")} | U14: Phani Gollamudi | V14: {=IFERROR(_xlfn.XLOOKUP($U14,'Time Plan (Single Release)'!$D$6:$D$194,'Time Plan (Single Release)'!$E$6:$E$194&" - "&'Time Plan (Single Release)'!$F$6:$F$194),"")} -> Level 3 - ServiceNow Developer | W14: =IFERROR(_xlfn.XLOOKUP($U14,'Time Plan (Single Release)'!$D$6:$D$64,'Time Plan (Single Release)'!$I$6:$I$64),"") -> 0 | X14: =IFERROR(W14*1.1,"") -> 0 | Y14: {=IFERROR(INDEX('Time Plan (Single Release)'!$Y$3:$JN$3, 1, _xlfn.XMATCH(TRUE, _xlfn.BYCOL(('Time Plan (Single Release)'!$Y$6:$JN$64)*('Time Plan (Single Release)'!$D$6:$D$64=$U14), _xlfn.LAMBDA(_xlpm.col, SUM(_xlpm.col)>0)), 0, 1)),"")} -> 46062 | Z14: {=IFERROR(INDEX('Time Plan (Single Release)'!$Y$3:$JN$3, 1, _xlfn.XMATCH(TRUE, _xlfn.BYCOL(('Time Plan (Single Release)'!$Y$6:$JN$64)*('Time Plan (Single Release)'!$D$6:$D$64=$U14), _xlfn.LAMBDA(_xlpm.col, SUM(_xlpm.col)>0)), 0,-1))+4,"")} -> 46206 | AA14: {=SUM(IFERROR(('Time Plan (Single Release)'!$U$6:$U$64*('Time Plan (Single Release)'!$D$6:$D$64=$U14)),0))} -> 0 | AB14: =AA14*1.1 -> 0 | AC14: {=IFERROR( (SUM('Time Plan (Single Release)'!$Y$6:$JN$64*(IFERROR('Time Plan (Single Release)'!$G$6:$G$64*40,0))*('Time Plan (Single Release)'!$D$6:$D$64=$U14)) - SUM('Time Plan (Single Release)'!$Y$6:$JN$64*(IFERROR('Time Plan (Single Release)'!$I$6:$I$64*40,0))*('Time Plan (Single Release)'!$D$6:$D$64=$U14))) / SUM('Time Plan (Single Release)'!$Y$6:$JN$64*(IFERROR('Time Plan (Single Release)'!$G$6:$G$64*40,0))*('Time Plan (Single Release)'!$D$6:$D$64=$U14)),"")} -> 1 | AD14: {=IFERROR( (SUM('Time Plan (Single Release)'!$Y$6:$JN$64*(IFERROR('Time Plan (Single Release)'!$I$6:$I$64*40,0))*('Time Plan (Single Release)'!$D$6:$D$64=$U14)) - SUM('Time Plan (Single Release)'!$Y$6:$JN$64*(IFERROR('Time Plan (Single Release)'!$K$6:$K$64*40,0))*('Time Plan (Single Release)'!$D$6:$D$64=$U14))) / SUM('Time Plan (Single Release)'!$Y$6:$JN$64*(IFERROR('Time Plan (Single Release)'!$I$6:$I$64*40,0))*('Time Plan (Single Release)'!$D$6:$D$64=$U14)),"")} | AE14: =SUMIF('Time Plan (Single Release)'!D$6:D$64,Pricing!U14,'Time Plan (Single Release)'!S$6:S$64) -> 660 | AF14: =AE14/8 -> 82.5 | AG14: =IFERROR(AE14+(AA$8*AI14/W14),"") | AH14: =IFERROR(AG14/8,"")
C15: {=IFERROR(INDEX('Time Plan (Single Release)'!$Y$3:$JN$3, 1, _xlfn.XMATCH(TRUE, _xlfn.BYCOL(('Time Plan (Single Release)'!$Y$6:$JN$64)*('Time Plan (Single Release)'!$B$6:$B$64=$B15), _xlfn.LAMBDA(_xlpm.col, SUM(_xlpm.col)>0)), 0, 1)),"")} | D15: {=IFERROR(INDEX('Time Plan (Single Release)'!$Y$3:$JN$3, 1, _xlfn.XMATCH(TRUE, _xlfn.BYCOL(('Time Plan (Single Release)'!$Y$6:$JN$64)*('Time Plan (Single Release)'!$B$6:$B$64=$B15), _xlfn.LAMBDA(_xlpm.col, SUM(_xlpm.col)>0)), 0,-1))+4,"")} | E15: =IFERROR(DATEDIF('Time Plan (Single Release)'!$Y$3,$D15+3,"d")/7,"") | F15: {=SUM(IFERROR(('Time Plan (Single Release)'!$U$6:$U$64*('Time Plan (Single Release)'!$B$6:$B$64=Pricing!$B15)),0))} -> 0 | G15: =$F15*0.1 -> 0 | H15: =$F15*1.1 -> 0 | I15: {=IFERROR( (SUM('Time Plan (Single Release)'!$Y$6:$JN$64*(IFERROR('Time Plan (Single Release)'!$G$6:$G$64*40,0))*('Time Plan (Single Release)'!$B$6:$B$64=Pricing!$B15)) - SUM('Time Plan (Single Release)'!$Y$6:$JN$64*(IFERROR('Time Plan (Single Release)'!$I$6:$I$64*40,0))*('Time Plan (Single Release)'!$B$6:$B$64=Pricing!$B15))) / SUM('Time Plan (Single Release)'!$Y$6:$JN$64*(IFERROR('Time Plan (Single Release)'!$G$6:$G$64*40,0))*('Time Plan (Single Release)'!$B$6:$B$64=Pricing!$B15)),"")} | J15: {=IFERROR( (SUM('Time Plan (Single Release)'!$Y$6:$JN$64*(IFERROR('Time Plan (Single Release)'!$I$6:$I$64*40,0))*('Time Plan (Single Release)'!$B$6:$B$64=Pricing!$B15)) - SUM('Time Plan (Single Release)'!$Y$6:$JN$64*(IFERROR('Time Plan (Single Release)'!$K$6:$K$64*40,0))*('Time Plan (Single Release)'!$B$6:$B$64=Pricing!$B15))) / SUM('Time Plan (Single Release)'!$Y$6:$JN$64*(IFERROR('Time Plan (Single Release)'!$I$6:$I$64*40,0))*('Time Plan (Single Release)'!$B$6:$B$64=Pricing!$B15)),"")} | M15: {=IFERROR(INDEX('Time Plan (Single Release)'!$Y$3:$JN$3, 1, _xlfn.XMATCH(TRUE, _xlfn.BYCOL(('Time Plan (Single Release)'!$Y$6:$JN$64)*('Time Plan (Single Release)'!$C$6:$C$64=$L15), _xlfn.LAMBDA(_xlpm.col, SUM(_xlpm.col)>0)), 0, 1)),"")} | N15: {=IFERROR(INDEX('Time Plan (Single Release)'!$Y$3:$JN$3, 1, _xlfn.XMATCH(TRUE, _xlfn.BYCOL(('Time Plan (Single Release)'!$Y$6:$JN$64)*('Time Plan (Single Release)'!$C$6:$C$64=$L15), _xlfn.LAMBDA(_xlpm.col, SUM(_xlpm.col)>0)), 0,-1))+4,"")} | O15: {=SUM(IFERROR(('Time Plan (Single Release)'!$U$6:$U$64*('Time Plan (Single Release)'!$C$6:$C$64=$L15)),0))} -> 0 | P15: =IFERROR(O15*0.1,"") -> 0 | Q15: =O15*1.1 -> 0 | R15: {=IFERROR( (SUM('Time Plan (Single Release)'!$Y$6:$JN$64*(IFERROR('Time Plan (Single Release)'!$G$6:$G$64*40,0))*('Time Plan (Single Release)'!$C$6:$C$64=$L15)) - SUM('Time Plan (Single Release)'!$Y$6:$JN$64*(IFERROR('Time Plan (Single Release)'!$I$6:$I$64*40,0))*('Time Plan (Single Release)'!$C$6:$C$64=$L15))) / SUM('Time Plan (Single Release)'!$Y$6:$JN$64*(IFERROR('Time Plan (Single Release)'!$G$6:$G$64*40,0))*('Time Plan (Single Release)'!$C$6:$C$64=$L15)),"")} | S15: {=IFERROR( (SUM('Time Plan (Single Release)'!$Y$6:$JN$64*(IFERROR('Time Plan (Single Release)'!$I$6:$I$64*40,0))*('Time Plan (Single Release)'!$C$6:$C$64=$L15)) - SUM('Time Plan (Single Release)'!$Y$6:$JN$64*(IFERROR('Time Plan (Single Release)'!$K$6:$K$64*40,0))*('Time Plan (Single Release)'!$C$6:$C$64=$L15))) / SUM('Time Plan (Single Release)'!$Y$6:$JN$64*(IFERROR('Time Plan (Single Release)'!$I$6:$I$64*40,0))*('Time Plan (Single Release)'!$C$6:$C$64=$L15)),"")} | V15: {=IFERROR(_xlfn.XLOOKUP($U15,'Time Plan (Single Release)'!$D$6:$D$194,'Time Plan (Single Release)'!$E$6:$E$194&" - "&'Time Plan (Single Release)'!$F$6:$F$194),"")} -> - | W15: =IFERROR(_xlfn.XLOOKUP($U15,'Time Plan (Single Release)'!$D$6:$D$64,'Time Plan (Single Release)'!$I$6:$I$64),"") | X15: =IFERROR(W15*1.1,"") | Y15: {=IFERROR(INDEX('Time Plan (Single Release)'!$Y$3:$JN$3, 1, _xlfn.XMATCH(TRUE, _xlfn.BYCOL(('Time Plan (Single Release)'!$Y$6:$JN$64)*('Time Plan (Single Release)'!$D$6:$D$64=$U15), _xlfn.LAMBDA(_xlpm.col, SUM(_xlpm.col)>0)), 0, 1)),"")} | Z15: {=IFERROR(INDEX('Time Plan (Single Release)'!$Y$3:$JN$3, 1, _xlfn.XMATCH(TRUE, _xlfn.BYCOL(('Time Plan (Single Release)'!$Y$6:$JN$64)*('Time Plan (Single Release)'!$D$6:$D$64=$U15), _xlfn.LAMBDA(_xlpm.col, SUM(_xlpm.col)>0)), 0,-1))+4,"")} | AA15: {=SUM(IFERROR(('Time Plan (Single Release)'!$U$6:$U$64*('Time Plan (Single Release)'!$D$6:$D$64=$U15)),0))} -> 0 | AB15: =AA15*1.1 -> 0 | AC15: {=IFERROR( (SUM('Time Plan (Single Release)'!$Y$6:$JN$64*(IFERROR('Time Plan (Single Release)'!$G$6:$G$64*40,0))*('Time Plan (Single Release)'!$D$6:$D$64=$U15)) - SUM('Time Plan (Single Release)'!$Y$6:$JN$64*(IFERROR('Time Plan (Single Release)'!$I$6:$I$64*40,0))*('Time Plan (Single Release)'!$D$6:$D$64=$U15))) / SUM('Time Plan (Single Release)'!$Y$6:$JN$64*(IFERROR('Time Plan (Single Release)'!$G$6:$G$64*40,0))*('Time Plan (Single Release)'!$D$6:$D$64=$U15)),"")} | AD15: {=IFERROR( (SUM('Time Plan (Single Release)'!$Y$6:$JN$64*(IFERROR('Time Plan (Single Release)'!$I$6:$I$64*40,0))*('Time Plan (Single Release)'!$D$6:$D$64=$U15)) - SUM('Time Plan (Single Release)'!$Y$6:$JN$64*(IFERROR('Time Plan (Single Release)'!$K$6:$K$64*40,0))*('Time Plan (Single Release)'!$D$6:$D$64=$U15))) / SUM('Time Plan (Single Release)'!$Y$6:$JN$64*(IFERROR('Time Plan (Single Release)'!$I$6:$I$64*40,0))*('Time Plan (Single Release)'!$D$6:$D$64=$U15)),"")} | AE15: =SUMIF('Time Plan (Single Release)'!D$6:D$64,Pricing!U15,'Time Plan (Single Release)'!S$6:S$64) -> 0 | AF15: =AE15/8 -> 0 | AG15: =IFERROR(AE15+(AA$8*AI15/W15),"") | AH15: =IFERROR(AG15/8,"")
C16: {=IFERROR(INDEX('Time Plan (Single Release)'!$Y$3:$JN$3, 1, _xlfn.XMATCH(TRUE, _xlfn.BYCOL(('Time Plan (Single Release)'!$Y$6:$JN$64)*('Time Plan (Single Release)'!$B$6:$B$64=$B16), _xlfn.LAMBDA(_xlpm.col, SUM(_xlpm.col)>0)), 0, 1)),"")} | D16: {=IFERROR(INDEX('Time Plan (Single Release)'!$Y$3:$JN$3, 1, _xlfn.XMATCH(TRUE, _xlfn.BYCOL(('Time Plan (Single Release)'!$Y$6:$JN$64)*('Time Plan (Single Release)'!$B$6:$B$64=$B16), _xlfn.LAMBDA(_xlpm.col, SUM(_xlpm.col)>0)), 0,-1))+4,"")} | E16: =IFERROR(DATEDIF('Time Plan (Single Release)'!$Y$3,$D16+3,"d")/7,"") | F16: {=SUM(IFERROR(('Time Plan (Single Release)'!$U$6:$U$64*('Time Plan (Single Release)'!$B$6:$B$64=Pricing!$B16)),0))} -> 0 | G16: =$F16*0.1 -> 0 | H16: =$F16*1.1 -> 0 | I16: {=IFERROR( (SUM('Time Plan (Single Release)'!$Y$6:$JN$64*(IFERROR('Time Plan (Single Release)'!$G$6:$G$64*40,0))*('Time Plan (Single Release)'!$B$6:$B$64=Pricing!$B16)) - SUM('Time Plan (Single Release)'!$Y$6:$JN$64*(IFERROR('Time Plan (Single Release)'!$I$6:$I$64*40,0))*('Time Plan (Single Release)'!$B$6:$B$64=Pricing!$B16))) / SUM('Time Plan (Single Release)'!$Y$6:$JN$64*(IFERROR('Time Plan (Single Release)'!$G$6:$G$64*40,0))*('Time Plan (Single Release)'!$B$6:$B$64=Pricing!$B16)),"")} | J16: {=IFERROR( (SUM('Time Plan (Single Release)'!$Y$6:$JN$64*(IFERROR('Time Plan (Single Release)'!$I$6:$I$64*40,0))*('Time Plan (Single Release)'!$B$6:$B$64=Pricing!$B16)) - SUM('Time Plan (Single Release)'!$Y$6:$JN$64*(IFERROR('Time Plan (Single Release)'!$K$6:$K$64*40,0))*('Time Plan (Single Release)'!$B$6:$B$64=Pricing!$B16))) / SUM('Time Plan (Single Release)'!$Y$6:$JN$64*(IFERROR('Time Plan (Single Release)'!$I$6:$I$64*40,0))*('Time Plan (Single Release)'!$B$6:$B$64=Pricing!$B16)),"")} | M16: {=IFERROR(INDEX('Time Plan (Single Release)'!$Y$3:$JN$3, 1, _xlfn.XMATCH(TRUE, _xlfn.BYCOL(('Time Plan (Single Release)'!$Y$6:$JN$64)*('Time Plan (Single Release)'!$C$6:$C$64=$L16), _xlfn.LAMBDA(_xlpm.col, SUM(_xlpm.col)>0)), 0, 1)),"")} | N16: {=IFERROR(INDEX('Time Plan (Single Release)'!$Y$3:$JN$3, 1, _xlfn.XMATCH(TRUE, _xlfn.BYCOL(('Time Plan (Single Release)'!$Y$6:$JN$64)*('Time Plan (Single Release)'!$C$6:$C$64=$L16), _xlfn.LAMBDA(_xlpm.col, SUM(_xlpm.col)>0)), 0,-1))+4,"")} | O16: {=SUM(IFERROR(('Time Plan (Single Release)'!$U$6:$U$64*('Time Plan (Single Release)'!$C$6:$C$64=$L16)),0))} -> 0 | P16: =IFERROR(O16*0.1,"") -> 0 | Q16: =O16*1.1 -> 0 | R16: {=IFERROR( (SUM('Time Plan (Single Release)'!$Y$6:$JN$64*(IFERROR('Time Plan (Single Release)'!$G$6:$G$64*40,0))*('Time Plan (Single Release)'!$C$6:$C$64=$L16)) - SUM('Time Plan (Single Release)'!$Y$6:$JN$64*(IFERROR('Time Plan (Single Release)'!$I$6:$I$64*40,0))*('Time Plan (Single Release)'!$C$6:$C$64=$L16))) / SUM('Time Plan (Single Release)'!$Y$6:$JN$64*(IFERROR('Time Plan (Single Release)'!$G$6:$G$64*40,0))*('Time Plan (Single Release)'!$C$6:$C$64=$L16)),"")} | S16: {=IFERROR( (SUM('Time Plan (Single Release)'!$Y$6:$JN$64*(IFERROR('Time Plan (Single Release)'!$I$6:$I$64*40,0))*('Time Plan (Single Release)'!$C$6:$C$64=$L16)) - SUM('Time Plan (Single Release)'!$Y$6:$JN$64*(IFERROR('Time Plan (Single Release)'!$K$6:$K$64*40,0))*('Time Plan (Single Release)'!$C$6:$C$64=$L16))) / SUM('Time Plan (Single Release)'!$Y$6:$JN$64*(IFERROR('Time Plan (Single Release)'!$I$6:$I$64*40,0))*('Time Plan (Single Release)'!$C$6:$C$64=$L16)),"")} | V16: {=IFERROR(_xlfn.XLOOKUP($U16,'Time Plan (Single Release)'!$D$6:$D$194,'Time Plan (Single Release)'!$E$6:$E$194&" - "&'Time Plan (Single Release)'!$F$6:$F$194),"")} -> - | W16: =IFERROR(_xlfn.XLOOKUP($U16,'Time Plan (Single Release)'!$D$6:$D$64,'Time Plan (Single Release)'!$I$6:$I$64),"") | X16: =IFERROR(W16*1.1,"") | Y16: {=IFERROR(INDEX('Time Plan (Single Release)'!$Y$3:$JN$3, 1, _xlfn.XMATCH(TRUE, _xlfn.BYCOL(('Time Plan (Single Release)'!$Y$6:$JN$64)*('Time Plan (Single Release)'!$D$6:$D$64=$U16), _xlfn.LAMBDA(_xlpm.col, SUM(_xlpm.col)>0)), 0, 1)),"")} | Z16: {=IFERROR(INDEX('Time Plan (Single Release)'!$Y$3:$JN$3, 1, _xlfn.XMATCH(TRUE, _xlfn.BYCOL(('Time Plan (Single Release)'!$Y$6:$JN$64)*('Time Plan (Single Release)'!$D$6:$D$64=$U16), _xlfn.LAMBDA(_xlpm.col, SUM(_xlpm.col)>0)), 0,-1))+4,"")} | AA16: {=SUM(IFERROR(('Time Plan (Single Release)'!$U$6:$U$64*('Time Plan (Single Release)'!$D$6:$D$64=$U16)),0))} -> 0 | AB16: =AA16*1.1 -> 0 | AC16: {=IFERROR( (SUM('Time Plan (Single Release)'!$Y$6:$JN$64*(IFERROR('Time Plan (Single Release)'!$G$6:$G$64*40,0))*('Time Plan (Single Release)'!$D$6:$D$64=$U16)) - SUM('Time Plan (Single Release)'!$Y$6:$JN$64*(IFERROR('Time Plan (Single Release)'!$I$6:$I$64*40,0))*('Time Plan (Single Release)'!$D$6:$D$64=$U16))) / SUM('Time Plan (Single Release)'!$Y$6:$JN$64*(IFERROR('Time Plan (Single Release)'!$G$6:$G$64*40,0))*('Time Plan (Single Release)'!$D$6:$D$64=$U16)),"")} | AD16: {=IFERROR( (SUM('Time Plan (Single Release)'!$Y$6:$JN$64*(IFERROR('Time Plan (Single Release)'!$I$6:$I$64*40,0))*('Time Plan (Single Release)'!$D$6:$D$64=$U16)) - SUM('Time Plan (Single Release)'!$Y$6:$JN$64*(IFERROR('Time Plan (Single Release)'!$K$6:$K$64*40,0))*('Time Plan (Single Release)'!$D$6:$D$64=$U16))) / SUM('Time Plan (Single Release)'!$Y$6:$JN$64*(IFERROR('Time Plan (Single Release)'!$I$6:$I$64*40,0))*('Time Plan (Single Release)'!$D$6:$D$64=$U16)),"")} | AE16: =SUMIF('Time Plan (Single Release)'!D$6:D$64,Pricing!U16,'Time Plan (Single Release)'!S$6:S$64) -> 0 | AF16: =AE16/8 -> 0 | AG16: =IFERROR(AE16+(AA$8*AI16/W16),"") | AH16: =IFERROR(AG16/8,"")
C17: {=IFERROR(INDEX('Time Plan (Single Release)'!$Y$3:$JN$3, 1, _xlfn.XMATCH(TRUE, _xlfn.BYCOL(('Time Plan (Single Release)'!$Y$6:$JN$64)*('Time Plan (Single Release)'!$B$6:$B$64=$B17), _xlfn.LAMBDA(_xlpm.col, SUM(_xlpm.col)>0)), 0, 1)),"")} | D17: {=IFERROR(INDEX('Time Plan (Single Release)'!$Y$3:$JN$3, 1, _xlfn.XMATCH(TRUE, _xlfn.BYCOL(('Time Plan (Single Release)'!$Y$6:$JN$64)*('Time Plan (Single Release)'!$B$6:$B$64=$B17), _xlfn.LAMBDA(_xlpm.col, SUM(_xlpm.col)>0)), 0,-1))+4,"")} | E17: =IFERROR(DATEDIF('Time Plan (Single Release)'!$Y$3,$D17+3,"d")/7,"") | F17: {=SUM(IFERROR(('Time Plan (Single Release)'!$U$6:$U$64*('Time Plan (Single Release)'!$B$6:$B$64=Pricing!$B17)),0))} -> 0 | G17: =$F17*0.1 -> 0 | H17: =$F17*1.1 -> 0 | I17: {=IFERROR( (SUM('Time Plan (Single Release)'!$Y$6:$JN$64*(IFERROR('Time Plan (Single Release)'!$G$6:$G$64*40,0))*('Time Plan (Single Release)'!$B$6:$B$64=Pricing!$B17)) - SUM('Time Plan (Single Release)'!$Y$6:$JN$64*(IFERROR('Time Plan (Single Release)'!$I$6:$I$64*40,0))*('Time Plan (Single Release)'!$B$6:$B$64=Pricing!$B17))) / SUM('Time Plan (Single Release)'!$Y$6:$JN$64*(IFERROR('Time Plan (Single Release)'!$G$6:$G$64*40,0))*('Time Plan (Single Release)'!$B$6:$B$64=Pricing!$B17)),"")} | J17: {=IFERROR( (SUM('Time Plan (Single Release)'!$Y$6:$JN$64*(IFERROR('Time Plan (Single Release)'!$I$6:$I$64*40,0))*('Time Plan (Single Release)'!$B$6:$B$64=Pricing!$B17)) - SUM('Time Plan (Single Release)'!$Y$6:$JN$64*(IFERROR('Time Plan (Single Release)'!$K$6:$K$64*40,0))*('Time Plan (Single Release)'!$B$6:$B$64=Pricing!$B17))) / SUM('Time Plan (Single Release)'!$Y$6:$JN$64*(IFERROR('Time Plan (Single Release)'!$I$6:$I$64*40,0))*('Time Plan (Single Release)'!$B$6:$B$64=Pricing!$B17)),"")} | M17: {=IFERROR(INDEX('Time Plan (Single Release)'!$Y$3:$JN$3, 1, _xlfn.XMATCH(TRUE, _xlfn.BYCOL(('Time Plan (Single Release)'!$Y$6:$JN$64)*('Time Plan (Single Release)'!$C$6:$C$64=$L17), _xlfn.LAMBDA(_xlpm.col, SUM(_xlpm.col)>0)), 0, 1)),"")} | N17: {=IFERROR(INDEX('Time Plan (Single Release)'!$Y$3:$JN$3, 1, _xlfn.XMATCH(TRUE, _xlfn.BYCOL(('Time Plan (Single Release)'!$Y$6:$JN$64)*('Time Plan (Single Release)'!$C$6:$C$64=$L17), _xlfn.LAMBDA(_xlpm.col, SUM(_xlpm.col)>0)), 0,-1))+4,"")} | O17: {=SUM(IFERROR(('Time Plan (Single Release)'!$U$6:$U$64*('Time Plan (Single Release)'!$C$6:$C$64=$L17)),0))} -> 0 | P17: =IFERROR(O17*0.1,"") -> 0 | Q17: =O17*1.1 -> 0 | R17: {=IFERROR( (SUM('Time Plan (Single Release)'!$Y$6:$JN$64*(IFERROR('Time Plan (Single Release)'!$G$6:$G$64*40,0))*('Time Plan (Single Release)'!$C$6:$C$64=$L17)) - SUM('Time Plan (Single Release)'!$Y$6:$JN$64*(IFERROR('Time Plan (Single Release)'!$I$6:$I$64*40,0))*('Time Plan (Single Release)'!$C$6:$C$64=$L17))) / SUM('Time Plan (Single Release)'!$Y$6:$JN$64*(IFERROR('Time Plan (Single Release)'!$G$6:$G$64*40,0))*('Time Plan (Single Release)'!$C$6:$C$64=$L17)),"")} | S17: {=IFERROR( (SUM('Time Plan (Single Release)'!$Y$6:$JN$64*(IFERROR('Time Plan (Single Release)'!$I$6:$I$64*40,0))*('Time Plan (Single Release)'!$C$6:$C$64=$L17)) - SUM('Time Plan (Single Release)'!$Y$6:$JN$64*(IFERROR('Time Plan (Single Release)'!$K$6:$K$64*40,0))*('Time Plan (Single Release)'!$C$6:$C$64=$L17))) / SUM('Time Plan (Single Release)'!$Y$6:$JN$64*(IFERROR('Time Plan (Single Release)'!$I$6:$I$64*40,0))*('Time Plan (Single Release)'!$C$6:$C$64=$L17)),"")} | V17: {=IFERROR(_xlfn.XLOOKUP($U17,'Time Plan (Single Release)'!$D$6:$D$194,'Time Plan (Single Release)'!$E$6:$E$194&" - "&'Time Plan (Single Release)'!$F$6:$F$194),"")} -> - | W17: =IFERROR(_xlfn.XLOOKUP($U17,'Time Plan (Single Release)'!$D$6:$D$64,'Time Plan (Single Release)'!$I$6:$I$64),"") | X17: =IFERROR(W17*1.1,"") | Y17: {=IFERROR(INDEX('Time Plan (Single Release)'!$Y$3:$JN$3, 1, _xlfn.XMATCH(TRUE, _xlfn.BYCOL(('Time Plan (Single Release)'!$Y$6:$JN$64)*('Time Plan (Single Release)'!$D$6:$D$64=$U17), _xlfn.LAMBDA(_xlpm.col, SUM(_xlpm.col)>0)), 0, 1)),"")} | Z17: {=IFERROR(INDEX('Time Plan (Single Release)'!$Y$3:$JN$3, 1, _xlfn.XMATCH(TRUE, _xlfn.BYCOL(('Time Plan (Single Release)'!$Y$6:$JN$64)*('Time Plan (Single Release)'!$D$6:$D$64=$U17), _xlfn.LAMBDA(_xlpm.col, SUM(_xlpm.col)>0)), 0,-1))+4,"")} | AA17: {=SUM(IFERROR(('Time Plan (Single Release)'!$U$6:$U$64*('Time Plan (Single Release)'!$D$6:$D$64=$U17)),0))} -> 0 | AB17: =AA17*1.1 -> 0 | AC17: {=IFERROR( (SUM('Time Plan (Single Release)'!$Y$6:$JN$64*(IFERROR('Time Plan (Single Release)'!$G$6:$G$64*40,0))*('Time Plan (Single Release)'!$D$6:$D$64=$U17)) - SUM('Time Plan (Single Release)'!$Y$6:$JN$64*(IFERROR('Time Plan (Single Release)'!$I$6:$I$64*40,0))*('Time Plan (Single Release)'!$D$6:$D$64=$U17))) / SUM('Time Plan (Single Release)'!$Y$6:$JN$64*(IFERROR('Time Plan (Single Release)'!$G$6:$G$64*40,0))*('Time Plan (Single Release)'!$D$6:$D$64=$U17)),"")} | AD17: {=IFERROR( (SUM('Time Plan (Single Release)'!$Y$6:$JN$64*(IFERROR('Time Plan (Single Release)'!$I$6:$I$64*40,0))*('Time Plan (Single Release)'!$D$6:$D$64=$U17)) - SUM('Time Plan (Single Release)'!$Y$6:$JN$64*(IFERROR('Time Plan (Single Release)'!$K$6:$K$64*40,0))*('Time Plan (Single Release)'!$D$6:$D$64=$U17))) / SUM('Time Plan (Single Release)'!$Y$6:$JN$64*(IFERROR('Time Plan (Single Release)'!$I$6:$I$64*40,0))*('Time Plan (Single Release)'!$D$6:$D$64=$U17)),"")} | AE17: =SUMIF('Time Plan (Single Release)'!D$6:D$64,Pricing!U17,'Time Plan (Single Release)'!S$6:S$64) -> 0 | AF17: =AE17/8 -> 0 | AG17: =IFERROR(AE17+(AA$8*AI17/W17),"") | AH17: =IFERROR(AG17/8,"")
C18: {=IFERROR(INDEX('Time Plan (Single Release)'!$Y$3:$JN$3, 1, _xlfn.XMATCH(TRUE, _xlfn.BYCOL(('Time Plan (Single Release)'!$Y$6:$JN$64)*('Time Plan (Single Release)'!$B$6:$B$64=$B18), _xlfn.LAMBDA(_xlpm.col, SUM(_xlpm.col)>0)), 0, 1)),"")} | D18: {=IFERROR(INDEX('Time Plan (Single Release)'!$Y$3:$JN$3, 1, _xlfn.XMATCH(TRUE, _xlfn.BYCOL(('Time Plan (Single Release)'!$Y$6:$JN$64)*('Time Plan (Single Release)'!$B$6:$B$64=$B18), _xlfn.LAMBDA(_xlpm.col, SUM(_xlpm.col)>0)), 0,-1))+4,"")} | E18: =IFERROR(DATEDIF('Time Plan (Single Release)'!$Y$3,$D18+3,"d")/7,"") | F18: {=SUM(IFERROR(('Time Plan (Single Release)'!$U$6:$U$64*('Time Plan (Single Release)'!$B$6:$B$64=Pricing!$B18)),0))} -> 0 | G18: =$F18*0.1 -> 0 | H18: =$F18*1.1 -> 0 | I18: {=IFERROR( (SUM('Time Plan (Single Release)'!$Y$6:$JN$64*(IFERROR('Time Plan (Single Release)'!$G$6:$G$64*40,0))*('Time Plan (Single Release)'!$B$6:$B$64=Pricing!$B18)) - SUM('Time Plan (Single Release)'!$Y$6:$JN$64*(IFERROR('Time Plan (Single Release)'!$I$6:$I$64*40,0))*('Time Plan (Single Release)'!$B$6:$B$64=Pricing!$B18))) / SUM('Time Plan (Single Release)'!$Y$6:$JN$64*(IFERROR('Time Plan (Single Release)'!$G$6:$G$64*40,0))*('Time Plan (Single Release)'!$B$6:$B$64=Pricing!$B18)),"")} | J18: {=IFERROR( (SUM('Time Plan (Single Release)'!$Y$6:$JN$64*(IFERROR('Time Plan (Single Release)'!$I$6:$I$64*40,0))*('Time Plan (Single Release)'!$B$6:$B$64=Pricing!$B18)) - SUM('Time Plan (Single Release)'!$Y$6:$JN$64*(IFERROR('Time Plan (Single Release)'!$K$6:$K$64*40,0))*('Time Plan (Single Release)'!$B$6:$B$64=Pricing!$B18))) / SUM('Time Plan (Single Release)'!$Y$6:$JN$64*(IFERROR('Time Plan (Single Release)'!$I$6:$I$64*40,0))*('Time Plan (Single Release)'!$B$6:$B$64=Pricing!$B18)),"")} | M18: {=IFERROR(INDEX('Time Plan (Single Release)'!$Y$3:$JN$3, 1, _xlfn.XMATCH(TRUE, _xlfn.BYCOL(('Time Plan (Single Release)'!$Y$6:$JN$64)*('Time Plan (Single Release)'!$C$6:$C$64=$L18), _xlfn.LAMBDA(_xlpm.col, SUM(_xlpm.col)>0)), 0, 1)),"")} | N18: {=IFERROR(INDEX('Time Plan (Single Release)'!$Y$3:$JN$3, 1, _xlfn.XMATCH(TRUE, _xlfn.BYCOL(('Time Plan (Single Release)'!$Y$6:$JN$64)*('Time Plan (Single Release)'!$C$6:$C$64=$L18), _xlfn.LAMBDA(_xlpm.col, SUM(_xlpm.col)>0)), 0,-1))+4,"")} | O18: {=SUM(IFERROR(('Time Plan (Single Release)'!$U$6:$U$64*('Time Plan (Single Release)'!$C$6:$C$64=$L18)),0))} -> 0 | P18: =IFERROR(O18*0.1,"") -> 0 | Q18: =O18*1.1 -> 0 | R18: {=IFERROR( (SUM('Time Plan (Single Release)'!$Y$6:$JN$64*(IFERROR('Time Plan (Single Release)'!$G$6:$G$64*40,0))*('Time Plan (Single Release)'!$C$6:$C$64=$L18)) - SUM('Time Plan (Single Release)'!$Y$6:$JN$64*(IFERROR('Time Plan (Single Release)'!$I$6:$I$64*40,0))*('Time Plan (Single Release)'!$C$6:$C$64=$L18))) / SUM('Time Plan (Single Release)'!$Y$6:$JN$64*(IFERROR('Time Plan (Single Release)'!$G$6:$G$64*40,0))*('Time Plan (Single Release)'!$C$6:$C$64=$L18)),"")} | S18: {=IFERROR( (SUM('Time Plan (Single Release)'!$Y$6:$JN$64*(IFERROR('Time Plan (Single Release)'!$I$6:$I$64*40,0))*('Time Plan (Single Release)'!$C$6:$C$64=$L18)) - SUM('Time Plan (Single Release)'!$Y$6:$JN$64*(IFERROR('Time Plan (Single Release)'!$K$6:$K$64*40,0))*('Time Plan (Single Release)'!$C$6:$C$64=$L18))) / SUM('Time Plan (Single Release)'!$Y$6:$JN$64*(IFERROR('Time Plan (Single Release)'!$I$6:$I$64*40,0))*('Time Plan (Single Release)'!$C$6:$C$64=$L18)),"")} | V18: {=IFERROR(_xlfn.XLOOKUP($U18,'Time Plan (Single Release)'!$D$6:$D$194,'Time Plan (Single Release)'!$E$6:$E$194&" - "&'Time Plan (Single Release)'!$F$6:$F$194),"")} -> - | W18: =IFERROR(_xlfn.XLOOKUP($U18,'Time Plan (Single Release)'!$D$6:$D$64,'Time Plan (Single Release)'!$I$6:$I$64),"") | X18: =IFERROR(W18*1.1,"") | Y18: {=IFERROR(INDEX('Time Plan (Single Release)'!$Y$3:$JN$3, 1, _xlfn.XMATCH(TRUE, _xlfn.BYCOL(('Time Plan (Single Release)'!$Y$6:$JN$64)*('Time Plan (Single Release)'!$D$6:$D$64=$U18), _xlfn.LAMBDA(_xlpm.col, SUM(_xlpm.col)>0)), 0, 1)),"")} | Z18: {=IFERROR(INDEX('Time Plan (Single Release)'!$Y$3:$JN$3, 1, _xlfn.XMATCH(TRUE, _xlfn.BYCOL(('Time Plan (Single Release)'!$Y$6:$JN$64)*('Time Plan (Single Release)'!$D$6:$D$64=$U18), _xlfn.LAMBDA(_xlpm.col, SUM(_xlpm.col)>0)), 0,-1))+4,"")} | AA18: {=SUM(IFERROR(('Time Plan (Single Release)'!$U$6:$U$64*('Time Plan (Single Release)'!$D$6:$D$64=$U18)),0))} -> 0 | AB18: =AA18*1.1 -> 0 | AC18: {=IFERROR( (SUM('Time Plan (Single Release)'!$Y$6:$JN$64*(IFERROR('Time Plan (Single Release)'!$G$6:$G$64*40,0))*('Time Plan (Single Release)'!$D$6:$D$64=$U18)) - SUM('Time Plan (Single Release)'!$Y$6:$JN$64*(IFERROR('Time Plan (Single Release)'!$I$6:$I$64*40,0))*('Time Plan (Single Release)'!$D$6:$D$64=$U18))) / SUM('Time Plan (Single Release)'!$Y$6:$JN$64*(IFERROR('Time Plan (Single Release)'!$G$6:$G$64*40,0))*('Time Plan (Single Release)'!$D$6:$D$64=$U18)),"")} | AD18: {=IFERROR( (SUM('Time Plan (Single Release)'!$Y$6:$JN$64*(IFERROR('Time Plan (Single Release)'!$I$6:$I$64*40,0))*('Time Plan (Single Release)'!$D$6:$D$64=$U18)) - SUM('Time Plan (Single Release)'!$Y$6:$JN$64*(IFERROR('Time Plan (Single Release)'!$K$6:$K$64*40,0))*('Time Plan (Single Release)'!$D$6:$D$64=$U18))) / SUM('Time Plan (Single Release)'!$Y$6:$JN$64*(IFERROR('Time Plan (Single Release)'!$I$6:$I$64*40,0))*('Time Plan (Single Release)'!$D$6:$D$64=$U18)),"")} | AE18: =SUMIF('Time Plan (Single Release)'!D$6:D$64,Pricing!U18,'Time Plan (Single Release)'!S$6:S$64) -> 0 | AF18: =AE18/8 -> 0 | AG18: =IFERROR(AE18+(AA$8*AI18/W18),"") | AH18: =IFERROR(AG18/8,"")
C19: {=IFERROR(INDEX('Time Plan (Single Release)'!$Y$3:$JN$3, 1, _xlfn.XMATCH(TRUE, _xlfn.BYCOL(('Time Plan (Single Release)'!$Y$6:$JN$64)*('Time Plan (Single Release)'!$B$6:$B$64=$B19), _xlfn.LAMBDA(_xlpm.col, SUM(_xlpm.col)>0)), 0, 1)),"")} | D19: {=IFERROR(INDEX('Time Plan (Single Release)'!$Y$3:$JN$3, 1, _xlfn.XMATCH(TRUE, _xlfn.BYCOL(('Time Plan (Single Release)'!$Y$6:$JN$64)*('Time Plan (Single Release)'!$B$6:$B$64=$B19), _xlfn.LAMBDA(_xlpm.col, SUM(_xlpm.col)>0)), 0,-1))+4,"")} | E19: =IFERROR(DATEDIF('Time Plan (Single Release)'!$Y$3,$D19+3,"d")/7,"") | F19: {=SUM(IFERROR(('Time Plan (Single Release)'!$U$6:$U$64*('Time Plan (Single Release)'!$B$6:$B$64=Pricing!$B19)),0))} -> 0 | G19: =$F19*0.1 -> 0 | H19: =$F19*1.1 -> 0 | I19: {=IFERROR( (SUM('Time Plan (Single Release)'!$Y$6:$JN$64*(IFERROR('Time Plan (Single Release)'!$G$6:$G$64*40,0))*('Time Plan (Single Release)'!$B$6:$B$64=Pricing!$B19)) - SUM('Time Plan (Single Release)'!$Y$6:$JN$64*(IFERROR('Time Plan (Single Release)'!$I$6:$I$64*40,0))*('Time Plan (Single Release)'!$B$6:$B$64=Pricing!$B19))) / SUM('Time Plan (Single Release)'!$Y$6:$JN$64*(IFERROR('Time Plan (Single Release)'!$G$6:$G$64*40,0))*('Time Plan (Single Release)'!$B$6:$B$64=Pricing!$B19)),"")} | J19: {=IFERROR( (SUM('Time Plan (Single Release)'!$Y$6:$JN$64*(IFERROR('Time Plan (Single Release)'!$I$6:$I$64*40,0))*('Time Plan (Single Release)'!$B$6:$B$64=Pricing!$B19)) - SUM('Time Plan (Single Release)'!$Y$6:$JN$64*(IFERROR('Time Plan (Single Release)'!$K$6:$K$64*40,0))*('Time Plan (Single Release)'!$B$6:$B$64=Pricing!$B19))) / SUM('Time Plan (Single Release)'!$Y$6:$JN$64*(IFERROR('Time Plan (Single Release)'!$I$6:$I$64*40,0))*('Time Plan (Single Release)'!$B$6:$B$64=Pricing!$B19)),"")} | M19: {=IFERROR(INDEX('Time Plan (Single Release)'!$Y$3:$JN$3, 1, _xlfn.XMATCH(TRUE, _xlfn.BYCOL(('Time Plan (Single Release)'!$Y$6:$JN$64)*('Time Plan (Single Release)'!$C$6:$C$64=$L19), _xlfn.LAMBDA(_xlpm.col, SUM(_xlpm.col)>0)), 0, 1)),"")} | N19: {=IFERROR(INDEX('Time Plan (Single Release)'!$Y$3:$JN$3, 1, _xlfn.XMATCH(TRUE, _xlfn.BYCOL(('Time Plan (Single Release)'!$Y$6:$JN$64)*('Time Plan (Single Release)'!$C$6:$C$64=$L19), _xlfn.LAMBDA(_xlpm.col, SUM(_xlpm.col)>0)), 0,-1))+4,"")} | O19: {=SUM(IFERROR(('Time Plan (Single Release)'!$U$6:$U$64*('Time Plan (Single Release)'!$C$6:$C$64=$L19)),0))} -> 0 | P19: =IFERROR(O19*0.1,"") -> 0 | Q19: =O19*1.1 -> 0 | R19: {=IFERROR( (SUM('Time Plan (Single Release)'!$Y$6:$JN$64*(IFERROR('Time Plan (Single Release)'!$G$6:$G$64*40,0))*('Time Plan (Single Release)'!$C$6:$C$64=$L19)) - SUM('Time Plan (Single Release)'!$Y$6:$JN$64*(IFERROR('Time Plan (Single Release)'!$I$6:$I$64*40,0))*('Time Plan (Single Release)'!$C$6:$C$64=$L19))) / SUM('Time Plan (Single Release)'!$Y$6:$JN$64*(IFERROR('Time Plan (Single Release)'!$G$6:$G$64*40,0))*('Time Plan (Single Release)'!$C$6:$C$64=$L19)),"")} | S19: {=IFERROR( (SUM('Time Plan (Single Release)'!$Y$6:$JN$64*(IFERROR('Time Plan (Single Release)'!$I$6:$I$64*40,0))*('Time Plan (Single Release)'!$C$6:$C$64=$L19)) - SUM('Time Plan (Single Release)'!$Y$6:$JN$64*(IFERROR('Time Plan (Single Release)'!$K$6:$K$64*40,0))*('Time Plan (Single Release)'!$C$6:$C$64=$L19))) / SUM('Time Plan (Single Release)'!$Y$6:$JN$64*(IFERROR('Time Plan (Single Release)'!$I$6:$I$64*40,0))*('Time Plan (Single Release)'!$C$6:$C$64=$L19)),"")} | V19: {=IFERROR(_xlfn.XLOOKUP($U19,'Time Plan (Single Release)'!$D$6:$D$194,'Time Plan (Single Release)'!$E$6:$E$194&" - "&'Time Plan (Single Release)'!$F$6:$F$194),"")} -> - | W19: =IFERROR(_xlfn.XLOOKUP($U19,'Time Plan (Single Release)'!$D$6:$D$64,'Time Plan (Single Release)'!$I$6:$I$64),"") | X19: =IFERROR(W19*1.1,"") | Y19: {=IFERROR(INDEX('Time Plan (Single Release)'!$Y$3:$JN$3, 1, _xlfn.XMATCH(TRUE, _xlfn.BYCOL(('Time Plan (Single Release)'!$Y$6:$JN$64)*('Time Plan (Single Release)'!$D$6:$D$64=$U19), _xlfn.LAMBDA(_xlpm.col, SUM(_xlpm.col)>0)), 0, 1)),"")} | Z19: {=IFERROR(INDEX('Time Plan (Single Release)'!$Y$3:$JN$3, 1, _xlfn.XMATCH(TRUE, _xlfn.BYCOL(('Time Plan (Single Release)'!$Y$6:$JN$64)*('Time Plan (Single Release)'!$D$6:$D$64=$U19), _xlfn.LAMBDA(_xlpm.col, SUM(_xlpm.col)>0)), 0,-1))+4,"")} | AA19: {=SUM(IFERROR(('Time Plan (Single Release)'!$U$6:$U$64*('Time Plan (Single Release)'!$D$6:$D$64=$U19)),0))} -> 0 | AB19: =AA19*1.1 -> 0 | AC19: {=IFERROR( (SUM('Time Plan (Single Release)'!$Y$6:$JN$64*(IFERROR('Time Plan (Single Release)'!$G$6:$G$64*40,0))*('Time Plan (Single Release)'!$D$6:$D$64=$U19)) - SUM('Time Plan (Single Release)'!$Y$6:$JN$64*(IFERROR('Time Plan (Single Release)'!$I$6:$I$64*40,0))*('Time Plan (Single Release)'!$D$6:$D$64=$U19))) / SUM('Time Plan (Single Release)'!$Y$6:$JN$64*(IFERROR('Time Plan (Single Release)'!$G$6:$G$64*40,0))*('Time Plan (Single Release)'!$D$6:$D$64=$U19)),"")} | AD19: {=IFERROR( (SUM('Time Plan (Single Release)'!$Y$6:$JN$64*(IFERROR('Time Plan (Single Release)'!$I$6:$I$64*40,0))*('Time Plan (Single Release)'!$D$6:$D$64=$U19)) - SUM('Time Plan (Single Release)'!$Y$6:$JN$64*(IFERROR('Time Plan (Single Release)'!$K$6:$K$64*40,0))*('Time Plan (Single Release)'!$D$6:$D$64=$U19))) / SUM('Time Plan (Single Release)'!$Y$6:$JN$64*(IFERROR('Time Plan (Single Release)'!$I$6:$I$64*40,0))*('Time Plan (Single Release)'!$D$6:$D$64=$U19)),"")} | AE19: =SUMIF('Time Plan (Single Release)'!D$6:D$64,Pricing!U19,'Time Plan (Single Release)'!S$6:S$64) -> 0 | AF19: =AE19/8 -> 0 | AG19: =IFERROR(AE19+(AA$8*AI19/W19),"") | AH19: =IFERROR(AG19/8,"")
M20: {=IFERROR(INDEX('Time Plan (Single Release)'!$Y$3:$JN$3, 1, _xlfn.XMATCH(TRUE, _xlfn.BYCOL(('Time Plan (Single Release)'!$Y$6:$JN$64)*('Time Plan (Single Release)'!$C$6:$C$64=$L20), _xlfn.LAMBDA(_xlpm.col, SUM(_xlpm.col)>0)), 0, 1)),"")} | N20: {=IFERROR(INDEX('Time Plan (Single Release)'!$Y$3:$JN$3, 1, _xlfn.XMATCH(TRUE, _xlfn.BYCOL(('Time Plan (Single Release)'!$Y$6:$JN$64)*('Time Plan (Single Release)'!$C$6:$C$64=$L20), _xlfn.LAMBDA(_xlpm.col, SUM(_xlpm.col)>0)), 0,-1))+4,"")} | O20: {=SUM(IFERROR(('Time Plan (Single Release)'!$U$6:$U$64*('Time Plan (Single Release)'!$C$6:$C$64=$L20)),0))} -> 0 | P20: =IFERROR(O20*0.1,"") -> 0 | Q20: =O20*1.1 -> 0 | R20: {=IFERROR( (SUM('Time Plan (Single Release)'!$Y$6:$JN$64*(IFERROR('Time Plan (Single Release)'!$G$6:$G$64*40,0))*('Time Plan (Single Release)'!$C$6:$C$64=$L20)) - SUM('Time Plan (Single Release)'!$Y$6:$JN$64*(IFERROR('Time Plan (Single Release)'!$I$6:$I$64*40,0))*('Time Plan (Single Release)'!$C$6:$C$64=$L20))) / SUM('Time Plan (Single Release)'!$Y$6:$JN$64*(IFERROR('Time Plan (Single Release)'!$G$6:$G$64*40,0))*('Time Plan (Single Release)'!$C$6:$C$64=$L20)),"")} | S20: {=IFERROR( (SUM('Time Plan (Single Release)'!$Y$6:$JN$64*(IFERROR('Time Plan (Single Release)'!$I$6:$I$64*40,0))*('Time Plan (Single Release)'!$C$6:$C$64=$L20)) - SUM('Time Plan (Single Release)'!$Y$6:$JN$64*(IFERROR('Time Plan (Single Release)'!$K$6:$K$64*40,0))*('Time Plan (Single Release)'!$C$6:$C$64=$L20))) / SUM('Time Plan (Single Release)'!$Y$6:$JN$64*(IFERROR('Time Plan (Single Release)'!$I$6:$I$64*40,0))*('Time Plan (Single Release)'!$C$6:$C$64=$L20)),"")} | AA20: {=SUM(IFERROR(('Time Plan (Single Release)'!$U$6:$U$64*('Time Plan (Single Release)'!$D$6:$D$64=$U20)),0))} -> 0 | AB20: =AA20*1.1 -> 0
M21: {=IFERROR(INDEX('Time Plan (Single Release)'!$Y$3:$JN$3, 1, _xlfn.XMATCH(TRUE, _xlfn.BYCOL(('Time Plan (Single Release)'!$Y$6:$JN$64)*('Time Plan (Single Release)'!$C$6:$C$64=$L21), _xlfn.LAMBDA(_xlpm.col, SUM(_xlpm.col)>0)), 0, 1)),"")} | N21: {=IFERROR(INDEX('Time Plan (Single Release)'!$Y$3:$JN$3, 1, _xlfn.XMATCH(TRUE, _xlfn.BYCOL(('Time Plan (Single Release)'!$Y$6:$JN$64)*('Time Plan (Single Release)'!$C$6:$C$64=$L21), _xlfn.LAMBDA(_xlpm.col, SUM(_xlpm.col)>0)), 0,-1))+4,"")} | O21: {=SUM(IFERROR(('Time Plan (Single Release)'!$U$6:$U$64*('Time Plan (Single Release)'!$C$6:$C$64=$L21)),0))} -> 0 | P21: =IFERROR(O21*0.1,"") -> 0 | Q21: =O21*1.1 -> 0 | R21: {=IFERROR( (SUM('Time Plan (Single Release)'!$Y$6:$JN$64*(IFERROR('Time Plan (Single Release)'!$G$6:$G$64*40,0))*('Time Plan (Single Release)'!$C$6:$C$64=$L21)) - SUM('Time Plan (Single Release)'!$Y$6:$JN$64*(IFERROR('Time Plan (Single Release)'!$I$6:$I$64*40,0))*('Time Plan (Single Release)'!$C$6:$C$64=$L21))) / SUM('Time Plan (Single Release)'!$Y$6:$JN$64*(IFERROR('Time Plan (Single Release)'!$G$6:$G$64*40,0))*('Time Plan (Single Release)'!$C$6:$C$64=$L21)),"")} | S21: {=IFERROR( (SUM('Time Plan (Single Release)'!$Y$6:$JN$64*(IFERROR('Time Plan (Single Release)'!$I$6:$I$64*40,0))*('Time Plan (Single Release)'!$C$6:$C$64=$L21)) - SUM('Time Plan (Single Release)'!$Y$6:$JN$64*(IFERROR('Time Plan (Single Release)'!$K$6:$K$64*40,0))*('Time Plan (Single Release)'!$C$6:$C$64=$L21))) / SUM('Time Plan (Single Release)'!$Y$6:$JN$64*(IFERROR('Time Plan (Single Release)'!$I$6:$I$64*40,0))*('Time Plan (Single Release)'!$C$6:$C$64=$L21)),"")} | AA21: {=SUM(IFERROR(('Time Plan (Single Release)'!$U$6:$U$64*('Time Plan (Single Release)'!$D$6:$D$64=$U21)),0))} -> 0 | AB21: =AA21*1.1 -> 0
M22: {=IFERROR(INDEX('Time Plan (Single Release)'!$Y$3:$JN$3, 1, _xlfn.XMATCH(TRUE, _xlfn.BYCOL(('Time Plan (Single Release)'!$Y$6:$JN$64)*('Time Plan (Single Release)'!$C$6:$C$64=$L22), _xlfn.LAMBDA(_xlpm.col, SUM(_xlpm.col)>0)), 0, 1)),"")} | N22: {=IFERROR(INDEX('Time Plan (Single Release)'!$Y$3:$JN$3, 1, _xlfn.XMATCH(TRUE, _xlfn.BYCOL(('Time Plan (Single Release)'!$Y$6:$JN$64)*('Time Plan (Single Release)'!$C$6:$C$64=$L22), _xlfn.LAMBDA(_xlpm.col, SUM(_xlpm.col)>0)), 0,-1))+4,"")} | O22: {=SUM(IFERROR(('Time Plan (Single Release)'!$U$6:$U$64*('Time Plan (Single Release)'!$C$6:$C$64=$L22)),0))} -> 0 | P22: =IFERROR(O22*0.1,"") -> 0 | Q22: =O22*1.1 -> 0 | R22: {=IFERROR( (SUM('Time Plan (Single Release)'!$Y$6:$JN$64*(IFERROR('Time Plan (Single Release)'!$G$6:$G$64*40,0))*('Time Plan (Single Release)'!$C$6:$C$64=$L22)) - SUM('Time Plan (Single Release)'!$Y$6:$JN$64*(IFERROR('Time Plan (Single Release)'!$I$6:$I$64*40,0))*('Time Plan (Single Release)'!$C$6:$C$64=$L22))) / SUM('Time Plan (Single Release)'!$Y$6:$JN$64*(IFERROR('Time Plan (Single Release)'!$G$6:$G$64*40,0))*('Time Plan (Single Release)'!$C$6:$C$64=$L22)),"")} | S22: {=IFERROR( (SUM('Time Plan (Single Release)'!$Y$6:$JN$64*(IFERROR('Time Plan (Single Release)'!$I$6:$I$64*40,0))*('Time Plan (Single Release)'!$C$6:$C$64=$L22)) - SUM('Time Plan (Single Release)'!$Y$6:$JN$64*(IFERROR('Time Plan (Single Release)'!$K$6:$K$64*40,0))*('Time Plan (Single Release)'!$C$6:$C$64=$L22))) / SUM('Time Plan (Single Release)'!$Y$6:$JN$64*(IFERROR('Time Plan (Single Release)'!$I$6:$I$64*40,0))*('Time Plan (Single Release)'!$C$6:$C$64=$L22)),"")} | AA22: {=SUM(IFERROR(('Time Plan (Single Release)'!$U$6:$U$64*('Time Plan (Single Release)'!$D$6:$D$64=$U22)),0))} -> 0 | AB22: =AA22*1.1 -> 0
M23: {=IFERROR(INDEX('Time Plan (Single Release)'!$Y$3:$JN$3, 1, _xlfn.XMATCH(TRUE, _xlfn.BYCOL(('Time Plan (Single Release)'!$Y$6:$JN$64)*('Time Plan (Single Release)'!$C$6:$C$64=$L23), _xlfn.LAMBDA(_xlpm.col, SUM(_xlpm.col)>0)), 0, 1)),"")} | N23: {=IFERROR(INDEX('Time Plan (Single Release)'!$Y$3:$JN$3, 1, _xlfn.XMATCH(TRUE, _xlfn.BYCOL(('Time Plan (Single Release)'!$Y$6:$JN$64)*('Time Plan (Single Release)'!$C$6:$C$64=$L23), _xlfn.LAMBDA(_xlpm.col, SUM(_xlpm.col)>0)), 0,-1))+4,"")} | O23: {=SUM(IFERROR(('Time Plan (Single Release)'!$U$6:$U$64*('Time Plan (Single Release)'!$C$6:$C$64=$L23)),0))} -> 0 | P23: =IFERROR(O23*0.1,"") -> 0 | Q23: =O23*1.1 -> 0 | R23: {=IFERROR( (SUM('Time Plan (Single Release)'!$Y$6:$JN$64*(IFERROR('Time Plan (Single Release)'!$G$6:$G$64*40,0))*('Time Plan (Single Release)'!$C$6:$C$64=$L23)) - SUM('Time Plan (Single Release)'!$Y$6:$JN$64*(IFERROR('Time Plan (Single Release)'!$I$6:$I$64*40,0))*('Time Plan (Single Release)'!$C$6:$C$64=$L23))) / SUM('Time Plan (Single Release)'!$Y$6:$JN$64*(IFERROR('Time Plan (Single Release)'!$G$6:$G$64*40,0))*('Time Plan (Single Release)'!$C$6:$C$64=$L23)),"")} | S23: {=IFERROR( (SUM('Time Plan (Single Release)'!$Y$6:$JN$64*(IFERROR('Time Plan (Single Release)'!$I$6:$I$64*40,0))*('Time Plan (Single Release)'!$C$6:$C$64=$L23)) - SUM('Time Plan (Single Release)'!$Y$6:$JN$64*(IFERROR('Time Plan (Single Release)'!$K$6:$K$64*40,0))*('Time Plan (Single Release)'!$C$6:$C$64=$L23))) / SUM('Time Plan (Single Release)'!$Y$6:$JN$64*(IFERROR('Time Plan (Single Release)'!$I$6:$I$64*40,0))*('Time Plan (Single Release)'!$C$6:$C$64=$L23)),"")} | AA23: {=SUM(IFERROR(('Time Plan (Single Release)'!$U$6:$U$64*('Time Plan (Single Release)'!$D$6:$D$64=$U23)),0))} -> 0 | AB23: =AA23*1.1 -> 0
M24: {=IFERROR(INDEX('Time Plan (Single Release)'!$Y$3:$JN$3, 1, _xlfn.XMATCH(TRUE, _xlfn.BYCOL(('Time Plan (Single Release)'!$Y$6:$JN$64)*('Time Plan (Single Release)'!$C$6:$C$64=$L24), _xlfn.LAMBDA(_xlpm.col, SUM(_xlpm.col)>0)), 0, 1)),"")} | N24: {=IFERROR(INDEX('Time Plan (Single Release)'!$Y$3:$JN$3, 1, _xlfn.XMATCH(TRUE, _xlfn.BYCOL(('Time Plan (Single Release)'!$Y$6:$JN$64)*('Time Plan (Single Release)'!$C$6:$C$64=$L24), _xlfn.LAMBDA(_xlpm.col, SUM(_xlpm.col)>0)), 0,-1))+4,"")} | O24: {=SUM(IFERROR(('Time Plan (Single Release)'!$U$6:$U$64*('Time Plan (Single Release)'!$C$6:$C$64=$L24)),0))} -> 0 | P24: =IFERROR(O24*0.1,"") -> 0 | Q24: =O24*1.1 -> 0 | R24: {=IFERROR( (SUM('Time Plan (Single Release)'!$Y$6:$JN$64*(IFERROR('Time Plan (Single Release)'!$G$6:$G$64*40,0))*('Time Plan (Single Release)'!$C$6:$C$64=$L24)) - SUM('Time Plan (Single Release)'!$Y$6:$JN$64*(IFERROR('Time Plan (Single Release)'!$I$6:$I$64*40,0))*('Time Plan (Single Release)'!$C$6:$C$64=$L24))) / SUM('Time Plan (Single Release)'!$Y$6:$JN$64*(IFERROR('Time Plan (Single Release)'!$G$6:$G$64*40,0))*('Time Plan (Single Release)'!$C$6:$C$64=$L24)),"")} | S24: {=IFERROR( (SUM('Time Plan (Single Release)'!$Y$6:$JN$64*(IFERROR('Time Plan (Single Release)'!$I$6:$I$64*40,0))*('Time Plan (Single Release)'!$C$6:$C$64=$L24)) - SUM('Time Plan (Single Release)'!$Y$6:$JN$64*(IFERROR('Time Plan (Single Release)'!$K$6:$K$64*40,0))*('Time Plan (Single Release)'!$C$6:$C$64=$L24))) / SUM('Time Plan (Single Release)'!$Y$6:$JN$64*(IFERROR('Time Plan (Single Release)'!$I$6:$I$64*40,0))*('Time Plan (Single Release)'!$C$6:$C$64=$L24)),"")} | AA24: {=SUM(IFERROR(('Time Plan (Single Release)'!$U$6:$U$64*('Time Plan (Single Release)'!$D$6:$D$64=$U24)),0))} -> 0 | AB24: =AA24*1.1 -> 0
M25: {=IFERROR(INDEX('Time Plan (Single Release)'!$Y$3:$JN$3, 1, _xlfn.XMATCH(TRUE, _xlfn.BYCOL(('Time Plan (Single Release)'!$Y$6:$JN$64)*('Time Plan (Single Release)'!$C$6:$C$64=$L25), _xlfn.LAMBDA(_xlpm.col, SUM(_xlpm.col)>0)), 0, 1)),"")} | N25: {=IFERROR(INDEX('Time Plan (Single Release)'!$Y$3:$JN$3, 1, _xlfn.XMATCH(TRUE, _xlfn.BYCOL(('Time Plan (Single Release)'!$Y$6:$JN$64)*('Time Plan (Single Release)'!$C$6:$C$64=$L25), _xlfn.LAMBDA(_xlpm.col, SUM(_xlpm.col)>0)), 0,-1))+4,"")} | O25: {=SUM(IFERROR(('Time Plan (Single Release)'!$U$6:$U$64*('Time Plan (Single Release)'!$C$6:$C$64=$L25)),0))} -> 0 | P25: =IFERROR(O25*0.1,"") -> 0 | Q25: =O25*1.1 -> 0 | R25: {=IFERROR( (SUM('Time Plan (Single Release)'!$Y$6:$JN$64*(IFERROR('Time Plan (Single Release)'!$G$6:$G$64*40,0))*('Time Plan (Single Release)'!$C$6:$C$64=$L25)) - SUM('Time Plan (Single Release)'!$Y$6:$JN$64*(IFERROR('Time Plan (Single Release)'!$I$6:$I$64*40,0))*('Time Plan (Single Release)'!$C$6:$C$64=$L25))) / SUM('Time Plan (Single Release)'!$Y$6:$JN$64*(IFERROR('Time Plan (Single Release)'!$G$6:$G$64*40,0))*('Time Plan (Single Release)'!$C$6:$C$64=$L25)),"")} | S25: {=IFERROR( (SUM('Time Plan (Single Release)'!$Y$6:$JN$64*(IFERROR('Time Plan (Single Release)'!$I$6:$I$64*40,0))*('Time Plan (Single Release)'!$C$6:$C$64=$L25)) - SUM('Time Plan (Single Release)'!$Y$6:$JN$64*(IFERROR('Time Plan (Single Release)'!$K$6:$K$64*40,0))*('Time Plan (Single Release)'!$C$6:$C$64=$L25))) / SUM('Time Plan (Single Release)'!$Y$6:$JN$64*(IFERROR('Time Plan (Single Release)'!$I$6:$I$64*40,0))*('Time Plan (Single Release)'!$C$6:$C$64=$L25)),"")} | V25: {=IFERROR(_xlfn.XLOOKUP($U25,'Time Plan (Single Release)'!$D$6:$D$194,'Time Plan (Single Release)'!$E$6:$E$194&" - "&'Time Plan (Single Release)'!$F$6:$F$194),"")} -> - | AA25: {=SUM(IFERROR(('Time Plan (Single Release)'!$U$6:$U$64*('Time Plan (Single Release)'!$D$6:$D$64=$U25)),0))} -> 0 | AB25: =AA25*1.1 -> 0 | AE25: =SUMIF('Time Plan (Single Release)'!D$6:D$64,Pricing!U25,'Time Plan (Single Release)'!S$6:S$64) -> 0 | AF25: =AE25/8 -> 0 | AG25: =IFERROR(AE25+(AA$8*AI25/W25),"") | AH25: =IFERROR(AG25/8,"")
M26: {=IFERROR(INDEX('Time Plan (Single Release)'!$Y$3:$JN$3, 1, _xlfn.XMATCH(TRUE, _xlfn.BYCOL(('Time Plan (Single Release)'!$Y$6:$JN$64)*('Time Plan (Single Release)'!$C$6:$C$64=$L26), _xlfn.LAMBDA(_xlpm.col, SUM(_xlpm.col)>0)), 0, 1)),"")} | N26: {=IFERROR(INDEX('Time Plan (Single Release)'!$Y$3:$JN$3, 1, _xlfn.XMATCH(TRUE, _xlfn.BYCOL(('Time Plan (Single Release)'!$Y$6:$JN$64)*('Time Plan (Single Release)'!$C$6:$C$64=$L26), _xlfn.LAMBDA(_xlpm.col, SUM(_xlpm.col)>0)), 0,-1))+4,"")} | O26: {=SUM(IFERROR(('Time Plan (Single Release)'!$U$6:$U$64*('Time Plan (Single Release)'!$C$6:$C$64=$L26)),0))} -> 0 | P26: =IFERROR(O26*0.1,"") -> 0 | Q26: =O26*1.1 -> 0 | R26: {=IFERROR( (SUM('Time Plan (Single Release)'!$Y$6:$JN$64*(IFERROR('Time Plan (Single Release)'!$G$6:$G$64*40,0))*('Time Plan (Single Release)'!$C$6:$C$64=$L26)) - SUM('Time Plan (Single Release)'!$Y$6:$JN$64*(IFERROR('Time Plan (Single Release)'!$I$6:$I$64*40,0))*('Time Plan (Single Release)'!$C$6:$C$64=$L26))) / SUM('Time Plan (Single Release)'!$Y$6:$JN$64*(IFERROR('Time Plan (Single Release)'!$G$6:$G$64*40,0))*('Time Plan (Single Release)'!$C$6:$C$64=$L26)),"")} | S26: {=IFERROR( (SUM('Time Plan (Single Release)'!$Y$6:$JN$64*(IFERROR('Time Plan (Single Release)'!$I$6:$I$64*40,0))*('Time Plan (Single Release)'!$C$6:$C$64=$L26)) - SUM('Time Plan (Single Release)'!$Y$6:$JN$64*(IFERROR('Time Plan (Single Release)'!$K$6:$K$64*40,0))*('Time Plan (Single Release)'!$C$6:$C$64=$L26))) / SUM('Time Plan (Single Release)'!$Y$6:$JN$64*(IFERROR('Time Plan (Single Release)'!$I$6:$I$64*40,0))*('Time Plan (Single Release)'!$C$6:$C$64=$L26)),"")} | V26: {=IFERROR(_xlfn.XLOOKUP($U26,'Time Plan (Single Release)'!$D$6:$D$194,'Time Plan (Single Release)'!$E$6:$E$194&" - "&'Time Plan (Single Release)'!$F$6:$F$194),"")} -> - | AA26: {=SUM(IFERROR(('Time Plan (Single Release)'!$U$6:$U$64*('Time Plan (Single Release)'!$D$6:$D$64=$U26)),0))} -> 0 | AB26: =AA26*1.1 -> 0 | AE26: =SUMIF('Time Plan (Single Release)'!D$6:D$64,Pricing!U26,'Time Plan (Single Release)'!S$6:S$64) -> 0 | AF26: =AE26/8 -> 0 | AG26: =IFERROR(AE26+(AA$8*AI26/W26),"") | AH26: =IFERROR(AG26/8,"")
R27: {=IFERROR( (SUM('Time Plan (Single Release)'!$Y$6:$JN$64*(IFERROR('Time Plan (Single Release)'!$G$6:$G$64*40,0))*('Time Plan (Single Release)'!$C$6:$C$64=$L27)) - SUM('Time Plan (Single Release)'!$Y$6:$JN$64*(IFERROR('Time Plan (Single Release)'!$I$6:$I$64*40,0))*('Time Plan (Single Release)'!$C$6:$C$64=$L27))) / SUM('Time Plan (Single Release)'!$Y$6:$JN$64*(IFERROR('Time Plan (Single Release)'!$G$6:$G$64*40,0))*('Time Plan (Single Release)'!$C$6:$C$64=$L27)),"")} | S27: {=IFERROR( (SUM('Time Plan (Single Release)'!$Y$6:$JN$64*(IFERROR('Time Plan (Single Release)'!$I$6:$I$64*40,0))*('Time Plan (Single Release)'!$C$6:$C$64=$L27)) - SUM('Time Plan (Single Release)'!$Y$6:$JN$64*(IFERROR('Time Plan (Single Release)'!$K$6:$K$64*40,0))*('Time Plan (Single Release)'!$C$6:$C$64=$L27))) / SUM('Time Plan (Single Release)'!$Y$6:$JN$64*(IFERROR('Time Plan (Single Release)'!$I$6:$I$64*40,0))*('Time Plan (Single Release)'!$C$6:$C$64=$L27)),"")} | V27: {=IFERROR(_xlfn.XLOOKUP($U27,'Time Plan (Single Release)'!$D$6:$D$194,'Time Plan (Single Release)'!$E$6:$E$194&" - "&'Time Plan (Single Release)'!$F$6:$F$194),"")} -> - | AA27: {=SUM(IFERROR(('Time Plan (Single Release)'!$U$6:$U$64*('Time Plan (Single Release)'!$D$6:$D$64=$U27)),0))} -> 0 | AB27: =AA27*1.1 -> 0 | AE27: =SUMIF('Time Plan (Single Release)'!D$6:D$64,Pricing!U27,'Time Plan (Single Release)'!S$6:S$64) -> 0 | AF27: =AE27/8 -> 0 | AG27: =IFERROR(AE27+(AA$8*AI27/W27),"") | AH27: =IFERROR(AG27/8,"")
M28: {=IFERROR(INDEX('Time Plan (Single Release)'!$Y$3:$JN$3, 1, _xlfn.XMATCH(TRUE, _xlfn.BYCOL(('Time Plan (Single Release)'!$Y$6:$JN$64)*('Time Plan (Single Release)'!$C$6:$C$64=$L28), _xlfn.LAMBDA(_xlpm.col, SUM(_xlpm.col)>0)), 0, 1)),"")} | N28: {=IFERROR(INDEX('Time Plan (Single Release)'!$Y$3:$JN$3, 1, _xlfn.XMATCH(TRUE, _xlfn.BYCOL(('Time Plan (Single Release)'!$Y$6:$JN$64)*('Time Plan (Single Release)'!$C$6:$C$64=$L28), _xlfn.LAMBDA(_xlpm.col, SUM(_xlpm.col)>0)), 0,-1))+4,"")} | O28: {=SUM(IFERROR(('Time Plan (Single Release)'!$U$6:$U$64*('Time Plan (Single Release)'!$C$6:$C$64=$L28)),0))} -> 0 | P28: =IFERROR(O28*0.1,"") -> 0 | Q28: =O28*1.1 -> 0 | R28: {=IFERROR( (SUM('Time Plan (Single Release)'!$Y$6:$JN$64*(IFERROR('Time Plan (Single Release)'!$G$6:$G$64*40,0))*('Time Plan (Single Release)'!$C$6:$C$64=$L28)) - SUM('Time Plan (Single Release)'!$Y$6:$JN$64*(IFERROR('Time Plan (Single Release)'!$I$6:$I$64*40,0))*('Time Plan (Single Release)'!$C$6:$C$64=$L28))) / SUM('Time Plan (Single Release)'!$Y$6:$JN$64*(IFERROR('Time Plan (Single Release)'!$G$6:$G$64*40,0))*('Time Plan (Single Release)'!$C$6:$C$64=$L28)),"")} | S28: {=IFERROR( (SUM('Time Plan (Single Release)'!$Y$6:$JN$64*(IFERROR('Time Plan (Single Release)'!$I$6:$I$64*40,0))*('Time Plan (Single Release)'!$C$6:$C$64=$L28)) - SUM('Time Plan (Single Release)'!$Y$6:$JN$64*(IFERROR('Time Plan (Single Release)'!$K$6:$K$64*40,0))*('Time Plan (Single Release)'!$C$6:$C$64=$L28))) / SUM('Time Plan (Single Release)'!$Y$6:$JN$64*(IFERROR('Time Plan (Single Release)'!$I$6:$I$64*40,0))*('Time Plan (Single Release)'!$C$6:$C$64=$L28)),"")} | V28: {=IFERROR(_xlfn.XLOOKUP($U28,'Time Plan (Single Release)'!$D$6:$D$194,'Time Plan (Single Release)'!$E$6:$E$194&" - "&'Time Plan (Single Release)'!$F$6:$F$194),"")} -> - | AA28: {=SUM(IFERROR(('Time Plan (Single Release)'!$U$6:$U$64*('Time Plan (Single Release)'!$D$6:$D$64=$U28)),0))} -> 0 | AB28: =AA28*1.1 -> 0 | AE28: =SUMIF('Time Plan (Single Release)'!D$6:D$64,Pricing!U28,'Time Plan (Single Release)'!S$6:S$64) -> 0 | AF28: =AE28/8 -> 0 | AG28: =IFERROR(AE28+(AA$8*AI28/W28),"") | AH28: =IFERROR(AG28/8,"")
C29: {=IFERROR(INDEX('Time Plan (Single Release)'!$Y$3:$JN$3, 1, _xlfn.XMATCH(TRUE, _xlfn.BYCOL(('Time Plan (Single Release)'!$Y$6:$JN$64)*('Time Plan (Single Release)'!$B$6:$B$64=$B29), _xlfn.LAMBDA(_xlpm.col, SUM(_xlpm.col)>0)), 0, 1)),"")} | D29: {=IFERROR(INDEX('Time Plan (Single Release)'!$Y$3:$JN$3, 1, _xlfn.XMATCH(TRUE, _xlfn.BYCOL(('Time Plan (Single Release)'!$Y$6:$JN$64)*('Time Plan (Single Release)'!$B$6:$B$64=$B29), _xlfn.LAMBDA(_xlpm.col, SUM(_xlpm.col)>0)), 0,-1))+4,"")} | E29: =IFERROR(DATEDIF('Time Plan (Single Release)'!$Y$3,$D29+3,"d")/7,"") | F29: {=SUM(IFERROR(('Time Plan (Single Release)'!$U$6:$U$64*('Time Plan (Single Release)'!$B$6:$B$64=Pricing!$B29)),0))} -> 0 | G29: =$F29*0.1 -> 0 | H29: =$F29*1.1 -> 0 | I29: {=IFERROR( (SUM('Time Plan (Single Release)'!$Y$6:$JN$64*(IFERROR('Time Plan (Single Release)'!$G$6:$G$64*40,0))*('Time Plan (Single Release)'!$B$6:$B$64=Pricing!$B29)) - SUM('Time Plan (Single Release)'!$Y$6:$JN$64*(IFERROR('Time Plan (Single Release)'!$I$6:$I$64*40,0))*('Time Plan (Single Release)'!$B$6:$B$64=Pricing!$B29))) / SUM('Time Plan (Single Release)'!$Y$6:$JN$64*(IFERROR('Time Plan (Single Release)'!$G$6:$G$64*40,0))*('Time Plan (Single Release)'!$B$6:$B$64=Pricing!$B29)),"")} | J29: {=IFERROR( (SUM('Time Plan (Single Release)'!$Y$6:$JN$64*(IFERROR('Time Plan (Single Release)'!$I$6:$I$64*40,0))*('Time Plan (Single Release)'!$B$6:$B$64=Pricing!$B29)) - SUM('Time Plan (Single Release)'!$Y$6:$JN$64*(IFERROR('Time Plan (Single Release)'!$K$6:$K$64*40,0))*('Time Plan (Single Release)'!$B$6:$B$64=Pricing!$B29))) / SUM('Time Plan (Single Release)'!$Y$6:$JN$64*(IFERROR('Time Plan (Single Release)'!$I$6:$I$64*40,0))*('Time Plan (Single Release)'!$B$6:$B$64=Pricing!$B29)),"")} | M29: {=IFERROR(INDEX('Time Plan (Single Release)'!$Y$3:$JN$3, 1, _xlfn.XMATCH(TRUE, _xlfn.BYCOL(('Time Plan (Single Release)'!$Y$6:$JN$64)*('Time Plan (Single Release)'!$C$6:$C$64=$L29), _xlfn.LAMBDA(_xlpm.col, SUM(_xlpm.col)>0)), 0, 1)),"")} | N29: {=IFERROR(INDEX('Time Plan (Single Release)'!$Y$3:$JN$3, 1, _xlfn.XMATCH(TRUE, _xlfn.BYCOL(('Time Plan (Single Release)'!$Y$6:$JN$64)*('Time Plan (Single Release)'!$C$6:$C$64=$L29), _xlfn.LAMBDA(_xlpm.col, SUM(_xlpm.col)>0)), 0,-1))+4,"")} | O29: {=SUM(IFERROR(('Time Plan (Single Release)'!$U$6:$U$64*('Time Plan (Single Release)'!$C$6:$C$64=$L29)),0))} -> 0 | P29: =IFERROR(O29*0.1,"") -> 0 | Q29: =O29*1.1 -> 0 | R29: {=IFERROR( (SUM('Time Plan (Single Release)'!$Y$6:$JN$64*(IFERROR('Time Plan (Single Release)'!$G$6:$G$64*40,0))*('Time Plan (Single Release)'!$C$6:$C$64=$L29)) - SUM('Time Plan (Single Release)'!$Y$6:$JN$64*(IFERROR('Time Plan (Single Release)'!$I$6:$I$64*40,0))*('Time Plan (Single Release)'!$C$6:$C$64=$L29))) / SUM('Time Plan (Single Release)'!$Y$6:$JN$64*(IFERROR('Time Plan (Single Release)'!$G$6:$G$64*40,0))*('Time Plan (Single Release)'!$C$6:$C$64=$L29)),"")} | S29: {=IFERROR( (SUM('Time Plan (Single Release)'!$Y$6:$JN$64*(IFERROR('Time Plan (Single Release)'!$I$6:$I$64*40,0))*('Time Plan (Single Release)'!$C$6:$C$64=$L29)) - SUM('Time Plan (Single Release)'!$Y$6:$JN$64*(IFERROR('Time Plan (Single Release)'!$K$6:$K$64*40,0))*('Time Plan (Single Release)'!$C$6:$C$64=$L29))) / SUM('Time Plan (Single Release)'!$Y$6:$JN$64*(IFERROR('Time Plan (Single Release)'!$I$6:$I$64*40,0))*('Time Plan (Single Release)'!$C$6:$C$64=$L29)),"")} | V29: {=IFERROR(_xlfn.XLOOKUP($U29,'Time Plan (Single Release)'!$D$6:$D$194,'Time Plan (Single Release)'!$E$6:$E$194&" - "&'Time Plan (Single Release)'!$F$6:$F$194),"")} -> - | W29: =IFERROR(_xlfn.XLOOKUP($U29,'Time Plan (Single Release)'!$D$6:$D$64,'Time Plan (Single Release)'!$I$6:$I$64),"") | X29: =IFERROR(W29*1.1,"") | Y29: {=IFERROR(INDEX('Time Plan (Single Release)'!$Y$3:$JN$3, 1, _xlfn.XMATCH(TRUE, _xlfn.BYCOL(('Time Plan (Single Release)'!$Y$6:$JN$64)*('Time Plan (Single Release)'!$D$6:$D$64=$U29), _xlfn.LAMBDA(_xlpm.col, SUM(_xlpm.col)>0)), 0, 1)),"")} | Z29: {=IFERROR(INDEX('Time Plan (Single Release)'!$Y$3:$JN$3, 1, _xlfn.XMATCH(TRUE, _xlfn.BYCOL(('Time Plan (Single Release)'!$Y$6:$JN$64)*('Time Plan (Single Release)'!$D$6:$D$64=$U29), _xlfn.LAMBDA(_xlpm.col, SUM(_xlpm.col)>0)), 0,-1))+4,"")} | AA29: {=SUM(IFERROR(('Time Plan (Single Release)'!$U$6:$U$64*('Time Plan (Single Release)'!$D$6:$D$64=$U29)),0))} -> 0 | AB29: =AA29*1.1 -> 0 | AC29: {=IFERROR( (SUM('Time Plan (Single Release)'!$Y$6:$JN$64*(IFERROR('Time Plan (Single Release)'!$G$6:$G$64*40,0))*('Time Plan (Single Release)'!$D$6:$D$64=$U29)) - SUM('Time Plan (Single Release)'!$Y$6:$JN$64*(IFERROR('Time Plan (Single Release)'!$I$6:$I$64*40,0))*('Time Plan (Single Release)'!$D$6:$D$64=$U29))) / SUM('Time Plan (Single Release)'!$Y$6:$JN$64*(IFERROR('Time Plan (Single Release)'!$G$6:$G$64*40,0))*('Time Plan (Single Release)'!$D$6:$D$64=$U29)),"")} | AD29: {=IFERROR( (SUM('Time Plan (Single Release)'!$Y$6:$JN$64*(IFERROR('Time Plan (Single Release)'!$I$6:$I$64*40,0))*('Time Plan (Single Release)'!$D$6:$D$64=$U29)) - SUM('Time Plan (Single Release)'!$Y$6:$JN$64*(IFERROR('Time Plan (Single Release)'!$K$6:$K$64*40,0))*('Time Plan (Single Release)'!$D$6:$D$64=$U29))) / SUM('Time Plan (Single Release)'!$Y$6:$JN$64*(IFERROR('Time Plan (Single Release)'!$I$6:$I$64*40,0))*('Time Plan (Single Release)'!$D$6:$D$64=$U29)),"")} | AE29: =SUMIF('Time Plan (Single Release)'!D$6:D$64,Pricing!U29,'Time Plan (Single Release)'!S$6:S$64) -> 0 | AF29: =AE29/8 -> 0 | AG29: =IFERROR(AE29+(AA$8*AI29/W29),"") | AH29: =IFERROR(AG29/8,"")
M30: {=IFERROR(INDEX('Time Plan (Single Release)'!$Y$3:$JN$3, 1, _xlfn.XMATCH(TRUE, _xlfn.BYCOL(('Time Plan (Single Release)'!$Y$6:$JN$64)*('Time Plan (Single Release)'!$C$6:$C$64=$L30), _xlfn.LAMBDA(_xlpm.col, SUM(_xlpm.col)>0)), 0, 1)),"")} | N30: {=IFERROR(INDEX('Time Plan (Single Release)'!$Y$3:$JN$3, 1, _xlfn.XMATCH(TRUE, _xlfn.BYCOL(('Time Plan (Single Release)'!$Y$6:$JN$64)*('Time Plan (Single Release)'!$C$6:$C$64=$L30), _xlfn.LAMBDA(_xlpm.col, SUM(_xlpm.col)>0)), 0,-1))+4,"")} | O30: {=SUM(IFERROR(('Time Plan (Single Release)'!$U$6:$U$64*('Time Plan (Single Release)'!$C$6:$C$64=$L30)),0))} -> 0 | P30: =IFERROR(O30*0.1,"") -> 0 | Q30: =O30*1.1 -> 0 | R30: {=IFERROR( (SUM('Time Plan (Single Release)'!$Y$6:$JN$64*(IFERROR('Time Plan (Single Release)'!$G$6:$G$64*40,0))*('Time Plan (Single Release)'!$C$6:$C$64=$L30)) - SUM('Time Plan (Single Release)'!$Y$6:$JN$64*(IFERROR('Time Plan (Single Release)'!$I$6:$I$64*40,0))*('Time Plan (Single Release)'!$C$6:$C$64=$L30))) / SUM('Time Plan (Single Release)'!$Y$6:$JN$64*(IFERROR('Time Plan (Single Release)'!$G$6:$G$64*40,0))*('Time Plan (Single Release)'!$C$6:$C$64=$L30)),"")} | S30: {=IFERROR( (SUM('Time Plan (Single Release)'!$Y$6:$JN$64*(IFERROR('Time Plan (Single Release)'!$I$6:$I$64*40,0))*('Time Plan (Single Release)'!$C$6:$C$64=$L30)) - SUM('Time Plan (Single Release)'!$Y$6:$JN$64*(IFERROR('Time Plan (Single Release)'!$K$6:$K$64*40,0))*('Time Plan (Single Release)'!$C$6:$C$64=$L30))) / SUM('Time Plan (Single Release)'!$Y$6:$JN$64*(IFERROR('Time Plan (Single Release)'!$I$6:$I$64*40,0))*('Time Plan (Single Release)'!$C$6:$C$64=$L30)),"")} | AA30: {=SUM(IFERROR(('Time Plan (Single Release)'!$U$6:$U$64*('Time Plan (Single Release)'!$D$6:$D$64=$U30)),0))} -> 0 | AB30: =AA30*1.1 -> 0
B31: Engagement Summary | C31: =MIN(C4:C30) -> 46062 | D31: =MAX(D4:D30) -> 46220 | E31: =MAX(E4:E30) -> 23 | F31: =SUM(F4:F30) -> 774770.44 | G31: =SUM(G4:G30) -> 77477.044 | H31: =SUM(H4:H30) -> 852247.48 | I31: {=IFERROR( (SUM('Time Plan (Single Release)'!$Y$6:$JN$64*(IFERROR('Time Plan (Single Release)'!$G$6:$G$64*40,0))) - SUM('Time Plan (Single Release)'!$Y$6:$JN$64*(IFERROR('Time Plan (Single Release)'!$I$6:$I$64*40,0)))) / SUM('Time Plan (Single Release)'!$Y$6:$JN$64*(IFERROR('Time Plan (Single Release)'!$G$6:$G$64*40,0))),"")} -> 0.41781296 | J31: {=IFERROR( (SUM('Time Plan (Single Release)'!$Y$6:$JN$64*(IFERROR('Time Plan (Single Release)'!$I$6:$I$64*40,0))) - SUM('Time Plan (Single Release)'!$Y$6:$JN$64*(IFERROR('Time Plan (Single Release)'!$K$6:$K$64*40,0)))) / SUM('Time Plan (Single Release)'!$Y$6:$JN$64*(IFERROR('Time Plan (Single Release)'!$I$6:$I$64*40,0))),"")} -> -0.049444836 | L31: Engagement Summary | M31: =MIN(M4:M30) -> 46062 | N31: =MAX(N4:N30) -> 46220 | O31: =SUM(O4:O30) -> 774770.44 | P31: =SUM(P4:P30) -> 77477.044 | Q31: =SUM(Q4:Q30) -> 852247.48 | R31: {=IFERROR( (SUM('Time Plan (Single Release)'!$Y$6:$JN$64*(IFERROR('Time Plan (Single Release)'!$G$6:$G$64*40,0))) - SUM('Time Plan (Single Release)'!$Y$6:$JN$64*(IFERROR('Time Plan (Single Release)'!$I$6:$I$64*40,0)))) / SUM('Time Plan (Single Release)'!$Y$6:$JN$64*(IFERROR('Time Plan (Single Release)'!$G$6:$G$64*40,0))),"")} -> 0.41781296 | S31: {=IFERROR( (SUM('Time Plan (Single Release)'!$Y$6:$JN$64*(IFERROR('Time Plan (Single Release)'!$I$6:$I$64*40,0))) - SUM('Time Plan (Single Release)'!$Y$6:$JN$64*(IFERROR('Time Plan (Single Release)'!$K$6:$K$64*40,0)))) / SUM('Time Plan (Single Release)'!$Y$6:$JN$64*(IFERROR('Time Plan (Single Release)'!$I$6:$I$64*40,0))),"")} -> -0.049444836 | U31: Engagement Summary | Y31: =MIN(Y4:Y30) -> 46062 | Z31: =MAX(Z4:Z30) -> 46220 | AA31: =SUM(AA4:AA30) -> 774770.44 | AB31: =SUM(AB4:AB30) -> 852247.48 | AC31: {=IFERROR( (SUM('Time Plan (Single Release)'!$Y$6:$JN$64*(IFERROR('Time Plan (Single Release)'!$G$6:$G$64*40,0))) - SUM('Time Plan (Single Release)'!$Y$6:$JN$64*(IFERROR('Time Plan (Single Release)'!$I$6:$I$64*40,0)))) / SUM('Time Plan (Single Release)'!$Y$6:$JN$64*(IFERROR('Time Plan (Single Release)'!$G$6:$G$64*40,0))),"")} -> 0.41781296 | AD31: {=IFERROR( (SUM('Time Plan (Single Release)'!$Y$6:$JN$64*(IFERROR('Time Plan (Single Release)'!$I$6:$I$64*40,0))) - SUM('Time Plan (Single Release)'!$Y$6:$JN$64*(IFERROR('Time Plan (Single Release)'!$K$6:$K$64*40,0)))) / SUM('Time Plan (Single Release)'!$Y$6:$JN$64*(IFERROR('Time Plan (Single Release)'!$I$6:$I$64*40,0))),"")} -> -0.049444836 | AE31: =SUM(AE4:AE30) -> 4889 | AF31: =SUM(AF4:AF30) -> 611.125 | AG31: =SUM(AG4:AG30) -> 4314.129 | AH31: =SUM(AH4:AH30) -> 539.26613 | AI31: =SUM(AI4:AI30) -> 1 | AJ31: =SUM(AJ4:AJ30) -> 624849.18
W34: =AA4/W4 -> 708 | X34: =AG4/8 -> 0
W35: =AA5/W5 -> 749.41176
W36: =AA6/W6 -> 12.215562
W37: =AA7/W7 -> 400
W38: =AA8/W8 -> 230
W39: =AA9/W9 -> 600
W40: =AA10/W10 -> 160
W41: =AA11/W11 -> 480
W42: =AA12/W12 -> 460
W46: 906
W47: 480
W48: 420
W49: 760
W50: 420
W51: 1140
W52: 480
W53: =SUM(W46:W52) -> 4606

Sheet Exemplars
B1: Forecast Date | C1: 45796 | Y1: Monday Commencing (Select)
B2: Contract Start Date | C2: 45797 | L2: Delivery | Y2: 1 | Z2: 2 | AA2: 3 | AB2: 4 | AC2: 5 | AD2: 6 | AE2: 7 | AF2: 8 | AG2: 9 | AH2: 10 | AI2: 11 | AJ2: 12 | AK2: 13 | AL2: 14 | AM2: 15 | AN2: 16 | AO2: 17 | AP2: 18 | AQ2: 19 | AR2: 20 | AS2: 21 | AT2: 22 | AU2: 23 | AV2: 24 | AW2: 25 | AX2: 26 | AY2: 27 | AZ2: 28 | BA2: 29 | BB2: 30 | BC2: 31 | BD2: 32 | BE2: 33 | BF2: 34 | BG2: 35 | BH2: 36 | BI2: 37 | BJ2: 38 | BK2: 39 | BL2: 40 | BM2: 41 | BN2: 42 | BO2: 43 | BP2: 44 | BQ2: 45 | BR2: 46 | BS2: 47 | BT2: 48 | BU2: 49 | BV2: 50 | BW2: 51 | BX2: 52 | BY2: 53 | BZ2: 54 | CA2: 55 | CB2: 56 | CC2: 57 | CD2: 58 | CE2: 59 | CF2: 60 | CG2: 61 | CH2: 62 | CI2: 63 | CJ2: 64 | CK2: 65 | CL2: 66 | CM2: 67 | CN2: 68 | CO2: 69 | CP2: 70 | CQ2: 71 | CR2: 72 | CS2: 73 | CT2: 74 | CU2: 75 | CV2: 76 | CW2: 77 | CX2: 78 | CY2: 79 | CZ2: 80
B3: Milestone | C3: Deliverable | D3: Resource | E3: Charge Out Level | F3: Job Role | G3: Panel Hourly Rate $ ex-GST | H3: Discount % | I3: Discounted Hourly Rate $ ex GST | J3: Panel Daily Rate $ ex-GST | K3: Hourly Gross Cost $ | L3: Budget Hours | M3: Budget $ ex GST | N3: Actual Hours as at 20-May | O3: Charge $ ex GST | P3: Balance $ ex GST (Budget - Charge) | Q3: Gross Cost $ ex GST | R3: Gross Margin | S3: Forecast hours | T3: Forecast Days | U3: Forecast $ ex GST | V3: Forecast Gross Cost $ ex GST | W3: Variance at completion ex GST | X3: Variance at completion % | Y3: 45796 | Z3: 45803 | AA3: 45810 | AB3: 45817 | AC3: 45824 | AD3: 45831 | AE3: 45838 | AF3: 45845 | AG3: 45852 | AH3: 45859 | AI3: 45866 | AJ3: 45873 | AK3: 45880 | AL3: 45887 | AM3: 45894 | AN3: 45901 | AO3: 45908 | AP3: 45915 | AQ3: 45922 | AR3: 45929 | AS3: 45936 | AT3: 45943 | AU3: 45950 | AV3: 45957 | AW3: 45964 | AX3: 45971 | AY3: 45978 | AZ3: 45985 | BA3: 45992 | BB3: 45999 | BC3: 46006 | BD3: 46013 | BE3: 46020 | BF3: 46027 | BG3: 46034 | BH3: 46041 | BI3: 46048 | BJ3: 46055 | BK3: 46062 | BL3: 46069 | BM3: 46076 | BN3: 46083 | BO3: 46090 | BP3: 46097 | BQ3: 46104 | BR3: 46111 | BS3: 46118 | BT3: 46125 | BU3: 46132 | BV3: 46139 | BW3: 46146 | BX3: 46153 | BY3: 46160 | BZ3: 46167 | CA3: 46174 | CB3: 46181 | CC3: 46188 | CD3: 46195 | CE3: 46202 | CF3: 46209 | CG3: 46216 | CH3: 46223 | CI3: 46230 | CJ3: 46237 | CK3: 46244 | CL3: 46251 | CM3: 46258 | CN3: 46265 | CO3: 46272 | CP3: 46279 | CQ3: 46286 | CR3: 46293 | CS3: 46300 | CT3: 46307 | CU3: 46314 | CV3: 46321 | CW3: 46328 | CX3: 46335 | CY3: 46342 | CZ3: 46349
C4: Account Manager | D4: Aleksandar Vranesevic | E4: Panel | F4: Boston Consulting Group (BCG) - Partner Rates | AA4: 0.2 | AB4: 0.2 | AS4: 0.2 | BD4: 1 | BE4: 1 | BI4: 0.2 | BO4: 0.2 | BR4: 0.2 | BS4: 0.2 | BU4: 0.2 | CA4: 0.2 | CB4: 0.2 | CS4: 0.2
C5: Engagement Manager | D5: Paul Jarah | E5: Category | F5: Standard | L5: 0 | M5: 0 | N5: 0 | O5: 0 | P5: 0 | Q5: 0 | R5: 0.46720704 | S5: 1648 | T5: 206 | U5: 518160 | V5: 276072 | W5: -518160
B7: Exemplar - BCG Business Case | C7: Leadership | D7: Aleksandar Vranesevic | E7: Partner | G7: 500 | I7: 500 | J7: 4000 | K7: 248 | M7: 0 | O7: 0 | P7: 0 | Q7: 0 | R7: 0.504 | S7: 112 | T7: 14 | U7: 56000 | V7: 27776 | W7: -56000 | Y7: 0.2 | Z7: 0.2 | AA7: 0.2 | AB7: 0.2 | AC7: 0.2 | AD7: 0.2 | AE7: 0.2 | AF7: 0.2 | AG7: 0.2 | AH7: 0.2 | AI7: 0.2 | AJ7: 0.2 | AK7: 0.2 | AL7: 0.2
B8: Exemplar - BCG Business Case | C8: Main Document / Engagement Lead | D8: Paul Jarah | E8: Director | G8: 340 | I8: 340 | J8: 2720 | K8: 189 | M8: 0 | O8: 0 | P8: 0 | Q8: 0 | R8: 0.44411765 | S8: 284 | T8: 35.5 | U8: 96560 | V8: 53676 | W8: -96560 | Y8: 1 | Z8: 1 | AA8: 1 | AB8: 0.9 | AC8: 0.6 | AD8: 0.2 | AE8: 0.2 | AF8: 0.2 | AG8: 0.2 | AH8: 0.2 | AI8: 0.4 | AJ8: 0.4 | AK8: 0.4 | AL8: 0.4
B9: Exemplar - BCG Business Case | C9: Attachment A - Costings | D9: Hanan Asghar | E9: Senior Manager | G9: 290 | I9: 290 | J9: 2320 | K9: 180 | M9: 0 | O9: 0 | P9: 0 | Q9: 0 | S9: 0 | T9: 0 | U9: 0 | V9: 0 | W9: 0
B10: Exemplar - BCG Business Case | C10: Attachment B - Project Management Plan | D10: Paul Jarah | E10: Director | G10: 340 | I10: 340 | J10: 2720 | K10: 189 | M10: 0 | O10: 0 | P10: 0 | Q10: 0 | R10: 0.44411765 | S10: 144 | T10: 18 | U10: 48960 | V10: 27216 | W10: -48960 | AB10: 0.1 | AC10: 0.4 | AD10: 0.4 | AE10: 0.4 | AF10: 0.4 | AG10: 0.4 | AH10: 0.3 | AI10: 0.3 | AJ10: 0.3 | AK10: 0.3 | AL10: 0.3
B11: Exemplar - BCG Business Case | C11: Attachment C - Risk Management Approach | D11: Nathan Richards | E11: Senior Manager | G11: 290 | I11: 290 | J11: 2320 | K11: 146 | M11: 0 | O11: 0 | P11: 0 | Q11: 0 | R11: 0.49655172 | S11: 16 | T11: 2 | U11: 4640 | V11: 2336 | W11: -4640 | AH11: 0.2 | AI11: 0.2
B12: Exemplar - BCG Business Case | C12: Attachment D - Risk Register | D12: Nathan Richards | E12: Senior Manager | G12: 290 | I12: 290 | J12: 2320 | K12: 146 | M12: 0 | O12: 0 | P12: 0 | Q12: 0 | R12: 0.49655172 | S12: 40 | T12: 5 | U12: 11600 | V12: 5840 | W12: -11600 | AH12: 0.2 | AI12: 0.2 | AJ12: 0.2 | AK12: 0.2 | AL12: 0.2
B13: Exemplar - BCG Business Case | C13: Attachment E - Benefits Realisation Plan and Register | D13: Hanan Asghar | E13: Senior Manager | G13: 290 | I13: 290 | J13: 2320 | K13: 180 | M13: 0 | O13: 0 | P13: 0 | Q13: 0 | R13: 0.37931034 | S13: 80 | T13: 10 | U13: 23200 | V13: 14400 | W13: -23200 | Z13: 0.4 | AA13: 0.4 | AB13: 0.4 | AC13: 0.4 | AD13: 0.4
B14: Exemplar - BCG Business Case | C14: Attachment F - Solution Architecture | D14: Phani Gollamudi | E14: Director | G14: 340 | I14: 340 | J14: 2720 | K14: 198 | M14: 0 | O14: 0 | P14: 0 | Q14: 0 | S14: 0 | T14: 0 | U14: 0 | V14: 0 | W14: 0
B15: Exemplar - BCG Business Case | C15: Attachment G - Business Process Models | D15: Hanan Asghar | E15: Senior Manager | G15: 290 | I15: 290 | J15: 2320 | K15: 180 | M15: 0 | O15: 0 | P15: 0 | Q15: 0 | R15: 0.37931034 | S15: 80 | T15: 10 | U15: 23200 | V15: 14400 | W15: -23200 | Z15: 0.4 | AA15: 0.4 | AB15: 0.4 | AC15: 0.4 | AD15: 0.4
B16: Exemplar - BCG Business Case | C16: Attachment H - Requirements / Benefit & Process | D16: Nathan Richards | E16: Senior Manager | G16: 290 | I16: 290 | J16: 2320 | K16: 146 | M16: 0 | O16: 0 | P16: 0 | Q16: 0 | R16: 0.49655172 | S16: 480 | T16: 60 | U16: 139200 | V16: 70080 | W16: -139200 | Y16: 1 | Z16: 1 | AA16: 1 | AB16: 1 | AC16: 1 | AD16: 1 | AE16: 1 | AF16: 1 | AG16: 1 | AH16: 0.6 | AI16: 0.6 | AJ16: 0.6 | AK16: 0.6 | AL16: 0.6
B17: Exemplar - BCG Business Case | C17: Attachment I - Quality Plan | D17: Michelle Chant | E17: Senior Manager | G17: 290 | I17: 290 | J17: 2320 | K17: 146 | M17: 0 | O17: 0 | P17: 0 | Q17: 0 | R17: 0.49655172 | S17: 24 | T17: 3 | U17: 6960 | V17: 3504 | W17: -6960 | AG17: 0.1 | AH17: 0.1 | AI17: 0.1 | AJ17: 0.1 | AK17: 0.1 | AL17: 0.1
B18: Exemplar - BCG Business Case | C18: Attachment J - Governance Plan | D18: Paul Jarah | E18: Director | G18: 340 | I18: 340 | J18: 2720 | K18: 189 | M18: 0 | O18: 0 | P18: 0 | Q18: 0 | R18: 0.44411765 | S18: 40 | T18: 5 | U18: 13600 | V18: 7560 | W18: -13600 | AD18: 0.2 | AE18: 0.2 | AF18: 0.2 | AG18: 0.2 | AH18: 0.2
B19: Exemplar - BCG Business Case | C19: Attachment K - Assurance Plan | D19: Paul Jarah | E19: Director | G19: 340 | I19: 340 | J19: 2720 | K19: 189 | M19: 0 | O19: 0 | P19: 0 | Q19: 0 | R19: 0.44411765 | S19: 40 | T19: 5 | U19: 13600 | V19: 7560 | W19: -13600 | AD19: 0.2 | AE19: 0.2 | AF19: 0.2 | AG19: 0.2 | AH19: 0.2
B20: Exemplar - BCG Business Case | C20: Attachment L - Procurement Plan | D20: Paul Jarah | E20: Senior Manager | G20: 290 | I20: 290 | J20: 2320 | K20: 189 | M20: 0 | O20: 0 | P20: 0 | Q20: 0 | R20: 0.34827586 | S20: 52 | T20: 6.5 | U20: 15080 | V20: 9828 | W20: -15080 | AH20: 0.1 | AI20: 0.3 | AJ20: 0.3 | AK20: 0.3 | AL20: 0.3
B21: Exemplar - BCG Business Case | C21: Attachment M - Cyber Security Plan | D21: Akshay Gupta | E21: Senior Manager | G21: 290 | I21: 290 | J21: 2320 | K21: 162.5 | M21: 0 | O21: 0 | P21: 0 | Q21: 0 | R21: 0.43965517 | S21: 48 | T21: 6 | U21: 13920 | V21: 7800 | W21: -13920 | AC21: 0.4 | AD21: 0.4 | AE21: 0.4
B22: Exemplar - BCG Business Case | C22: Attachment N - Change, Stakeholder, Management and Taining Plan | D22: Michelle Chant | E22: Senior Manager | G22: 290 | I22: 290 | J22: 2320 | K22: 146 | M22: 0 | O22: 0 | P22: 0 | Q22: 0 | R22: 0.49655172 | S22: 72 | T22: 9 | U22: 20880 | V22: 10512 | W22: -20880 | AG22: 0.3 | AH22: 0.3 | AI22: 0.3 | AJ22: 0.3 | AK22: 0.3 | AL22: 0.3
B23: Exemplar - BCG Business Case | C23: Attachment O - Workforce Plan | D23: Nathan Richards | E23: Senior Manager | G23: 290 | I23: 290 | J23: 2320 | K23: 146 | M23: 0 | O23: 0 | P23: 0 | Q23: 0 | R23: 0.49655172 | S23: 24 | T23: 3 | U23: 6960 | V23: 3504 | W23: -6960 | AJ23: 0.2 | AK23: 0.2 | AL23: 0.2
B24: Exemplar - BCG Business Case | C24: Project & Document Coordinator | D24: Sian Davies | E24: Senior Consultant | G24: 212.5 | I24: 212.5 | J24: 1700 | K24: 90 | M24: 0 | O24: 0 | P24: 0 | Q24: 0 | R24: 0.57647059 | S24: 112 | T24: 14 | U24: 23800 | V24: 10080 | W24: -23800 | Y24: 0.2 | Z24: 0.2 | AA24: 0.2 | AB24: 0.2 | AC24: 0.2 | AD24: 0.2 | AE24: 0.2 | AF24: 0.2 | AG24: 0.2 | AH24: 0.2 | AI24: 0.2 | AJ24: 0.2 | AK24: 0.2 | AL24: 0.2
B26: Exemplar - IT Review - $160k | E26: Partner | F26: Client Manager | G26: 0 | I26: 0 | S26: 32 | T26: 4 | U26: 0 | Y26: 0.1 | Z26: 0.1 | AA26: 0.1 | AB26: 0.1 | AC26: 0.1 | AD26: 0.1 | AE26: 0.1 | AF26: 0.1
B27: Exemplar - IT Review - $160k | C27: Expert report | E27: Senior Manager | F27: Lead Consultant | G27: 290 | I27: 290 | S27: 320 | T27: 40 | U27: 92800 | Y27: 1 | Z27: 1 | AA27: 1 | AB27: 1 | AC27: 1 | AD27: 1 | AE27: 1 | AF27: 1
B28: Exemplar - IT Review - $160k | C28: Engagement support and analysis | E28: Senior Consultant | F28: Support Consultant | G28: 212.5 | I28: 212.5 | S28: 320 | T28: 40 | U28: 68000 | Y28: 1 | Z28: 1 | AA28: 1 | AB28: 1 | AC28: 1 | AD28: 1 | AE28: 1 | AF28: 1
B30: Exemplar - ICT Business case: 8-12 weeks = $900K | C30: Client Manager | E30: Partner | F30: Client Manager | G30: 500 | H30: 0 | I30: 500 | S30: 144 | T30: 18 | U30: 72000 | Y30: 0.3 | Z30: 0.3 | AA30: 0.3 | AB30: 0.3 | AC30: 0.3 | AD30: 0.3 | AE30: 0.3 | AF30: 0.3 | AG30: 0.3 | AH30: 0.3 | AI30: 0.3 | AJ30: 0.3
B31: Exemplar - ICT Business case: 8-12 weeks = $900K | C31: Narrative, Main body, roadmap | E31: Principal | F31: Engagement Mgr/Lead Consultant | G31: 340 | H31: 0 | I31: 340 | S31: 480 | T31: 60 | U31: 163200 | Y31: 1 | Z31: 1 | AA31: 1 | AB31: 1 | AC31: 1 | AD31: 1 | AE31: 1 | AF31: 1 | AG31: 1 | AH31: 1 | AI31: 1 | AJ31: 1
B32: Exemplar - ICT Business case: 8-12 weeks = $900K | C32: Tech design, requirements/features, arch current/future, cyber | E32: Principal | F32: Tech Lead | G32: 340 | H32: 0 | I32: 340 | S32: 480 | T32: 60 | U32: 163200 | Y32: 1 | Z32: 1 | AA32: 1 | AB32: 1 | AC32: 1 | AD32: 1 | AE32: 1 | AF32: 1 | AG32: 1 | AH32: 1 | AI32: 1 | AJ32: 1
B33: Exemplar - ICT Business case: 8-12 weeks = $900K | C33: Reqmnts, process analysis, current/future | E33: Senior Manager | F33: Business Lead | G33: 290 | H33: 0 | I33: 290 | S33: 480 | T33: 60 | U33: 139200 | Y33: 1 | Z33: 1 | AA33: 1 | AB33: 1 | AC33: 1 | AD33: 1 | AE33: 1 | AF33: 1 | AG33: 1 | AH33: 1 | AI33: 1 | AJ33: 1
B34: Exemplar - ICT Business case: 8-12 weeks = $900K | C34: Costings, benefits, (squad costings based on reqmts) | E34: Senior Manager | F34: CBA analyst | G34: 290 | H34: 0 | I34: 290 | S34: 480 | T34: 60 | U34: 139200 | Y34: 1 | Z34: 1 | AA34: 1 | AB34: 1 | AC34: 1 | AD34: 1 | AE34: 1 | AF34: 1 | AG34: 1 | AH34: 1 | AI34: 1 | AJ34: 1
B35: Exemplar - ICT Business case: 8-12 weeks = $900K | C35: PMP, supporting docs | E35: Manager | F35: Business Analyst | G35: 250 | H35: 0 | I35: 250 | S35: 480 | T35: 60 | U35: 120000 | Y35: 1 | Z35: 1 | AA35: 1 | AB35: 1 | AC35: 1 | AD35: 1 | AE35: 1 | AF35: 1 | AG35: 1 | AH35: 1 | AI35: 1 | AJ35: 1
B36: Exemplar - ICT Business case: 8-12 weeks = $900K | C36: Supporting docs, engagement support, project coords | E36: Senior Consultant | F36: Business Analyst | G36: 212.5 | H36: 0 | I36: 212.5 | S36: 480 | T36: 60 | U36: 102000 | Y36: 1 | Z36: 1 | AA36: 1 | AB36: 1 | AC36: 1 | AD36: 1 | AE36: 1 | AF36: 1 | AG36: 1 | AH36: 1 | AI36: 1 | AJ36: 1
B38: Exemplar - Mercury team (medium) - IT build $1M | C38: Client Manager | E38: Partner | F38: Client Manager | G38: 500 | H38: 0 | I38: 500 | U38: 52000 | Y38: 0.2 | Z38: 0.2 | AA38: 0.2 | AB38: 0.2 | AC38: 0.2 | AD38: 0.2 | AE38: 0.2 | AF38: 0.2 | AG38: 0.2 | AH38: 0.2 | AI38: 0.2 | AJ38: 0.2 | AK38: 0.2
B39: Exemplar - Mercury team (medium) - IT build $1M | C39: Delivery Manager | E39: Principal | F39: Delivery Manager | G39: 340 | H39: 0 | I39: 340 | U39: 176800 | Y39: 1 | Z39: 1 | AA39: 1 | AB39: 1 | AC39: 1 | AD39: 1 | AE39: 1 | AF39: 1 | AG39: 1 | AH39: 1 | AI39: 1 | AJ39: 1 | AK39: 1
B40: Exemplar - Mercury team (medium) - IT build $1M | C40: Architect | E40: Principal | F40: Architect | G40: 340 | H40: 0 | I40: 340 | U40: 176800 | Y40: 1 | Z40: 1 | AA40: 1 | AB40: 1 | AC40: 1 | AD40: 1 | AE40: 1 | AF40: 1 | AG40: 1 | AH40: 1 | AI40: 1 | AJ40: 1 | AK40: 1
B41: Exemplar - Mercury team (medium) - IT build $1M | C41: Developer | E41: Senior Manager | F41: Developer | G41: 290 | H41: 0 | I41: 290 | U41: 150800 | Y41: 1 | Z41: 1 | AA41: 1 | AB41: 1 | AC41: 1 | AD41: 1 | AE41: 1 | AF41: 1 | AG41: 1 | AH41: 1 | AI41: 1 | AJ41: 1 | AK41: 1
B42: Exemplar - Mercury team (medium) - IT build $1M | C42: Data & Cyber | E42: Senior Manager | F42: Data & Cyber | G42: 290 | H42: 0 | I42: 290 | U42: 150800 | Y42: 1 | Z42: 1 | AA42: 1 | AB42: 1 | AC42: 1 | AD42: 1 | AE42: 1 | AF42: 1 | AG42: 1 | AH42: 1 | AI42: 1 | AJ42: 1 | AK42: 1
B43: Exemplar - Mercury team (medium) - IT build $1M | C43: Integration | E43: Senior Manager | F43: Integration | G43: 290 | H43: 0 | I43: 290 | U43: 150800 | Y43: 1 | Z43: 1 | AA43: 1 | AB43: 1 | AC43: 1 | AD43: 1 | AE43: 1 | AF43: 1 | AG43: 1 | AH43: 1 | AI43: 1 | AJ43: 1 | AK43: 1
B44: Exemplar - Mercury team (medium) - IT build $1M | C44: Dashboard & Viz | E44: Senior Manager | F44: Dashboard & Viz | G44: 290 | H44: 0 | I44: 290 | U44: 150800 | Y44: 1 | Z44: 1 | AA44: 1 | AB44: 1 | AC44: 1 | AD44: 1 | AE44: 1 | AF44: 1 | AG44: 1 | AH44: 1 | AI44: 1 | AJ44: 1 | AK44: 1
B46: Exemplar - ICT Procurement (medium): $240K | C46: Client Manager | E46: Partner | F46: Client Manager | G46: 500 | H46: 0 | I46: 500 | S46: 80 | T46: 10 | U46: 40000 | Y46: 0.2 | Z46: 0.2 | AA46: 0.2 | AB46: 0.2 | AC46: 0.2 | AD46: 0.2 | AE46: 0.2 | AF46: 0.2 | AG46: 0.2 | AH46: 0.2
B47: Exemplar - ICT Procurement (medium): $240K | C47: Expert report | E47: Senior Manager | F47: Lead Consultant | G47: 290 | H47: 0 | I47: 290 | S47: 400 | T47: 50 | U47: 116000 | Y47: 1 | Z47: 1 | AA47: 1 | AB47: 1 | AC47: 1 | AD47: 1 | AE47: 1 | AF47: 1 | AG47: 1 | AH47: 1
B48: Exemplar - ICT Procurement (medium): $240K | C48: Engagement support and analysis | E48: Senior Consultant | F48: Support Consultant | G48: 212.5 | H48: 0 | I48: 212.5 | S48: 400 | T48: 50 | U48: 85000 | Y48: 1 | Z48: 1 | AA48: 1 | AB48: 1 | AC48: 1 | AD48: 1 | AE48: 1 | AF48: 1 | AG48: 1 | AH48: 1

Sheet KPIs
B1: KPIs | C1: INITIAL POSITION | D1: FINAL POSITION | E1: COMMENTARY | F1: NOTES
B2: CX | C2: N/A | F2: Agree on the CX value for the engagement and record any exception against any particular team member(s) at the point of closure
B3: Revenue Recognition | F3: Enter in name and percentage of people to be recognised. Total % needs to add up to 100%. Percentage should be broken down by Find, Win, Deliver (Refer to guidance material for more instructions) Example: John Smith - 20% Find John Doe - 20% Win 20% Deliver Brandon Jones - 40% - Win
B4: Financial: Budget $ ex GST | C4: =Coversheet!C19 -> 0 | D4: ='Time Plan (Single Release)'!M4 -> 0 | F4: Explain any variance and the proposed treatment
B5: Actual $ ex GST | C5: N/A | D5: ='Time Plan (Single Release)'!O4 -> 0
B6: Variance $ ex GST | C6: N/A | D6: =D4-D5 -> 0
B7: PO Variance $ ex GST | C7: =Coversheet!C20 -> 0 | D7: =Coversheet!C19-KPIs!D5 -> 0

Sheet Closing financials
A1: NOTES
A3: INSERT FINAL POSITION (PRE-BALANCING - OPS TEAM) | N3: INSERT FINAL POSITION (POST-BALANCING - OPS TEAM)
A4: Screenshot of i-time Project Task Budget Report | N4: Screenshot of i-time Project Task Budget Report

Sheet Closure
B1: CLOSURES
B2: Reason for closure | C2: Example: All deliverables completed and accepted. Note that further improvements to deliverables have been identified and handed over to Client for further actioning.
B3: Key deliverables | C3: Insert screenshot from Engagement SharePoint content for harvest folder
B4: Client feedback | C4: (Embed evidence if possible)
B5: Client's Agreement to be referee | C5: Yes, No, Possible
C6: (Written evidence or provide comments) Comments:
B8: capture names and details of people, eg RAIN behaviours
B12: CLOSURE CHECKLIST
B13: Activity | C13: Who | D13: Action taken / Result | E13: Done
B14: Reason for closure | C14: Engagement manager | D14: see above
B15: Key deliverables for harvest | C15: Engagement manager | D15: see above
B16: Client feedback | C16: Engagement manager | D16: see above
B17: Client's Agreement to be referee | C17: Engagement manager | D17: see above
B18: Update profiles (EM to remind team) | C18: Entire team
B19: Conduct a lessons learnt | C19: Entire team
B20: Write project brief (background, what we did, outcome) | C20: Engagement manager
B21: Add follow-on opportunities to KAM sales pipeline | C21: Engagement manager
B22: Provide feedback (up, down and sideways) | C22: Entire team
B23: Closure meeting | C23: Engagement manager & COO

Sheet Expenses
B1: EXPENSES
B2: Date | C2: Description | D2: Amount (ex. GST) | E2: Recoverable from Client | F2: Billed to Client
B12: Total | D12: =SUBTOTAL(109,Table3[Amount (ex. GST)]) -> 0

Sheet Time Plan HY
B1: Forecast Date | C1: 45964 | Y1: Monday Commencing (Select) | BF1: Hypercare
B2: Contract Start Date | C2: 45964 | L2: Delivery | Y2: =1+(DATEDIF($Y3,Y3,"d")/7) -> 1 | Z2: =1+(DATEDIF($Y3,Z3,"d")/7) -> 2 | AA2: =1+(DATEDIF($Y3,AA3,"d")/7) -> 3 | AB2: =1+(DATEDIF($Y3,AB3,"d")/7) -> 4 | AC2: =1+(DATEDIF($Y3,AC3,"d")/7) -> 5 | AD2: =1+(DATEDIF($Y3,AD3,"d")/7) -> 6 | AE2: =1+(DATEDIF($Y3,AE3,"d")/7) -> 7 | AF2: =1+(DATEDIF($Y3,AF3,"d")/7) -> 8 | ... WQ2: =1+(DATEDIF($Y3,WQ3,"d")/7) -> 591
B3: Milestone | C3: Deliverable | D3: Resource | E3: Charge Out Level | F3: Job Role | G3: Panel Hourly Rate $ ex-GST | H3: Discount (%) | I3: Discounted Hourly Rate $ ex GST | J3: Panel Daily Rate $ ex-GST | K3: Hourly Gross Cost $ | L3: Budget Hours | M3: Budget $ ex GST | N3: ="Actual Hours as at "&TEXT($C$2,"dd-mmm") -> Actual Hours as at 03-Nov | O3: Charge $ ex GST | P3: Balance $ ex GST (Budget - Charge) | Q3: Gross Cost $ ex GST | R3: Gross Margin | S3: Forecast hours | T3: Forecast Days | U3: Forecast $ ex GST | V3: Forecast Gross Cost $ ex GST | W3: Variance at completion (ex GST) | X3: Variance at completion (%) | Y3: 45964 | Z3: =Y3+7 -> 45971 | AA3: =Z3+7 -> 45978 | AB3: =AA3+7 -> 45985 | AC3: =AB3+7 -> 45992 | AD3: =AC3+7 -> 45999 | AE3: =AD3+7 -> 46006 | AF3: =AE3+7 -> 46013 | AG3: =AF3+7 -> 46020 | ... WQ3: =WP3+7 -> 50094
C4: Account Manager | D4: Aleksandar Vranesevic | E4: Panel | F4: Software & ERP Marketplace | Y4: =IFERROR(IF(_xlfn.XLOOKUP(Y3,Table9[Mondays],Table9[ACT Public Holidays])=0,"",_xlfn.XLOOKUP(Y3,Table9[Mondays],Table9[ACT Public Holidays])),"") | Z4: =IFERROR(IF(_xlfn.XLOOKUP(Z3,Table9[Mondays],Table9[ACT Public Holidays])=0,"",_xlfn.XLOOKUP(Z3,Table9[Mondays],Table9[ACT Public Holidays])),"") | AA4: =IFERROR(IF(_xlfn.XLOOKUP(AA3,Table9[Mondays],Table9[ACT Public Holidays])=0,"",_xlfn.XLOOKUP(AA3,Table9[Mondays],Table9[ACT Public Holidays])),"") | AB4: =IFERROR(IF(_xlfn.XLOOKUP(AB3,Table9[Mondays],Table9[ACT Public Holidays])=0,"",_xlfn.XLOOKUP(AB3,Table9[Mondays],Table9[ACT Public Holidays])),"") | AC4: =IFERROR(IF(_xlfn.XLOOKUP(AC3,Table9[Mondays],Table9[ACT Public Holidays])=0,"",_xlfn.XLOOKUP(AC3,Table9[Mondays],Table9[ACT Public Holidays])),"") | AD4: =IFERROR(IF(_xlfn.XLOOKUP(AD3,Table9[Mondays],Table9[ACT Public Holidays])=0,"",_xlfn.XLOOKUP(AD3,Table9[Mondays],Table9[ACT Public Holidays])),"") | AE4: =IFERROR(IF(_xlfn.XLOOKUP(AE3,Table9[Mondays],Table9[ACT Public Holidays])=0,"",_xlfn.XLOOKUP(AE3,Table9[Mondays],Table9[ACT Public Holidays])),"") | AF4: =IFERROR(IF(_xlfn.XLOOKUP(AF3,Table9[Mondays],Table9[ACT Public Holidays])=0,"",_xlfn.XLOOKUP(AF3,Table9[Mondays],Table9[ACT Public Holidays])),"") -> 1 | ... WQ4: =IFERROR(IF(_xlfn.XLOOKUP(WQ3,Table9[Mondays],Table9[ACT Public Holidays])=0,"",_xlfn.XLOOKUP(WQ3,Table9[Mondays],Table9[ACT Public Holidays])),"")
C5: Engagement Manager | D5: Alex Kocz | E5: Category | F5: Analysis, Design and COTS Development Services for a Software Acquisition and or Implementation | L5: =SUM(L6:L221) -> 0 | M5: =SUM(M6:M221) -> 0 | N5: =SUM(N6:N221) -> 0 | O5: =SUM(O6:O221) -> 0 | P5: =SUM(P6:P221) -> 0 | Q5: =SUM(Q6:Q221) -> 0 | R5: =IFERROR(((U5+O5)-(V5+Q5))/(U5+O5),"") -> 1 | S5: =SUM(S6:S221) -> 2992 | T5: =SUM(T6:T221) -> 374 | U5: =SUM(U6:U221) -> 701300 | V5: =SUM(V6:V221) -> 0 | W5: =SUM(W6:W221) -> -701300 | X5: =IFERROR(W5/M5,"")
B6: M1 Discovery | C6: 1.1 Detailed requirements, business process mapping complete and signed off | D6: Contractor-Delivery Manager/PM/Scrum Master/Scheduler | E6: Experienced Practitioner | G6: {=IFERROR(INDEX(Panel_Rates[[1]:[12]],MATCH(Panel_New&Category_New,Panel_Rates[Panel]&Panel_Rates[Category],0),MATCH('Time Plan HY'!E6,OFFSET(Variable!$AF$2,MATCH(Panel_New&Category_New,Panel_Rates[Panel]&Panel_Rates[Category],0)-1,0,1,12),0))/8,"")} -> 275 | I6: =IFERROR(G6*(1-H6),"") -> 275 | J6: =IFERROR(G6*8,"") -> 2200 | K6: =IFERROR(_xlfn.XLOOKUP(D6,CostTableLookup[Name],CostTableLookup[Gross Cost]),"") | M6: =IFERROR(L6*I6,"") -> 0 | O6: =IFERROR(N6*I6,"") -> 0 | P6: =IFERROR(M6-O6,"") -> 0 | Q6: =IFERROR(N6*K6,"") | R6: =IFERROR(((U6+O6)-(V6+Q6))/(U6+O6),"") | S6: =IFERROR(SUM(OFFSET(Y6,0,MATCH(Forecast_New,$Y$3:$WQ$3,0)-1,1,500))*40,"") -> 92 | T6: =IFERROR(S6/8,"") -> 11.5 | U6: =IFERROR($S6*I6,"") -> 25300 | V6: =IFERROR($S6*K6,"") | W6: =IFERROR(M6-(O6+U6),"") -> -25300 | X6: =IFERROR(W6/M6,"") | Y6: 0.8 | Z6: 0.5 | AA6: 0.5 | AB6: 0.5
B7: M1 Discovery | C7: 1.1 Detailed requirements, business process mapping complete and signed off | D7: Contractor-Business/System Analyst | E7: Qualified Practitioner | G7: {=IFERROR(INDEX(Panel_Rates[[1]:[12]],MATCH(Panel_New&Category_New,Panel_Rates[Panel]&Panel_Rates[Category],0),MATCH('Time Plan HY'!E7,OFFSET(Variable!$AF$2,MATCH(Panel_New&Category_New,Panel_Rates[Panel]&Panel_Rates[Category],0)-1,0,1,12),0))/8,"")} -> 190 | I7: =IFERROR(G7*(1-H7),"") -> 190 | J7: =IFERROR(G7*8,"") -> 1520 | K7: =IFERROR(_xlfn.XLOOKUP(D7,CostTableLookup[Name],CostTableLookup[Gross Cost]),"") | M7: =IFERROR(L7*I7,"") -> 0 | O7: =IFERROR(N7*I7,"") -> 0 | P7: =IFERROR(M7-O7,"") -> 0 | Q7: =IFERROR(N7*K7,"") | R7: =IFERROR(((U7+O7)-(V7+Q7))/(U7+O7),"") | S7: =IFERROR(SUM(OFFSET(Y7,0,MATCH(Forecast_New,$Y$3:$WQ$3,0)-1,1,500))*40,"") -> 100 | T7: =IFERROR(S7/8,"") -> 12.5 | U7: =IFERROR($S7*I7,"") -> 19000 | V7: =IFERROR($S7*K7,"") | W7: =IFERROR(M7-(O7+U7),"") -> -19000 | X7: =IFERROR(W7/M7,"") | Y7: 1 | Z7: 0.5 | AA7: 0.5 | AB7: 0.5
B8: M1 Discovery | C8: 1.1 Detailed requirements, business process mapping complete and signed off | D8: Contractor-Senior Architect | E8: Experienced Practitioner | F8: ServiceNow architect | G8: {=IFERROR(INDEX(Panel_Rates[[1]:[12]],MATCH(Panel_New&Category_New,Panel_Rates[Panel]&Panel_Rates[Category],0),MATCH('Time Plan HY'!E8,OFFSET(Variable!$AF$2,MATCH(Panel_New&Category_New,Panel_Rates[Panel]&Panel_Rates[Category],0)-1,0,1,12),0))/8,"")} -> 275 | I8: =IFERROR(G8*(1-H8),"") -> 275 | J8: =IFERROR(G8*8,"") -> 2200 | K8: =IFERROR(_xlfn.XLOOKUP(D8,CostTableLookup[Name],CostTableLookup[Gross Cost]),"") | M8: =IFERROR(L8*I8,"") -> 0 | O8: =IFERROR(N8*I8,"") -> 0 | P8: =IFERROR(M8-O8,"") -> 0 | Q8: =IFERROR(N8*K8,"") | R8: =IFERROR(((U8+O8)-(V8+Q8))/(U8+O8),"") | S8: =IFERROR(SUM(OFFSET(Y8,0,MATCH(Forecast_New,$Y$3:$WQ$3,0)-1,1,500))*40,"") -> 100 | T8: =IFERROR(S8/8,"") -> 12.5 | U8: =IFERROR($S8*I8,"") -> 27500 | V8: =IFERROR($S8*K8,"") | W8: =IFERROR(M8-(O8+U8),"") -> -27500 | X8: =IFERROR(W8/M8,"") | Y8: 1 | Z8: 0.5 | AA8: 0.5 | AB8: 0.5
B9: M1 Discovery | C9: 1.1 Detailed requirements, business process mapping complete and signed off | D9: Contractor-Developer | E9: Junior Practitioner | F9: ServiceNow developer | G9: {=IFERROR(INDEX(Panel_Rates[[1]:[12]],MATCH(Panel_New&Category_New,Panel_Rates[Panel]&Panel_Rates[Category],0),MATCH('Time Plan HY'!E9,OFFSET(Variable!$AF$2,MATCH(Panel_New&Category_New,Panel_Rates[Panel]&Panel_Rates[Category],0)-1,0,1,12),0))/8,"")} -> 165 | I9: =IFERROR(G9*(1-H9),"") -> 165 | J9: =IFERROR(G9*8,"") -> 1320 | K9: =IFERROR(_xlfn.XLOOKUP(D9,CostTableLookup[Name],CostTableLookup[Gross Cost]),"") | M9: =IFERROR(L9*I9,"") -> 0 | O9: =IFERROR(N9*I9,"") -> 0 | P9: =IFERROR(M9-O9,"") -> 0 | Q9: =IFERROR(N9*K9,"") | R9: =IFERROR(((U9+O9)-(V9+Q9))/(U9+O9),"") | S9: =IFERROR(SUM(OFFSET(Y9,0,MATCH(Forecast_New,$Y$3:$WQ$3,0)-1,1,500))*40,"") -> 60 | T9: =IFERROR(S9/8,"") -> 7.5 | U9: =IFERROR($S9*I9,"") -> 9900 | V9: =IFERROR($S9*K9,"") | W9: =IFERROR(M9-(O9+U9),"") -> -9900 | X9: =IFERROR(W9/M9,"") | Y9: 0.5 | Z9: 0.5 | AA9: 0.25 | AB9: 0.25
B10: M1 Discovery | C10: 1.3 Detailed delivery plan and RACI of build and delivery meeting AGD Operating Model requirements | D10: Contractor-Delivery Manager/PM/Scrum Master/Scheduler | E10: Experienced Practitioner | G10: {=IFERROR(INDEX(Panel_Rates[[1]:[12]],MATCH(Panel_New&Category_New,Panel_Rates[Panel]&Panel_Rates[Category],0),MATCH('Time Plan HY'!E10,OFFSET(Variable!$AF$2,MATCH(Panel_New&Category_New,Panel_Rates[Panel]&Panel_Rates[Category],0)-1,0,1,12),0))/8,"")} -> 275 | I10: =IFERROR(G10*(1-H10),"") -> 275 | J10: =IFERROR(G10*8,"") -> 2200 | K10: =IFERROR(_xlfn.XLOOKUP(D10,CostTableLookup[Name],CostTableLookup[Gross Cost]),"") | M10: =IFERROR(L10*I10,"") -> 0 | O10: =IFERROR(N10*I10,"") -> 0 | P10: =IFERROR(M10-O10,"") -> 0 | Q10: =IFERROR(N10*K10,"") | R10: =IFERROR(((U10+O10)-(V10+Q10))/(U10+O10),"") | S10: =IFERROR(SUM(OFFSET(Y10,0,MATCH(Forecast_New,$Y$3:$WQ$3,0)-1,1,500))*40,"") -> 32 | T10: =IFERROR(S10/8,"") -> 4 | U10: =IFERROR($S10*I10,"") -> 8800 | V10: =IFERROR($S10*K10,"") | W10: =IFERROR(M10-(O10+U10),"") -> -8800 | X10: =IFERROR(W10/M10,"") | Y10: 0.2 | Z10: 0.2 | AA10: 0.2 | AB10: 0.2
B12: M2A Build and delivery | C12: 2.1 Build and data migration | D12: Contractor-Delivery Manager/PM/Scrum Master/Scheduler | E12: Experienced Practitioner | G12: {=IFERROR(INDEX(Panel_Rates[[1]:[12]],MATCH(Panel_New&Category_New,Panel_Rates[Panel]&Panel_Rates[Category],0),MATCH('Time Plan HY'!E12,OFFSET(Variable!$AF$2,MATCH(Panel_New&Category_New,Panel_Rates[Panel]&Panel_Rates[Category],0)-1,0,1,12),0))/8,"")} -> 275 | I12: =IFERROR(G12*(1-H12),"") -> 275 | J12: =IFERROR(G12*8,"") -> 2200 | K12: =IFERROR(_xlfn.XLOOKUP(D12,CostTableLookup[Name],CostTableLookup[Gross Cost]),"") | M12: =IFERROR(L12*I12,"") -> 0 | O12: =IFERROR(N12*I12,"") -> 0 | P12: =IFERROR(M12-O12,"") -> 0 | Q12: =IFERROR(N12*K12,"") | R12: =IFERROR(((U12+O12)-(V12+Q12))/(U12+O12),"") | S12: =IFERROR(SUM(OFFSET(Y12,0,MATCH(Forecast_New,$Y$3:$WQ$3,0)-1,1,500))*40,"") -> 272 | T12: =IFERROR(S12/8,"") -> 34 | U12: =IFERROR($S12*I12,"") -> 74800 | V12: =IFERROR($S12*K12,"") | W12: =IFERROR(M12-(O12+U12),"") -> -74800 | X12: =IFERROR(W12/M12,"") | AC12: 0.5 | AD12: 0.5 | AE12: 0.5 | AH12: 0.5 | AI12: 0.5 | AJ12: 0.5 | AK12: 0.4 | AL12: 0.5 | AM12: 0.5 | AN12: 0.5 | AO12: 0.5 | AP12: 0.5 | AQ12: 0.4 | AR12: 0.5
B13: M2A Build and delivery | C13: 2.1 Build and data migration | D13: Contractor-Senior Architect | E13: Experienced Practitioner | G13: {=IFERROR(INDEX(Panel_Rates[[1]:[12]],MATCH(Panel_New&Category_New,Panel_Rates[Panel]&Panel_Rates[Category],0),MATCH('Time Plan HY'!E13,OFFSET(Variable!$AF$2,MATCH(Panel_New&Category_New,Panel_Rates[Panel]&Panel_Rates[Category],0)-1,0,1,12),0))/8,"")} -> 275 | I13: =IFERROR(G13*(1-H13),"") -> 275 | J13: =IFERROR(G13*8,"") -> 2200 | K13: =IFERROR(_xlfn.XLOOKUP(D13,CostTableLookup[Name],CostTableLookup[Gross Cost]),"") | M13: =IFERROR(L13*I13,"") -> 0 | O13: =IFERROR(N13*I13,"") -> 0 | P13: =IFERROR(M13-O13,"") -> 0 | Q13: =IFERROR(N13*K13,"") | R13: =IFERROR(((U13+O13)-(V13+Q13))/(U13+O13),"") | S13: =IFERROR(SUM(OFFSET(Y13,0,MATCH(Forecast_New,$Y$3:$WQ$3,0)-1,1,500))*40,"") -> 140 | T13: =IFERROR(S13/8,"") -> 17.5 | U13: =IFERROR($S13*I13,"") -> 38500 | V13: =IFERROR($S13*K13,"") | W13: =IFERROR(M13-(O13+U13),"") -> -38500 | X13: =IFERROR(W13/M13,"") | AC13: 0.25 | AD13: 0.25 | AE13: 0.25 | AH13: 0.25 | AI13: 0.25 | AJ13: 0.25 | AK13: 0.25 | AL13: 0.25 | AM13: 0.25 | AN13: 0.25 | AO13: 0.25 | AP13: 0.25 | AQ13: 0.25 | AR13: 0.25
B14: M2A Build and delivery | C14: 2.1 Build and data migration | D14: Contractor-Change Manager | E14: Qualified Practitioner | G14: {=IFERROR(INDEX(Panel_Rates[[1]:[12]],MATCH(Panel_New&Category_New,Panel_Rates[Panel]&Panel_Rates[Category],0),MATCH('Time Plan HY'!E14,OFFSET(Variable!$AF$2,MATCH(Panel_New&Category_New,Panel_Rates[Panel]&Panel_Rates[Category],0)-1,0,1,12),0))/8,"")} -> 190 | I14: =IFERROR(G14*(1-H14),"") -> 190 | J14: =IFERROR(G14*8,"") -> 1520 | K14: =IFERROR(_xlfn.XLOOKUP(D14,CostTableLookup[Name],CostTableLookup[Gross Cost]),"") | M14: =IFERROR(L14*I14,"") -> 0 | O14: =IFERROR(N14*I14,"") -> 0 | P14: =IFERROR(M14-O14,"") -> 0 | Q14: =IFERROR(N14*K14,"") | R14: =IFERROR(((U14+O14)-(V14+Q14))/(U14+O14),"") | S14: =IFERROR(SUM(OFFSET(Y14,0,MATCH(Forecast_New,$Y$3:$WQ$3,0)-1,1,500))*40,"") -> 280 | T14: =IFERROR(S14/8,"") -> 35 | U14: =IFERROR($S14*I14,"") -> 53200 | V14: =IFERROR($S14*K14,"") | W14: =IFERROR(M14-(O14+U14),"") -> -53200 | X14: =IFERROR(W14/M14,"") | AC14: 0.5 | AD14: 0.5 | AE14: 0.5 | AH14: 0.5 | AI14: 0.5 | AJ14: 0.5 | AK14: 0.5 | AL14: 0.5 | AM14: 0.5 | AN14: 0.5 | AO14: 0.5 | AP14: 0.5 | AQ14: 0.5 | AR14: 0.5
B15: M2A Build and delivery | C15: 2.1 Build and data migration | D15: Contractor-Developer | E15: Experienced Practitioner | G15: {=IFERROR(INDEX(Panel_Rates[[1]:[12]],MATCH(Panel_New&Category_New,Panel_Rates[Panel]&Panel_Rates[Category],0),MATCH('Time Plan HY'!E15,OFFSET(Variable!$AF$2,MATCH(Panel_New&Category_New,Panel_Rates[Panel]&Panel_Rates[Category],0)-1,0,1,12),0))/8,"")} -> 275 | I15: =IFERROR(G15*(1-H15),"") -> 275 | J15: =IFERROR(G15*8,"") -> 2200 | K15: =IFERROR(_xlfn.XLOOKUP(D15,CostTableLookup[Name],CostTableLookup[Gross Cost]),"") | M15: =IFERROR(L15*I15,"") -> 0 | O15: =IFERROR(N15*I15,"") -> 0 | P15: =IFERROR(M15-O15,"") -> 0 | Q15: =IFERROR(N15*K15,"") | R15: =IFERROR(((U15+O15)-(V15+Q15))/(U15+O15),"") | S15: =IFERROR(SUM(OFFSET(Y15,0,MATCH(Forecast_New,$Y$3:$WQ$3,0)-1,1,500))*40,"") -> 280 | T15: =IFERROR(S15/8,"") -> 35 | U15: =IFERROR($S15*I15,"") -> 77000 | V15: =IFERROR($S15*K15,"") | W15: =IFERROR(M15-(O15+U15),"") -> -77000 | X15: =IFERROR(W15/M15,"") | AC15: 0.5 | AD15: 0.5 | AE15: 0.5 | AH15: 0.5 | AI15: 0.5 | AJ15: 0.5 | AK15: 0.5 | AL15: 0.5 | AM15: 0.5 | AN15: 0.5 | AO15: 0.5 | AP15: 0.5 | AQ15: 0.5 | AR15: 0.5
B16: M2A Build and delivery | C16: 2.1 Build and data migration | D16: Contractor-Developer | E16: Junior Practitioner | G16: {=IFERROR(INDEX(Panel_Rates[[1]:[12]],MATCH(Panel_New&Category_New,Panel_Rates[Panel]&Panel_Rates[Category],0),MATCH('Time Plan HY'!E16,OFFSET(Variable!$AF$2,MATCH(Panel_New&Category_New,Panel_Rates[Panel]&Panel_Rates[Category],0)-1,0,1,12),0))/8,"")} -> 165 | I16: =IFERROR(G16*(1-H16),"") -> 165 | J16: =IFERROR(G16*8,"") -> 1320 | K16: =IFERROR(_xlfn.XLOOKUP(D16,CostTableLookup[Name],CostTableLookup[Gross Cost]),"") | M16: =IFERROR(L16*I16,"") -> 0 | O16: =IFERROR(N16*I16,"") -> 0 | P16: =IFERROR(M16-O16,"") -> 0 | Q16: =IFERROR(N16*K16,"") | R16: =IFERROR(((U16+O16)-(V16+Q16))/(U16+O16),"") | S16: =IFERROR(SUM(OFFSET(Y16,0,MATCH(Forecast_New,$Y$3:$WQ$3,0)-1,1,500))*40,"") -> 280 | T16: =IFERROR(S16/8,"") -> 35 | U16: =IFERROR($S16*I16,"") -> 46200 | V16: =IFERROR($S16*K16,"") | W16: =IFERROR(M16-(O16+U16),"") -> -46200 | X16: =IFERROR(W16/M16,"") | AC16: 0.5 | AD16: 0.5 | AE16: 0.5 | AH16: 0.5 | AI16: 0.5 | AJ16: 0.5 | AK16: 0.5 | AL16: 0.5 | AM16: 0.5 | AN16: 0.5 | AO16: 0.5 | AP16: 0.5 | AQ16: 0.5 | AR16: 0.5
B17: M2A Build and delivery | C17: 2.1 Build and data migration | D17: Contractor-Developer | E17: Junior Practitioner | G17: {=IFERROR(INDEX(Panel_Rates[[1]:[12]],MATCH(Panel_New&Category_New,Panel_Rates[Panel]&Panel_Rates[Category],0),MATCH('Time Plan HY'!E17,OFFSET(Variable!$AF$2,MATCH(Panel_New&Category_New,Panel_Rates[Panel]&Panel_Rates[Category],0)-1,0,1,12),0))/8,"")} -> 165 | I17: =IFERROR(G17*(1-H17),"") -> 165 | J17: =IFERROR(G17*8,"") -> 1320 | K17: =IFERROR(_xlfn.XLOOKUP(D17,CostTableLookup[Name],CostTableLookup[Gross Cost]),"") | M17: =IFERROR(L17*I17,"") -> 0 | O17: =IFERROR(N17*I17,"") -> 0 | P17: =IFERROR(M17-O17,"") -> 0 | Q17: =IFERROR(N17*K17,"") | R17: =IFERROR(((U17+O17)-(V17+Q17))/(U17+O17),"") | S17: =IFERROR(SUM(OFFSET(Y17,0,MATCH(Forecast_New,$Y$3:$WQ$3,0)-1,1,500))*40,"") -> 280 | T17: =IFERROR(S17/8,"") -> 35 | U17: =IFERROR($S17*I17,"") -> 46200 | V17: =IFERROR($S17*K17,"") | W17: =IFERROR(M17-(O17+U17),"") -> -46200 | X17: =IFERROR(W17/M17,"") | AC17: 0.5 | AD17: 0.5 | AE17: 0.5 | AH17: 0.5 | AI17: 0.5 | AJ17: 0.5 | AK17: 0.5 | AL17: 0.5 | AM17: 0.5 | AN17: 0.5 | AO17: 0.5 | AP17: 0.5 | AQ17: 0.5 | AR17: 0.5
C18: 2.1 Build and data migration | D18: Contractor-Test Manager | E18: Experienced Practitioner | AC18: 0.25 | AD18: 0.25 | AE18: 0.25 | AH18: 0.25 | AI18: 0.25 | AJ18: 0.25 | AK18: 0.25 | AL18: 0.25 | AM18: 0.25 | AN18: 0.25 | AO18: 0.25 | AP18: 0.25 | AQ18: 0.25 | AR18: 0.25
B19: M2A Build and delivery
B20: M2A Build and delivery | C20: 2.2. Training | D20: Contractor-Delivery Manager/PM/Scrum Master/Scheduler | E20: Experienced Practitioner | AS20: 0.5 | AT20: 0.5 | AU20: 0.5
B21: M2A Build and delivery | C21: 2.2. Training | D21: Contractor-Business/System Analyst | E21: Qualified Practitioner | AS21: 0.5 | AT21: 0.5 | AU21: 0.5
B22: M2A Build and delivery | C22: 2.2. Training | D22: Contractor-Developer | E22: Junior Practitioner | AS22: 0.25 | AT22: 0.25 | AU22: 0.25
C23: 2.2. Training | D23: Contractor-Change Manager | E23: Qualified Practitioner
B24: M2A Build and delivery
B25: M2A Build and delivery | C25: 2.3 Testing | D25: Contractor-Delivery Manager/PM/Scrum Master/Scheduler | E25: Experienced Practitioner | AV25: 0.5 | AW25: 0.5 | AX25: 0.5 | AY25: 0.5
B26: M2A Build and delivery | C26: 2.3 Testing | D26: Contractor-Developer | E26: Junior Practitioner | AV26: 0.5 | AW26: 0.5 | AX26: 0.5 | AY26: 0.5
B27: M2A Build and delivery | C27: 2.3 Testing | D27: Contractor-Developer | E27: Experienced Practitioner | AV27: 0.5 | AW27: 0.5 | AX27: 0.5 | AY27: 0.5
B28: M2A Build and delivery | C28: 2.3 Testing | D28: Contractor-Test Manager | E28: Experienced Practitioner | AV28: 0.5 | AW28: 0.5 | AX28: 0.5 | AY28: 0.5
B29: M2A Build and delivery
B30: M2A Build and delivery | C30: 2.4 Go Live | D30: Contractor-Delivery Manager/PM/Scrum Master/Scheduler | E30: Experienced Practitioner | AZ30: 0.5 | BA30: 0.5
B31: M2A Build and delivery | C31: 2.4 Go Live | D31: Contractor-Developer | E31: Junior Practitioner | AZ31: 0.5 | BA31: 0.5
B32: M2A Build and delivery | C32: 2.4 Go Live | D32: Contractor-Developer | E32: Experienced Practitioner | AZ32: 0.5 | BA32: 0.5
B33: M2A Build and delivery | C33: 2.4 Go Live | D33: Contractor-Test Manager | E33: Experienced Practitioner | AZ33: 0.5 | BA33: 0.5
B35: M2A Build and delivery | C35: 2.5 Hypercare & 2.9 Handover | D35: Contractor-Delivery Manager/PM/Scrum Master/Scheduler | E35: Experienced Practitioner | G35: {=IFERROR(INDEX(Panel_Rates[[1]:[12]],MATCH(Panel_New&Category_New,Panel_Rates[Panel]&Panel_Rates[Category],0),MATCH('Time Plan HY'!E35,OFFSET(Variable!$AF$2,MATCH(Panel_New&Category_New,Panel_Rates[Panel]&Panel_Rates[Category],0)-1,0,1,12),0))/8,"")} -> 275 | I35: =IFERROR(G35*(1-H35),"") -> 275 | J35: =IFERROR(G35*8,"") -> 2200 | K35: =IFERROR(_xlfn.XLOOKUP(D35,CostTableLookup[Name],CostTableLookup[Gross Cost]),"") | M35: =IFERROR(L35*I35,"") -> 0 | O35: =IFERROR(N35*I35,"") -> 0 | P35: =IFERROR(M35-O35,"") -> 0 | Q35: =IFERROR(N35*K35,"") | R35: =IFERROR(((U35+O35)-(V35+Q35))/(U35+O35),"") | S35: =IFERROR(SUM(OFFSET(Y35,0,MATCH(Forecast_New,$Y$3:$WQ$3,0)-1,1,500))*40,"") -> 40 | T35: =IFERROR(S35/8,"") -> 5 | U35: =IFERROR($S35*I35,"") -> 11000 | V35: =IFERROR($S35*K35,"") | W35: =IFERROR(M35-(O35+U35),"") -> -11000 | X35: =IFERROR(W35/M35,"") | BB35: 0.25 | BC35: 0.25 | BD35: 0.25 | BE35: 0.25
B36: M2A Build and delivery | C36: 2.5 Hypercare & 2.9 Handover | D36: Contractor-Developer | E36: Junior Practitioner | G36: {=IFERROR(INDEX(Panel_Rates[[1]:[12]],MATCH(Panel_New&Category_New,Panel_Rates[Panel]&Panel_Rates[Category],0),MATCH('Time Plan HY'!E36,OFFSET(Variable!$AF$2,MATCH(Panel_New&Category_New,Panel_Rates[Panel]&Panel_Rates[Category],0)-1,0,1,12),0))/8,"")} -> 165 | I36: =IFERROR(G36*(1-H36),"") -> 165 | J36: =IFERROR(G36*8,"") -> 1320 | K36: =IFERROR(_xlfn.XLOOKUP(D36,CostTableLookup[Name],CostTableLookup[Gross Cost]),"") | M36: =IFERROR(L36*I36,"") -> 0 | O36: =IFERROR(N36*I36,"") -> 0 | P36: =IFERROR(M36-O36,"") -> 0 | Q36: =IFERROR(N36*K36,"") | R36: =IFERROR(((U36+O36)-(V36+Q36))/(U36+O36),"") | S36: =IFERROR(SUM(OFFSET(Y36,0,MATCH(Forecast_New,$Y$3:$WQ$3,0)-1,1,500))*40,"") -> 80 | T36: =IFERROR(S36/8,"") -> 10 | U36: =IFERROR($S36*I36,"") -> 13200 | V36: =IFERROR($S36*K36,"") | W36: =IFERROR(M36-(O36+U36),"") -> -13200 | X36: =IFERROR(W36/M36,"") | BB36: 0.5 | BC36: 0.5 | BD36: 0.5 | BE36: 0.5
B37: M2A Build and delivery | C37: 2.5 Hypercare & 2.9 Handover | D37: Contractor-Test Manager | E37: Experienced Practitioner | G37: {=IFERROR(INDEX(Panel_Rates[[1]:[12]],MATCH(Panel_New&Category_New,Panel_Rates[Panel]&Panel_Rates[Category],0),MATCH('Time Plan HY'!E37,OFFSET(Variable!$AF$2,MATCH(Panel_New&Category_New,Panel_Rates[Panel]&Panel_Rates[Category],0)-1,0,1,12),0))/8,"")} -> 275 | I37: =IFERROR(G37*(1-H37),"") -> 275 | J37: =IFERROR(G37*8,"") -> 2200 | K37: =IFERROR(_xlfn.XLOOKUP(D37,CostTableLookup[Name],CostTableLookup[Gross Cost]),"") | M37: =IFERROR(L37*I37,"") -> 0 | O37: =IFERROR(N37*I37,"") -> 0 | P37: =IFERROR(M37-O37,"") -> 0 | Q37: =IFERROR(N37*K37,"") | R37: =IFERROR(((U37+O37)-(V37+Q37))/(U37+O37),"") | S37: =IFERROR(SUM(OFFSET(Y37,0,MATCH(Forecast_New,$Y$3:$WQ$3,0)-1,1,500))*40,"") -> 40 | T37: =IFERROR(S37/8,"") -> 5 | U37: =IFERROR($S37*I37,"") -> 11000 | V37: =IFERROR($S37*K37,"") | W37: =IFERROR(M37-(O37+U37),"") -> -11000 | X37: =IFERROR(W37/M37,"") | BB37: 0.25 | BC37: 0.25 | BD37: 0.25 | BE37: 0.25
B38: M2A Build and delivery
B39: M2B AI Proof of Concept | C39: 2.6 Detailed requirements, business process mapping complete and signed off | D39: Contractor-Delivery Manager/PM/Scrum Master/Scheduler | E39: Experienced Practitioner | G39: {=IFERROR(INDEX(Panel_Rates[[1]:[12]],MATCH(Panel_New&Category_New,Panel_Rates[Panel]&Panel_Rates[Category],0),MATCH('Time Plan HY'!E39,OFFSET(Variable!$AF$2,MATCH(Panel_New&Category_New,Panel_Rates[Panel]&Panel_Rates[Category],0)-1,0,1,12),0))/8,"")} -> 275 | I39: =IFERROR(G39*(1-H39),"") -> 275 | J39: =IFERROR(G39*8,"") -> 2200 | K39: =IFERROR(_xlfn.XLOOKUP(D39,CostTableLookup[Name],CostTableLookup[Gross Cost]),"") | M39: =IFERROR(L39*I39,"") -> 0 | O39: =IFERROR(N39*I39,"") -> 0 | P39: =IFERROR(M39-O39,"") -> 0 | Q39: =IFERROR(N39*K39,"") | R39: =IFERROR(((U39+O39)-(V39+Q39))/(U39+O39),"") | S39: =IFERROR(SUM(OFFSET(Y39,0,MATCH(Forecast_New,$Y$3:$WQ$3,0)-1,1,500))*40,"") -> 12 | T39: =IFERROR(S39/8,"") -> 1.5 | U39: =IFERROR($S39*I39,"") -> 3300 | V39: =IFERROR($S39*K39,"") | W39: =IFERROR(M39-(O39+U39),"") -> -3300 | X39: =IFERROR(W39/M39,"") | AB39: 0.3
B40: M2B AI Proof of Concept | C40: 2.6 Detailed requirements, business process mapping complete and signed off | D40: Contractor-Business/System Analyst | E40: Qualified Practitioner | AB40: 0.5
B41: M2B AI Proof of Concept | C41: 2.6 Detailed requirements, business process mapping complete and signed off | D41: Contractor-Senior Architect | E41: Experienced Practitioner | AB41: 0.5
B42: M2B AI Proof of Concept | C42: 2.6 Detailed requirements, business process mapping complete and signed off | D42: Contractor-Developer | E42: Junior Practitioner | AB42: 0.25
B43: M2B AI Proof of Concept | G43: {=IFERROR(INDEX(Panel_Rates[[1]:[12]],MATCH(Panel_New&Category_New,Panel_Rates[Panel]&Panel_Rates[Category],0),MATCH('Time Plan HY'!E43,OFFSET(Variable!$AF$2,MATCH(Panel_New&Category_New,Panel_Rates[Panel]&Panel_Rates[Category],0)-1,0,1,12),0))/8,"")} | I43: =IFERROR(G43*(1-H43),"") | J43: =IFERROR(G43*8,"") | K43: =IFERROR(_xlfn.XLOOKUP(D43,CostTableLookup[Name],CostTableLookup[Gross Cost]),"") | M43: =IFERROR(L43*I43,"") | O43: =IFERROR(N43*I43,"") | P43: =IFERROR(M43-O43,"") | Q43: =IFERROR(N43*K43,"") | R43: =IFERROR(((U43+O43)-(V43+Q43))/(U43+O43),"") | S43: =IFERROR(SUM(OFFSET(Y43,0,MATCH(Forecast_New,$Y$3:$WQ$3,0)-1,1,500))*40,"") -> 0 | T43: =IFERROR(S43/8,"") -> 0 | U43: =IFERROR($S43*I43,"") | V43: =IFERROR($S43*K43,"") | W43: =IFERROR(M43-(O43+U43),"") | X43: =IFERROR(W43/M43,"")
B44: M2B AI Proof of Concept | C44: 2.7 Proof of Concept - including the delivery of an accuracy, return on investment, delivery plan to production and model upgrade plan | D44: Contractor-Delivery Manager/PM/Scrum Master/Scheduler | E44: Experienced Practitioner | G44: {=IFERROR(INDEX(Panel_Rates[[1]:[12]],MATCH(Panel_New&Category_New,Panel_Rates[Panel]&Panel_Rates[Category],0),MATCH('Time Plan HY'!E44,OFFSET(Variable!$AF$2,MATCH(Panel_New&Category_New,Panel_Rates[Panel]&Panel_Rates[Category],0)-1,0,1,12),0))/8,"")} -> 275 | I44: =IFERROR(G44*(1-H44),"") -> 275 | J44: =IFERROR(G44*8,"") -> 2200 | K44: =IFERROR(_xlfn.XLOOKUP(D44,CostTableLookup[Name],CostTableLookup[Gross Cost]),"") | M44: =IFERROR(L44*I44,"") -> 0 | O44: =IFERROR(N44*I44,"") -> 0 | P44: =IFERROR(M44-O44,"") -> 0 | Q44: =IFERROR(N44*K44,"") | R44: =IFERROR(((U44+O44)-(V44+Q44))/(U44+O44),"") | S44: =IFERROR(SUM(OFFSET(Y44,0,MATCH(Forecast_New,$Y$3:$WQ$3,0)-1,1,500))*40,"") -> 80 | T44: =IFERROR(S44/8,"") -> 10 | U44: =IFERROR($S44*I44,"") -> 22000 | V44: =IFERROR($S44*K44,"") | W44: =IFERROR(M44-(O44+U44),"") -> -22000 | X44: =IFERROR(W44/M44,"") | AI44: 0.5 | AJ44: 0.5 | AK44: 0.5 | AL44: 0.5
B45: M2B AI Proof of Concept | C45: 2.7 Proof of Concept - including the delivery of an accuracy, return on investment, delivery plan to production and model upgrade plan | D45: Contractor-Senior Architect | E45: Experienced Practitioner | AI45: 0.25 | AJ45: 0.25 | AK45: 0.25 | AL45: 0.25
B46: M2B AI Proof of Concept | C46: 2.7 Proof of Concept - including the delivery of an accuracy, return on investment, delivery plan to production and model upgrade plan | D46: Contractor-Developer | E46: Junior Practitioner | AI46: 0.5 | AJ46: 0.5 | AK46: 0.5 | AL46: 0.5
B48: M2B AI Proof of Concept | C48: 2.8 Detailed evaluation report and delivery plan | D48: Contractor-Delivery Manager/PM/Scrum Master/Scheduler | E48: Experienced Practitioner | G48: {=IFERROR(INDEX(Panel_Rates[[1]:[12]],MATCH(Panel_New&Category_New,Panel_Rates[Panel]&Panel_Rates[Category],0),MATCH('Time Plan HY'!E48,OFFSET(Variable!$AF$2,MATCH(Panel_New&Category_New,Panel_Rates[Panel]&Panel_Rates[Category],0)-1,0,1,12),0))/8,"")} -> 275 | I48: =IFERROR(G48*(1-H48),"") -> 275 | J48: =IFERROR(G48*8,"") -> 2200 | K48: =IFERROR(_xlfn.XLOOKUP(D48,CostTableLookup[Name],CostTableLookup[Gross Cost]),"") | M48: =IFERROR(L48*I48,"") -> 0 | O48: =IFERROR(N48*I48,"") -> 0 | P48: =IFERROR(M48-O48,"") -> 0 | Q48: =IFERROR(N48*K48,"") | R48: =IFERROR(((U48+O48)-(V48+Q48))/(U48+O48),"") | S48: =IFERROR(SUM(OFFSET(Y48,0,MATCH(Forecast_New,$Y$3:$WQ$3,0)-1,1,500))*40,"") -> 40 | T48: =IFERROR(S48/8,"") -> 5 | U48: =IFERROR($S48*I48,"") -> 11000 | V48: =IFERROR($S48*K48,"") | W48: =IFERROR(M48-(O48+U48),"") -> -11000 | X48: =IFERROR(W48/M48,"") | AM48: 0.5 | AN48: 0.5
B49: M2B AI Proof of Concept | C49: 2.8 Detailed evaluation report and delivery plan | D49: Contractor-Business/System Analyst | E49: Qualified Practitioner | AM49: 0.5 | AN49: 0.5
B50: M2B AI Proof of Concept | C50: 2.8 Detailed evaluation report and delivery plan | D50: Contractor-Senior Architect | E50: Experienced Practitioner | AM50: 0.5 | AN50: 0.5
B52: M2C Self-service portal | C52: 2.9 Detailed requirements, business process mapping complete and signed off | D52: Contractor-Delivery Manager/PM/Scrum Master/Scheduler | E52: Experienced Practitioner | G52: {=IFERROR(INDEX(Panel_Rates[[1]:[12]],MATCH(Panel_New&Category_New,Panel_Rates[Panel]&Panel_Rates[Category],0),MATCH('Time Plan HY'!E52,OFFSET(Variable!$AF$2,MATCH(Panel_New&Category_New,Panel_Rates[Panel]&Panel_Rates[Category],0)-1,0,1,12),0))/8,"")} -> 275 | I52: =IFERROR(G52*(1-H52),"") -> 275 | J52: =IFERROR(G52*8,"") -> 2200 | K52: =IFERROR(_xlfn.XLOOKUP(D52,CostTableLookup[Name],CostTableLookup[Gross Cost]),"") | M52: =IFERROR(L52*I52,"") -> 0 | O52: =IFERROR(N52*I52,"") -> 0 | P52: =IFERROR(M52-O52,"") -> 0 | Q52: =IFERROR(N52*K52,"") | R52: =IFERROR(((U52+O52)-(V52+Q52))/(U52+O52),"") | S52: =IFERROR(SUM(OFFSET(Y52,0,MATCH(Forecast_New,$Y$3:$WQ$3,0)-1,1,500))*40,"") -> 24 | T52: =IFERROR(S52/8,"") -> 3 | U52: =IFERROR($S52*I52,"") -> 6600 | V52: =IFERROR($S52*K52,"") | W52: =IFERROR(M52-(O52+U52),"") -> -6600 | X52: =IFERROR(W52/M52,"") | Z52: 0.3 | AA52: 0.3
B53: M2C Self-service portal | C53: 2.9 Detailed requirements, business process mapping complete and signed off | D53: Contractor-Business/System Analyst | E53: Qualified Practitioner | G53: {=IFERROR(INDEX(Panel_Rates[[1]:[12]],MATCH(Panel_New&Category_New,Panel_Rates[Panel]&Panel_Rates[Category],0),MATCH('Time Plan HY'!E53,OFFSET(Variable!$AF$2,MATCH(Panel_New&Category_New,Panel_Rates[Panel]&Panel_Rates[Category],0)-1,0,1,12),0))/8,"")} -> 190 | I53: =IFERROR(G53*(1-H53),"") -> 190 | J53: =IFERROR(G53*8,"") -> 1520 | K53: =IFERROR(_xlfn.XLOOKUP(D53,CostTableLookup[Name],CostTableLookup[Gross Cost]),"") | M53: =IFERROR(L53*I53,"") -> 0 | O53: =IFERROR(N53*I53,"") -> 0 | P53: =IFERROR(M53-O53,"") -> 0 | Q53: =IFERROR(N53*K53,"") | R53: =IFERROR(((U53+O53)-(V53+Q53))/(U53+O53),"") | S53: =IFERROR(SUM(OFFSET(Y53,0,MATCH(Forecast_New,$Y$3:$WQ$3,0)-1,1,500))*40,"") -> 40 | T53: =IFERROR(S53/8,"") -> 5 | U53: =IFERROR($S53*I53,"") -> 7600 | V53: =IFERROR($S53*K53,"") | W53: =IFERROR(M53-(O53+U53),"") -> -7600 | X53: =IFERROR(W53/M53,"") | Z53: 0.5 | AA53: 0.5
B54: M2C Self-service portal | C54: 2.9 Detailed requirements, business process mapping complete and signed off | D54: Contractor-Senior Architect | E54: Experienced Practitioner | G54: {=IFERROR(INDEX(Panel_Rates[[1]:[12]],MATCH(Panel_New&Category_New,Panel_Rates[Panel]&Panel_Rates[Category],0),MATCH('Time Plan HY'!E54,OFFSET(Variable!$AF$2,MATCH(Panel_New&Category_New,Panel_Rates[Panel]&Panel_Rates[Category],0)-1,0,1,12),0))/8,"")} -> 275 | I54: =IFERROR(G54*(1-H54),"") -> 275 | J54: =IFERROR(G54*8,"") -> 2200 | K54: =IFERROR(_xlfn.XLOOKUP(D54,CostTableLookup[Name],CostTableLookup[Gross Cost]),"") | M54: =IFERROR(L54*I54,"") -> 0 | O54: =IFERROR(N54*I54,"") -> 0 | P54: =IFERROR(M54-O54,"") -> 0 | Q54: =IFERROR(N54*K54,"") | R54: =IFERROR(((U54+O54)-(V54+Q54))/(U54+O54),"") | S54: =IFERROR(SUM(OFFSET(Y54,0,MATCH(Forecast_New,$Y$3:$WQ$3,0)-1,1,500))*40,"") -> 40 | T54: =IFERROR(S54/8,"") -> 5 | U54: =IFERROR($S54*I54,"") -> 11000 | V54: =IFERROR($S54*K54,"") | W54: =IFERROR(M54-(O54+U54),"") -> -11000 | X54: =IFERROR(W54/M54,"") | Z54: 0.5 | AA54: 0.5
B55: M2C Self-service portal | C55: 2.9 Detailed requirements, business process mapping complete and signed off | D55: Contractor-Developer | E55: Junior Practitioner | G55: {=IFERROR(INDEX(Panel_Rates[[1]:[12]],MATCH(Panel_New&Category_New,Panel_Rates[Panel]&Panel_Rates[Category],0),MATCH('Time Plan HY'!E55,OFFSET(Variable!$AF$2,MATCH(Panel_New&Category_New,Panel_Rates[Panel]&Panel_Rates[Category],0)-1,0,1,12),0))/8,"")} -> 165 | I55: =IFERROR(G55*(1-H55),"") -> 165 | J55: =IFERROR(G55*8,"") -> 1320 | K55: =IFERROR(_xlfn.XLOOKUP(D55,CostTableLookup[Name],CostTableLookup[Gross Cost]),"") | M55: =IFERROR(L55*I55,"") -> 0 | O55: =IFERROR(N55*I55,"") -> 0 | P55: =IFERROR(M55-O55,"") -> 0 | Q55: =IFERROR(N55*K55,"") | R55: =IFERROR(((U55+O55)-(V55+Q55))/(U55+O55),"") | S55: =IFERROR(SUM(OFFSET(Y55,0,MATCH(Forecast_New,$Y$3:$WQ$3,0)-1,1,500))*40,"") -> 20 | T55: =IFERROR(S55/8,"") -> 2.5 | U55: =IFERROR($S55*I55,"") -> 3300 | V55: =IFERROR($S55*K55,"") | W55: =IFERROR(M55-(O55+U55),"") -> -3300 | X55: =IFERROR(W55/M55,"") | Z55: 0.25 | AA55: 0.25
B56: M2C Self-service portal
B57: M2C Self-service portal | C57: 2.10 Build/delivery of self-service portal | D57: Contractor-Delivery Manager/PM/Scrum Master/Scheduler | E57: Experienced Practitioner | G57: {=IFERROR(INDEX(Panel_Rates[[1]:[12]],MATCH(Panel_New&Category_New,Panel_Rates[Panel]&Panel_Rates[Category],0),MATCH('Time Plan HY'!E57,OFFSET(Variable!$AF$2,MATCH(Panel_New&Category_New,Panel_Rates[Panel]&Panel_Rates[Category],0)-1,0,1,12),0))/8,"")} -> 275 | I57: =IFERROR(G57*(1-H57),"") -> 275 | J57: =IFERROR(G57*8,"") -> 2200 | K57: =IFERROR(_xlfn.XLOOKUP(D57,CostTableLookup[Name],CostTableLookup[Gross Cost]),"") | M57: =IFERROR(L57*I57,"") -> 0 | O57: =IFERROR(N57*I57,"") -> 0 | P57: =IFERROR(M57-O57,"") -> 0 | Q57: =IFERROR(N57*K57,"") | R57: =IFERROR(((U57+O57)-(V57+Q57))/(U57+O57),"") | S57: =IFERROR(SUM(OFFSET(Y57,0,MATCH(Forecast_New,$Y$3:$WQ$3,0)-1,1,500))*40,"") -> 120 | T57: =IFERROR(S57/8,"") -> 15 | U57: =IFERROR($S57*I57,"") -> 33000 | V57: =IFERROR($S57*K57,"") | W57: =IFERROR(M57-(O57+U57),"") -> -33000 | X57: =IFERROR(W57/M57,"") | AC57: 0.5 | AD57: 0.5 | AE57: 0.5 | AF57: 0.5 | AG57: 0.5 | AH57: 0.5
B58: M2C Self-service portal | C58: 2.10 Build/delivery of self-service portal | D58: Contractor-Senior Architect | E58: Experienced Practitioner | AC58: 0.25 | AD58: 0.25 | AE58: 0.25 | AF58: 0.25 | AG58: 0.25 | AH58: 0.25
B59: M2C Self-service portal | C59: 2.10 Build/delivery of self-service portal | D59: Contractor-Developer | E59: Junior Practitioner | AC59: 0.5 | AD59: 0.5 | AE59: 0.5 | AF59: 0.5 | AG59: 0.5 | AH59: 0.5
C60: 2.10 Build/delivery of self-service portal | D60: Contractor-Developer | E60: Experienced Practitioner | AC60: 0.5 | AD60: 0.5 | AE60: 0.5 | AF60: 0.5 | AG60: 0.5 | AH60: 0.5
C61: 2.10 Build/delivery of self-service portal | D61: Contractor-Test Manager | E61: Experienced Practitioner | AC61: 0.25 | AD61: 0.25 | AE61: 0.25 | AF61: 0.25 | AG61: 0.25 | AH61: 0.25
B62: M2C Self-service portal
B63: M2C Self-service portal | C63: 2.11 Training | D63: Contractor-Delivery Manager/PM/Scrum Master/Scheduler | E63: Experienced Practitioner | AS63: 0.5 | AT63: 0.5
B64: M2C Self-service portal | C64: 2.11 Training | D64: Contractor-Business/System Analyst | E64: Qualified Practitioner | AS64: 0.5 | AT64: 0.5
B65: M2C Self-service portal | C65: 2.11 Training | D65: Contractor-Developer | E65: Junior Practitioner | AS65: 0.5 | AT65: 0.5
C66: 2.11 Training | D66: Contractor-Change Manager | E66: Qualified Practitioner | AS66: 0.5 | AT66: 0.5
B68: M2C Self-service portal | C68: 2.12 Testing: including testing plan and UAT requirements | D68: Contractor-Delivery Manager/PM/Scrum Master/Scheduler | E68: Experienced Practitioner | G68: {=IFERROR(INDEX(Panel_Rates[[1]:[12]],MATCH(Panel_New&Category_New,Panel_Rates[Panel]&Panel_Rates[Category],0),MATCH('Time Plan HY'!E68,OFFSET(Variable!$AF$2,MATCH(Panel_New&Category_New,Panel_Rates[Panel]&Panel_Rates[Category],0)-1,0,1,12),0))/8,"")} -> 275 | I68: =IFERROR(G68*(1-H68),"") -> 275 | J68: =IFERROR(G68*8,"") -> 2200 | K68: =IFERROR(_xlfn.XLOOKUP(D68,CostTableLookup[Name],CostTableLookup[Gross Cost]),"") | M68: =IFERROR(L68*I68,"") -> 0 | O68: =IFERROR(N68*I68,"") -> 0 | P68: =IFERROR(M68-O68,"") -> 0 | Q68: =IFERROR(N68*K68,"") | R68: =IFERROR(((U68+O68)-(V68+Q68))/(U68+O68),"") | S68: =IFERROR(SUM(OFFSET(Y68,0,MATCH(Forecast_New,$Y$3:$WQ$3,0)-1,1,500))*40,"") -> 140 | T68: =IFERROR(S68/8,"") -> 17.5 | U68: =IFERROR($S68*I68,"") -> 38500 | V68: =IFERROR($S68*K68,"") | W68: =IFERROR(M68-(O68+U68),"") -> -38500 | X68: =IFERROR(W68/M68,"") | AW68: 0.5 | AX68: 0.5 | AY68: 0.5 | BD68: 1 | BE68: 1
B69: M2C Self-service portal | C69: 2.12 Testing: including testing plan and UAT requirements | D69: Contractor-Developer | E69: Junior Practitioner | AW69: 0.5 | AX69: 0.5 | AY69: 0.5
C70: 2.12 Testing: including testing plan and UAT requirements | D70: Contractor-Developer | E70: Junior Practitioner | AW70: 0.5 | AX70: 0.5 | AY70: 0.5
B71: M2C Self-service portal | C71: 2.12 Testing: including testing plan and UAT requirements | D71: Contractor-Test Manager | E71: Experienced Practitioner | AW71: 0.5 | AX71: 0.5 | AY71: 0.5
B72: M2C Self-service portal
B73: M2C Self-service portal | C73: 2.4 Go Live | D73: Contractor-Delivery Manager/PM/Scrum Master/Scheduler | E73: Experienced Practitioner | AZ73: 0.5 | BA73: 0.5
B74: M2C Self-service portal | C74: 2.4 Go Live | D74: Contractor-Developer | E74: Junior Practitioner | AZ74: 0.5 | BA74: 0.5
B75: M2C Self-service portal | C75: 2.4 Go Live | D75: Contractor-Developer | E75: Experienced Practitioner | AZ75: 0.5 | BA75: 0.5
B76: M2C Self-service portal | C76: 2.4 Go Live | D76: Contractor-Test Manager | E76: Experienced Practitioner | AZ76: 0.5 | BA76: 0.5
B77: M2C Self-service portal
B78: M3 Implementation of AI | C78: 3.1 AI Build | D78: Contractor-Delivery Manager/PM/Scrum Master/Scheduler | E78: Experienced Practitioner | G78: {=IFERROR(INDEX(Panel_Rates[[1]:[12]],MATCH(Panel_New&Category_New,Panel_Rates[Panel]&Panel_Rates[Category],0),MATCH('Time Plan HY'!E78,OFFSET(Variable!$AF$2,MATCH(Panel_New&Category_New,Panel_Rates[Panel]&Panel_Rates[Category],0)-1,0,1,12),0))/8,"")} -> 275 | I78: =IFERROR(G78*(1-H78),"") -> 275 | J78: =IFERROR(G78*8,"") -> 2200 | K78: =IFERROR(_xlfn.XLOOKUP(D78,CostTableLookup[Name],CostTableLookup[Gross Cost]),"") | M78: =IFERROR(L78*I78,"") -> 0 | O78: =IFERROR(N78*I78,"") -> 0 | P78: =IFERROR(M78-O78,"") -> 0 | Q78: =IFERROR(N78*K78,"") | R78: =IFERROR(((U78+O78)-(V78+Q78))/(U78+O78),"") | S78: =IFERROR(SUM(OFFSET(Y78,0,MATCH(Forecast_New,$Y$3:$WQ$3,0)-1,1,500))*40,"") -> 220 | T78: =IFERROR(S78/8,"") -> 27.5 | U78: =IFERROR($S78*I78,"") -> 60500 | V78: =IFERROR($S78*K78,"") | W78: =IFERROR(M78-(O78+U78),"") -> -60500 | X78: =IFERROR(W78/M78,"") | AO78: 0.5 | AP78: 0.5 | AQ78: 0.5 | AR78: 1 | AS78: 0.5 | AT78: 0.5 | BD78: 1 | BE78: 1
B79: M3 Implementation of AI | C79: 3.1 AI Build | D79: Contractor-Senior Architect | E79: Experienced Practitioner | AO79: 0.5 | AP79: 0.5 | AQ79: 0.5 | AR79: 1 | AS79: 0.5 | AT79: 0.5
B80: M3 Implementation of AI | C80: 3.1 AI Build | D80: Contractor-Developer | E80: Junior Practitioner | AO80: 0.5 | AP80: 0.5 | AQ80: 0.5 | AR80: 1 | AS80: 0.5 | AT80: 0.5
C81: 3.1 AI Build | D81: Contractor-Test Manager | E81: Experienced Practitioner | AO81: 0.5 | AP81: 0.5 | AQ81: 0.5 | AR81: 1 | AS81: 0.5 | AT81: 0.5
B82: M3 Implementation of AI
B83: M3 Implementation of AI | C83: 3.2 Training | D83: Contractor-Delivery Manager/PM/Scrum Master/Scheduler | E83: Experienced Practitioner | AU83: 0.5
B84: M3 Implementation of AI | C84: 3.2 Training | D84: Contractor-Business/System Analyst | E84: Qualified Practitioner | AU84: 0.5
B85: M3 Implementation of AI | C85: 3.2 Training | D85: Contractor-Developer | E85: Junior Practitioner | G85: {=IFERROR(INDEX(Panel_Rates[[1]:[12]],MATCH(Panel_New&Category_New,Panel_Rates[Panel]&Panel_Rates[Category],0),MATCH('Time Plan HY'!E85,OFFSET(Variable!$AF$2,MATCH(Panel_New&Category_New,Panel_Rates[Panel]&Panel_Rates[Category],0)-1,0,1,12),0))/8,"")} -> 165 | I85: =IFERROR(G85*(1-H85),"") -> 165 | J85: =IFERROR(G85*8,"") -> 1320 | K85: =IFERROR(_xlfn.XLOOKUP(D85,CostTableLookup[Name],CostTableLookup[Gross Cost]),"") | M85: =IFERROR(L85*I85,"") -> 0 | O85: =IFERROR(N85*I85,"") -> 0 | P85: =IFERROR(M85-O85,"") -> 0 | Q85: =IFERROR(N85*K85,"") | R85: =IFERROR(((U85+O85)-(V85+Q85))/(U85+O85),"") | S85: =IFERROR(SUM(OFFSET(Y85,0,MATCH(Forecast_New,$Y$3:$WQ$3,0)-1,1,500))*40,"") -> 20 | T85: =IFERROR(S85/8,"") -> 2.5 | U85: =IFERROR($S85*I85,"") -> 3300 | V85: =IFERROR($S85*K85,"") | W85: =IFERROR(M85-(O85+U85),"") -> -3300 | X85: =IFERROR(W85/M85,"") | AU85: 0.5
B86: M3 Implementation of AI | C86: 3.2 Training | D86: Contractor-Change Manager | E86: Qualified Practitioner | AU86: 0.5
B87: M3 Implementation of AI
B88: M3 Implementation of AI | C88: 3.3 Testing: including testing plan and UAT requirements | D88: Contractor-Delivery Manager/PM/Scrum Master/Scheduler | E88: Experienced Practitioner | AW88: 0.5 | AX88: 0.5
B89: M3 Implementation of AI | C89: 3.3 Testing: including testing plan and UAT requirements | D89: Contractor-Developer | E89: Junior Practitioner | AW89: 0.5 | AX89: 0.5
B90: M3 Implementation of AI | C90: 3.3 Testing: including testing plan and UAT requirements | D90: Contractor-Developer | E90: Junior Practitioner | AW90: 0.5 | AX90: 0.5
B91: M3 Implementation of AI | C91: 3.3 Testing: including testing plan and UAT requirements | D91: Contractor-Test Manager | E91: Experienced Practitioner | G91: {=IFERROR(INDEX(Panel_Rates[[1]:[12]],MATCH(Panel_New&Category_New,Panel_Rates[Panel]&Panel_Rates[Category],0),MATCH('Time Plan HY'!E91,OFFSET(Variable!$AF$2,MATCH(Panel_New&Category_New,Panel_Rates[Panel]&Panel_Rates[Category],0)-1,0,1,12),0))/8,"")} -> 275 | I91: =IFERROR(G91*(1-H91),"") -> 275 | J91: =IFERROR(G91*8,"") -> 2200 | K91: =IFERROR(_xlfn.XLOOKUP(D91,CostTableLookup[Name],CostTableLookup[Gross Cost]),"") | M91: =IFERROR(L91*I91,"") -> 0 | O91: =IFERROR(N91*I91,"") -> 0 | P91: =IFERROR(M91-O91,"") -> 0 | Q91: =IFERROR(N91*K91,"") | R91: =IFERROR(((U91+O91)-(V91+Q91))/(U91+O91),"") | S91: =IFERROR(SUM(OFFSET(Y91,0,MATCH(Forecast_New,$Y$3:$WQ$3,0)-1,1,500))*40,"") -> 0 | T91: =IFERROR(S91/8,"") -> 0 | U91: =IFERROR($S91*I91,"") -> 0 | V91: =IFERROR($S91*K91,"") | W91: =IFERROR(M91-(O91+U91),"") -> 0 | X91: =IFERROR(W91/M91,"")
B92: M3 Implementation of AI | G92: {=IFERROR(INDEX(Panel_Rates[[1]:[12]],MATCH(Panel_New&Category_New,Panel_Rates[Panel]&Panel_Rates[Category],0),MATCH('Time Plan HY'!E92,OFFSET(Variable!$AF$2,MATCH(Panel_New&Category_New,Panel_Rates[Panel]&Panel_Rates[Category],0)-1,0,1,12),0))/8,"")} | I92: =IFERROR(G92*(1-H92),"") | J92: =IFERROR(G92*8,"") | K92: =IFERROR(_xlfn.XLOOKUP(D92,CostTableLookup[Name],CostTableLookup[Gross Cost]),"") | M92: =IFERROR(L92*I92,"") | O92: =IFERROR(N92*I92,"") | P92: =IFERROR(M92-O92,"") | Q92: =IFERROR(N92*K92,"") | R92: =IFERROR(((U92+O92)-(V92+Q92))/(U92+O92),"") | S92: =IFERROR(SUM(OFFSET(Y92,0,MATCH(Forecast_New,$Y$3:$WQ$3,0)-1,1,500))*40,"") -> 0 | T92: =IFERROR(S92/8,"") -> 0 | U92: =IFERROR($S92*I92,"") | V92: =IFERROR($S92*K92,"") | W92: =IFERROR(M92-(O92+U92),"") | X92: =IFERROR(W92/M92,"")
B93: M3 Implementation of AI | C93: 2.4 Go Live | D93: Contractor-Delivery Manager/PM/Scrum Master/Scheduler | E93: Experienced Practitioner | G93: {=IFERROR(INDEX(Panel_Rates[[1]:[12]],MATCH(Panel_New&Category_New,Panel_Rates[Panel]&Panel_Rates[Category],0),MATCH('Time Plan HY'!E93,OFFSET(Variable!$AF$2,MATCH(Panel_New&Category_New,Panel_Rates[Panel]&Panel_Rates[Category],0)-1,0,1,12),0))/8,"")} -> 275 | I93: =IFERROR(G93*(1-H93),"") -> 275 | J93: =IFERROR(G93*8,"") -> 2200 | K93: =IFERROR(_xlfn.XLOOKUP(D93,CostTableLookup[Name],CostTableLookup[Gross Cost]),"") | M93: =IFERROR(L93*I93,"") -> 0 | O93: =IFERROR(N93*I93,"") -> 0 | P93: =IFERROR(M93-O93,"") -> 0 | Q93: =IFERROR(N93*K93,"") | R93: =IFERROR(((U93+O93)-(V93+Q93))/(U93+O93),"") | S93: =IFERROR(SUM(OFFSET(Y93,0,MATCH(Forecast_New,$Y$3:$WQ$3,0)-1,1,500))*40,"") -> 40 | T93: =IFERROR(S93/8,"") -> 5 | U93: =IFERROR($S93*I93,"") -> 11000 | V93: =IFERROR($S93*K93,"") | W93: =IFERROR(M93-(O93+U93),"") -> -11000 | X93: =IFERROR(W93/M93,"") | AZ93: 0.5 | BA93: 0.5
B94: M3 Implementation of AI | C94: 2.4 Go Live | D94: Contractor-Developer | E94: Junior Practitioner | G94: {=IFERROR(INDEX(Panel_Rates[[1]:[12]],MATCH(Panel_New&Category_New,Panel_Rates[Panel]&Panel_Rates[Category],0),MATCH('Time Plan HY'!E94,OFFSET(Variable!$AF$2,MATCH(Panel_New&Category_New,Panel_Rates[Panel]&Panel_Rates[Category],0)-1,0,1,12),0))/8,"")} -> 165 | I94: =IFERROR(G94*(1-H94),"") -> 165 | J94: =IFERROR(G94*8,"") -> 1320 | K94: =IFERROR(_xlfn.XLOOKUP(D94,CostTableLookup[Name],CostTableLookup[Gross Cost]),"") | M94: =IFERROR(L94*I94,"") -> 0 | O94: =IFERROR(N94*I94,"") -> 0 | P94: =IFERROR(M94-O94,"") -> 0 | Q94: =IFERROR(N94*K94,"") | R94: =IFERROR(((U94+O94)-(V94+Q94))/(U94+O94),"") | S94: =IFERROR(SUM(OFFSET(Y94,0,MATCH(Forecast_New,$Y$3:$WQ$3,0)-1,1,500))*40,"") -> 40 | T94: =IFERROR(S94/8,"") -> 5 | U94: =IFERROR($S94*I94,"") -> 6600 | V94: =IFERROR($S94*K94,"") | W94: =IFERROR(M94-(O94+U94),"") -> -6600 | X94: =IFERROR(W94/M94,"") | AZ94: 0.5 | BA94: 0.5
B95: M3 Implementation of AI | C95: 2.4 Go Live | D95: Contractor-Developer | E95: Experienced Practitioner | G95: {=IFERROR(INDEX(Panel_Rates[[1]:[12]],MATCH(Panel_New&Category_New,Panel_Rates[Panel]&Panel_Rates[Category],0),MATCH('Time Plan HY'!E95,OFFSET(Variable!$AF$2,MATCH(Panel_New&Category_New,Panel_Rates[Panel]&Panel_Rates[Category],0)-1,0,1,12),0))/8,"")} -> 275 | I95: =IFERROR(G95*(1-H95),"") -> 275 | J95: =IFERROR(G95*8,"") -> 2200 | K95: =IFERROR(_xlfn.XLOOKUP(D95,CostTableLookup[Name],CostTableLookup[Gross Cost]),"") | M95: =IFERROR(L95*I95,"") -> 0 | O95: =IFERROR(N95*I95,"") -> 0 | P95: =IFERROR(M95-O95,"") -> 0 | Q95: =IFERROR(N95*K95,"") | R95: =IFERROR(((U95+O95)-(V95+Q95))/(U95+O95),"") | S95: =IFERROR(SUM(OFFSET(Y95,0,MATCH(Forecast_New,$Y$3:$WQ$3,0)-1,1,500))*40,"") -> 40 | T95: =IFERROR(S95/8,"") -> 5 | U95: =IFERROR($S95*I95,"") -> 11000 | V95: =IFERROR($S95*K95,"") | W95: =IFERROR(M95-(O95+U95),"") -> -11000 | X95: =IFERROR(W95/M95,"") | AZ95: 0.5 | BA95: 0.5
B96: M3 Implementation of AI | C96: 2.4 Go Live | D96: Contractor-Test Manager | E96: Experienced Practitioner | G96: {=IFERROR(INDEX(Panel_Rates[[1]:[12]],MATCH(Panel_New&Category_New,Panel_Rates[Panel]&Panel_Rates[Category],0),MATCH('Time Plan HY'!E96,OFFSET(Variable!$AF$2,MATCH(Panel_New&Category_New,Panel_Rates[Panel]&Panel_Rates[Category],0)-1,0,1,12),0))/8,"")} -> 275 | I96: =IFERROR(G96*(1-H96),"") -> 275 | J96: =IFERROR(G96*8,"") -> 2200 | K96: =IFERROR(_xlfn.XLOOKUP(D96,CostTableLookup[Name],CostTableLookup[Gross Cost]),"") | M96: =IFERROR(L96*I96,"") -> 0 | O96: =IFERROR(N96*I96,"") -> 0 | P96: =IFERROR(M96-O96,"") -> 0 | Q96: =IFERROR(N96*K96,"") | R96: =IFERROR(((U96+O96)-(V96+Q96))/(U96+O96),"") | S96: =IFERROR(SUM(OFFSET(Y96,0,MATCH(Forecast_New,$Y$3:$WQ$3,0)-1,1,500))*40,"") -> 40 | T96: =IFERROR(S96/8,"") -> 5 | U96: =IFERROR($S96*I96,"") -> 11000 | V96: =IFERROR($S96*K96,"") | W96: =IFERROR(M96-(O96+U96),"") -> -11000 | X96: =IFERROR(W96/M96,"") | AZ96: 0.5 | BA96: 0.5
G97: {=IFERROR(INDEX(Panel_Rates[[1]:[12]],MATCH(Panel_New&Category_New,Panel_Rates[Panel]&Panel_Rates[Category],0),MATCH('Time Plan HY'!E97,OFFSET(Variable!$AF$2,MATCH(Panel_New&Category_New,Panel_Rates[Panel]&Panel_Rates[Category],0)-1,0,1,12),0))/8,"")} | I97: =IFERROR(G97*(1-H97),"") | J97: =IFERROR(G97*8,"") | K97: =IFERROR(_xlfn.XLOOKUP(D97,CostTableLookup[Name],CostTableLookup[Gross Cost]),"") | M97: =IFERROR(L97*I97,"") | O97: =IFERROR(N97*I97,"") | P97: =IFERROR(M97-O97,"") | Q97: =IFERROR(N97*K97,"") | R97: =IFERROR(((U97+O97)-(V97+Q97))/(U97+O97),"") | S97: =IFERROR(SUM(OFFSET(Y97,0,MATCH(Forecast_New,$Y$3:$WQ$3,0)-1,1,500))*40,"") -> 0 | T97: =IFERROR(S97/8,"") -> 0 | U97: =IFERROR($S97*I97,"") | V97: =IFERROR($S97*K97,"") | W97: =IFERROR(M97-(O97+U97),"") | X97: =IFERROR(W97/M97,"")
G98: {=IFERROR(INDEX(Panel_Rates[[1]:[12]],MATCH(Panel_New&Category_New,Panel_Rates[Panel]&Panel_Rates[Category],0),MATCH('Time Plan HY'!E98,OFFSET(Variable!$AF$2,MATCH(Panel_New&Category_New,Panel_Rates[Panel]&Panel_Rates[Category],0)-1,0,1,12),0))/8,"")} | I98: =IFERROR(G98*(1-H98),"") | J98: =IFERROR(G98*8,"") | K98: =IFERROR(_xlfn.XLOOKUP(D98,CostTableLookup[Name],CostTableLookup[Gross Cost]),"") | M98: =IFERROR(L98*I98,"") | O98: =IFERROR(N98*I98,"") | P98: =IFERROR(M98-O98,"") | Q98: =IFERROR(N98*K98,"") | R98: =IFERROR(((U98+O98)-(V98+Q98))/(U98+O98),"") | S98: =IFERROR(SUM(OFFSET(Y98,0,MATCH(Forecast_New,$Y$3:$WQ$3,0)-1,1,500))*40,"") -> 0 | T98: =IFERROR(S98/8,"") -> 0 | U98: =IFERROR($S98*I98,"") | V98: =IFERROR($S98*K98,"") | W98: =IFERROR(M98-(O98+U98),"") | X98: =IFERROR(W98/M98,"")
G99: {=IFERROR(INDEX(Panel_Rates[[1]:[12]],MATCH(Panel_New&Category_New,Panel_Rates[Panel]&Panel_Rates[Category],0),MATCH('Time Plan HY'!E99,OFFSET(Variable!$AF$2,MATCH(Panel_New&Category_New,Panel_Rates[Panel]&Panel_Rates[Category],0)-1,0,1,12),0))/8,"")} | I99: =IFERROR(G99*(1-H99),"") | J99: =IFERROR(G99*8,"") | K99: =IFERROR(_xlfn.XLOOKUP(D99,CostTableLookup[Name],CostTableLookup[Gross Cost]),"") | M99: =IFERROR(L99*I99,"") | O99: =IFERROR(N99*I99,"") | P99: =IFERROR(M99-O99,"") | Q99: =IFERROR(N99*K99,"") | R99: =IFERROR(((U99+O99)-(V99+Q99))/(U99+O99),"") | S99: =IFERROR(SUM(OFFSET(Y99,0,MATCH(Forecast_New,$Y$3:$WQ$3,0)-1,1,500))*40,"") -> 0 | T99: =IFERROR(S99/8,"") -> 0 | U99: =IFERROR($S99*I99,"") | V99: =IFERROR($S99*K99,"") | W99: =IFERROR(M99-(O99+U99),"") | X99: =IFERROR(W99/M99,"")
G100: {=IFERROR(INDEX(Panel_Rates[[1]:[12]],MATCH(Panel_New&Category_New,Panel_Rates[Panel]&Panel_Rates[Category],0),MATCH('Time Plan HY'!E100,OFFSET(Variable!$AF$2,MATCH(Panel_New&Category_New,Panel_Rates[Panel]&Panel_Rates[Category],0)-1,0,1,12),0))/8,"")} | I100: =IFERROR(G100*(1-H100),"") | J100: =IFERROR(G100*8,"") | K100: =IFERROR(_xlfn.XLOOKUP(D100,CostTableLookup[Name],CostTableLookup[Gross Cost]),"") | M100: =IFERROR(L100*I100,"") | O100: =IFERROR(N100*I100,"") | P100: =IFERROR(M100-O100,"") | Q100: =IFERROR(N100*K100,"") | R100: =IFERROR(((U100+O100)-(V100+Q100))/(U100+O100),"") | S100: =IFERROR(SUM(OFFSET(Y100,0,MATCH(Forecast_New,$Y$3:$WQ$3,0)-1,1,500))*40,"") -> 0 | T100: =IFERROR(S100/8,"") -> 0 | U100: =IFERROR($S100*I100,"") | V100: =IFERROR($S100*K100,"") | W100: =IFERROR(M100-(O100+U100),"") | X100: =IFERROR(W100/M100,"")
G101: {=IFERROR(INDEX(Panel_Rates[[1]:[12]],MATCH(Panel_New&Category_New,Panel_Rates[Panel]&Panel_Rates[Category],0),MATCH('Time Plan HY'!E101,OFFSET(Variable!$AF$2,MATCH(Panel_New&Category_New,Panel_Rates[Panel]&Panel_Rates[Category],0)-1,0,1,12),0))/8,"")} | I101: =IFERROR(G101*(1-H101),"") | J101: =IFERROR(G101*8,"") | K101: =IFERROR(_xlfn.XLOOKUP(D101,CostTableLookup[Name],CostTableLookup[Gross Cost]),"") | M101: =IFERROR(L101*I101,"") | O101: =IFERROR(N101*I101,"") | P101: =IFERROR(M101-O101,"") | Q101: =IFERROR(N101*K101,"") | R101: =IFERROR(((U101+O101)-(V101+Q101))/(U101+O101),"") | S101: =IFERROR(SUM(OFFSET(Y101,0,MATCH(Forecast_New,$Y$3:$WQ$3,0)-1,1,500))*40,"") -> 0 | T101: =IFERROR(S101/8,"") -> 0 | U101: =IFERROR($S101*I101,"") | V101: =IFERROR($S101*K101,"") | W101: =IFERROR(M101-(O101+U101),"") | X101: =IFERROR(W101/M101,"")
G102: {=IFERROR(INDEX(Panel_Rates[[1]:[12]],MATCH(Panel_New&Category_New,Panel_Rates[Panel]&Panel_Rates[Category],0),MATCH('Time Plan HY'!E102,OFFSET(Variable!$AF$2,MATCH(Panel_New&Category_New,Panel_Rates[Panel]&Panel_Rates[Category],0)-1,0,1,12),0))/8,"")} | I102: =IFERROR(G102*(1-H102),"") | J102: =IFERROR(G102*8,"") | K102: =IFERROR(_xlfn.XLOOKUP(D102,CostTableLookup[Name],CostTableLookup[Gross Cost]),"") | M102: =IFERROR(L102*I102,"") | O102: =IFERROR(N102*I102,"") | P102: =IFERROR(M102-O102,"") | Q102: =IFERROR(N102*K102,"") | R102: =IFERROR(((U102+O102)-(V102+Q102))/(U102+O102),"") | S102: =IFERROR(SUM(OFFSET(Y102,0,MATCH(Forecast_New,$Y$3:$WQ$3,0)-1,1,500))*40,"") -> 0 | T102: =IFERROR(S102/8,"") -> 0 | U102: =IFERROR($S102*I102,"") | V102: =IFERROR($S102*K102,"") | W102: =IFERROR(M102-(O102+U102),"") | X102: =IFERROR(W102/M102,"")
G103: {=IFERROR(INDEX(Panel_Rates[[1]:[12]],MATCH(Panel_New&Category_New,Panel_Rates[Panel]&Panel_Rates[Category],0),MATCH('Time Plan HY'!E103,OFFSET(Variable!$AF$2,MATCH(Panel_New&Category_New,Panel_Rates[Panel]&Panel_Rates[Category],0)-1,0,1,12),0))/8,"")} | I103: =IFERROR(G103*(1-H103),"") | J103: =IFERROR(G103*8,"") | K103: =IFERROR(_xlfn.XLOOKUP(D103,CostTableLookup[Name],CostTableLookup[Gross Cost]),"") | M103: =IFERROR(L103*I103,"") | O103: =IFERROR(N103*I103,"") | P103: =IFERROR(M103-O103,"") | Q103: =IFERROR(N103*K103,"") | R103: =IFERROR(((U103+O103)-(V103+Q103))/(U103+O103),"") | S103: =IFERROR(SUM(OFFSET(Y103,0,MATCH(Forecast_New,$Y$3:$WQ$3,0)-1,1,500))*40,"") -> 0 | T103: =IFERROR(S103/8,"") -> 0 | U103: =IFERROR($S103*I103,"") | V103: =IFERROR($S103*K103,"") | W103: =IFERROR(M103-(O103+U103),"") | X103: =IFERROR(W103/M103,"")
G104: {=IFERROR(INDEX(Panel_Rates[[1]:[12]],MATCH(Panel_New&Category_New,Panel_Rates[Panel]&Panel_Rates[Category],0),MATCH('Time Plan HY'!E104,OFFSET(Variable!$AF$2,MATCH(Panel_New&Category_New,Panel_Rates[Panel]&Panel_Rates[Category],0)-1,0,1,12),0))/8,"")} | I104: =IFERROR(G104*(1-H104),"") | J104: =IFERROR(G104*8,"") | K104: =IFERROR(_xlfn.XLOOKUP(D104,CostTableLookup[Name],CostTableLookup[Gross Cost]),"") | M104: =IFERROR(L104*I104,"") | O104: =IFERROR(N104*I104,"") | P104: =IFERROR(M104-O104,"") | Q104: =IFERROR(N104*K104,"") | R104: =IFERROR(((U104+O104)-(V104+Q104))/(U104+O104),"") | S104: =IFERROR(SUM(OFFSET(Y104,0,MATCH(Forecast_New,$Y$3:$WQ$3,0)-1,1,500))*40,"") -> 0 | T104: =IFERROR(S104/8,"") -> 0 | U104: =IFERROR($S104*I104,"") | V104: =IFERROR($S104*K104,"") | W104: =IFERROR(M104-(O104+U104),"") | X104: =IFERROR(W104/M104,"")
G105: {=IFERROR(INDEX(Panel_Rates[[1]:[12]],MATCH(Panel_New&Category_New,Panel_Rates[Panel]&Panel_Rates[Category],0),MATCH('Time Plan HY'!E105,OFFSET(Variable!$AF$2,MATCH(Panel_New&Category_New,Panel_Rates[Panel]&Panel_Rates[Category],0)-1,0,1,12),0))/8,"")} | I105: =IFERROR(G105*(1-H105),"") | J105: =IFERROR(G105*8,"") | K105: =IFERROR(_xlfn.XLOOKUP(D105,CostTableLookup[Name],CostTableLookup[Gross Cost]),"") | M105: =IFERROR(L105*I105,"") | O105: =IFERROR(N105*I105,"") | P105: =IFERROR(M105-O105,"") | Q105: =IFERROR(N105*K105,"") | R105: =IFERROR(((U105+O105)-(V105+Q105))/(U105+O105),"") | S105: =IFERROR(SUM(OFFSET(Y105,0,MATCH(Forecast_New,$Y$3:$WQ$3,0)-1,1,500))*40,"") -> 0 | T105: =IFERROR(S105/8,"") -> 0 | U105: =IFERROR($S105*I105,"") | V105: =IFERROR($S105*K105,"") | W105: =IFERROR(M105-(O105+U105),"") | X105: =IFERROR(W105/M105,"")
...

Sheet Variable
B1: Client Name | C1: VAT | D1: VAT Lead | F1: Names | H1: Name | I1: Gross Cost | J1: JID | K1: Schedule Start | L1: Schedule End | M1: Team | N1: Comments | O1: Location | Q1: Panel | R1: Category | S1: 1 | T1: 2 | U1: 3 | V1: 4 | W1: 5 | X1: 6 | Y1: 7 | Z1: 8 | AA1: 9 | AB1: 10 | AC1: 11 | AD1: 12 | AF1: 1 | AG1: 2 | AH1: 3 | AI1: 4 | AJ1: 5 | AK1: 6 | AL1: 7 | AM1: 8 | AN1: 9 | AO1: 10 | AP1: 11 | AQ1: 12 | AS1: Mondays | AT1: ACT Public Holidays | AV1: Panel | AX1: Category List | AZ1: Level_List
B2: AAT - Administrative Appeals Tribunal | C2: Growth | D2: Aleksandar Vranesevic | F2: Aleksandar Vranesevic | H2: Aaron Riddell | I2: 100 | J2: CO2 | M2: CSD | Q2: Reason Group - Standard Rates | R2: Market Rates | S2: 1320 | T2: 1520 | U2: 1960 | V2: 2440 | W2: 3160 | X2: 3960 | AF2: Consultant | AG2: Senior Consultant | AH2: Manager | AI2: Senior Manager | AJ2: Director | AK2: Partner | AS2: 45586 | AV2: ACT Govt - Professional and Consulting Services Panel | AX2: {=IF(Panel_Rates[Panel]=Panel_New,Panel_Rates[Category],"")} | AZ2: {=TRANSPOSE(_xlfn._xlws.FILTER(Panel_Names[], Panel_Rates[Panel]&Panel_Rates[Category]=Panel_New&Category_New))} -> Level 1
B3: ABC - Australian Broadcasting Corporation | C3: Growth | D3: Aleksandar Vranesevic | F3: Alex Kocz | H3: Aaron Yang | I3: 130 | J3: EN3 | M3: CSD | Q3: Digital Marketplace | R3: Strategy and Policy | S3: 1320 | T3: 1520 | U3: 1700 | V3: 2000 | W3: 2320 | X3: 2720 | Y3: 4000 | Z3: 4550 | AF3: Associate | AG3: Consultant | AH3: Senior Consultant | AI3: Manager | AJ3: Senior Manager | AK3: Principal Consultant | AL3: Partner | AM3: Senior Partner | AS3: =AS2+7 -> 45593 | AV3: Alex Kocz - Custom Rates | AZ3: Level 2
B4: ABS - Australian Bureau of Statistics | C4: Growth | D4: Aleksandar Vranesevic | F4: Anil Kinagi | H4: Abdul Mohammad | I4: 147 | J4: 0 | K4: 45628 | L4: 46326 | M4: CSD | Q4: Digital Marketplace | R4: Change and Transformation | S4: 1320 | T4: 1520 | U4: 1700 | V4: 2000 | W4: 2320 | X4: 2720 | Y4: 4000 | Z4: 4550 | AF4: Associate | AG4: Consultant | AH4: Senior Consultant | AI4: Manager | AJ4: Senior Manager | AK4: Principal Consultant | AL4: Partner | AM4: Senior Partner | AS4: =AS3+7 -> 45600 | AV4: Boston Consulting Group (BCG) - teaming rates | AZ4: Level 3
B5: ACC - Australia Competition and Consumer Commission | C5: Growth | D5: Aleksandar Vranesevic | F5: Arjun Wariar | H5: Abhinav Arya | I5: 193 | J5: 0 | M5: CSD | Q5: Digital Marketplace | R5: Agile delivery and Governance | S5: 1320 | T5: 1520 | U5: 1700 | V5: 2000 | W5: 2320 | X5: 2720 | Y5: 4000 | Z5: 4550 | AF5: Associate | AG5: Consultant | AH5: Senior Consultant | AI5: Manager | AJ5: Senior Manager | AK5: Principal Consultant | AL5: Partner | AM5: Senior Partner | AS5: =AS4+7 -> 45607 | AV5: DAFF DBD DM-26233 - Contractor micropanel | AZ5: Level 4
B6: ACI - Australian Criminal Intelligence Commission | C6: Growth | D6: Scott Foley | F6: Hadas Yehezkel | H6: Adam Harris | I6: 193 | J6: 0 | M6: CSD | Q6: Digital Marketplace | R6: Digital sourcing and ICT procurement | S6: 1320 | T6: 1520 | U6: 1700 | V6: 2000 | W6: 2320 | X6: 2720 | Y6: 4000 | Z6: 4550 | AF6: Associate | AG6: Consultant | AH6: Senior Consultant | AI6: Manager | AJ6: Senior Manager | AK6: Principal Consultant | AL6: Partner | AM6: Senior Partner | AS6: =AS5+7 -> 45614 | AV6: DAFF STEPS - Advisory micropanel | AZ6: Level 5
B7: ACM - Australian Communications and Media Authority | C7: Growth | D7: Aleksandar Vranesevic | F7: Joelle Blake | H7: Adeel Rtiaz Qadri | I7: 125 | J7: 0 | M7: CSD | Q7: Digital Marketplace | R7: ICT risk management and audit activities | S7: 1320 | T7: 1520 | U7: 1700 | V7: 2000 | W7: 2320 | X7: 2720 | Y7: 4000 | Z7: 4550 | AF7: Associate | AG7: Consultant | AH7: Senior Consultant | AI7: Manager | AJ7: Senior Manager | AK7: Principal Consultant | AL7: Partner | AM7: Senior Partner | AS7: =AS6+7 -> 45621 | AV7: Defence - ICT Provider Arrangement (ICTPA) | AZ7: Level 6
B8: ACR - Accenture | C8: Growth | D8: Scott Foley | F8: Lacy Pejcinovic | H8: Adi Mukherjee | I8: 189.66 | J8: 0 | M8: CSD | Q8: Digital Marketplace | R8: User research and Design | S8: 1320 | T8: 1520 | U8: 1700 | V8: 2000 | W8: 2320 | X8: 2720 | Y8: 4000 | Z8: 4550 | AF8: Associate | AG8: Consultant | AH8: Senior Consultant | AI8: Manager | AJ8: Senior Manager | AK8: Principal Consultant | AL8: Partner | AM8: Senior Partner | AS8: =AS7+7 -> 45628 | AV8: Department of Finance - Management Advisory Services
B9: ACS - Australian Commission on Safety and Quality in Health Care | C9: Growth | D9: Aleksandar Vranesevic | F9: Mark Volpato | H9: Ahmed Shaikh | I9: 152.91 | J9: 0 | K9: 45880 | L9: 45991 | M9: CSD | Q9: Digital Marketplace | R9: Software engineering and Development | S9: 1320 | T9: 1520 | U9: 1700 | V9: 2000 | W9: 2320 | X9: 2720 | Y9: 4000 | Z9: 4550 | AF9: Associate | AG9: Consultant | AH9: Senior Consultant | AI9: Manager | AJ9: Senior Manager | AK9: Principal Consultant | AL9: Partner | AM9: Senior Partner | AS9: =AS8+7 -> 45635 | AV9: Digital Marketplace
B10: ACT - ACT Government | C10: Growth | D10: Aleksandar Vranesevic | F10: Michelle Chant | H10: Ajay Peddu | I10: 145 | J10: 0 | M10: CSD | Q10: Digital Marketplace | R10: Marketing, Communications and Engagement | S10: 1320 | T10: 1520 | U10: 1700 | V10: 2000 | W10: 2320 | X10: 2720 | Y10: 4000 | Z10: 4550 | AF10: Associate | AG10: Consultant | AH10: Senior Consultant | AI10: Manager | AJ10: Senior Manager | AK10: Principal Consultant | AL10: Partner | AM10: Senior Partner | AS10: =AS9+7 -> 45642 | AV10: Digital Marketplace 2
B11: ADE - Australian Diabetes Educators Association | C11: Growth | D11: Aleksandar Vranesevic | F11: Nathan Richards | H11: Ajit Thomas | I11: 200 | J11: EN4 | M11: CSD | Q11: Digital Marketplace | R11: Support and Operations | S11: 1320 | T11: 1520 | U11: 1700 | V11: 2000 | W11: 2320 | X11: 2720 | Y11: 4000 | Z11: 4550 | AF11: Associate | AG11: Consultant | AH11: Senior Consultant | AI11: Manager | AJ11: Senior Manager | AK11: Principal Consultant | AL11: Partner | AM11: Senior Partner | AS11: =AS10+7 -> 45649 | AT11: 1 | AV11: DOH SME Supplementary Teams Arrangement (STA) - micropanel
