Workbook
Name CompanyFairToggle: Summary!$D$61
Name CompanyGoodToggle: Summary!$D$60
Name CompanyRiskToggle: Summary!$D$62
Name DAFFFairToggle: 'DAFF VAT Summary'!$M$3
Name DAFFGoodToggle: 'DAFF VAT Summary'!$L$3
Name DAFFRiskToggle: 'DAFF VAT Summary'!$N$3
Name DISRFairToggle: 'DISR VAT Summary'!$M$3
Name DISRGoodToggle: 'DISR VAT Summary'!$L$3
Name DISRRiskToggle: 'DISR VAT Summary'!$N$3
Name EmergingFairToggle: 'EMERGING VAT Summary'!$M$3
Name EmergingGoodToggle: 'EMERGING VAT Summary'!$L$3
Name EmergingRiskToggle: 'EMERGING VAT Summary'!$N$3
Name FairToggle: 'COMPANY Spread'!$E$64
Name GoodToggle: 'COMPANY Spread'!$D$64
Name GROWTHFairToggle: 'GROWTH VAT Summary'!$M$3
Name GROWTHGoodToggle: 'GROWTH VAT Summary'!$L$3
Name GROWTHRiskToggle: 'GROWTH VAT Summary'!$N$3
Name QBlockGMC: _xlfn.LET(_xlpm.top,'Q Spread Calculation'!$A$4, OFFSET(_xlpm.top, -1, 0, ROWS(_xlfn.ANCHORARRAY(_xlpm.top))+1, COLUMNS(_xlfn.ANCHORARRAY(_xlpm.top))+12))
Name QBlockRev: _xlfn.LET(_xlpm.top,'Q Spread Calculation'!$S$4, OFFSET(_xlpm.top, -1, 0, ROWS(_xlfn.ANCHORARRAY(_xlpm.top))+1, COLUMNS(_xlfn.ANCHORARRAY(_xlpm.top))+12))
Name RiskToggle: 'COMPANY Spread'!$F$64
Name SAUFairToggle: 'DISR VAT Summary'!$M$3
Name SAUFairToggle: 'EMERGING VAT Summary'!$M$3
Name SAUFairToggle: 'SAU VAT Summary'!$M$3
Name SAUGoodToggle: 'DISR VAT Summary'!$L$3
Name SAUGoodToggle: 'EMERGING VAT Summary'!$L$3
Name SAUGoodToggle: 'SAU VAT Summary'!$L$3
Name SAURiskToggle: 'DISR VAT Summary'!$N$3
Name SAURiskToggle: 'EMERGING VAT Summary'!$N$3
Name SAURiskToggle: 'SAU VAT Summary'!$N$3
Name Slicer_Status: #N/A
Name Slicer_VAT: #N/A
Name Slicer_VAT1: #N/A
Name VATSelector: 'COMPANY Spread'!$B$66
Name VICFairToggle: 'VIC VAT Summary'!$M$3
Name VICGoodToggle: 'VIC VAT Summary'!$L$3
Name VICRiskToggle: 'VIC VAT Summary'!$N$3

Sheet Summary
B2: SALES DASHBOARD
C5: TOTAL | D5: Revenue Target | H5: Revenue
D6: OK | E6: Good | F6: Great | G6: Amazing | H6: Earned to Date | J6: Revenue | K6: GM % | L6: Current Jobs @ Completion | N6: Revenue | O6: GM % | P6: Plus Selected | R6: Plus Shortlisted (DVF) | T6: Plus Submitted (DF)
D7: ='FY2526 VAT Financial KPIs'!E4 -> 24648402 | E7: ='FY2526 VAT Financial KPIs'!F4 -> 33946753 | F7: ='FY2526 VAT Financial KPIs'!G4 -> 42979437 | G7: ='FY2526 VAT Financial KPIs'!H4 -> 46362500 | H7: =Job_Status[[#Totals],[Actual]] -> 14133437 | I7: =H7/E7 -> 0.41634135 | L7: =Job_Status[[#Totals],[Forecasted Revenue]] -> 20744604 | M7: =L7/E7 -> 0.61109242 | P7: =IF(CompanyGoodToggle=TRUE,SUMIFS(OppSpreadData[FY25/26],OppSpreadData[Open Opps Phase],"5.S - Selected",OppSpreadData[OppsStatus],"Good"),0)+IF(CompanyFairToggle=TRUE,SUMIFS(OppSpreadData[FY25/26],OppSpreadData[Open Opps Phase],"5.S - Selected",OppSpreadData[OppsStatus],"Fair"),0)+IF(CompanyRiskToggle=TRUE,SUMIFS(OppSpreadData[FY25/26],OppSpreadData[Open Opps Phase],"5.S - Selected",OppSpreadData[OppsStatus],"Risk"),0)+L7 -> 20744604 | Q7: =P7/E7 -> 0.61109242 | R7: =IF(CompanyGoodToggle=TRUE,SUMIFS(OppSpreadData[FY25/26],OppSpreadData[Open Opps Phase],"4.DVF - Shortlisted",OppSpreadData[OppsStatus],"Good"),0)+IF(CompanyFairToggle=TRUE,SUMIFS(OppSpreadData[FY25/26],OppSpreadData[Open Opps Phase],"4.DVF - Shortlisted",OppSpreadData[OppsStatus],"Fair"),0)+IF(CompanyRiskToggle=TRUE,SUMIFS(OppSpreadData[FY25/26],OppSpreadData[Open Opps Phase],"4.DVF - Shortlisted",OppSpreadData[OppsStatus],"Risk"),0)+P7 -> 25242354 | S7: =R7/E7 -> 0.74358669 | T7: =IF(CompanyGoodToggle=TRUE,SUMIFS(OppSpreadData[FY25/26],OppSpreadData[Open Opps Phase],"3.DF - Submitted",OppSpreadData[OppsStatus],"Good"),0)+IF(CompanyFairToggle=TRUE,SUMIFS(OppSpreadData[FY25/26],OppSpreadData[Open Opps Phase],"3.DF - Submitted",OppSpreadData[OppsStatus],"Fair"),0)+IF(CompanyRiskToggle=TRUE,SUMIFS(OppSpreadData[FY25/26],OppSpreadData[Open Opps Phase],"3.DF - Submitted",OppSpreadData[OppsStatus],"Risk"),0)+R7 -> 25242354 | U7: =T7/E7 -> 0.74358669
D8: Gross Margin Contribution Target | H8: GM Contribution
C9: VAT | D9: OK | E9: Good | F9: Great | G9: Amazing | H9: Earned to Date | J9: Revenue | K9: GM % | L9: Current Jobs @ Completion | N9: Revenue | O9: GM % | P9: Plus Selected | R9: Plus Shortlisted (DVF) | T9: Plus Submitted (DF)
C10: DAFF | D10: ='FY2526 VAT Financial KPIs'!E7 -> 1800000 | E10: ='FY2526 VAT Financial KPIs'!F7 -> 2250000 | F10: ='FY2526 VAT Financial KPIs'!G7 -> 2700000 | G10: ='FY2526 VAT Financial KPIs'!H7 -> 3150000 | H10: =SUMIF(Job_Status[VAT],Summary!C10,Job_Status[To Date Gross Profit]) -> 799904.52 | I10: =H10/E10 -> 0.35551312 | J10: =SUMIF(Job_Status[VAT],Summary!C10,Job_Status[Actual]) -> 3157524.8 | K10: =IFERROR(H10/J10,"") -> 0.25333278 | L10: =SUMIF(Job_Status[VAT],Summary!C10,Job_Status[GP at completion]) -> 1019174.6 | M10: =L10/E10 -> 0.45296649 | N10: =SUMIF(Job_Status[VAT],Summary!C10,Job_Status[Forecasted Revenue]) -> 4480245.8 | O10: =L10/N10 -> 0.22748185 | P10: =IF(CompanyGoodToggle=TRUE,SUMIFS(TotalGMContribution[FY25/26],TotalGMContribution[Opps Status],"Good",TotalGMContribution[Open Opps Phase],"5.S - Selected",TotalGMContribution[VAT],Summary!$C10),0)+IF(CompanyFairToggle=TRUE,SUMIFS(TotalGMContribution[FY25/26],TotalGMContribution[Opps Status],"Fair",TotalGMContribution[Open Opps Phase],"5.S - Selected",TotalGMContribution[VAT],Summary!$C10),0)+IF(CompanyRiskToggle=TRUE,SUMIFS(TotalGMContribution[FY25/26],TotalGMContribution[Opps Status],"Risk",TotalGMContribution[Open Opps Phase],"5.S - Selected",TotalGMContribution[VAT],Summary!$C10),0)+L10 -> 1019174.6 | Q10: =P10/E10 -> 0.45296649 | R10: =IF(CompanyGoodToggle=TRUE,SUMIFS(TotalGMContribution[FY25/26],TotalGMContribution[Opps Status],"Good",TotalGMContribution[Open Opps Phase],"4.DVF - Shortlisted",TotalGMContribution[VAT],Summary!$C10),0)+IF(CompanyFairToggle=TRUE,SUMIFS(TotalGMContribution[FY25/26],TotalGMContribution[Opps Status],"Fair",TotalGMContribution[Open Opps Phase],"4.DVF - Shortlisted",TotalGMContribution[VAT],Summary!$C10),0)+IF(CompanyRiskToggle=TRUE,SUMIFS(TotalGMContribution[FY25/26],TotalGMContribution[Opps Status],"Risk",TotalGMContribution[Open Opps Phase],"4.DVF - Shortlisted",TotalGMContribution[VAT],Summary!$C10),0)+P10 -> 1019174.6 | S10: =R10/E10 -> 0.45296649 | T10: =IF(CompanyGoodToggle=TRUE,SUMIFS(TotalGMContribution[FY25/26],TotalGMContribution[Opps Status],"Good",TotalGMContribution[Open Opps Phase],"3.DF - Submitted",TotalGMContribution[VAT],Summary!$C10),0)+IF(CompanyFairToggle=TRUE,SUMIFS(TotalGMContribution[FY25/26],TotalGMContribution[Opps Status],"Fair",TotalGMContribution[Open Opps Phase],"3.DF - Submitted",TotalGMContribution[VAT],Summary!$C10),0)+IF(CompanyRiskToggle=TRUE,SUMIFS(TotalGMContribution[FY25/26],TotalGMContribution[Opps Status],"Risk",TotalGMContribution[Open Opps Phase],"3.DF - Submitted",TotalGMContribution[VAT],Summary!$C10),0)+R10 -> 1019174.6 | U10: =T10/E10 -> 0.45296649
C11: SAU | D11: ='FY2526 VAT Financial KPIs'!E15 -> 900000 | E11: ='FY2526 VAT Financial KPIs'!F15 -> 1350000 | F11: ='FY2526 VAT Financial KPIs'!G15 -> 1800000 | G11: ='FY2526 VAT Financial KPIs'!H15 -> 2250000 | H11: =SUMIF(Job_Status[VAT],Summary!C11,Job_Status[To Date Gross Profit]) -> 371345.48 | I11: =H11/E11 -> 0.27507073 | J11: =SUMIF(Job_Status[VAT],Summary!C11,Job_Status[Actual]) -> 2815849.9 | K11: =IFERROR(H11/J11,"") -> 0.13187687 | L11: =SUMIF(Job_Status[VAT],Summary!C11,Job_Status[GP at completion]) -> 587063.76 | M11: =L11/E11 -> 0.43486204 | N11: =SUMIF(Job_Status[VAT],Summary!C11,Job_Status[Forecasted Revenue]) -> 4568637.9 | O11: =L11/N11 -> 0.12849864 | P11: =IF(CompanyGoodToggle=TRUE,SUMIFS(TotalGMContribution[FY25/26],TotalGMContribution[Opps Status],"Good",TotalGMContribution[Open Opps Phase],"5.S - Selected",TotalGMContribution[VAT],Summary!$C11),0)+IF(CompanyFairToggle=TRUE,SUMIFS(TotalGMContribution[FY25/26],TotalGMContribution[Opps Status],"Fair",TotalGMContribution[Open Opps Phase],"5.S - Selected",TotalGMContribution[VAT],Summary!$C11),0)+IF(CompanyRiskToggle=TRUE,SUMIFS(TotalGMContribution[FY25/26],TotalGMContribution[Opps Status],"Risk",TotalGMContribution[Open Opps Phase],"5.S - Selected",TotalGMContribution[VAT],Summary!$C11),0)+L11 -> 587063.76 | Q11: =P11/E11 -> 0.43486204 | R11: =IF(CompanyGoodToggle=TRUE,SUMIFS(TotalGMContribution[FY25/26],TotalGMContribution[Opps Status],"Good",TotalGMContribution[Open Opps Phase],"4.DVF - Shortlisted",TotalGMContribution[VAT],Summary!$C11),0)+IF(CompanyFairToggle=TRUE,SUMIFS(TotalGMContribution[FY25/26],TotalGMContribution[Opps Status],"Fair",TotalGMContribution[Open Opps Phase],"4.DVF - Shortlisted",TotalGMContribution[VAT],Summary!$C11),0)+IF(CompanyRiskToggle=TRUE,SUMIFS(TotalGMContribution[FY25/26],TotalGMContribution[Opps Status],"Risk",TotalGMContribution[Open Opps Phase],"4.DVF - Shortlisted",TotalGMContribution[VAT],Summary!$C11),0)+P11 -> 618169.2 | S11: =R11/E11 -> 0.45790311 | T11: =IF(CompanyGoodToggle=TRUE,SUMIFS(TotalGMContribution[FY25/26],TotalGMContribution[Opps Status],"Good",TotalGMContribution[Open Opps Phase],"3.DF - Submitted",TotalGMContribution[VAT],Summary!$C11),0)+IF(CompanyFairToggle=TRUE,SUMIFS(TotalGMContribution[FY25/26],TotalGMContribution[Opps Status],"Fair",TotalGMContribution[Open Opps Phase],"3.DF - Submitted",TotalGMContribution[VAT],Summary!$C11),0)+IF(CompanyRiskToggle=TRUE,SUMIFS(TotalGMContribution[FY25/26],TotalGMContribution[Opps Status],"Risk",TotalGMContribution[Open Opps Phase],"3.DF - Submitted",TotalGMContribution[VAT],Summary!$C11),0)+R11 -> 618169.2 | U11: =T11/E11 -> 0.45790311
C12: VIC Gov | D12: ='FY2526 VAT Financial KPIs'!E11 -> 1800000 | E12: ='FY2526 VAT Financial KPIs'!F11 -> 2250000 | F12: ='FY2526 VAT Financial KPIs'!G11 -> 2700000 | G12: ='FY2526 VAT Financial KPIs'!H11 -> 3150000 | H12: =SUMIF(Job_Status[VAT],Summary!C12,Job_Status[To Date Gross Profit]) -> 1008147.9 | I12: =H12/E12 -> 0.44806574 | J12: =SUMIF(Job_Status[VAT],Summary!C12,Job_Status[Actual]) -> 3194123.7 | K12: =IFERROR(H12/J12,"") -> 0.31562582 | L12: =SUMIF(Job_Status[VAT],Summary!C12,Job_Status[GP at completion]) -> 1026935 | M12: =L12/E12 -> 0.45641557 | N12: =SUMIF(Job_Status[VAT],Summary!C12,Job_Status[Forecasted Revenue]) -> 3253993.7 | O12: =L12/N12 -> 0.3155922 | P12: =IF(CompanyGoodToggle=TRUE,SUMIFS(TotalGMContribution[FY25/26],TotalGMContribution[Opps Status],"Good",TotalGMContribution[Open Opps Phase],"5.S - Selected",TotalGMContribution[VAT],Summary!$C12),0)+IF(CompanyFairToggle=TRUE,SUMIFS(TotalGMContribution[FY25/26],TotalGMContribution[Opps Status],"Fair",TotalGMContribution[Open Opps Phase],"5.S - Selected",TotalGMContribution[VAT],Summary!$C12),0)+IF(CompanyRiskToggle=TRUE,SUMIFS(TotalGMContribution[FY25/26],TotalGMContribution[Opps Status],"Risk",TotalGMContribution[Open Opps Phase],"5.S - Selected",TotalGMContribution[VAT],Summary!$C12),0)+L12 -> 1026935 | Q12: =P12/E12 -> 0.45641557 | R12: =IF(CompanyGoodToggle=TRUE,SUMIFS(TotalGMContribution[FY25/26],TotalGMContribution[Opps Status],"Good",TotalGMContribution[Open Opps Phase],"4.DVF - Shortlisted",TotalGMContribution[VAT],Summary!$C12),0)+IF(CompanyFairToggle=TRUE,SUMIFS(TotalGMContribution[FY25/26],TotalGMContribution[Opps Status],"Fair",TotalGMContribution[Open Opps Phase],"4.DVF - Shortlisted",TotalGMContribution[VAT],Summary!$C12),0)+IF(CompanyRiskToggle=TRUE,SUMIFS(TotalGMContribution[FY25/26],TotalGMContribution[Opps Status],"Risk",TotalGMContribution[Open Opps Phase],"4.DVF - Shortlisted",TotalGMContribution[VAT],Summary!$C12),0)+P12 -> 1026935 | S12: =R12/E12 -> 0.45641557 | T12: =IF(CompanyGoodToggle=TRUE,SUMIFS(TotalGMContribution[FY25/26],TotalGMContribution[Opps Status],"Good",TotalGMContribution[Open Opps Phase],"3.DF - Submitted",TotalGMContribution[VAT],Summary!$C12),0)+IF(CompanyFairToggle=TRUE,SUMIFS(TotalGMContribution[FY25/26],TotalGMContribution[Opps Status],"Fair",TotalGMContribution[Open Opps Phase],"3.DF - Submitted",TotalGMContribution[VAT],Summary!$C12),0)+IF(CompanyRiskToggle=TRUE,SUMIFS(TotalGMContribution[FY25/26],TotalGMContribution[Opps Status],"Risk",TotalGMContribution[Open Opps Phase],"3.DF - Submitted",TotalGMContribution[VAT],Summary!$C12),0)+R12 -> 1026935 | U12: =T12/E12 -> 0.45641557
C13: DISR | D13: ='FY2526 VAT Financial KPIs'!E28 -> 690000 | E13: ='FY2526 VAT Financial KPIs'!F28 -> 1200000 | F13: ='FY2526 VAT Financial KPIs'!G28 -> 1500000 | G13: ='FY2526 VAT Financial KPIs'!H28 -> 2100000 | H13: =SUMIF(Job_Status[VAT],Summary!C13,Job_Status[To Date Gross Profit]) -> 480114.13 | I13: =H13/E13 -> 0.40009511 | J13: =SUMIF(Job_Status[VAT],Summary!C13,Job_Status[Actual]) -> 1728891.5 | K13: =IFERROR(H13/J13,"") -> 0.27770055 | L13: =SUMIF(Job_Status[VAT],Summary!C13,Job_Status[GP at completion]) -> 1217245.1 | M13: =L13/E13 -> 1.0143709 | N13: =SUMIF(Job_Status[VAT],Summary!C13,Job_Status[Forecasted Revenue]) -> 4359363.5 | O13: =L13/N13 -> 0.27922543 | P13: =IF(CompanyGoodToggle=TRUE,SUMIFS(TotalGMContribution[FY25/26],TotalGMContribution[Opps Status],"Good",TotalGMContribution[Open Opps Phase],"5.S - Selected",TotalGMContribution[VAT],Summary!$C13),0)+IF(CompanyFairToggle=TRUE,SUMIFS(TotalGMContribution[FY25/26],TotalGMContribution[Opps Status],"Fair",TotalGMContribution[Open Opps Phase],"5.S - Selected",TotalGMContribution[VAT],Summary!$C13),0)+IF(CompanyRiskToggle=TRUE,SUMIFS(TotalGMContribution[FY25/26],TotalGMContribution[Opps Status],"Risk",TotalGMContribution[Open Opps Phase],"5.S - Selected",TotalGMContribution[VAT],Summary!$C13),0)+L13 -> 1217245.1 | Q13: =P13/E13 -> 1.0143709 | R13: =IF(CompanyGoodToggle=TRUE,SUMIFS(TotalGMContribution[FY25/26],TotalGMContribution[Opps Status],"Good",TotalGMContribution[Open Opps Phase],"4.DVF - Shortlisted",TotalGMContribution[VAT],Summary!$C13),0)+IF(CompanyFairToggle=TRUE,SUMIFS(TotalGMContribution[FY25/26],TotalGMContribution[Opps Status],"Fair",TotalGMContribution[Open Opps Phase],"4.DVF - Shortlisted",TotalGMContribution[VAT],Summary!$C13),0)+IF(CompanyRiskToggle=TRUE,SUMIFS(TotalGMContribution[FY25/26],TotalGMContribution[Opps Status],"Risk",TotalGMContribution[Open Opps Phase],"4.DVF - Shortlisted",TotalGMContribution[VAT],Summary!$C13),0)+P13 -> 1217245.1 | S13: =R13/E13 -> 1.0143709 | T13: =IF(CompanyGoodToggle=TRUE,SUMIFS(TotalGMContribution[FY25/26],TotalGMContribution[Opps Status],"Good",TotalGMContribution[Open Opps Phase],"3.DF - Submitted",TotalGMContribution[VAT],Summary!$C13),0)+IF(CompanyFairToggle=TRUE,SUMIFS(TotalGMContribution[FY25/26],TotalGMContribution[Opps Status],"Fair",TotalGMContribution[Open Opps Phase],"3.DF - Submitted",TotalGMContribution[VAT],Summary!$C13),0)+IF(CompanyRiskToggle=TRUE,SUMIFS(TotalGMContribution[FY25/26],TotalGMContribution[Opps Status],"Risk",TotalGMContribution[Open Opps Phase],"3.DF - Submitted",TotalGMContribution[VAT],Summary!$C13),0)+R13 -> 1217245.1 | U13: =T13/E13 -> 1.0143709
C14: Emerging | D14: ='FY2526 VAT Financial KPIs'!E23 -> 540000 | E14: ='FY2526 VAT Financial KPIs'!F23 -> 880000 | F14: ='FY2526 VAT Financial KPIs'!G23 -> 1100000 | G14: ='FY2526 VAT Financial KPIs'!H23 -> 1375000 | H14: =SUMIF(Job_Status[VAT],Summary!C14,Job_Status[To Date Gross Profit]) -> 336887.66 | I14: =H14/E14 -> 0.38282689 | J14: =SUMIF(Job_Status[VAT],Summary!C14,Job_Status[Actual]) -> 820317.05 | K14: =IFERROR(H14/J14,"") -> 0.41067982 | L14: =SUMIF(Job_Status[VAT],Summary!C14,Job_Status[GP at completion]) -> 341191.66 | M14: =L14/E14 -> 0.3877178 | N14: =SUMIF(Job_Status[VAT],Summary!C14,Job_Status[Forecasted Revenue]) -> 955549.05 | O14: =L14/N14 -> 0.35706347 | P14: =IF(CompanyGoodToggle=TRUE,SUMIFS(TotalGMContribution[FY25/26],TotalGMContribution[Opps Status],"Good",TotalGMContribution[Open Opps Phase],"5.S - Selected",TotalGMContribution[VAT],Summary!$C14),0)+IF(CompanyFairToggle=TRUE,SUMIFS(TotalGMContribution[FY25/26],TotalGMContribution[Opps Status],"Fair",TotalGMContribution[Open Opps Phase],"5.S - Selected",TotalGMContribution[VAT],Summary!$C14),0)+IF(CompanyRiskToggle=TRUE,SUMIFS(TotalGMContribution[FY25/26],TotalGMContribution[Opps Status],"Risk",TotalGMContribution[Open Opps Phase],"5.S - Selected",TotalGMContribution[VAT],Summary!$C14),0)+L14 -> 341191.66 | Q14: =P14/E14 -> 0.3877178 | R14: =IF(CompanyGoodToggle=TRUE,SUMIFS(TotalGMContribution[FY25/26],TotalGMContribution[Opps Status],"Good",TotalGMContribution[Open Opps Phase],"4.DVF - Shortlisted",TotalGMContribution[VAT],Summary!$C14),0)+IF(CompanyFairToggle=TRUE,SUMIFS(TotalGMContribution[FY25/26],TotalGMContribution[Opps Status],"Fair",TotalGMContribution[Open Opps Phase],"4.DVF - Shortlisted",TotalGMContribution[VAT],Summary!$C14),0)+IF(CompanyRiskToggle=TRUE,SUMIFS(TotalGMContribution[FY25/26],TotalGMContribution[Opps Status],"Risk",TotalGMContribution[Open Opps Phase],"4.DVF - Shortlisted",TotalGMContribution[VAT],Summary!$C14),0)+P14 -> 341191.66 | S14: =R14/E14 -> 0.3877178 | T14: =IF(CompanyGoodToggle=TRUE,SUMIFS(TotalGMContribution[FY25/26],TotalGMContribution[Opps Status],"Good",TotalGMContribution[Open Opps Phase],"3.DF - Submitted",TotalGMContribution[VAT],Summary!$C14),0)+IF(CompanyFairToggle=TRUE,SUMIFS(TotalGMContribution[FY25/26],TotalGMContribution[Opps Status],"Fair",TotalGMContribution[Open Opps Phase],"3.DF - Submitted",TotalGMContribution[VAT],Summary!$C14),0)+IF(CompanyRiskToggle=TRUE,SUMIFS(TotalGMContribution[FY25/26],TotalGMContribution[Opps Status],"Risk",TotalGMContribution[Open Opps Phase],"3.DF - Submitted",TotalGMContribution[VAT],Summary!$C14),0)+R14 -> 341191.66 | U14: =T14/E14 -> 0.3877178
C15: GROWTH | D15: ='FY2526 VAT Financial KPIs'!E19 -> 1350000 | E15: ='FY2526 VAT Financial KPIs'!F19 -> 2200000 | F15: ='FY2526 VAT Financial KPIs'!G19 -> 3300000 | G15: ='FY2526 VAT Financial KPIs'!H19 -> 4400000 | H15: =SUMIF(Job_Status[VAT],Summary!C15,Job_Status[To Date Gross Profit]) -> 1322337.3 | I15: =H15/E15 -> 0.60106241 | J15: =SUMIF(Job_Status[VAT],Summary!C15,Job_Status[Actual]) -> 2416730 | K15: =IFERROR(H15/J15,"") -> 0.54715972 | L15: =SUMIF(Job_Status[VAT],Summary!C15,Job_Status[GP at completion]) -> 1275502.3 | M15: =L15/E15 -> 0.57977379 | N15: =SUMIF(Job_Status[VAT],Summary!C15,Job_Status[Forecasted Revenue]) -> 3126813.6 | O15: =L15/N15 -> 0.40792401 | P15: =IF(CompanyGoodToggle=TRUE,SUMIFS(TotalGMContribution[FY25/26],TotalGMContribution[Opps Status],"Good",TotalGMContribution[Open Opps Phase],"5.S - Selected",TotalGMContribution[VAT],Summary!$C15),0)+IF(CompanyFairToggle=TRUE,SUMIFS(TotalGMContribution[FY25/26],TotalGMContribution[Opps Status],"Fair",TotalGMContribution[Open Opps Phase],"5.S - Selected",TotalGMContribution[VAT],Summary!$C15),0)+IF(CompanyRiskToggle=TRUE,SUMIFS(TotalGMContribution[FY25/26],TotalGMContribution[Opps Status],"Risk",TotalGMContribution[Open Opps Phase],"5.S - Selected",TotalGMContribution[VAT],Summary!$C15),0)+L15 -> 1275502.3 | Q15: =P15/E15 -> 0.57977379 | R15: =IF(CompanyGoodToggle=TRUE,SUMIFS(TotalGMContribution[FY25/26],TotalGMContribution[Opps Status],"Good",TotalGMContribution[Open Opps Phase],"4.DVF - Shortlisted",TotalGMContribution[VAT],Summary!$C15),0)+IF(CompanyFairToggle=TRUE,SUMIFS(TotalGMContribution[FY25/26],TotalGMContribution[Opps Status],"Fair",TotalGMContribution[Open Opps Phase],"4.DVF - Shortlisted",TotalGMContribution[VAT],Summary!$C15),0)+IF(CompanyRiskToggle=TRUE,SUMIFS(TotalGMContribution[FY25/26],TotalGMContribution[Opps Status],"Risk",TotalGMContribution[Open Opps Phase],"4.DVF - Shortlisted",TotalGMContribution[VAT],Summary!$C15),0)+P15 -> 3451376.7 | S15: =R15/E15 -> 1.5688076 | T15: =IF(CompanyGoodToggle=TRUE,SUMIFS(TotalGMContribution[FY25/26],TotalGMContribution[Opps Status],"Good",TotalGMContribution[Open Opps Phase],"3.DF - Submitted",TotalGMContribution[VAT],Summary!$C15),0)+IF(CompanyFairToggle=TRUE,SUMIFS(TotalGMContribution[FY25/26],TotalGMContribution[Opps Status],"Fair",TotalGMContribution[Open Opps Phase],"3.DF - Submitted",TotalGMContribution[VAT],Summary!$C15),0)+IF(CompanyRiskToggle=TRUE,SUMIFS(TotalGMContribution[FY25/26],TotalGMContribution[Opps Status],"Risk",TotalGMContribution[Open Opps Phase],"3.DF - Submitted",TotalGMContribution[VAT],Summary!$C15),0)+R15 -> 3451376.7 | U15: =T15/E15 -> 1.5688076
C16: TOTAL | D16: =SUM(D10:D15) -> 7080000 | E16: =SUM(E10:E15) -> 10130000 | F16: =SUM(F10:F15) -> 13100000 | G16: =SUM(G10:G15) -> 16425000 | H16: =SUM(H10:H15) -> 4318737 | I16: =H16/E16 -> 0.42633139 | J16: =SUM(J10:J15) -> 14133437 | K16: =H16/J16 -> 0.30556877 | L16: =SUM(L10:L15) -> 5467112.5 | M16: =L16/E16 -> 0.53969521 | N16: =SUM(N10:N15) -> 20744604 | O16: =L16/N16 -> 0.26354384 | P16: =SUM(P10:P15) -> 5467112.5 | Q16: =P16/E16 -> 0.53969521 | R16: =SUM(R10:R15) -> 7674092.4 | S16: =R16/E16 -> 0.75756094 | T16: =SUM(T10:T15) -> 7674092.4 | U16: =T16/E16 -> 0.75756094
C17: GM% | D17: =D16/D7 -> 0.28723971 | E17: =E16/E7 -> 0.29840851 | F17: =F16/F7 -> 0.30479692 | G17: =G16/G7 -> 0.35427339 | H17: =H16/H7 -> 0.30556877 | L17: =L16/L7 -> 0.26354384 | P17: =P16/P7 -> 0.26354384 | R17: =R16/R7 -> 0.30401651 | T17: =T16/T7 -> 0.30401651
H19: GM Contribution Earned | L19: GM Contribution @ Completion
G20: WORK TYPE | H20: Earned to Date | I20: GM % | J20: Revenue | K20: GM % | L20: Current Jobs @ Completion | M20: GM % | N20: Revenue | O20: GM % | P20: Plus Selected | Q20: GM % | R20: Plus Dev. Forecast (DVF) | S20: GM % | T20: Plus Defined (DF) | U20: GM % | Z20: Path | AA20: sites/RGSales/Shared Documents/General/1.Open Opportunities
G21: Advisory | H21: =SUMIF(Job_Status[Work Type],G21,Job_Status[To Date Gross Profit]) -> 1552171.7 | I21: =H21/SUMIFS(Job_Status[Actual],Job_Status[Work Type],Summary!G21) -> 0.54779326 | J21: =SUMIF(Job_Status[Work Type],Summary!G21,Job_Status[Actual]) -> 2833499 | K21: =IFERROR(H21/J21,"") -> 0.54779326 | L21: =SUMIF(Job_Status[Work Type],G21,Job_Status[GP at completion]) -> 1454981.7 | M21: =L21/SUMIFS(Job_Status[Forecasted Revenue],Job_Status[Work Type],Summary!G21) -> 0.53173149 | N21: =SUMIF(Job_Status[Work Type],G21,Job_Status[Forecasted Revenue]) -> 2736309 | O21: =L21/N21 -> 0.53173149 | P21: =IF(CompanyGoodToggle=TRUE,SUMIFS(TotalGMContribution[FY25/26],TotalGMContribution[Work Type],Summary!$G21,TotalGMContribution[Open Opps Phase],"5.S - Selected",TotalGMContribution[Opps Status],"Good"),0)+IF(CompanyFairToggle=TRUE,SUMIFS(TotalGMContribution[FY25/26],TotalGMContribution[Work Type],Summary!$G21,TotalGMContribution[Open Opps Phase],"5.S - Selected",TotalGMContribution[Opps Status],"Fair"),0)+IF(CompanyRiskToggle=TRUE,SUMIFS(TotalGMContribution[FY25/26],TotalGMContribution[Work Type],Summary!$G21,TotalGMContribution[Open Opps Phase],"5.S - Selected",TotalGMContribution[Opps Status],"Risk"),0)+L21 -> 1454981.7 | Q21: {=(SUMPRODUCT(Table_query[Value $ ex GST]*Table_query[Margin]*(Table_query[Work Type]=G21)*(Table_query[Phase]="5.S - Selected")*(Table_query[Path]="sites/RGSales/Shared Documents/General/1.Open Opportunities"))+L21)/(N21+SUMIFS(Table_query[Value $ ex GST],Table_query[Work Type],G21,Table_query[Phase],"5.S - Selected",Table_query[Path],"sites/RGSales/Shared Documents/General/1.Open Opportunities"))} -> 0.53173149 | R21: =IF(CompanyGoodToggle=TRUE,SUMIFS(TotalGMContribution[FY25/26],TotalGMContribution[Work Type],Summary!$G21,TotalGMContribution[Open Opps Phase],"4.DVF - Shortlisted",TotalGMContribution[Opps Status],"Good"),0)+IF(CompanyFairToggle=TRUE,SUMIFS(TotalGMContribution[FY25/26],TotalGMContribution[Work Type],Summary!$G21,TotalGMContribution[Open Opps Phase],"4.DVF - Shortlisted",TotalGMContribution[Opps Status],"Fair"),0)+IF(CompanyRiskToggle=TRUE,SUMIFS(TotalGMContribution[FY25/26],TotalGMContribution[Work Type],Summary!$G21,TotalGMContribution[Open Opps Phase],"4.DVF - Shortlisted",TotalGMContribution[Opps Status],"Risk"),0)+P21 -> 1454981.7 | S21: =(R21)/(N21+SUMIFS(Table_query[Value $ ex GST],Table_query[Work Type],G21,Table_query[Phase],"5.S - Selected",Table_query[Path],"sites/RGSales/Shared Documents/General/1.Open Opportunities")+SUMIFS(Table_query[Value $ ex GST],Table_query[Work Type],G21,Table_query[Phase],"3.DF - Submitted",Table_query[Path],"sites/RGSales/Shared Documents/General/1.Open Opportunities")) -> 0.53173149 | T21: =IF(CompanyGoodToggle=TRUE,SUMIFS(TotalGMContribution[FY25/26],TotalGMContribution[Work Type],Summary!$G21,TotalGMContribution[Open Opps Phase],"3.DF - Submitted",TotalGMContribution[Opps Status],"Good"),0)+IF(CompanyFairToggle=TRUE,SUMIFS(TotalGMContribution[FY25/26],TotalGMContribution[Work Type],Summary!$G21,TotalGMContribution[Open Opps Phase],"3.DF - Submitted",TotalGMContribution[Opps Status],"Fair"),0)+IF(CompanyRiskToggle=TRUE,SUMIFS(TotalGMContribution[FY25/26],TotalGMContribution[Work Type],Summary!$G21,TotalGMContribution[Open Opps Phase],"3.DF - Submitted",TotalGMContribution[Opps Status],"Risk"),0)+R21 -> 1454981.7 | U21: =(T21)/(N21+SUMIFS(Table_query[Value $ ex GST],Table_query[Work Type],G21,Table_query[Phase],"5.S - Selected",Table_query[Path],"sites/RGSales/Shared Documents/General/1.Open Opportunities")+SUMIFS(Table_query[Value $ ex GST],Table_query[Work Type],G21,Table_query[Phase],"3.DF - Submitted",Table_query[Path],"sites/RGSales/Shared Documents/General/1.Open Opportunities")+SUMIFS(Table_query[Value $ ex GST],Table_query[Work Type],G21,Table_query[Phase],"3.DF - Submitted",Table_query[Path],"sites/RGSales/Shared Documents/General/1.Open Opportunities")) -> 0.53173149 | Z21: Work Type | AA21: (Multiple Items)
G22: Delivery | H22: =SUMIF(Job_Status[Work Type],G22,Job_Status[To Date Gross Profit]) -> 1971998.7 | I22: =H22/SUMIFS(Job_Status[Actual],Job_Status[Work Type],Summary!G22) -> 0.29816909 | J22: =SUMIF(Job_Status[Work Type],Summary!G22,Job_Status[Actual]) -> 6613692.8 | K22: =IFERROR(H22/J22,"") -> 0.29816909 | L22: =SUMIF(Job_Status[Work Type],G22,Job_Status[GP at completion]) -> 2913123.9 | M22: =L22/SUMIFS(Job_Status[Forecasted Revenue],Job_Status[Work Type],Summary!G22) -> 0.26707216 | N22: =SUMIF(Job_Status[Work Type],G22,Job_Status[Forecasted Revenue]) -> 10907628 | O22: =L22/N22 -> 0.26707216 | P22: =IF(CompanyGoodToggle=TRUE,SUMIFS(TotalGMContribution[FY25/26],TotalGMContribution[Work Type],Summary!$G22,TotalGMContribution[Open Opps Phase],"5.S - Selected",TotalGMContribution[Opps Status],"Good"),0)+IF(CompanyFairToggle=TRUE,SUMIFS(TotalGMContribution[FY25/26],TotalGMContribution[Work Type],Summary!$G22,TotalGMContribution[Open Opps Phase],"5.S - Selected",TotalGMContribution[Opps Status],"Fair"),0)+IF(CompanyRiskToggle=TRUE,SUMIFS(TotalGMContribution[FY25/26],TotalGMContribution[Work Type],Summary!$G22,TotalGMContribution[Open Opps Phase],"5.S - Selected",TotalGMContribution[Opps Status],"Risk"),0)+L22 -> 2913123.9 | Q22: {=(SUMPRODUCT(Table_query[Value $ ex GST]*Table_query[Margin]*(Table_query[Work Type]=G22)*(Table_query[Phase]="5.S - Selected")*(Table_query[Path]="sites/RGSales/Shared Documents/General/1.Open Opportunities"))+L22)/(N22+SUMIFS(Table_query[Value $ ex GST],Table_query[Work Type],G22,Table_query[Phase],"5.S - Selected",Table_query[Path],"sites/RGSales/Shared Documents/General/1.Open Opportunities"))} -> 0.26707216 | R22: =IF(CompanyGoodToggle=TRUE,SUMIFS(TotalGMContribution[FY25/26],TotalGMContribution[Work Type],Summary!$G22,TotalGMContribution[Open Opps Phase],"4.DVF - Shortlisted",TotalGMContribution[Opps Status],"Good"),0)+IF(CompanyFairToggle=TRUE,SUMIFS(TotalGMContribution[FY25/26],TotalGMContribution[Work Type],Summary!$G22,TotalGMContribution[Open Opps Phase],"4.DVF - Shortlisted",TotalGMContribution[Opps Status],"Fair"),0)+IF(CompanyRiskToggle=TRUE,SUMIFS(TotalGMContribution[FY25/26],TotalGMContribution[Work Type],Summary!$G22,TotalGMContribution[Open Opps Phase],"4.DVF - Shortlisted",TotalGMContribution[Opps Status],"Risk"),0)+P22 -> 5088998.3 | S22: =(R22)/(N22+SUMIFS(Table_query[Value $ ex GST],Table_query[Work Type],G22,Table_query[Phase],"5.S - Selected",Table_query[Path],"sites/RGSales/Shared Documents/General/1.Open Opportunities")+SUMIFS(Table_query[Value $ ex GST],Table_query[Work Type],G22,Table_query[Phase],"3.DF - Submitted",Table_query[Path],"sites/RGSales/Shared Documents/General/1.Open Opportunities")) -> 0.39372873 | T22: =IF(CompanyGoodToggle=TRUE,SUMIFS(TotalGMContribution[FY25/26],TotalGMContribution[Work Type],Summary!$G22,TotalGMContribution[Open Opps Phase],"3.DF - Submitted",TotalGMContribution[Opps Status],"Good"),0)+IF(CompanyFairToggle=TRUE,SUMIFS(TotalGMContribution[FY25/26],TotalGMContribution[Work Type],Summary!$G22,TotalGMContribution[Open Opps Phase],"3.DF - Submitted",TotalGMContribution[Opps Status],"Fair"),0)+IF(CompanyRiskToggle=TRUE,SUMIFS(TotalGMContribution[FY25/26],TotalGMContribution[Work Type],Summary!$G22,TotalGMContribution[Open Opps Phase],"3.DF - Submitted",TotalGMContribution[Opps Status],"Risk"),0)+R22 -> 5088998.3 | U22: =(T22)/(N22+SUMIFS(Table_query[Value $ ex GST],Table_query[Work Type],G22,Table_query[Phase],"5.S - Selected",Table_query[Path],"sites/RGSales/Shared Documents/General/1.Open Opportunities")+SUMIFS(Table_query[Value $ ex GST],Table_query[Work Type],G22,Table_query[Phase],"3.DF - Submitted",Table_query[Path],"sites/RGSales/Shared Documents/General/1.Open Opportunities")+SUMIFS(Table_query[Value $ ex GST],Table_query[Work Type],G22,Table_query[Phase],"3.DF - Submitted",Table_query[Path],"sites/RGSales/Shared Documents/General/1.Open Opportunities")) -> 0.3405687
G23: Resource Pool | H23: =SUMIF(Job_Status[Work Type],G23,Job_Status[To Date Gross Profit]) -> 332766.98 | I23: =H23/SUMIFS(Job_Status[Actual],Job_Status[Work Type],Summary!G23) -> 0.23156783 | J23: =SUMIF(Job_Status[Work Type],Summary!G23,Job_Status[Actual]) -> 1437017.3 | K23: =IFERROR(H23/J23,"") -> 0.23156783 | L23: =SUMIF(Job_Status[Work Type],G23,Job_Status[GP at completion]) -> 392169.53 | M23: =L23/SUMIFS(Job_Status[Forecasted Revenue],Job_Status[Work Type],Summary!G23) -> 0.21582186 | N23: =SUMIF(Job_Status[Work Type],G23,Job_Status[Forecasted Revenue]) -> 1817098.3 | O23: =L23/N23 -> 0.21582186 | P23: =IF(CompanyGoodToggle=TRUE,SUMIFS(TotalGMContribution[FY25/26],TotalGMContribution[Work Type],Summary!$G23,TotalGMContribution[Open Opps Phase],"5.S - Selected",TotalGMContribution[Opps Status],"Good"),0)+IF(CompanyFairToggle=TRUE,SUMIFS(TotalGMContribution[FY25/26],TotalGMContribution[Work Type],Summary!$G23,TotalGMContribution[Open Opps Phase],"5.S - Selected",TotalGMContribution[Opps Status],"Fair"),0)+IF(CompanyRiskToggle=TRUE,SUMIFS(TotalGMContribution[FY25/26],TotalGMContribution[Work Type],Summary!$G23,TotalGMContribution[Open Opps Phase],"5.S - Selected",TotalGMContribution[Opps Status],"Risk"),0)+L23 -> 392169.53 | Q23: {=(SUMPRODUCT(Table_query[Value $ ex GST]*Table_query[Margin]*(Table_query[Work Type]=G23)*(Table_query[Phase]="5.S - Selected")*(Table_query[Path]="sites/RGSales/Shared Documents/General/1.Open Opportunities"))+L23)/(N23+SUMIFS(Table_query[Value $ ex GST],Table_query[Work Type],G23,Table_query[Phase],"5.S - Selected",Table_query[Path],"sites/RGSales/Shared Documents/General/1.Open Opportunities"))} -> 0.21582186 | R23: =IF(CompanyGoodToggle=TRUE,SUMIFS(TotalGMContribution[FY25/26],TotalGMContribution[Work Type],Summary!$G23,TotalGMContribution[Open Opps Phase],"4.DVF - Shortlisted",TotalGMContribution[Opps Status],"Good"),0)+IF(CompanyFairToggle=TRUE,SUMIFS(TotalGMContribution[FY25/26],TotalGMContribution[Work Type],Summary!$G23,TotalGMContribution[Open Opps Phase],"4.DVF - Shortlisted",TotalGMContribution[Opps Status],"Fair"),0)+IF(CompanyRiskToggle=TRUE,SUMIFS(TotalGMContribution[FY25/26],TotalGMContribution[Work Type],Summary!$G23,TotalGMContribution[Open Opps Phase],"4.DVF - Shortlisted",TotalGMContribution[Opps Status],"Risk"),0)+P23 -> 392169.53 | S23: =(R23)/(N23+SUMIFS(Table_query[Value $ ex GST],Table_query[Work Type],G23,Table_query[Phase],"5.S - Selected",Table_query[Path],"sites/RGSales/Shared Documents/General/1.Open Opportunities")+SUMIFS(Table_query[Value $ ex GST],Table_query[Work Type],G23,Table_query[Phase],"3.DF - Submitted",Table_query[Path],"sites/RGSales/Shared Documents/General/1.Open Opportunities")) -> 0.17917804 | T23: =IF(CompanyGoodToggle=TRUE,SUMIFS(TotalGMContribution[FY25/26],TotalGMContribution[Work Type],Summary!$G23,TotalGMContribution[Open Opps Phase],"3.DF - Submitted",TotalGMContribution[Opps Status],"Good"),0)+IF(CompanyFairToggle=TRUE,SUMIFS(TotalGMContribution[FY25/26],TotalGMContribution[Work Type],Summary!$G23,TotalGMContribution[Open Opps Phase],"3.DF - Submitted",TotalGMContribution[Opps Status],"Fair"),0)+IF(CompanyRiskToggle=TRUE,SUMIFS(TotalGMContribution[FY25/26],TotalGMContribution[Work Type],Summary!$G23,TotalGMContribution[Open Opps Phase],"3.DF - Submitted",TotalGMContribution[Opps Status],"Risk"),0)+R23 -> 392169.53 | U23: =(T23)/(N23+SUMIFS(Table_query[Value $ ex GST],Table_query[Work Type],G23,Table_query[Phase],"5.S - Selected",Table_query[Path],"sites/RGSales/Shared Documents/General/1.Open Opportunities")+SUMIFS(Table_query[Value $ ex GST],Table_query[Work Type],G23,Table_query[Phase],"3.DF - Submitted",Table_query[Path],"sites/RGSales/Shared Documents/General/1.Open Opportunities")+SUMIFS(Table_query[Value $ ex GST],Table_query[Work Type],G23,Table_query[Phase],"3.DF - Submitted",Table_query[Path],"sites/RGSales/Shared Documents/General/1.Open Opportunities")) -> 0.15317146 | Z23: Phase | AA23: Name | AB23: Status
G24: Labour Hire | H24: =SUMIF(Job_Status[Work Type],G24,Job_Status[To Date Gross Profit]) -> 461799.6 | I24: =H24/SUMIFS(Job_Status[Actual],Job_Status[Work Type],Summary!G24) -> 0.14212595 | J24: =SUMIF(Job_Status[Work Type],Summary!G24,Job_Status[Actual]) -> 3249227.9 | K24: =IFERROR(H24/J24,"") -> 0.14212595 | L24: =SUMIF(Job_Status[Work Type],G24,Job_Status[GP at completion]) -> 706837.4 | M24: =L24/SUMIFS(Job_Status[Forecasted Revenue],Job_Status[Work Type],Summary!G24) -> 0.13378032 | N24: =SUMIF(Job_Status[Work Type],G24,Job_Status[Forecasted Revenue]) -> 5283567.9 | O24: =L24/N24 -> 0.13378032 | P24: =IF(CompanyGoodToggle=TRUE,SUMIFS(TotalGMContribution[FY25/26],TotalGMContribution[Work Type],Summary!$G24,TotalGMContribution[Open Opps Phase],"5.S - Selected",TotalGMContribution[Opps Status],"Good"),0)+IF(CompanyFairToggle=TRUE,SUMIFS(TotalGMContribution[FY25/26],TotalGMContribution[Work Type],Summary!$G24,TotalGMContribution[Open Opps Phase],"5.S - Selected",TotalGMContribution[Opps Status],"Fair"),0)+IF(CompanyRiskToggle=TRUE,SUMIFS(TotalGMContribution[FY25/26],TotalGMContribution[Work Type],Summary!$G24,TotalGMContribution[Open Opps Phase],"5.S - Selected",TotalGMContribution[Opps Status],"Risk"),0)+L24 -> 706837.4 | Q24: {=(SUMPRODUCT(Table_query[Value $ ex GST]*Table_query[Margin]*(Table_query[Work Type]=G24)*(Table_query[Phase]="5.S - Selected")*(Table_query[Path]="sites/RGSales/Shared Documents/General/1.Open Opportunities"))+L24)/(N24+SUMIFS(Table_query[Value $ ex GST],Table_query[Work Type],G24,Table_query[Phase],"5.S - Selected",Table_query[Path],"sites/RGSales/Shared Documents/General/1.Open Opportunities"))} -> 0.13378032 | R24: =IF(CompanyGoodToggle=TRUE,SUMIFS(TotalGMContribution[FY25/26],TotalGMContribution[Work Type],Summary!$G24,TotalGMContribution[Open Opps Phase],"4.DVF - Shortlisted",TotalGMContribution[Opps Status],"Good"),0)+IF(CompanyFairToggle=TRUE,SUMIFS(TotalGMContribution[FY25/26],TotalGMContribution[Work Type],Summary!$G24,TotalGMContribution[Open Opps Phase],"4.DVF - Shortlisted",TotalGMContribution[Opps Status],"Fair"),0)+IF(CompanyRiskToggle=TRUE,SUMIFS(TotalGMContribution[FY25/26],TotalGMContribution[Work Type],Summary!$G24,TotalGMContribution[Open Opps Phase],"4.DVF - Shortlisted",TotalGMContribution[Opps Status],"Risk"),0)+P24 -> 737942.84 | S24: =(R24)/(N24+SUMIFS(Table_query[Value $ ex GST],Table_query[Work Type],G24,Table_query[Phase],"5.S - Selected",Table_query[Path],"sites/RGSales/Shared Documents/General/1.Open Opportunities")+SUMIFS(Table_query[Value $ ex GST],Table_query[Work Type],G24,Table_query[Phase],"3.DF - Submitted",Table_query[Path],"sites/RGSales/Shared Documents/General/1.Open Opportunities")) -> 0.085368475 | T24: =IF(CompanyGoodToggle=TRUE,SUMIFS(TotalGMContribution[FY25/26],TotalGMContribution[Work Type],Summary!$G24,TotalGMContribution[Open Opps Phase],"3.DF - Submitted",TotalGMContribution[Opps Status],"Good"),0)+IF(CompanyFairToggle=TRUE,SUMIFS(TotalGMContribution[FY25/26],TotalGMContribution[Work Type],Summary!$G24,TotalGMContribution[Open Opps Phase],"3.DF - Submitted",TotalGMContribution[Opps Status],"Fair"),0)+IF(CompanyRiskToggle=TRUE,SUMIFS(TotalGMContribution[FY25/26],TotalGMContribution[Work Type],Summary!$G24,TotalGMContribution[Open Opps Phase],"3.DF - Submitted",TotalGMContribution[Opps Status],"Risk"),0)+R24 -> 737942.84 | U24: =(T24)/(N24+SUMIFS(Table_query[Value $ ex GST],Table_query[Work Type],G24,Table_query[Phase],"5.S - Selected",Table_query[Path],"sites/RGSales/Shared Documents/General/1.Open Opportunities")+SUMIFS(Table_query[Value $ ex GST],Table_query[Work Type],G24,Table_query[Phase],"3.DF - Submitted",Table_query[Path],"sites/RGSales/Shared Documents/General/1.Open Opportunities")+SUMIFS(Table_query[Value $ ex GST],Table_query[Work Type],G24,Table_query[Phase],"3.DF - Submitted",Table_query[Path],"sites/RGSales/Shared Documents/General/1.Open Opportunities")) -> 0.061470403 | Z24: 4.DVF - Shortlisted | AA24: DPSXXX RFQ Cyber Security Assessor 202601 | AB24: Risk
G25: TOTAL | H25: =SUM(H21:H24) -> 4318737 | I25: =Job_Status[[#Totals],[TD GM(%)]] -> 0.30556877 | L25: =SUM(L21:L24) -> 5467112.5 | M25: =Job_Status[[#Totals],[Forecast GM @ completion (%)]] -> 0.26354384 | P25: =SUM(P21:P24) -> 5467112.5 | Q25: =P25/P7 -> 0.26354384 | R25: =SUM(R21:R24) -> 7674092.4 | S25: =R25/R7 -> 0.30401651 | T25: =SUM(T21:T24) -> 7674092.4 | U25: =T25/T7 -> 0.30401651 | AA25: FWO001-XX Digital Transformation CPBC - PoC | AB25: Risk
AA26: FWO001-XX Digital Transformation CPBC - Revision and Submission Support | AB26: Fair
C27: REVENUE | D27: Q1 | E27: Q2 | F27: Q3 | G27: Q4 | H27: FY25-26 | AA27: LAB001-01 DCC Program Plan (Extension) | AB27: Good
C28: Good' Target | D28: =SUM('COMPANY Spread'!Q60:S60) -> 7611688.3 | E28: =SUM('COMPANY Spread'!T60:V60) -> 7187445.9 | F28: =SUM('COMPANY Spread'!W60:Y60) -> 9573809.5 | G28: =SUM('COMPANY Spread'!Z60:AB60) -> 9573809.5 | H28: =SUM(D28:G28) -> 33946753 | AA28: SAU045-XX Senior Technology Architect (Sidd) | AB28: Good
C29: YTD | D29: =SUM(Job_Status[[#Totals],[Revenue Q1]]) -> 5912887.3 | E29: =SUM(Job_Status[[#Totals],[Revenue Q2]]) -> 6505901.8 | F29: =SUM(Job_Status[[#Totals],[Revenue Q3]]) -> 1714647.9 | G29: =SUM(Job_Status[[#Totals],[Revenue Q4]]) -> 0 | H29: =SUM(D29:G29) -> 14133437 | AA29: SAU046-XX Delivery Manager (Alex) | AB29: Good
C30: Forecast | D30: =SUM('COMPANY Spread'!Q54:S54) -> 5912887.3 | E30: =SUM('COMPANY Spread'!T54:V54) -> 6505901.8 | F30: =SUM('COMPANY Spread'!W54:Y54) -> 4737991.5 | G30: =SUM('COMPANY Spread'!Z54:AB54) -> 3473100.6 | H30: =SUM(D30:G30) -> 20629881 | L30: ="$"&ROUNDDOWN(H30-L7,0)&" difference to L7 due to potential write-ups/write-off not broken down by quarters into the future." -> $-114722 difference to L7 due to potential write-ups/write-off not broken down by quarters into the future. | AA30: SAU052-XX Senior Solution Architect (Aniket) | AB30: Good
C31: Variance | D31: =D30-D28 -> -1698801 | E31: =E30-E28 -> -681544.04 | F31: =F30-F28 -> -4835818 | G31: =G30-G28 -> -6100708.9 | H31: =SUM(D31:G31) -> -13316872 | AA31: TECXXX DEWR DE RFQ ERP 202510 | AB31: Good
C32: GM CONT. | D32: Q1 | E32: Q2 | F32: Q3 | G32: Q4 | H32: FY25-26 | AA32: TECXXX INF RFQ TechOne - ERP Products, Implementation, Operational | AB32: Good
C33: Good' Target | D33: =SUM('COMPANY Spread'!C60:E60) -> 2270000 | E33: =SUM('COMPANY Spread'!F60:H60) -> 2320000 | F33: =SUM('COMPANY Spread'!I60:K60) -> 2770000 | G33: =SUM('COMPANY Spread'!L60:N60) -> 2770000 | H33: =SUM(D33:G33) -> 10130000 | AA33: VICXXX DEECA RFQ Permissions System 202512 | AB33: Good
C34: YTD | D34: =Job_Status[[#Totals],[Gross Profit Q1]] -> 1791429.4 | E34: =Job_Status[[#Totals],[Gross Profit Q2]] -> 2131155.7 | F34: =Job_Status[[#Totals],[Gross Profit Q3]] -> 396151.9 | G34: =Job_Status[[#Totals],[Gross Profit Q4]] -> 0 | H34: =SUM(D34:G34) -> 4318737 | Z34: 3.DF - Submitted | AA34: AFPXXX LH-05147 One (1) Lead Business Architect 202512 | AB34: Risk
C35: Forecast | D35: =SUM('COMPANY Spread'!C54:E54) -> 1791429.4 | E35: =SUM('COMPANY Spread'!F54:H54) -> 2131155.7 | F35: =SUM('COMPANY Spread'!I54:K54) -> 901231.5 | G35: =SUM('COMPANY Spread'!L54:N54) -> 528573.68 | H35: =SUM(D35:G35) -> 5352390.3 | L35: ="$"&ROUNDDOWN(H35-L16,0)&" difference to L7 due to potential write-ups not broken down by quarters into future." -> $-114722 difference to L7 due to potential write-ups not broken down by quarters into future. | AA35: AGDXXX RFQ Review of ICT Services for AGS 202512 | AB35: Risk
C36: Variance | D36: =D35-D33 -> -478570.6 | E36: =E35-E33 -> -188844.29 | F36: =F35-F33 -> -1868768.5 | G36: =G35-G33 -> -2241426.3 | H36: =SUM(D36:G36) -> -4777609.7 | AA36: AREXXX RFQ Design Future Data Platform 202601 | AB36: Risk
AA37: DAFXXX RFQ Incident and Major Incident Management Review | AB37: Good
AA38: DAFXXX TRACE ServiceNow | AB38: Risk
B39: Opportunity Tracker | AA39: DHAXXX LH-04367 Two Senior Pega Analyst 202508 | AB39: Risk
B40: Opportunity Status | C40: A | D40: Q | E40: DF | F40: DVF | G40: S | AA40: DHAXXX LH-04634 One Senior Pega Developer 202509 | AB40: Risk
B41: Good | C41: =IF(VATSelector="ALL",COUNTIFS(Table_query[Path],"sites/RGSales/Shared Documents/General/1.Open Opportunities",Table_query[Phase],_xlfn.XLOOKUP(C$40,Phase[Phase Code],Phase[Phase Description]),Table_query[Status],Summary!$B41),COUNTIFS(Table_query[Path],"sites/RGSales/Shared Documents/General/1.Open Opportunities",Table_query[Phase],_xlfn.XLOOKUP(C$40,Phase[Phase Code],Phase[Phase Description]),Table_query[Status],Summary!$B41,Table_query[VAT],VATSelector)) -> 2 | D41: =IF(VATSelector="ALL",COUNTIFS(Table_query[Path],"sites/RGSales/Shared Documents/General/1.Open Opportunities",Table_query[Phase],_xlfn.XLOOKUP(D$40,Phase[Phase Code],Phase[Phase Description]),Table_query[Status],Summary!$B41),COUNTIFS(Table_query[Path],"sites/RGSales/Shared Documents/General/1.Open Opportunities",Table_query[Phase],_xlfn.XLOOKUP(D$40,Phase[Phase Code],Phase[Phase Description]),Table_query[Status],Summary!$B41,Table_query[VAT],VATSelector)) -> 7 | E41: 1 | F41: =IF(VATSelector="ALL",COUNTIFS(Table_query[Path],"sites/RGSales/Shared Documents/General/1.Open Opportunities",Table_query[Phase],_xlfn.XLOOKUP(F$40,Phase[Phase Code],Phase[Phase Description]),Table_query[Status],Summary!$B41),COUNTIFS(Table_query[Path],"sites/RGSales/Shared Documents/General/1.Open Opportunities",Table_query[Phase],_xlfn.XLOOKUP(F$40,Phase[Phase Code],Phase[Phase Description]),Table_query[Status],Summary!$B41,Table_query[VAT],VATSelector)) -> 9 | G41: =IF(VATSelector="ALL",COUNTIFS(Table_query[Path],"sites/RGSales/Shared Documents/General/1.Open Opportunities",Table_query[Phase],_xlfn.XLOOKUP(G$40,Phase[Phase Code],Phase[Phase Description]),Table_query[Status],Summary!$B41),COUNTIFS(Table_query[Path],"sites/RGSales/Shared Documents/General/1.Open Opportunities",Table_query[Phase],_xlfn.XLOOKUP(G$40,Phase[Phase Code],Phase[Phase Description]),Table_query[Status],Summary!$B41,Table_query[VAT],VATSelector)) -> 0 | AA41: DHAXXX RFQ On-demand services for mainframe Capability 202511 | AB41: Risk
B42: Fair | C42: =IF(VATSelector="ALL",COUNTIFS(Table_query[Path],"sites/RGSales/Shared Documents/General/1.Open Opportunities",Table_query[Phase],_xlfn.XLOOKUP(C$40,Phase[Phase Code],Phase[Phase Description]),Table_query[Status],Summary!$B42),COUNTIFS(Table_query[Path],"sites/RGSales/Shared Documents/General/1.Open Opportunities",Table_query[Phase],_xlfn.XLOOKUP(C$40,Phase[Phase Code],Phase[Phase Description]),Table_query[Status],Summary!$B42,Table_query[VAT],VATSelector)) -> 16 | D42: =IF(VATSelector="ALL",COUNTIFS(Table_query[Path],"sites/RGSales/Shared Documents/General/1.Open Opportunities",Table_query[Phase],_xlfn.XLOOKUP(D$40,Phase[Phase Code],Phase[Phase Description]),Table_query[Status],Summary!$B42),COUNTIFS(Table_query[Path],"sites/RGSales/Shared Documents/General/1.Open Opportunities",Table_query[Phase],_xlfn.XLOOKUP(D$40,Phase[Phase Code],Phase[Phase Description]),Table_query[Status],Summary!$B42,Table_query[VAT],VATSelector)) -> 2 | E42: =IF(VATSelector="ALL",COUNTIFS(Table_query[Path],"sites/RGSales/Shared Documents/General/1.Open Opportunities",Table_query[Phase],_xlfn.XLOOKUP(E$40,Phase[Phase Code],Phase[Phase Description]),Table_query[Status],Summary!$B42),COUNTIFS(Table_query[Path],"sites/RGSales/Shared Documents/General/1.Open Opportunities",Table_query[Phase],_xlfn.XLOOKUP(E$40,Phase[Phase Code],Phase[Phase Description]),Table_query[Status],Summary!$B42,Table_query[VAT],VATSelector)) -> 1 | F42: =IF(VATSelector="ALL",COUNTIFS(Table_query[Path],"sites/RGSales/Shared Documents/General/1.Open Opportunities",Table_query[Phase],_xlfn.XLOOKUP(F$40,Phase[Phase Code],Phase[Phase Description]),Table_query[Status],Summary!$B42),COUNTIFS(Table_query[Path],"sites/RGSales/Shared Documents/General/1.Open Opportunities",Table_query[Phase],_xlfn.XLOOKUP(F$40,Phase[Phase Code],Phase[Phase Description]),Table_query[Status],Summary!$B42,Table_query[VAT],VATSelector)) -> 1 | G42: =IF(VATSelector="ALL",COUNTIFS(Table_query[Path],"sites/RGSales/Shared Documents/General/1.Open Opportunities",Table_query[Phase],_xlfn.XLOOKUP(G$40,Phase[Phase Code],Phase[Phase Description]),Table_query[Status],Summary!$B42),COUNTIFS(Table_query[Path],"sites/RGSales/Shared Documents/General/1.Open Opportunities",Table_query[Phase],_xlfn.XLOOKUP(G$40,Phase[Phase Code],Phase[Phase Description]),Table_query[Status],Summary!$B42,Table_query[VAT],VATSelector)) -> 0 | AA42: DODXXX RFQ Workforce Prioritisation Workshops 202512 | AB42: Risk
B43: Risk | C43: =IF(VATSelector="ALL",COUNTIFS(Table_query[Path],"sites/RGSales/Shared Documents/General/1.Open Opportunities",Table_query[Phase],_xlfn.XLOOKUP(C$40,Phase[Phase Code],Phase[Phase Description]),Table_query[Status],Summary!$B43),COUNTIFS(Table_query[Path],"sites/RGSales/Shared Documents/General/1.Open Opportunities",Table_query[Phase],_xlfn.XLOOKUP(C$40,Phase[Phase Code],Phase[Phase Description]),Table_query[Status],Summary!$B43,Table_query[VAT],VATSelector)) -> 3 | D43: =IF(VATSelector="ALL",COUNTIFS(Table_query[Path],"sites/RGSales/Shared Documents/General/1.Open Opportunities",Table_query[Phase],_xlfn.XLOOKUP(D$40,Phase[Phase Code],Phase[Phase Description]),Table_query[Status],Summary!$B43),COUNTIFS(Table_query[Path],"sites/RGSales/Shared Documents/General/1.Open Opportunities",Table_query[Phase],_xlfn.XLOOKUP(D$40,Phase[Phase Code],Phase[Phase Description]),Table_query[Status],Summary!$B43,Table_query[VAT],VATSelector)) -> 1 | E43: =IF(VATSelector="ALL",COUNTIFS(Table_query[Path],"sites/RGSales/Shared Documents/General/1.Open Opportunities",Table_query[Phase],_xlfn.XLOOKUP(E$40,Phase[Phase Code],Phase[Phase Description]),Table_query[Status],Summary!$B43),COUNTIFS(Table_query[Path],"sites/RGSales/Shared Documents/General/1.Open Opportunities",Table_query[Phase],_xlfn.XLOOKUP(E$40,Phase[Phase Code],Phase[Phase Description]),Table_query[Status],Summary!$B43,Table_query[VAT],VATSelector)) -> 9 | F43: =IF(VATSelector="ALL",COUNTIFS(Table_query[Path],"sites/RGSales/Shared Documents/General/1.Open Opportunities",Table_query[Phase],_xlfn.XLOOKUP(F$40,Phase[Phase Code],Phase[Phase Description]),Table_query[Status],Summary!$B43),COUNTIFS(Table_query[Path],"sites/RGSales/Shared Documents/General/1.Open Opportunities",Table_query[Phase],_xlfn.XLOOKUP(F$40,Phase[Phase Code],Phase[Phase Description]),Table_query[Status],Summary!$B43,Table_query[VAT],VATSelector)) -> 2 | G43: =IF(VATSelector="ALL",COUNTIFS(Table_query[Path],"sites/RGSales/Shared Documents/General/1.Open Opportunities",Table_query[Phase],_xlfn.XLOOKUP(G$40,Phase[Phase Code],Phase[Phase Description]),Table_query[Status],Summary!$B43),COUNTIFS(Table_query[Path],"sites/RGSales/Shared Documents/General/1.Open Opportunities",Table_query[Phase],_xlfn.XLOOKUP(G$40,Phase[Phase Code],Phase[Phase Description]),Table_query[Status],Summary!$B43,Table_query[VAT],VATSelector)) -> 0 | AA43: SAUXXX SPES Micro-Panel - RFQLH-02700 EL1 Senior Software Engineer | AB43: Risk
AA44: VICXXX CenITex Initial Strategy for One VPS | AB44: Good
B45: Likelihood and relevance - Days since submitted | AA45: IND004-01 Portfolio Management - IRM Implementation Extension) | AB45: Good
B46: Opportunity Status | C46: A | D46: Q | E46: DF | F46: DVF | G46: S | Z46: Grand Total
B47: <=7 days | C47: =IF(VATSelector="ALL",COUNTIFS(Table_query[Path],"sites/RGSales/Shared Documents/General/1.Open Opportunities",Table_query[Phase],_xlfn.XLOOKUP(C$46,Phase[Phase Code],Phase[Phase Description]),Table_query[Days submitted],"<=7"),COUNTIFS(Table_query[Path],"sites/RGSales/Shared Documents/General/1.Open Opportunities",Table_query[Phase],_xlfn.XLOOKUP(Summary!C$46,Phase[Phase Code],Phase[Phase Description]),Table_query[Days submitted],"<=7",Table_query[VAT],VATSelector)) -> 0 | D47: =IF(VATSelector="ALL",COUNTIFS(Table_query[Path],"sites/RGSales/Shared Documents/General/1.Open Opportunities",Table_query[Phase],_xlfn.XLOOKUP(D$46,Phase[Phase Code],Phase[Phase Description]),Table_query[Days submitted],"<=7"),COUNTIFS(Table_query[Path],"sites/RGSales/Shared Documents/General/1.Open Opportunities",Table_query[Phase],_xlfn.XLOOKUP(Summary!D$46,Phase[Phase Code],Phase[Phase Description]),Table_query[Days submitted],"<=7",Table_query[VAT],VATSelector)) -> 0 | E47: =IF(VATSelector="ALL",COUNTIFS(Table_query[Path],"sites/RGSales/Shared Documents/General/1.Open Opportunities",Table_query[Phase],_xlfn.XLOOKUP(E$46,Phase[Phase Code],Phase[Phase Description]),Table_query[Days submitted],"<=7"),COUNTIFS(Table_query[Path],"sites/RGSales/Shared Documents/General/1.Open Opportunities",Table_query[Phase],_xlfn.XLOOKUP(Summary!E$46,Phase[Phase Code],Phase[Phase Description]),Table_query[Days submitted],"<=7",Table_query[VAT],VATSelector)) -> 2 | F47: =IF(VATSelector="ALL",COUNTIFS(Table_query[Path],"sites/RGSales/Shared Documents/General/1.Open Opportunities",Table_query[Phase],_xlfn.XLOOKUP(F$46,Phase[Phase Code],Phase[Phase Description]),Table_query[Days submitted],"<=7"),COUNTIFS(Table_query[Path],"sites/RGSales/Shared Documents/General/1.Open Opportunities",Table_query[Phase],_xlfn.XLOOKUP(Summary!F$46,Phase[Phase Code],Phase[Phase Description]),Table_query[Days submitted],"<=7",Table_query[VAT],VATSelector)) -> 1 | G47: =IF(VATSelector="ALL",COUNTIFS(Table_query[Path],"sites/RGSales/Shared Documents/General/1.Open Opportunities",Table_query[Phase],_xlfn.XLOOKUP(G$46,Phase[Phase Code],Phase[Phase Description]),Table_query[Days submitted],"<=7"),COUNTIFS(Table_query[Path],"sites/RGSales/Shared Documents/General/1.Open Opportunities",Table_query[Phase],_xlfn.XLOOKUP(Summary!G$46,Phase[Phase Code],Phase[Phase Description]),Table_query[Days submitted],"<=7",Table_query[VAT],VATSelector)) -> 0
B48: 8-14 days | C48: =IF(VATSelector="ALL",COUNTIFS(Table_query[Path],"sites/RGSales/Shared Documents/General/1.Open Opportunities",Table_query[Phase],_xlfn.XLOOKUP(C$46,Phase[Phase Code],Phase[Phase Description]),Table_query[Days submitted],">7",Table_query[Days submitted],"<=14"),COUNTIFS(Table_query[Path],"sites/RGSales/Shared Documents/General/1.Open Opportunities",Table_query[Phase],_xlfn.XLOOKUP(Summary!C$46,Phase[Phase Code],Phase[Phase Description]),Table_query[Days submitted],">7",Table_query[Days submitted],"<=14",Table_query[VAT],VATSelector)) -> 0 | D48: =IF(VATSelector="ALL",COUNTIFS(Table_query[Path],"sites/RGSales/Shared Documents/General/1.Open Opportunities",Table_query[Phase],_xlfn.XLOOKUP(D$46,Phase[Phase Code],Phase[Phase Description]),Table_query[Days submitted],">7",Table_query[Days submitted],"<=14"),COUNTIFS(Table_query[Path],"sites/RGSales/Shared Documents/General/1.Open Opportunities",Table_query[Phase],_xlfn.XLOOKUP(Summary!D$46,Phase[Phase Code],Phase[Phase Description]),Table_query[Days submitted],">7",Table_query[Days submitted],"<=14",Table_query[VAT],VATSelector)) -> 0 | E48: =IF(VATSelector="ALL",COUNTIFS(Table_query[Path],"sites/RGSales/Shared Documents/General/1.Open Opportunities",Table_query[Phase],_xlfn.XLOOKUP(E$46,Phase[Phase Code],Phase[Phase Description]),Table_query[Days submitted],">7",Table_query[Days submitted],"<=14"),COUNTIFS(Table_query[Path],"sites/RGSales/Shared Documents/General/1.Open Opportunities",Table_query[Phase],_xlfn.XLOOKUP(Summary!E$46,Phase[Phase Code],Phase[Phase Description]),Table_query[Days submitted],">7",Table_query[Days submitted],"<=14",Table_query[VAT],VATSelector)) -> 0 | F48: =IF(VATSelector="ALL",COUNTIFS(Table_query[Path],"sites/RGSales/Shared Documents/General/1.Open Opportunities",Table_query[Phase],_xlfn.XLOOKUP(F$46,Phase[Phase Code],Phase[Phase Description]),Table_query[Days submitted],">7",Table_query[Days submitted],"<=14"),COUNTIFS(Table_query[Path],"sites/RGSales/Shared Documents/General/1.Open Opportunities",Table_query[Phase],_xlfn.XLOOKUP(Summary!F$46,Phase[Phase Code],Phase[Phase Description]),Table_query[Days submitted],">7",Table_query[Days submitted],"<=14",Table_query[VAT],VATSelector)) -> 0 | G48: =IF(VATSelector="ALL",COUNTIFS(Table_query[Path],"sites/RGSales/Shared Documents/General/1.Open Opportunities",Table_query[Phase],_xlfn.XLOOKUP(G$46,Phase[Phase Code],Phase[Phase Description]),Table_query[Days submitted],">7",Table_query[Days submitted],"<=14"),COUNTIFS(Table_query[Path],"sites/RGSales/Shared Documents/General/1.Open Opportunities",Table_query[Phase],_xlfn.XLOOKUP(Summary!G$46,Phase[Phase Code],Phase[Phase Description]),Table_query[Days submitted],">7",Table_query[Days submitted],"<=14",Table_query[VAT],VATSelector)) -> 0
B49: 15-30 days | C49: =IF(VATSelector="ALL",COUNTIFS(Table_query[Path],"sites/RGSales/Shared Documents/General/1.Open Opportunities",Table_query[Phase],_xlfn.XLOOKUP(C$46,Phase[Phase Code],Phase[Phase Description]),Table_query[Days submitted],">14",Table_query[Days submitted],"<=30"),COUNTIFS(Table_query[Path],"sites/RGSales/Shared Documents/General/1.Open Opportunities",Table_query[Phase],_xlfn.XLOOKUP(Summary!C$46,Phase[Phase Code],Phase[Phase Description]),Table_query[Days submitted],">14",Table_query[Days submitted],"<=30",Table_query[VAT],VATSelector)) -> 0 | D49: =IF(VATSelector="ALL",COUNTIFS(Table_query[Path],"sites/RGSales/Shared Documents/General/1.Open Opportunities",Table_query[Phase],_xlfn.XLOOKUP(D$46,Phase[Phase Code],Phase[Phase Description]),Table_query[Days submitted],">14",Table_query[Days submitted],"<=30"),COUNTIFS(Table_query[Path],"sites/RGSales/Shared Documents/General/1.Open Opportunities",Table_query[Phase],_xlfn.XLOOKUP(Summary!D$46,Phase[Phase Code],Phase[Phase Description]),Table_query[Days submitted],">14",Table_query[Days submitted],"<=30",Table_query[VAT],VATSelector)) -> 0 | E49: =IF(VATSelector="ALL",COUNTIFS(Table_query[Path],"sites/RGSales/Shared Documents/General/1.Open Opportunities",Table_query[Phase],_xlfn.XLOOKUP(E$46,Phase[Phase Code],Phase[Phase Description]),Table_query[Days submitted],">14",Table_query[Days submitted],"<=30"),COUNTIFS(Table_query[Path],"sites/RGSales/Shared Documents/General/1.Open Opportunities",Table_query[Phase],_xlfn.XLOOKUP(Summary!E$46,Phase[Phase Code],Phase[Phase Description]),Table_query[Days submitted],">14",Table_query[Days submitted],"<=30",Table_query[VAT],VATSelector)) -> 4 | F49: =IF(VATSelector="ALL",COUNTIFS(Table_query[Path],"sites/RGSales/Shared Documents/General/1.Open Opportunities",Table_query[Phase],_xlfn.XLOOKUP(F$46,Phase[Phase Code],Phase[Phase Description]),Table_query[Days submitted],">14",Table_query[Days submitted],"<=30"),COUNTIFS(Table_query[Path],"sites/RGSales/Shared Documents/General/1.Open Opportunities",Table_query[Phase],_xlfn.XLOOKUP(Summary!F$46,Phase[Phase Code],Phase[Phase Description]),Table_query[Days submitted],">14",Table_query[Days submitted],"<=30",Table_query[VAT],VATSelector)) -> 1 | G49: =IF(VATSelector="ALL",COUNTIFS(Table_query[Path],"sites/RGSales/Shared Documents/General/1.Open Opportunities",Table_query[Phase],_xlfn.XLOOKUP(G$46,Phase[Phase Code],Phase[Phase Description]),Table_query[Days submitted],">14",Table_query[Days submitted],"<=30"),COUNTIFS(Table_query[Path],"sites/RGSales/Shared Documents/General/1.Open Opportunities",Table_query[Phase],_xlfn.XLOOKUP(Summary!G$46,Phase[Phase Code],Phase[Phase Description]),Table_query[Days submitted],">14",Table_query[Days submitted],"<=30",Table_query[VAT],VATSelector)) -> 0
B50: 31 days+ | C50: =IF(VATSelector="ALL",COUNTIFS(Table_query[Path],"sites/RGSales/Shared Documents/General/1.Open Opportunities",Table_query[Phase],_xlfn.XLOOKUP(C$46,Phase[Phase Code],Phase[Phase Description]),Table_query[Days submitted],">30"),COUNTIFS(Table_query[Path],"sites/RGSales/Shared Documents/General/1.Open Opportunities",Table_query[Phase],_xlfn.XLOOKUP(Summary!C$46,Phase[Phase Code],Phase[Phase Description]),Table_query[Days submitted],">30",Table_query[VAT],VATSelector)) -> 0 | D50: =IF(VATSelector="ALL",COUNTIFS(Table_query[Path],"sites/RGSales/Shared Documents/General/1.Open Opportunities",Table_query[Phase],_xlfn.XLOOKUP(D$46,Phase[Phase Code],Phase[Phase Description]),Table_query[Days submitted],">30"),COUNTIFS(Table_query[Path],"sites/RGSales/Shared Documents/General/1.Open Opportunities",Table_query[Phase],_xlfn.XLOOKUP(Summary!D$46,Phase[Phase Code],Phase[Phase Description]),Table_query[Days submitted],">30",Table_query[VAT],VATSelector)) -> 0 | E50: =IF(VATSelector="ALL",COUNTIFS(Table_query[Path],"sites/RGSales/Shared Documents/General/1.Open Opportunities",Table_query[Phase],_xlfn.XLOOKUP(E$46,Phase[Phase Code],Phase[Phase Description]),Table_query[Days submitted],">30"),COUNTIFS(Table_query[Path],"sites/RGSales/Shared Documents/General/1.Open Opportunities",Table_query[Phase],_xlfn.XLOOKUP(Summary!E$46,Phase[Phase Code],Phase[Phase Description]),Table_query[Days submitted],">30",Table_query[VAT],VATSelector)) -> 8 | F50: =IF(VATSelector="ALL",COUNTIFS(Table_query[Path],"sites/RGSales/Shared Documents/General/1.Open Opportunities",Table_query[Phase],_xlfn.XLOOKUP(F$46,Phase[Phase Code],Phase[Phase Description]),Table_query[Days submitted],">30"),COUNTIFS(Table_query[Path],"sites/RGSales/Shared Documents/General/1.Open Opportunities",Table_query[Phase],_xlfn.XLOOKUP(Summary!F$46,Phase[Phase Code],Phase[Phase Description]),Table_query[Days submitted],">30",Table_query[VAT],VATSelector)) -> 6 | G50: =IF(VATSelector="ALL",COUNTIFS(Table_query[Path],"sites/RGSales/Shared Documents/General/1.Open Opportunities",Table_query[Phase],_xlfn.XLOOKUP(G$46,Phase[Phase Code],Phase[Phase Description]),Table_query[Days submitted],">30"),COUNTIFS(Table_query[Path],"sites/RGSales/Shared Documents/General/1.Open Opportunities",Table_query[Phase],_xlfn.XLOOKUP(Summary!G$46,Phase[Phase Code],Phase[Phase Description]),Table_query[Days submitted],">30",Table_query[VAT],VATSelector)) -> 0
B53: Pursuit Intensity - Days since last modified
B54: Opportunity Status | C54: A | D54: Q | E54: DF | F54: DVF | G54: S
B55: <=7 days | C55: =IF(VATSelector="ALL",COUNTIFS(Table_query[Path],"sites/RGSales/Shared Documents/General/1.Open Opportunities",Table_query[Phase],_xlfn.XLOOKUP(C$54,Phase[Phase Code],Phase[Phase Description]),Table_query[Days modified],"<=7"),COUNTIFS(Table_query[Path],"sites/RGSales/Shared Documents/General/1.Open Opportunities",Table_query[Phase],_xlfn.XLOOKUP(C$54,Phase[Phase Code],Phase[Phase Description]),Table_query[Days modified],"<=7",Table_query[VAT],VATSelector)) -> 22 | D55: =IF(VATSelector="ALL",COUNTIFS(Table_query[Path],"sites/RGSales/Shared Documents/General/1.Open Opportunities",Table_query[Phase],_xlfn.XLOOKUP(D$54,Phase[Phase Code],Phase[Phase Description]),Table_query[Days modified],"<=7"),COUNTIFS(Table_query[Path],"sites/RGSales/Shared Documents/General/1.Open Opportunities",Table_query[Phase],_xlfn.XLOOKUP(D$54,Phase[Phase Code],Phase[Phase Description]),Table_query[Days modified],"<=7",Table_query[VAT],VATSelector)) -> 9 | E55: =IF(VATSelector="ALL",COUNTIFS(Table_query[Path],"sites/RGSales/Shared Documents/General/1.Open Opportunities",Table_query[Phase],_xlfn.XLOOKUP(E$54,Phase[Phase Code],Phase[Phase Description]),Table_query[Days modified],"<=7"),COUNTIFS(Table_query[Path],"sites/RGSales/Shared Documents/General/1.Open Opportunities",Table_query[Phase],_xlfn.XLOOKUP(E$54,Phase[Phase Code],Phase[Phase Description]),Table_query[Days modified],"<=7",Table_query[VAT],VATSelector)) -> 7 | F55: =IF(VATSelector="ALL",COUNTIFS(Table_query[Path],"sites/RGSales/Shared Documents/General/1.Open Opportunities",Table_query[Phase],_xlfn.XLOOKUP(F$54,Phase[Phase Code],Phase[Phase Description]),Table_query[Days modified],"<=7"),COUNTIFS(Table_query[Path],"sites/RGSales/Shared Documents/General/1.Open Opportunities",Table_query[Phase],_xlfn.XLOOKUP(F$54,Phase[Phase Code],Phase[Phase Description]),Table_query[Days modified],"<=7",Table_query[VAT],VATSelector)) -> 4 | G55: =IF(VATSelector="ALL",COUNTIFS(Table_query[Path],"sites/RGSales/Shared Documents/General/1.Open Opportunities",Table_query[Phase],_xlfn.XLOOKUP(G$54,Phase[Phase Code],Phase[Phase Description]),Table_query[Days modified],"<=7"),COUNTIFS(Table_query[Path],"sites/RGSales/Shared Documents/General/1.Open Opportunities",Table_query[Phase],_xlfn.XLOOKUP(G$54,Phase[Phase Code],Phase[Phase Description]),Table_query[Days modified],"<=7",Table_query[VAT],VATSelector)) -> 0
B56: 8-14 days | C56: =IF(VATSelector="ALL",COUNTIFS(Table_query[Path],"sites/RGSales/Shared Documents/General/1.Open Opportunities",Table_query[Phase],_xlfn.XLOOKUP(C$54,Phase[Phase Code],Phase[Phase Description]),Table_query[Days modified],">7",Table_query[Days modified],"<=14"),COUNTIFS(Table_query[Path],"sites/RGSales/Shared Documents/General/1.Open Opportunities",Table_query[Phase],_xlfn.XLOOKUP(C$54,Phase[Phase Code],Phase[Phase Description]),Table_query[Days modified],">7",Table_query[Days modified],"<=14",Table_query[VAT],VATSelector)) -> 13 | D56: =IF(VATSelector="ALL",COUNTIFS(Table_query[Path],"sites/RGSales/Shared Documents/General/1.Open Opportunities",Table_query[Phase],_xlfn.XLOOKUP(D$54,Phase[Phase Code],Phase[Phase Description]),Table_query[Days modified],">7",Table_query[Days modified],"<=14"),COUNTIFS(Table_query[Path],"sites/RGSales/Shared Documents/General/1.Open Opportunities",Table_query[Phase],_xlfn.XLOOKUP(D$54,Phase[Phase Code],Phase[Phase Description]),Table_query[Days modified],">7",Table_query[Days modified],"<=14",Table_query[VAT],VATSelector)) -> 1 | E56: =IF(VATSelector="ALL",COUNTIFS(Table_query[Path],"sites/RGSales/Shared Documents/General/1.Open Opportunities",Table_query[Phase],_xlfn.XLOOKUP(E$54,Phase[Phase Code],Phase[Phase Description]),Table_query[Days modified],">7",Table_query[Days modified],"<=14"),COUNTIFS(Table_query[Path],"sites/RGSales/Shared Documents/General/1.Open Opportunities",Table_query[Phase],_xlfn.XLOOKUP(E$54,Phase[Phase Code],Phase[Phase Description]),Table_query[Days modified],">7",Table_query[Days modified],"<=14",Table_query[VAT],VATSelector)) -> 2 | F56: =IF(VATSelector="ALL",COUNTIFS(Table_query[Path],"sites/RGSales/Shared Documents/General/1.Open Opportunities",Table_query[Phase],_xlfn.XLOOKUP(F$54,Phase[Phase Code],Phase[Phase Description]),Table_query[Days modified],">7",Table_query[Days modified],"<=14"),COUNTIFS(Table_query[Path],"sites/RGSales/Shared Documents/General/1.Open Opportunities",Table_query[Phase],_xlfn.XLOOKUP(F$54,Phase[Phase Code],Phase[Phase Description]),Table_query[Days modified],">7",Table_query[Days modified],"<=14",Table_query[VAT],VATSelector)) -> 6 | G56: =IF(VATSelector="ALL",COUNTIFS(Table_query[Path],"sites/RGSales/Shared Documents/General/1.Open Opportunities",Table_query[Phase],_xlfn.XLOOKUP(G$54,Phase[Phase Code],Phase[Phase Description]),Table_query[Days modified],">7",Table_query[Days modified],"<=14"),COUNTIFS(Table_query[Path],"sites/RGSales/Shared Documents/General/1.Open Opportunities",Table_query[Phase],_xlfn.XLOOKUP(G$54,Phase[Phase Code],Phase[Phase Description]),Table_query[Days modified],">7",Table_query[Days modified],"<=14",Table_query[VAT],VATSelector)) -> 0
B57: 15-30 days | C57: =IF(VATSelector="ALL",COUNTIFS(Table_query[Path],"sites/RGSales/Shared Documents/General/1.Open Opportunities",Table_query[Phase],_xlfn.XLOOKUP(C$54,Phase[Phase Code],Phase[Phase Description]),Table_query[Days modified],">14",Table_query[Days modified],"<=30"),COUNTIFS(Table_query[Path],"sites/RGSales/Shared Documents/General/1.Open Opportunities",Table_query[Phase],_xlfn.XLOOKUP(C$54,Phase[Phase Code],Phase[Phase Description]),Table_query[Days modified],">14",Table_query[Days modified],"<=30",Table_query[VAT],VATSelector)) -> 11 | D57: =IF(VATSelector="ALL",COUNTIFS(Table_query[Path],"sites/RGSales/Shared Documents/General/1.Open Opportunities",Table_query[Phase],_xlfn.XLOOKUP(D$54,Phase[Phase Code],Phase[Phase Description]),Table_query[Days modified],">14",Table_query[Days modified],"<=30"),COUNTIFS(Table_query[Path],"sites/RGSales/Shared Documents/General/1.Open Opportunities",Table_query[Phase],_xlfn.XLOOKUP(D$54,Phase[Phase Code],Phase[Phase Description]),Table_query[Days modified],">14",Table_query[Days modified],"<=30",Table_query[VAT],VATSelector)) -> 0 | E57: =IF(VATSelector="ALL",COUNTIFS(Table_query[Path],"sites/RGSales/Shared Documents/General/1.Open Opportunities",Table_query[Phase],_xlfn.XLOOKUP(E$54,Phase[Phase Code],Phase[Phase Description]),Table_query[Days modified],">14",Table_query[Days modified],"<=30"),COUNTIFS(Table_query[Path],"sites/RGSales/Shared Documents/General/1.Open Opportunities",Table_query[Phase],_xlfn.XLOOKUP(E$54,Phase[Phase Code],Phase[Phase Description]),Table_query[Days modified],">14",Table_query[Days modified],"<=30",Table_query[VAT],VATSelector)) -> 4 | F57: =IF(VATSelector="ALL",COUNTIFS(Table_query[Path],"sites/RGSales/Shared Documents/General/1.Open Opportunities",Table_query[Phase],_xlfn.XLOOKUP(F$54,Phase[Phase Code],Phase[Phase Description]),Table_query[Days modified],">14",Table_query[Days modified],"<=30"),COUNTIFS(Table_query[Path],"sites/RGSales/Shared Documents/General/1.Open Opportunities",Table_query[Phase],_xlfn.XLOOKUP(F$54,Phase[Phase Code],Phase[Phase Description]),Table_query[Days modified],">14",Table_query[Days modified],"<=30",Table_query[VAT],VATSelector)) -> 2 | G57: =IF(VATSelector="ALL",COUNTIFS(Table_query[Path],"sites/RGSales/Shared Documents/General/1.Open Opportunities",Table_query[Phase],_xlfn.XLOOKUP(G$54,Phase[Phase Code],Phase[Phase Description]),Table_query[Days modified],">14",Table_query[Days modified],"<=30"),COUNTIFS(Table_query[Path],"sites/RGSales/Shared Documents/General/1.Open Opportunities",Table_query[Phase],_xlfn.XLOOKUP(G$54,Phase[Phase Code],Phase[Phase Description]),Table_query[Days modified],">14",Table_query[Days modified],"<=30",Table_query[VAT],VATSelector)) -> 0
B58: 31 days+ | C58: =IF(VATSelector="ALL",COUNTIFS(Table_query[Path],"sites/RGSales/Shared Documents/General/1.Open Opportunities",Table_query[Phase],_xlfn.XLOOKUP(C$54,Phase[Phase Code],Phase[Phase Description]),Table_query[Days modified],">=31"),COUNTIFS(Table_query[Path],"sites/RGSales/Shared Documents/General/1.Open Opportunities",Table_query[Phase],_xlfn.XLOOKUP(C$54,Phase[Phase Code],Phase[Phase Description]),Table_query[Days modified],">=31",Table_query[VAT],VATSelector)) -> 7 | D58: =IF(VATSelector="ALL",COUNTIFS(Table_query[Path],"sites/RGSales/Shared Documents/General/1.Open Opportunities",Table_query[Phase],_xlfn.XLOOKUP(D$54,Phase[Phase Code],Phase[Phase Description]),Table_query[Days modified],">=31"),COUNTIFS(Table_query[Path],"sites/RGSales/Shared Documents/General/1.Open Opportunities",Table_query[Phase],_xlfn.XLOOKUP(D$54,Phase[Phase Code],Phase[Phase Description]),Table_query[Days modified],">=31",Table_query[VAT],VATSelector)) -> 0 | E58: =IF(VATSelector="ALL",COUNTIFS(Table_query[Path],"sites/RGSales/Shared Documents/General/1.Open Opportunities",Table_query[Phase],_xlfn.XLOOKUP(E$54,Phase[Phase Code],Phase[Phase Description]),Table_query[Days modified],">=31"),COUNTIFS(Table_query[Path],"sites/RGSales/Shared Documents/General/1.Open Opportunities",Table_query[Phase],_xlfn.XLOOKUP(E$54,Phase[Phase Code],Phase[Phase Description]),Table_query[Days modified],">=31",Table_query[VAT],VATSelector)) -> 2 | F58: =IF(VATSelector="ALL",COUNTIFS(Table_query[Path],"sites/RGSales/Shared Documents/General/1.Open Opportunities",Table_query[Phase],_xlfn.XLOOKUP(F$54,Phase[Phase Code],Phase[Phase Description]),Table_query[Days modified],">=31"),COUNTIFS(Table_query[Path],"sites/RGSales/Shared Documents/General/1.Open Opportunities",Table_query[Phase],_xlfn.XLOOKUP(F$54,Phase[Phase Code],Phase[Phase Description]),Table_query[Days modified],">=31",Table_query[VAT],VATSelector)) -> 0 | G58: =IF(VATSelector="ALL",COUNTIFS(Table_query[Path],"sites/RGSales/Shared Documents/General/1.Open Opportunities",Table_query[Phase],_xlfn.XLOOKUP(G$54,Phase[Phase Code],Phase[Phase Description]),Table_query[Days modified],">=31"),COUNTIFS(Table_query[Path],"sites/RGSales/Shared Documents/General/1.Open Opportunities",Table_query[Phase],_xlfn.XLOOKUP(G$54,Phase[Phase Code],Phase[Phase Description]),Table_query[Days modified],">=31",Table_query[VAT],VATSelector)) -> 0
C59: What open opps to include
C60: Good | D60: TRUE
C61: Fair | D61: FALSE
C62: Risk | D62: FALSE

Sheet COMPANY Spread
B41: Cumulative View - Gross Margin Contribution | P41: Cumulative View - Revenue
B42: STATUS | C42: July | D42: August | E42: September | F42: October | G42: November | H42: December | I42: January | J42: February | K42: March | L42: April | M42: May | N42: June | P42: STATUS | Q42: July | R42: August | S42: September | T42: October | U42: November | V42: December | W42: January | X42: February | Y42: March | Z42: April | AA42: May | AB42: June
B43: C | C43: =C54 -> 371824.25 | D43: =SUM($C54:D54) -> 996334.71 | E43: =SUM($C54:E54) -> 1791429.4 | F43: =SUM($C54:F54) -> 2809151.2 | G43: =SUM($C54:G54) -> 3458448.8 | H43: =SUM($C54:H54) -> 3922585.1 | I43: =SUM($C54:I54) -> 4250178.2 | J43: =SUM($C54:J54) -> 4545961.7 | K43: =SUM($C54:K54) -> 4823816.6 | ... N43: =SUM($C54:N54) -> 5352390.3 | P43: C | Q43: =Q54 -> 1489443.4 | R43: =SUM($Q54:R54) -> 3380720.4 | S43: =SUM($Q54:S54) -> 5912887.3 | T43: =SUM($Q54:T54) -> 8541298.4 | U43: =SUM($Q54:U54) -> 10744629 | V43: =SUM($Q54:V54) -> 12418789 | W43: =SUM($Q54:W54) -> 13865663 | X43: =SUM($Q54:X54) -> 15392756 | Y43: =SUM($Q54:Y54) -> 17156781 | ... AB43: =SUM($Q54:AB54) -> 20629881
B44: S | C44: =C43+C55 -> 371824.25 | D44: =SUM($C55:D55)+D43 -> 996334.71 | E44: =SUM($C55:E55)+E43 -> 1791429.4 | F44: =SUM($C55:F55)+F43 -> 2809151.2 | G44: =SUM($C55:G55)+G43 -> 3458448.8 | H44: =SUM($C55:H55)+H43 -> 3922585.1 | I44: =SUM($C55:I55)+I43 -> 4250178.2 | J44: =SUM($C55:J55)+J43 -> 4545961.7 | K44: =SUM($C55:K55)+K43 -> 4823816.6 | ... N44: =SUM($C55:N55)+N43 -> 5352390.3 | P44: S | Q44: =Q55+Q43 -> 1489443.4 | R44: =SUM($Q55:R55)+R43 -> 3380720.4 | S44: =SUM($Q55:S55)+S43 -> 5912887.3 | T44: =SUM($Q55:T55)+T43 -> 8541298.4 | U44: =SUM($Q55:U55)+U43 -> 10744629 | V44: =SUM($Q55:V55)+V43 -> 12418789 | W44: =SUM($Q55:W55)+W43 -> 13865663 | X44: =SUM($Q55:X55)+X43 -> 15392756 | Y44: =SUM($Q55:Y55)+Y43 -> 17156781 | ... AB44: =SUM($Q55:AB55)+AB43 -> 20629881
B45: DVF | C45: =C44+C56 -> 371824.25 | D45: =SUM($C56:D56)+D44 -> 996334.71 | E45: =SUM($C56:E56)+E44 -> 1791429.4 | F45: =SUM($C56:F56)+F44 -> 2809151.2 | G45: =SUM($C56:G56)+G44 -> 3458448.8 | H45: =SUM($C56:H56)+H44 -> 3922585.1 | I45: =SUM($C56:I56)+I44 -> 4250178.2 | J45: =SUM($C56:J56)+J44 -> 4554962.1 | K45: =SUM($C56:K56)+K44 -> 4878192.1 | ... N45: =SUM($C56:N56)+N44 -> 7559370.1 | P45: DVF | Q45: =Q56+Q44 -> 1489443.4 | R45: =SUM($Q56:R56)+R44 -> 3380720.4 | S45: =SUM($Q56:S56)+S44 -> 5912887.3 | T45: =SUM($Q56:T56)+T44 -> 8541298.4 | U45: =SUM($Q56:U56)+U44 -> 10744629 | V45: =SUM($Q56:V56)+V44 -> 12418789 | W45: =SUM($Q56:W56)+W44 -> 13865663 | X45: =SUM($Q56:X56)+X44 -> 15412800 | Y45: =SUM($Q56:Y56)+Y44 -> 17285041 | ... AB45: =SUM($Q56:AB56)+AB44 -> 25127632
B46: DF+ | C46: =C45+C57 -> 371824.25 | D46: =SUM($C57:D57)+D45 -> 996334.71 | E46: =SUM($C57:E57)+E45 -> 1791429.4 | F46: =SUM($C57:F57)+F45 -> 2809151.2 | G46: =SUM($C57:G57)+G45 -> 3458448.8 | H46: =SUM($C57:H57)+H45 -> 3922585.1 | I46: =SUM($C57:I57)+I45 -> 4250178.2 | J46: =SUM($C57:J57)+J45 -> 4554962.1 | K46: =SUM($C57:K57)+K45 -> 4878192.1 | ... N46: =SUM($C57:N57)+N45 -> 7559370.1 | P46: DF+ | Q46: =Q57+Q45 -> 1489443.4 | R46: =SUM($Q57:R57)+R45 -> 3380720.4 | S46: =SUM($Q57:S57)+S45 -> 5912887.3 | T46: =SUM($Q57:T57)+T45 -> 8541298.4 | U46: =SUM($Q57:U57)+U45 -> 10744629 | V46: =SUM($Q57:V57)+V45 -> 12418789 | W46: =SUM($Q57:W57)+W45 -> 13865663 | X46: =SUM($Q57:X57)+X45 -> 15412800 | Y46: =SUM($Q57:Y57)+Y45 -> 17285041 | ... AB46: =SUM($Q57:AB57)+AB45 -> 25127632
B47: Q+ | C47: =C46+C58 -> 371824.25 | D47: =SUM($C58:D58)+D46 -> 996334.71 | E47: =SUM($C58:E58)+E46 -> 1791429.4 | F47: =SUM($C58:F58)+F46 -> 2809151.2 | G47: =SUM($C58:G58)+G46 -> 3458448.8 | H47: =SUM($C58:H58)+H46 -> 3922585.1 | I47: =SUM($C58:I58)+I46 -> 4250178.2 | J47: =SUM($C58:J58)+J46 -> 4554962.1 | K47: =SUM($C58:K58)+K46 -> 4878192.1 | ... N47: =SUM($C58:N58)+N46 -> 7559370.1 | P47: Q+ | Q47: =Q58+Q46 -> 1489443.4 | R47: =SUM($Q58:R58)+R46 -> 3380720.4 | S47: =SUM($Q58:S58)+S46 -> 5912887.3 | T47: =SUM($Q58:T58)+T46 -> 8541298.4 | U47: =SUM($Q58:U58)+U46 -> 10744629 | V47: =SUM($Q58:V58)+V46 -> 12418789 | W47: =SUM($Q58:W58)+W46 -> 13865663 | X47: =SUM($Q58:X58)+X46 -> 15532800 | Y47: =SUM($Q58:Y58)+Y46 -> 17525041 | ... AB47: =SUM($Q58:AB58)+AB46 -> 26063346
B48: GREAT | C48: =C59 -> 971166.67 | D48: =SUM($C59:D59) -> 1946833.3 | E48: =SUM($C59:E59) -> 2937500 | F48: =SUM($C59:F59) -> 3891666.7 | G48: =SUM($C59:G59) -> 4845833.3 | H48: =SUM($C59:H59) -> 5800000 | I48: =SUM($C59:I59) -> 7016666.7 | J48: =SUM($C59:J59) -> 8233333.3 | K48: =SUM($C59:K59) -> 9450000 | ... N48: =SUM($C59:N59) -> 13100000 | P48: GREAT | Q48: =Q59 -> 3179953.1 | R48: =SUM($Q59:R59) -> 6374906.2 | S48: =SUM($Q59:S59) -> 9619859.3 | T48: =SUM($Q59:T59) -> 12432540 | U48: =SUM($Q59:U59) -> 15245220 | V48: =SUM($Q59:V59) -> 18057900 | W48: =SUM($Q59:W59) -> 22211490 | X48: =SUM($Q59:X59) -> 26365079 | Y48: =SUM($Q59:Y59) -> 30518669 | ... AB48: =SUM($Q59:AB59) -> 42979437
B49: GOOD | C49: =C60 -> 748666.67 | D49: =SUM($C60:D60) -> 1501833.3 | E49: =SUM($C60:E60) -> 2270000 | F49: =SUM($C60:F60) -> 3043333.3 | G49: =SUM($C60:G60) -> 3816666.7 | H49: =SUM($C60:H60) -> 4590000 | I49: =SUM($C60:I60) -> 5513333.3 | J49: =SUM($C60:J60) -> 6436666.7 | K49: =SUM($C60:K60) -> 7360000 | ... N49: =SUM($C60:N60) -> 10130000 | P49: GOOD | Q49: =Q60 -> 2510562.8 | R49: =SUM($Q60:R60) -> 5036125.5 | S49: =SUM($Q60:S60) -> 7611688.3 | T49: =SUM($Q60:T60) -> 10007504 | U49: =SUM($Q60:U60) -> 12403319 | V49: =SUM($Q60:V60) -> 14799134 | W49: =SUM($Q60:W60) -> 17990404 | X49: =SUM($Q60:X60) -> 21181674 | Y49: =SUM($Q60:Y60) -> 24372944 | ... AB49: =SUM($Q60:AB60) -> 33946753
B50: OK | C50: =C61 -> 537000 | D50: =SUM($C61:D61) -> 1078500 | E50: =SUM($C61:E61) -> 1635000 | F50: =SUM($C61:F61) -> 2215000 | G50: =SUM($C61:G61) -> 2795000 | H50: =SUM($C61:H61) -> 3375000 | I50: =SUM($C61:I61) -> 3992500 | J50: =SUM($C61:J61) -> 4610000 | K50: =SUM($C61:K61) -> 5227500 | ... N50: =SUM($C61:N61) -> 7080000 | P50: OK | Q50: =Q61 -> 1877366.9 | R50: =SUM($Q61:R61) -> 3769733.7 | S50: =SUM($Q61:S61) -> 5712100.6 | T50: =SUM($Q61:T61) -> 7643720.3 | U50: =SUM($Q61:U61) -> 9575340.1 | V50: =SUM($Q61:V61) -> 11506960 | W50: =SUM($Q61:W61) -> 13697200 | X50: =SUM($Q61:X61) -> 15887441 | Y50: =SUM($Q61:Y61) -> 18077681 | ... AB50: =SUM($Q61:AB61) -> 24648402
B52: Monthly View - Gross Margin Contribution | P52: Monthly View - Revenue
B53: STATUS | C53: July | D53: August | E53: September | F53: October | G53: November | H53: December | I53: January | J53: February | K53: March | L53: April | M53: May | N53: June | P53: STATUS | Q53: July | R53: August | S53: September | T53: October | U53: November | V53: December | W53: January | X53: February | Y53: March | Z53: April | AA53: May | AB53: June
B54: C | C54: =IF(VATSelector="ALL",Job_Status[[#Totals],[P1]],SUMIF(Job_Status[VAT],VATSelector,Job_Status[P1])) -> 371824.25 | D54: =IF(VATSelector="ALL",Job_Status[[#Totals],[P2]],SUMIF(Job_Status[VAT],VATSelector,Job_Status[P2])) -> 624510.46 | E54: =IF(VATSelector="ALL",Job_Status[[#Totals],[P3]],SUMIF(Job_Status[VAT],VATSelector,Job_Status[P3])) -> 795094.69 | F54: =IF(VATSelector="ALL",Job_Status[[#Totals],[P4]],SUMIF(Job_Status[VAT],VATSelector,Job_Status[P4])) -> 1017721.8 | G54: =IF(VATSelector="ALL",Job_Status[[#Totals],[P5]],SUMIF(Job_Status[VAT],VATSelector,Job_Status[P5])) -> 649297.64 | H54: =IF(VATSelector="ALL",Job_Status[[#Totals],[P6]],SUMIF(Job_Status[VAT],VATSelector,Job_Status[P6])) -> 464136.3 | I54: =IF(VATSelector="ALL",Job_Status[[#Totals],[P7]],SUMIF(Job_Status[VAT],VATSelector,Job_Status[P7])) -> 327593.11 | J54: =IF(VATSelector="ALL",Job_Status[[#Totals],[P8]],SUMIF(Job_Status[VAT],VATSelector,Job_Status[P8])) -> 295783.44 | K54: =IF(VATSelector="ALL",Job_Status[[#Totals],[P9]],SUMIF(Job_Status[VAT],VATSelector,Job_Status[P9])) -> 277854.96 | L54: =IF(VATSelector="ALL",Job_Status[[#Totals],[P10]],SUMIF(Job_Status[VAT],VATSelector,Job_Status[P10])) -> 157710.36 | M54: =IF(VATSelector="ALL",Job_Status[[#Totals],[P11]],SUMIF(Job_Status[VAT],VATSelector,Job_Status[P11])) -> 163082.2 | N54: =IF(VATSelector="ALL",Job_Status[[#Totals],[P12]],SUMIF(Job_Status[VAT],VATSelector,Job_Status[P12])) -> 207781.13 | P54: C | Q54: =Job_Status[[#Totals],[R1]] -> 1489443.4 | R54: =Job_Status[[#Totals],[R2]] -> 1891277 | S54: =Job_Status[[#Totals],[R3]] -> 2532166.9 | T54: =Job_Status[[#Totals],[R4]] -> 2628411.1 | U54: =Job_Status[[#Totals],[R5]] -> 2203330.7 | V54: =Job_Status[[#Totals],[R6]] -> 1674160.1 | W54: =Job_Status[[#Totals],[R7]] -> 1446873.6 | X54: =Job_Status[[#Totals],[R8]] -> 1527093.3 | Y54: =Job_Status[[#Totals],[R9]] -> 1764024.6 | Z54: =Job_Status[[#Totals],[R10]] -> 1139120.8 | AA54: =Job_Status[[#Totals],[R11]] -> 1132235.1 | AB54: =Job_Status[[#Totals],[R12]] -> 1201744.8
B55: S | C55: =IF(CompanyGoodToggle=TRUE,SUMIFS(TotalGMContribution[July],TotalGMContribution[Status],GMConSpreadTable[[#This Row],[STATUS]],TotalGMContribution[Opps Status],"Good"),0)+IF(CompanyFairToggle=TRUE,SUMIFS(TotalGMContribution[July],TotalGMContribution[Status],GMConSpreadTable[[#This Row],[STATUS]],TotalGMContribution[Opps Status],"Fair"),0)+IF(CompanyRiskToggle=TRUE,SUMIFS(TotalGMContribution[July],TotalGMContribution[Status],GMConSpreadTable[[#This Row],[STATUS]],TotalGMContribution[Opps Status],"Risk"),0) -> 0 | D55: =IF(CompanyGoodToggle=TRUE,SUMIFS(TotalGMContribution[August],TotalGMContribution[Status],GMConSpreadTable[[#This Row],[STATUS]],TotalGMContribution[Opps Status],"Good"),0)+IF(CompanyFairToggle=TRUE,SUMIFS(TotalGMContribution[August],TotalGMContribution[Status],GMConSpreadTable[[#This Row],[STATUS]],TotalGMContribution[Opps Status],"Fair"),0)+IF(CompanyRiskToggle=TRUE,SUMIFS(TotalGMContribution[August],TotalGMContribution[Status],GMConSpreadTable[[#This Row],[STATUS]],TotalGMContribution[Opps Status],"Risk"),0) -> 0 | E55: =IF(CompanyGoodToggle=TRUE,SUMIFS(TotalGMContribution[September],TotalGMContribution[Status],GMConSpreadTable[[#This Row],[STATUS]],TotalGMContribution[Opps Status],"Good"),0)+IF(CompanyFairToggle=TRUE,SUMIFS(TotalGMContribution[September],TotalGMContribution[Status],GMConSpreadTable[[#This Row],[STATUS]],TotalGMContribution[Opps Status],"Fair"),0)+IF(CompanyRiskToggle=TRUE,SUMIFS(TotalGMContribution[September],TotalGMContribution[Status],GMConSpreadTable[[#This Row],[STATUS]],TotalGMContribution[Opps Status],"Risk"),0) -> 0 | F55: =IF(CompanyGoodToggle=TRUE,SUMIFS(TotalGMContribution[October],TotalGMContribution[Status],GMConSpreadTable[[#This Row],[STATUS]],TotalGMContribution[Opps Status],"Good"),0)+IF(CompanyFairToggle=TRUE,SUMIFS(TotalGMContribution[October],TotalGMContribution[Status],GMConSpreadTable[[#This Row],[STATUS]],TotalGMContribution[Opps Status],"Fair"),0)+IF(CompanyRiskToggle=TRUE,SUMIFS(TotalGMContribution[October],TotalGMContribution[Status],GMConSpreadTable[[#This Row],[STATUS]],TotalGMContribution[Opps Status],"Risk"),0) -> 0 | G55: =IF(CompanyGoodToggle=TRUE,SUMIFS(TotalGMContribution[November],TotalGMContribution[Status],GMConSpreadTable[[#This Row],[STATUS]],TotalGMContribution[Opps Status],"Good"),0)+IF(CompanyFairToggle=TRUE,SUMIFS(TotalGMContribution[November],TotalGMContribution[Status],GMConSpreadTable[[#This Row],[STATUS]],TotalGMContribution[Opps Status],"Fair"),0)+IF(CompanyRiskToggle=TRUE,SUMIFS(TotalGMContribution[November],TotalGMContribution[Status],GMConSpreadTable[[#This Row],[STATUS]],TotalGMContribution[Opps Status],"Risk"),0) -> 0 | H55: =IF(CompanyGoodToggle=TRUE,SUMIFS(TotalGMContribution[December],TotalGMContribution[Status],GMConSpreadTable[[#This Row],[STATUS]],TotalGMContribution[Opps Status],"Good"),0)+IF(CompanyFairToggle=TRUE,SUMIFS(TotalGMContribution[December],TotalGMContribution[Status],GMConSpreadTable[[#This Row],[STATUS]],TotalGMContribution[Opps Status],"Fair"),0)+IF(CompanyRiskToggle=TRUE,SUMIFS(TotalGMContribution[December],TotalGMContribution[Status],GMConSpreadTable[[#This Row],[STATUS]],TotalGMContribution[Opps Status],"Risk"),0) -> 0 | I55: =IF(CompanyGoodToggle=TRUE,SUMIFS(TotalGMContribution[January],TotalGMContribution[Status],GMConSpreadTable[[#This Row],[STATUS]],TotalGMContribution[Opps Status],"Good"),0)+IF(CompanyFairToggle=TRUE,SUMIFS(TotalGMContribution[January],TotalGMContribution[Status],GMConSpreadTable[[#This Row],[STATUS]],TotalGMContribution[Opps Status],"Fair"),0)+IF(CompanyRiskToggle=TRUE,SUMIFS(TotalGMContribution[January],TotalGMContribution[Status],GMConSpreadTable[[#This Row],[STATUS]],TotalGMContribution[Opps Status],"Risk"),0) -> 0 | J55: =IF(CompanyGoodToggle=TRUE,SUMIFS(TotalGMContribution[February],TotalGMContribution[Status],GMConSpreadTable[[#This Row],[STATUS]],TotalGMContribution[Opps Status],"Good"),0)+IF(CompanyFairToggle=TRUE,SUMIFS(TotalGMContribution[February],TotalGMContribution[Status],GMConSpreadTable[[#This Row],[STATUS]],TotalGMContribution[Opps Status],"Fair"),0)+IF(CompanyRiskToggle=TRUE,SUMIFS(TotalGMContribution[February],TotalGMContribution[Status],GMConSpreadTable[[#This Row],[STATUS]],TotalGMContribution[Opps Status],"Risk"),0) -> 0 | K55: =IF(CompanyGoodToggle=TRUE,SUMIFS(TotalGMContribution[March],TotalGMContribution[Status],GMConSpreadTable[[#This Row],[STATUS]],TotalGMContribution[Opps Status],"Good"),0)+IF(CompanyFairToggle=TRUE,SUMIFS(TotalGMContribution[March],TotalGMContribution[Status],GMConSpreadTable[[#This Row],[STATUS]],TotalGMContribution[Opps Status],"Fair"),0)+IF(CompanyRiskToggle=TRUE,SUMIFS(TotalGMContribution[March],TotalGMContribution[Status],GMConSpreadTable[[#This Row],[STATUS]],TotalGMContribution[Opps Status],"Risk"),0) -> 0 | L55: =IF(CompanyGoodToggle=TRUE,SUMIFS(TotalGMContribution[April],TotalGMContribution[Status],GMConSpreadTable[[#This Row],[STATUS]],TotalGMContribution[Opps Status],"Good"),0)+IF(CompanyFairToggle=TRUE,SUMIFS(TotalGMContribution[April],TotalGMContribution[Status],GMConSpreadTable[[#This Row],[STATUS]],TotalGMContribution[Opps Status],"Fair"),0)+IF(CompanyRiskToggle=TRUE,SUMIFS(TotalGMContribution[April],TotalGMContribution[Status],GMConSpreadTable[[#This Row],[STATUS]],TotalGMContribution[Opps Status],"Risk"),0) -> 0 | M55: =IF(CompanyGoodToggle=TRUE,SUMIFS(TotalGMContribution[May],TotalGMContribution[Status],GMConSpreadTable[[#This Row],[STATUS]],TotalGMContribution[Opps Status],"Good"),0)+IF(CompanyFairToggle=TRUE,SUMIFS(TotalGMContribution[May],TotalGMContribution[Status],GMConSpreadTable[[#This Row],[STATUS]],TotalGMContribution[Opps Status],"Fair"),0)+IF(CompanyRiskToggle=TRUE,SUMIFS(TotalGMContribution[May],TotalGMContribution[Status],GMConSpreadTable[[#This Row],[STATUS]],TotalGMContribution[Opps Status],"Risk"),0) -> 0 | N55: =IF(CompanyGoodToggle=TRUE,SUMIFS(TotalGMContribution[June],TotalGMContribution[Status],GMConSpreadTable[[#This Row],[STATUS]],TotalGMContribution[Opps Status],"Good"),0)+IF(CompanyFairToggle=TRUE,SUMIFS(TotalGMContribution[June],TotalGMContribution[Status],GMConSpreadTable[[#This Row],[STATUS]],TotalGMContribution[Opps Status],"Fair"),0)+IF(CompanyRiskToggle=TRUE,SUMIFS(TotalGMContribution[June],TotalGMContribution[Status],GMConSpreadTable[[#This Row],[STATUS]],TotalGMContribution[Opps Status],"Risk"),0) -> 0 | P55: S | Q55: =IF(CompanyGoodToggle=TRUE,SUMIFS(OppSpreadData[July], OppSpreadData[Phase],RevSpreadTable[[#This Row],[STATUS]],OppSpreadData[OppsStatus],"Good"),0)+ IF(CompanyFairToggle=TRUE,SUMIFS(OppSpreadData[July],OppSpreadData[Phase],RevSpreadTable[[#This Row],[STATUS]],OppSpreadData[OppsStatus],"Fair"),0)+ IF(CompanyRiskToggle=TRUE,SUMIFS(OppSpreadData[July],OppSpreadData[Phase],RevSpreadTable[[#This Row],[STATUS]],OppSpreadData[OppsStatus],"Risk"),0) -> 0 | R55: =IF(CompanyGoodToggle=TRUE,SUMIFS(OppSpreadData[August], OppSpreadData[Phase],RevSpreadTable[[#This Row],[STATUS]],OppSpreadData[OppsStatus],"Good"),0)+ IF(CompanyFairToggle=TRUE,SUMIFS(OppSpreadData[August],OppSpreadData[Phase],RevSpreadTable[[#This Row],[STATUS]],OppSpreadData[OppsStatus],"Fair"),0)+ IF(CompanyRiskToggle=TRUE,SUMIFS(OppSpreadData[August],OppSpreadData[Phase],RevSpreadTable[[#This Row],[STATUS]],OppSpreadData[OppsStatus],"Risk"),0) -> 0 | S55: =IF(CompanyGoodToggle=TRUE,SUMIFS(OppSpreadData[September], OppSpreadData[Phase],RevSpreadTable[[#This Row],[STATUS]],OppSpreadData[OppsStatus],"Good"),0)+ IF(CompanyFairToggle=TRUE,SUMIFS(OppSpreadData[September],OppSpreadData[Phase],RevSpreadTable[[#This Row],[STATUS]],OppSpreadData[OppsStatus],"Fair"),0)+ IF(CompanyRiskToggle=TRUE,SUMIFS(OppSpreadData[September],OppSpreadData[Phase],RevSpreadTable[[#This Row],[STATUS]],OppSpreadData[OppsStatus],"Risk"),0) -> 0 | T55: =IF(CompanyGoodToggle=TRUE,SUMIFS(OppSpreadData[October], OppSpreadData[Phase],RevSpreadTable[[#This Row],[STATUS]],OppSpreadData[OppsStatus],"Good"),0)+ IF(CompanyFairToggle=TRUE,SUMIFS(OppSpreadData[October],OppSpreadData[Phase],RevSpreadTable[[#This Row],[STATUS]],OppSpreadData[OppsStatus],"Fair"),0)+ IF(CompanyRiskToggle=TRUE,SUMIFS(OppSpreadData[October],OppSpreadData[Phase],RevSpreadTable[[#This Row],[STATUS]],OppSpreadData[OppsStatus],"Risk"),0) -> 0 | U55: =IF(CompanyGoodToggle=TRUE,SUMIFS(OppSpreadData[November], OppSpreadData[Phase],RevSpreadTable[[#This Row],[STATUS]],OppSpreadData[OppsStatus],"Good"),0)+ IF(CompanyFairToggle=TRUE,SUMIFS(OppSpreadData[November],OppSpreadData[Phase],RevSpreadTable[[#This Row],[STATUS]],OppSpreadData[OppsStatus],"Fair"),0)+ IF(CompanyRiskToggle=TRUE,SUMIFS(OppSpreadData[November],OppSpreadData[Phase],RevSpreadTable[[#This Row],[STATUS]],OppSpreadData[OppsStatus],"Risk"),0) -> 0 | V55: =IF(CompanyGoodToggle=TRUE,SUMIFS(OppSpreadData[December], OppSpreadData[Phase],RevSpreadTable[[#This Row],[STATUS]],OppSpreadData[OppsStatus],"Good"),0)+ IF(CompanyFairToggle=TRUE,SUMIFS(OppSpreadData[December],OppSpreadData[Phase],RevSpreadTable[[#This Row],[STATUS]],OppSpreadData[OppsStatus],"Fair"),0)+ IF(CompanyRiskToggle=TRUE,SUMIFS(OppSpreadData[December],OppSpreadData[Phase],RevSpreadTable[[#This Row],[STATUS]],OppSpreadData[OppsStatus],"Risk"),0) -> 0 | W55: =IF(CompanyGoodToggle=TRUE,SUMIFS(OppSpreadData[January], OppSpreadData[Phase],RevSpreadTable[[#This Row],[STATUS]],OppSpreadData[OppsStatus],"Good"),0)+ IF(CompanyFairToggle=TRUE,SUMIFS(OppSpreadData[January],OppSpreadData[Phase],RevSpreadTable[[#This Row],[STATUS]],OppSpreadData[OppsStatus],"Fair"),0)+ IF(CompanyRiskToggle=TRUE,SUMIFS(OppSpreadData[January],OppSpreadData[Phase],RevSpreadTable[[#This Row],[STATUS]],OppSpreadData[OppsStatus],"Risk"),0) -> 0 | X55: =IF(CompanyGoodToggle=TRUE,SUMIFS(OppSpreadData[February], OppSpreadData[Phase],RevSpreadTable[[#This Row],[STATUS]],OppSpreadData[OppsStatus],"Good"),0)+ IF(CompanyFairToggle=TRUE,SUMIFS(OppSpreadData[February],OppSpreadData[Phase],RevSpreadTable[[#This Row],[STATUS]],OppSpreadData[OppsStatus],"Fair"),0)+ IF(CompanyRiskToggle=TRUE,SUMIFS(OppSpreadData[February],OppSpreadData[Phase],RevSpreadTable[[#This Row],[STATUS]],OppSpreadData[OppsStatus],"Risk"),0) -> 0 | Y55: =IF(CompanyGoodToggle=TRUE,SUMIFS(OppSpreadData[March], OppSpreadData[Phase],RevSpreadTable[[#This Row],[STATUS]],OppSpreadData[OppsStatus],"Good"),0)+ IF(CompanyFairToggle=TRUE,SUMIFS(OppSpreadData[March],OppSpreadData[Phase],RevSpreadTable[[#This Row],[STATUS]],OppSpreadData[OppsStatus],"Fair"),0)+ IF(CompanyRiskToggle=TRUE,SUMIFS(OppSpreadData[March],OppSpreadData[Phase],RevSpreadTable[[#This Row],[STATUS]],OppSpreadData[OppsStatus],"Risk"),0) -> 0 | Z55: =IF(CompanyGoodToggle=TRUE,SUMIFS(OppSpreadData[April], OppSpreadData[Phase],RevSpreadTable[[#This Row],[STATUS]],OppSpreadData[OppsStatus],"Good"),0)+ IF(CompanyFairToggle=TRUE,SUMIFS(OppSpreadData[April],OppSpreadData[Phase],RevSpreadTable[[#This Row],[STATUS]],OppSpreadData[OppsStatus],"Fair"),0)+ IF(CompanyRiskToggle=TRUE,SUMIFS(OppSpreadData[April],OppSpreadData[Phase],RevSpreadTable[[#This Row],[STATUS]],OppSpreadData[OppsStatus],"Risk"),0) -> 0 | AA55: =IF(CompanyGoodToggle=TRUE,SUMIFS(OppSpreadData[May], OppSpreadData[Phase],RevSpreadTable[[#This Row],[STATUS]],OppSpreadData[OppsStatus],"Good"),0)+ IF(CompanyFairToggle=TRUE,SUMIFS(OppSpreadData[May],OppSpreadData[Phase],RevSpreadTable[[#This Row],[STATUS]],OppSpreadData[OppsStatus],"Fair"),0)+ IF(CompanyRiskToggle=TRUE,SUMIFS(OppSpreadData[May],OppSpreadData[Phase],RevSpreadTable[[#This Row],[STATUS]],OppSpreadData[OppsStatus],"Risk"),0) -> 0 | AB55: =IF(CompanyGoodToggle=TRUE,SUMIFS(OppSpreadData[June], OppSpreadData[Phase],RevSpreadTable[[#This Row],[STATUS]],OppSpreadData[OppsStatus],"Good"),0)+ IF(CompanyFairToggle=TRUE,SUMIFS(OppSpreadData[June],OppSpreadData[Phase],RevSpreadTable[[#This Row],[STATUS]],OppSpreadData[OppsStatus],"Fair"),0)+ IF(CompanyRiskToggle=TRUE,SUMIFS(OppSpreadData[June],OppSpreadData[Phase],RevSpreadTable[[#This Row],[STATUS]],OppSpreadData[OppsStatus],"Risk"),0) -> 0
B56: DVF | C56: =IF(CompanyGoodToggle=TRUE,SUMIFS(TotalGMContribution[July],TotalGMContribution[Status],GMConSpreadTable[[#This Row],[STATUS]],TotalGMContribution[Opps Status],"Good"),0)+IF(CompanyFairToggle=TRUE,SUMIFS(TotalGMContribution[July],TotalGMContribution[Status],GMConSpreadTable[[#This Row],[STATUS]],TotalGMContribution[Opps Status],"Fair"),0)+IF(CompanyRiskToggle=TRUE,SUMIFS(TotalGMContribution[July],TotalGMContribution[Status],GMConSpreadTable[[#This Row],[STATUS]],TotalGMContribution[Opps Status],"Risk"),0) -> 0 | D56: =IF(CompanyGoodToggle=TRUE,SUMIFS(TotalGMContribution[August],TotalGMContribution[Status],GMConSpreadTable[[#This Row],[STATUS]],TotalGMContribution[Opps Status],"Good"),0)+IF(CompanyFairToggle=TRUE,SUMIFS(TotalGMContribution[August],TotalGMContribution[Status],GMConSpreadTable[[#This Row],[STATUS]],TotalGMContribution[Opps Status],"Fair"),0)+IF(CompanyRiskToggle=TRUE,SUMIFS(TotalGMContribution[August],TotalGMContribution[Status],GMConSpreadTable[[#This Row],[STATUS]],TotalGMContribution[Opps Status],"Risk"),0) -> 0 | E56: =IF(CompanyGoodToggle=TRUE,SUMIFS(TotalGMContribution[September],TotalGMContribution[Status],GMConSpreadTable[[#This Row],[STATUS]],TotalGMContribution[Opps Status],"Good"),0)+IF(CompanyFairToggle=TRUE,SUMIFS(TotalGMContribution[September],TotalGMContribution[Status],GMConSpreadTable[[#This Row],[STATUS]],TotalGMContribution[Opps Status],"Fair"),0)+IF(CompanyRiskToggle=TRUE,SUMIFS(TotalGMContribution[September],TotalGMContribution[Status],GMConSpreadTable[[#This Row],[STATUS]],TotalGMContribution[Opps Status],"Risk"),0) -> 0 | F56: =IF(CompanyGoodToggle=TRUE,SUMIFS(TotalGMContribution[October],TotalGMContribution[Status],GMConSpreadTable[[#This Row],[STATUS]],TotalGMContribution[Opps Status],"Good"),0)+IF(CompanyFairToggle=TRUE,SUMIFS(TotalGMContribution[October],TotalGMContribution[Status],GMConSpreadTable[[#This Row],[STATUS]],TotalGMContribution[Opps Status],"Fair"),0)+IF(CompanyRiskToggle=TRUE,SUMIFS(TotalGMContribution[October],TotalGMContribution[Status],GMConSpreadTable[[#This Row],[STATUS]],TotalGMContribution[Opps Status],"Risk"),0) -> 0 | G56: =IF(CompanyGoodToggle=TRUE,SUMIFS(TotalGMContribution[November],TotalGMContribution[Status],GMConSpreadTable[[#This Row],[STATUS]],TotalGMContribution[Opps Status],"Good"),0)+IF(CompanyFairToggle=TRUE,SUMIFS(TotalGMContribution[November],TotalGMContribution[Status],GMConSpreadTable[[#This Row],[STATUS]],TotalGMContribution[Opps Status],"Fair"),0)+IF(CompanyRiskToggle=TRUE,SUMIFS(TotalGMContribution[November],TotalGMContribution[Status],GMConSpreadTable[[#This Row],[STATUS]],TotalGMContribution[Opps Status],"Risk"),0) -> 0 | H56: =IF(CompanyGoodToggle=TRUE,SUMIFS(TotalGMContribution[December],TotalGMContribution[Status],GMConSpreadTable[[#This Row],[STATUS]],TotalGMContribution[Opps Status],"Good"),0)+IF(CompanyFairToggle=TRUE,SUMIFS(TotalGMContribution[December],TotalGMContribution[Status],GMConSpreadTable[[#This Row],[STATUS]],TotalGMContribution[Opps Status],"Fair"),0)+IF(CompanyRiskToggle=TRUE,SUMIFS(TotalGMContribution[December],TotalGMContribution[Status],GMConSpreadTable[[#This Row],[STATUS]],TotalGMContribution[Opps Status],"Risk"),0) -> 0 | I56: =IF(CompanyGoodToggle=TRUE,SUMIFS(TotalGMContribution[January],TotalGMContribution[Status],GMConSpreadTable[[#This Row],[STATUS]],TotalGMContribution[Opps Status],"Good"),0)+IF(CompanyFairToggle=TRUE,SUMIFS(TotalGMContribution[January],TotalGMContribution[Status],GMConSpreadTable[[#This Row],[STATUS]],TotalGMContribution[Opps Status],"Fair"),0)+IF(CompanyRiskToggle=TRUE,SUMIFS(TotalGMContribution[January],TotalGMContribution[Status],GMConSpreadTable[[#This Row],[STATUS]],TotalGMContribution[Opps Status],"Risk"),0) -> 0 | J56: =IF(CompanyGoodToggle=TRUE,SUMIFS(TotalGMContribution[February],TotalGMContribution[Status],GMConSpreadTable[[#This Row],[STATUS]],TotalGMContribution[Opps Status],"Good"),0)+IF(CompanyFairToggle=TRUE,SUMIFS(TotalGMContribution[February],TotalGMContribution[Status],GMConSpreadTable[[#This Row],[STATUS]],TotalGMContribution[Opps Status],"Fair"),0)+IF(CompanyRiskToggle=TRUE,SUMIFS(TotalGMContribution[February],TotalGMContribution[Status],GMConSpreadTable[[#This Row],[STATUS]],TotalGMContribution[Opps Status],"Risk"),0) -> 9000.4 | K56: =IF(CompanyGoodToggle=TRUE,SUMIFS(TotalGMContribution[March],TotalGMContribution[Status],GMConSpreadTable[[#This Row],[STATUS]],TotalGMContribution[Opps Status],"Good"),0)+IF(CompanyFairToggle=TRUE,SUMIFS(TotalGMContribution[March],TotalGMContribution[Status],GMConSpreadTable[[#This Row],[STATUS]],TotalGMContribution[Opps Status],"Fair"),0)+IF(CompanyRiskToggle=TRUE,SUMIFS(TotalGMContribution[March],TotalGMContribution[Status],GMConSpreadTable[[#This Row],[STATUS]],TotalGMContribution[Opps Status],"Risk"),0) -> 45375.12 | L56: =IF(CompanyGoodToggle=TRUE,SUMIFS(TotalGMContribution[April],TotalGMContribution[Status],GMConSpreadTable[[#This Row],[STATUS]],TotalGMContribution[Opps Status],"Good"),0)+IF(CompanyFairToggle=TRUE,SUMIFS(TotalGMContribution[April],TotalGMContribution[Status],GMConSpreadTable[[#This Row],[STATUS]],TotalGMContribution[Opps Status],"Fair"),0)+IF(CompanyRiskToggle=TRUE,SUMIFS(TotalGMContribution[April],TotalGMContribution[Status],GMConSpreadTable[[#This Row],[STATUS]],TotalGMContribution[Opps Status],"Risk"),0) -> 990836.72 | M56: =IF(CompanyGoodToggle=TRUE,SUMIFS(TotalGMContribution[May],TotalGMContribution[Status],GMConSpreadTable[[#This Row],[STATUS]],TotalGMContribution[Opps Status],"Good"),0)+IF(CompanyFairToggle=TRUE,SUMIFS(TotalGMContribution[May],TotalGMContribution[Status],GMConSpreadTable[[#This Row],[STATUS]],TotalGMContribution[Opps Status],"Fair"),0)+IF(CompanyRiskToggle=TRUE,SUMIFS(TotalGMContribution[May],TotalGMContribution[Status],GMConSpreadTable[[#This Row],[STATUS]],TotalGMContribution[Opps Status],"Risk"),0) -> 311614 | N56: =IF(CompanyGoodToggle=TRUE,SUMIFS(TotalGMContribution[June],TotalGMContribution[Status],GMConSpreadTable[[#This Row],[STATUS]],TotalGMContribution[Opps Status],"Good"),0)+IF(CompanyFairToggle=TRUE,SUMIFS(TotalGMContribution[June],TotalGMContribution[Status],GMConSpreadTable[[#This Row],[STATUS]],TotalGMContribution[Opps Status],"Fair"),0)+IF(CompanyRiskToggle=TRUE,SUMIFS(TotalGMContribution[June],TotalGMContribution[Status],GMConSpreadTable[[#This Row],[STATUS]],TotalGMContribution[Opps Status],"Risk"),0) -> 850153.6 | P56: DVF | Q56: =IF(CompanyGoodToggle=TRUE,SUMIFS(OppSpreadData[July], OppSpreadData[Phase],RevSpreadTable[[#This Row],[STATUS]],OppSpreadData[OppsStatus],"Good"),0)+ IF(CompanyFairToggle=TRUE,SUMIFS(OppSpreadData[July],OppSpreadData[Phase],RevSpreadTable[[#This Row],[STATUS]],OppSpreadData[OppsStatus],"Fair"),0)+ IF(CompanyRiskToggle=TRUE,SUMIFS(OppSpreadData[July],OppSpreadData[Phase],RevSpreadTable[[#This Row],[STATUS]],OppSpreadData[OppsStatus],"Risk"),0) -> 0 | R56: =IF(CompanyGoodToggle=TRUE,SUMIFS(OppSpreadData[August], OppSpreadData[Phase],RevSpreadTable[[#This Row],[STATUS]],OppSpreadData[OppsStatus],"Good"),0)+ IF(CompanyFairToggle=TRUE,SUMIFS(OppSpreadData[August],OppSpreadData[Phase],RevSpreadTable[[#This Row],[STATUS]],OppSpreadData[OppsStatus],"Fair"),0)+ IF(CompanyRiskToggle=TRUE,SUMIFS(OppSpreadData[August],OppSpreadData[Phase],RevSpreadTable[[#This Row],[STATUS]],OppSpreadData[OppsStatus],"Risk"),0) -> 0 | S56: =IF(CompanyGoodToggle=TRUE,SUMIFS(OppSpreadData[September], OppSpreadData[Phase],RevSpreadTable[[#This Row],[STATUS]],OppSpreadData[OppsStatus],"Good"),0)+ IF(CompanyFairToggle=TRUE,SUMIFS(OppSpreadData[September],OppSpreadData[Phase],RevSpreadTable[[#This Row],[STATUS]],OppSpreadData[OppsStatus],"Fair"),0)+ IF(CompanyRiskToggle=TRUE,SUMIFS(OppSpreadData[September],OppSpreadData[Phase],RevSpreadTable[[#This Row],[STATUS]],OppSpreadData[OppsStatus],"Risk"),0) -> 0 | T56: =IF(CompanyGoodToggle=TRUE,SUMIFS(OppSpreadData[October], OppSpreadData[Phase],RevSpreadTable[[#This Row],[STATUS]],OppSpreadData[OppsStatus],"Good"),0)+ IF(CompanyFairToggle=TRUE,SUMIFS(OppSpreadData[October],OppSpreadData[Phase],RevSpreadTable[[#This Row],[STATUS]],OppSpreadData[OppsStatus],"Fair"),0)+ IF(CompanyRiskToggle=TRUE,SUMIFS(OppSpreadData[October],OppSpreadData[Phase],RevSpreadTable[[#This Row],[STATUS]],OppSpreadData[OppsStatus],"Risk"),0) -> 0 | U56: =IF(CompanyGoodToggle=TRUE,SUMIFS(OppSpreadData[November], OppSpreadData[Phase],RevSpreadTable[[#This Row],[STATUS]],OppSpreadData[OppsStatus],"Good"),0)+ IF(CompanyFairToggle=TRUE,SUMIFS(OppSpreadData[November],OppSpreadData[Phase],RevSpreadTable[[#This Row],[STATUS]],OppSpreadData[OppsStatus],"Fair"),0)+ IF(CompanyRiskToggle=TRUE,SUMIFS(OppSpreadData[November],OppSpreadData[Phase],RevSpreadTable[[#This Row],[STATUS]],OppSpreadData[OppsStatus],"Risk"),0) -> 0 | V56: =IF(CompanyGoodToggle=TRUE,SUMIFS(OppSpreadData[December], OppSpreadData[Phase],RevSpreadTable[[#This Row],[STATUS]],OppSpreadData[OppsStatus],"Good"),0)+ IF(CompanyFairToggle=TRUE,SUMIFS(OppSpreadData[December],OppSpreadData[Phase],RevSpreadTable[[#This Row],[STATUS]],OppSpreadData[OppsStatus],"Fair"),0)+ IF(CompanyRiskToggle=TRUE,SUMIFS(OppSpreadData[December],OppSpreadData[Phase],RevSpreadTable[[#This Row],[STATUS]],OppSpreadData[OppsStatus],"Risk"),0) -> 0 | W56: =IF(CompanyGoodToggle=TRUE,SUMIFS(OppSpreadData[January], OppSpreadData[Phase],RevSpreadTable[[#This Row],[STATUS]],OppSpreadData[OppsStatus],"Good"),0)+ IF(CompanyFairToggle=TRUE,SUMIFS(OppSpreadData[January],OppSpreadData[Phase],RevSpreadTable[[#This Row],[STATUS]],OppSpreadData[OppsStatus],"Fair"),0)+ IF(CompanyRiskToggle=TRUE,SUMIFS(OppSpreadData[January],OppSpreadData[Phase],RevSpreadTable[[#This Row],[STATUS]],OppSpreadData[OppsStatus],"Risk"),0) -> 0 | X56: =IF(CompanyGoodToggle=TRUE,SUMIFS(OppSpreadData[February], OppSpreadData[Phase],RevSpreadTable[[#This Row],[STATUS]],OppSpreadData[OppsStatus],"Good"),0)+ IF(CompanyFairToggle=TRUE,SUMIFS(OppSpreadData[February],OppSpreadData[Phase],RevSpreadTable[[#This Row],[STATUS]],OppSpreadData[OppsStatus],"Fair"),0)+ IF(CompanyRiskToggle=TRUE,SUMIFS(OppSpreadData[February],OppSpreadData[Phase],RevSpreadTable[[#This Row],[STATUS]],OppSpreadData[OppsStatus],"Risk"),0) -> 20044.4 | Y56: =IF(CompanyGoodToggle=TRUE,SUMIFS(OppSpreadData[March], OppSpreadData[Phase],RevSpreadTable[[#This Row],[STATUS]],OppSpreadData[OppsStatus],"Good"),0)+ IF(CompanyFairToggle=TRUE,SUMIFS(OppSpreadData[March],OppSpreadData[Phase],RevSpreadTable[[#This Row],[STATUS]],OppSpreadData[OppsStatus],"Fair"),0)+ IF(CompanyRiskToggle=TRUE,SUMIFS(OppSpreadData[March],OppSpreadData[Phase],RevSpreadTable[[#This Row],[STATUS]],OppSpreadData[OppsStatus],"Risk"),0) -> 108215.52 | Z56: =IF(CompanyGoodToggle=TRUE,SUMIFS(OppSpreadData[April], OppSpreadData[Phase],RevSpreadTable[[#This Row],[STATUS]],OppSpreadData[OppsStatus],"Good"),0)+ IF(CompanyFairToggle=TRUE,SUMIFS(OppSpreadData[April],OppSpreadData[Phase],RevSpreadTable[[#This Row],[STATUS]],OppSpreadData[OppsStatus],"Fair"),0)+ IF(CompanyRiskToggle=TRUE,SUMIFS(OppSpreadData[April],OppSpreadData[Phase],RevSpreadTable[[#This Row],[STATUS]],OppSpreadData[OppsStatus],"Risk"),0) -> 1536298.7 | AA56: =IF(CompanyGoodToggle=TRUE,SUMIFS(OppSpreadData[May], OppSpreadData[Phase],RevSpreadTable[[#This Row],[STATUS]],OppSpreadData[OppsStatus],"Good"),0)+ IF(CompanyFairToggle=TRUE,SUMIFS(OppSpreadData[May],OppSpreadData[Phase],RevSpreadTable[[#This Row],[STATUS]],OppSpreadData[OppsStatus],"Fair"),0)+ IF(CompanyRiskToggle=TRUE,SUMIFS(OppSpreadData[May],OppSpreadData[Phase],RevSpreadTable[[#This Row],[STATUS]],OppSpreadData[OppsStatus],"Risk"),0) -> 788874 | AB56: =IF(CompanyGoodToggle=TRUE,SUMIFS(OppSpreadData[June], OppSpreadData[Phase],RevSpreadTable[[#This Row],[STATUS]],OppSpreadData[OppsStatus],"Good"),0)+ IF(CompanyFairToggle=TRUE,SUMIFS(OppSpreadData[June],OppSpreadData[Phase],RevSpreadTable[[#This Row],[STATUS]],OppSpreadData[OppsStatus],"Fair"),0)+ IF(CompanyRiskToggle=TRUE,SUMIFS(OppSpreadData[June],OppSpreadData[Phase],RevSpreadTable[[#This Row],[STATUS]],OppSpreadData[OppsStatus],"Risk"),0) -> 2044317.6
B57: DF | C57: =IF(CompanyGoodToggle=TRUE,SUMIFS(TotalGMContribution[July],TotalGMContribution[Status],GMConSpreadTable[[#This Row],[STATUS]],TotalGMContribution[Opps Status],"Good"),0)+IF(CompanyFairToggle=TRUE,SUMIFS(TotalGMContribution[July],TotalGMContribution[Status],GMConSpreadTable[[#This Row],[STATUS]],TotalGMContribution[Opps Status],"Fair"),0)+IF(CompanyRiskToggle=TRUE,SUMIFS(TotalGMContribution[July],TotalGMContribution[Status],GMConSpreadTable[[#This Row],[STATUS]],TotalGMContribution[Opps Status],"Risk"),0) -> 0 | D57: =IF(CompanyGoodToggle=TRUE,SUMIFS(TotalGMContribution[August],TotalGMContribution[Status],GMConSpreadTable[[#This Row],[STATUS]],TotalGMContribution[Opps Status],"Good"),0)+IF(CompanyFairToggle=TRUE,SUMIFS(TotalGMContribution[August],TotalGMContribution[Status],GMConSpreadTable[[#This Row],[STATUS]],TotalGMContribution[Opps Status],"Fair"),0)+IF(CompanyRiskToggle=TRUE,SUMIFS(TotalGMContribution[August],TotalGMContribution[Status],GMConSpreadTable[[#This Row],[STATUS]],TotalGMContribution[Opps Status],"Risk"),0) -> 0 | E57: =IF(CompanyGoodToggle=TRUE,SUMIFS(TotalGMContribution[September],TotalGMContribution[Status],GMConSpreadTable[[#This Row],[STATUS]],TotalGMContribution[Opps Status],"Good"),0)+IF(CompanyFairToggle=TRUE,SUMIFS(TotalGMContribution[September],TotalGMContribution[Status],GMConSpreadTable[[#This Row],[STATUS]],TotalGMContribution[Opps Status],"Fair"),0)+IF(CompanyRiskToggle=TRUE,SUMIFS(TotalGMContribution[September],TotalGMContribution[Status],GMConSpreadTable[[#This Row],[STATUS]],TotalGMContribution[Opps Status],"Risk"),0) -> 0 | F57: =IF(CompanyGoodToggle=TRUE,SUMIFS(TotalGMContribution[October],TotalGMContribution[Status],GMConSpreadTable[[#This Row],[STATUS]],TotalGMContribution[Opps Status],"Good"),0)+IF(CompanyFairToggle=TRUE,SUMIFS(TotalGMContribution[October],TotalGMContribution[Status],GMConSpreadTable[[#This Row],[STATUS]],TotalGMContribution[Opps Status],"Fair"),0)+IF(CompanyRiskToggle=TRUE,SUMIFS(TotalGMContribution[October],TotalGMContribution[Status],GMConSpreadTable[[#This Row],[STATUS]],TotalGMContribution[Opps Status],"Risk"),0) -> 0 | G57: =IF(CompanyGoodToggle=TRUE,SUMIFS(TotalGMContribution[November],TotalGMContribution[Status],GMConSpreadTable[[#This Row],[STATUS]],TotalGMContribution[Opps Status],"Good"),0)+IF(CompanyFairToggle=TRUE,SUMIFS(TotalGMContribution[November],TotalGMContribution[Status],GMConSpreadTable[[#This Row],[STATUS]],TotalGMContribution[Opps Status],"Fair"),0)+IF(CompanyRiskToggle=TRUE,SUMIFS(TotalGMContribution[November],TotalGMContribution[Status],GMConSpreadTable[[#This Row],[STATUS]],TotalGMContribution[Opps Status],"Risk"),0) -> 0 | H57: =IF(CompanyGoodToggle=TRUE,SUMIFS(TotalGMContribution[December],TotalGMContribution[Status],GMConSpreadTable[[#This Row],[STATUS]],TotalGMContribution[Opps Status],"Good"),0)+IF(CompanyFairToggle=TRUE,SUMIFS(TotalGMContribution[December],TotalGMContribution[Status],GMConSpreadTable[[#This Row],[STATUS]],TotalGMContribution[Opps Status],"Fair"),0)+IF(CompanyRiskToggle=TRUE,SUMIFS(TotalGMContribution[December],TotalGMContribution[Status],GMConSpreadTable[[#This Row],[STATUS]],TotalGMContribution[Opps Status],"Risk"),0) -> 0 | I57: =IF(CompanyGoodToggle=TRUE,SUMIFS(TotalGMContribution[January],TotalGMContribution[Status],GMConSpreadTable[[#This Row],[STATUS]],TotalGMContribution[Opps Status],"Good"),0)+IF(CompanyFairToggle=TRUE,SUMIFS(TotalGMContribution[January],TotalGMContribution[Status],GMConSpreadTable[[#This Row],[STATUS]],TotalGMContribution[Opps Status],"Fair"),0)+IF(CompanyRiskToggle=TRUE,SUMIFS(TotalGMContribution[January],TotalGMContribution[Status],GMConSpreadTable[[#This Row],[STATUS]],TotalGMContribution[Opps Status],"Risk"),0) -> 0 | J57: =IF(CompanyGoodToggle=TRUE,SUMIFS(TotalGMContribution[February],TotalGMContribution[Status],GMConSpreadTable[[#This Row],[STATUS]],TotalGMContribution[Opps Status],"Good"),0)+IF(CompanyFairToggle=TRUE,SUMIFS(TotalGMContribution[February],TotalGMContribution[Status],GMConSpreadTable[[#This Row],[STATUS]],TotalGMContribution[Opps Status],"Fair"),0)+IF(CompanyRiskToggle=TRUE,SUMIFS(TotalGMContribution[February],TotalGMContribution[Status],GMConSpreadTable[[#This Row],[STATUS]],TotalGMContribution[Opps Status],"Risk"),0) -> 0 | K57: =IF(CompanyGoodToggle=TRUE,SUMIFS(TotalGMContribution[March],TotalGMContribution[Status],GMConSpreadTable[[#This Row],[STATUS]],TotalGMContribution[Opps Status],"Good"),0)+IF(CompanyFairToggle=TRUE,SUMIFS(TotalGMContribution[March],TotalGMContribution[Status],GMConSpreadTable[[#This Row],[STATUS]],TotalGMContribution[Opps Status],"Fair"),0)+IF(CompanyRiskToggle=TRUE,SUMIFS(TotalGMContribution[March],TotalGMContribution[Status],GMConSpreadTable[[#This Row],[STATUS]],TotalGMContribution[Opps Status],"Risk"),0) -> 0 | L57: =IF(CompanyGoodToggle=TRUE,SUMIFS(TotalGMContribution[April],TotalGMContribution[Status],GMConSpreadTable[[#This Row],[STATUS]],TotalGMContribution[Opps Status],"Good"),0)+IF(CompanyFairToggle=TRUE,SUMIFS(TotalGMContribution[April],TotalGMContribution[Status],GMConSpreadTable[[#This Row],[STATUS]],TotalGMContribution[Opps Status],"Fair"),0)+IF(CompanyRiskToggle=TRUE,SUMIFS(TotalGMContribution[April],TotalGMContribution[Status],GMConSpreadTable[[#This Row],[STATUS]],TotalGMContribution[Opps Status],"Risk"),0) -> 0 | M57: =IF(CompanyGoodToggle=TRUE,SUMIFS(TotalGMContribution[May],TotalGMContribution[Status],GMConSpreadTable[[#This Row],[STATUS]],TotalGMContribution[Opps Status],"Good"),0)+IF(CompanyFairToggle=TRUE,SUMIFS(TotalGMContribution[May],TotalGMContribution[Status],GMConSpreadTable[[#This Row],[STATUS]],TotalGMContribution[Opps Status],"Fair"),0)+IF(CompanyRiskToggle=TRUE,SUMIFS(TotalGMContribution[May],TotalGMContribution[Status],GMConSpreadTable[[#This Row],[STATUS]],TotalGMContribution[Opps Status],"Risk"),0) -> 0 | N57: =IF(CompanyGoodToggle=TRUE,SUMIFS(TotalGMContribution[June],TotalGMContribution[Status],GMConSpreadTable[[#This Row],[STATUS]],TotalGMContribution[Opps Status],"Good"),0)+IF(CompanyFairToggle=TRUE,SUMIFS(TotalGMContribution[June],TotalGMContribution[Status],GMConSpreadTable[[#This Row],[STATUS]],TotalGMContribution[Opps Status],"Fair"),0)+IF(CompanyRiskToggle=TRUE,SUMIFS(TotalGMContribution[June],TotalGMContribution[Status],GMConSpreadTable[[#This Row],[STATUS]],TotalGMContribution[Opps Status],"Risk"),0) -> 0 | P57: DF | Q57: =IF(CompanyGoodToggle=TRUE,SUMIFS(OppSpreadData[July], OppSpreadData[Phase],RevSpreadTable[[#This Row],[STATUS]],OppSpreadData[OppsStatus],"Good"),0)+ IF(CompanyFairToggle=TRUE,SUMIFS(OppSpreadData[July],OppSpreadData[Phase],RevSpreadTable[[#This Row],[STATUS]],OppSpreadData[OppsStatus],"Fair"),0)+ IF(CompanyRiskToggle=TRUE,SUMIFS(OppSpreadData[July],OppSpreadData[Phase],RevSpreadTable[[#This Row],[STATUS]],OppSpreadData[OppsStatus],"Risk"),0) -> 0 | R57: =IF(CompanyGoodToggle=TRUE,SUMIFS(OppSpreadData[August], OppSpreadData[Phase],RevSpreadTable[[#This Row],[STATUS]],OppSpreadData[OppsStatus],"Good"),0)+ IF(CompanyFairToggle=TRUE,SUMIFS(OppSpreadData[August],OppSpreadData[Phase],RevSpreadTable[[#This Row],[STATUS]],OppSpreadData[OppsStatus],"Fair"),0)+ IF(CompanyRiskToggle=TRUE,SUMIFS(OppSpreadData[August],OppSpreadData[Phase],RevSpreadTable[[#This Row],[STATUS]],OppSpreadData[OppsStatus],"Risk"),0) -> 0 | S57: =IF(CompanyGoodToggle=TRUE,SUMIFS(OppSpreadData[September], OppSpreadData[Phase],RevSpreadTable[[#This Row],[STATUS]],OppSpreadData[OppsStatus],"Good"),0)+ IF(CompanyFairToggle=TRUE,SUMIFS(OppSpreadData[September],OppSpreadData[Phase],RevSpreadTable[[#This Row],[STATUS]],OppSpreadData[OppsStatus],"Fair"),0)+ IF(CompanyRiskToggle=TRUE,SUMIFS(OppSpreadData[September],OppSpreadData[Phase],RevSpreadTable[[#This Row],[STATUS]],OppSpreadData[OppsStatus],"Risk"),0) -> 0 | T57: =IF(CompanyGoodToggle=TRUE,SUMIFS(OppSpreadData[October], OppSpreadData[Phase],RevSpreadTable[[#This Row],[STATUS]],OppSpreadData[OppsStatus],"Good"),0)+ IF(CompanyFairToggle=TRUE,SUMIFS(OppSpreadData[October],OppSpreadData[Phase],RevSpreadTable[[#This Row],[STATUS]],OppSpreadData[OppsStatus],"Fair"),0)+ IF(CompanyRiskToggle=TRUE,SUMIFS(OppSpreadData[October],OppSpreadData[Phase],RevSpreadTable[[#This Row],[STATUS]],OppSpreadData[OppsStatus],"Risk"),0) -> 0 | U57: =IF(CompanyGoodToggle=TRUE,SUMIFS(OppSpreadData[November], OppSpreadData[Phase],RevSpreadTable[[#This Row],[STATUS]],OppSpreadData[OppsStatus],"Good"),0)+ IF(CompanyFairToggle=TRUE,SUMIFS(OppSpreadData[November],OppSpreadData[Phase],RevSpreadTable[[#This Row],[STATUS]],OppSpreadData[OppsStatus],"Fair"),0)+ IF(CompanyRiskToggle=TRUE,SUMIFS(OppSpreadData[November],OppSpreadData[Phase],RevSpreadTable[[#This Row],[STATUS]],OppSpreadData[OppsStatus],"Risk"),0) -> 0 | V57: =IF(CompanyGoodToggle=TRUE,SUMIFS(OppSpreadData[December], OppSpreadData[Phase],RevSpreadTable[[#This Row],[STATUS]],OppSpreadData[OppsStatus],"Good"),0)+ IF(CompanyFairToggle=TRUE,SUMIFS(OppSpreadData[December],OppSpreadData[Phase],RevSpreadTable[[#This Row],[STATUS]],OppSpreadData[OppsStatus],"Fair"),0)+ IF(CompanyRiskToggle=TRUE,SUMIFS(OppSpreadData[December],OppSpreadData[Phase],RevSpreadTable[[#This Row],[STATUS]],OppSpreadData[OppsStatus],"Risk"),0) -> 0 | W57: =IF(CompanyGoodToggle=TRUE,SUMIFS(OppSpreadData[January], OppSpreadData[Phase],RevSpreadTable[[#This Row],[STATUS]],OppSpreadData[OppsStatus],"Good"),0)+ IF(CompanyFairToggle=TRUE,SUMIFS(OppSpreadData[January],OppSpreadData[Phase],RevSpreadTable[[#This Row],[STATUS]],OppSpreadData[OppsStatus],"Fair"),0)+ IF(CompanyRiskToggle=TRUE,SUMIFS(OppSpreadData[January],OppSpreadData[Phase],RevSpreadTable[[#This Row],[STATUS]],OppSpreadData[OppsStatus],"Risk"),0) -> 0 | X57: =IF(CompanyGoodToggle=TRUE,SUMIFS(OppSpreadData[February], OppSpreadData[Phase],RevSpreadTable[[#This Row],[STATUS]],OppSpreadData[OppsStatus],"Good"),0)+ IF(CompanyFairToggle=TRUE,SUMIFS(OppSpreadData[February],OppSpreadData[Phase],RevSpreadTable[[#This Row],[STATUS]],OppSpreadData[OppsStatus],"Fair"),0)+ IF(CompanyRiskToggle=TRUE,SUMIFS(OppSpreadData[February],OppSpreadData[Phase],RevSpreadTable[[#This Row],[STATUS]],OppSpreadData[OppsStatus],"Risk"),0) -> 0 | Y57: =IF(CompanyGoodToggle=TRUE,SUMIFS(OppSpreadData[March], OppSpreadData[Phase],RevSpreadTable[[#This Row],[STATUS]],OppSpreadData[OppsStatus],"Good"),0)+ IF(CompanyFairToggle=TRUE,SUMIFS(OppSpreadData[March],OppSpreadData[Phase],RevSpreadTable[[#This Row],[STATUS]],OppSpreadData[OppsStatus],"Fair"),0)+ IF(CompanyRiskToggle=TRUE,SUMIFS(OppSpreadData[March],OppSpreadData[Phase],RevSpreadTable[[#This Row],[STATUS]],OppSpreadData[OppsStatus],"Risk"),0) -> 0 | Z57: =IF(CompanyGoodToggle=TRUE,SUMIFS(OppSpreadData[April], OppSpreadData[Phase],RevSpreadTable[[#This Row],[STATUS]],OppSpreadData[OppsStatus],"Good"),0)+ IF(CompanyFairToggle=TRUE,SUMIFS(OppSpreadData[April],OppSpreadData[Phase],RevSpreadTable[[#This Row],[STATUS]],OppSpreadData[OppsStatus],"Fair"),0)+ IF(CompanyRiskToggle=TRUE,SUMIFS(OppSpreadData[April],OppSpreadData[Phase],RevSpreadTable[[#This Row],[STATUS]],OppSpreadData[OppsStatus],"Risk"),0) -> 0 | AA57: =IF(CompanyGoodToggle=TRUE,SUMIFS(OppSpreadData[May], OppSpreadData[Phase],RevSpreadTable[[#This Row],[STATUS]],OppSpreadData[OppsStatus],"Good"),0)+ IF(CompanyFairToggle=TRUE,SUMIFS(OppSpreadData[May],OppSpreadData[Phase],RevSpreadTable[[#This Row],[STATUS]],OppSpreadData[OppsStatus],"Fair"),0)+ IF(CompanyRiskToggle=TRUE,SUMIFS(OppSpreadData[May],OppSpreadData[Phase],RevSpreadTable[[#This Row],[STATUS]],OppSpreadData[OppsStatus],"Risk"),0) -> 0 | AB57: =IF(CompanyGoodToggle=TRUE,SUMIFS(OppSpreadData[June], OppSpreadData[Phase],RevSpreadTable[[#This Row],[STATUS]],OppSpreadData[OppsStatus],"Good"),0)+ IF(CompanyFairToggle=TRUE,SUMIFS(OppSpreadData[June],OppSpreadData[Phase],RevSpreadTable[[#This Row],[STATUS]],OppSpreadData[OppsStatus],"Fair"),0)+ IF(CompanyRiskToggle=TRUE,SUMIFS(OppSpreadData[June],OppSpreadData[Phase],RevSpreadTable[[#This Row],[STATUS]],OppSpreadData[OppsStatus],"Risk"),0) -> 0
B58: Q | C58: =IF(CompanyGoodToggle=TRUE,SUMIFS(TotalGMContribution[July],TotalGMContribution[Status],GMConSpreadTable[[#This Row],[STATUS]],TotalGMContribution[Opps Status],"Good"),0)+IF(CompanyFairToggle=TRUE,SUMIFS(TotalGMContribution[July],TotalGMContribution[Status],GMConSpreadTable[[#This Row],[STATUS]],TotalGMContribution[Opps Status],"Fair"),0)+IF(CompanyRiskToggle=TRUE,SUMIFS(TotalGMContribution[July],TotalGMContribution[Status],GMConSpreadTable[[#This Row],[STATUS]],TotalGMContribution[Opps Status],"Risk"),0) -> 0 | D58: =IF(CompanyGoodToggle=TRUE,SUMIFS(TotalGMContribution[August],TotalGMContribution[Status],GMConSpreadTable[[#This Row],[STATUS]],TotalGMContribution[Opps Status],"Good"),0)+IF(CompanyFairToggle=TRUE,SUMIFS(TotalGMContribution[August],TotalGMContribution[Status],GMConSpreadTable[[#This Row],[STATUS]],TotalGMContribution[Opps Status],"Fair"),0)+IF(CompanyRiskToggle=TRUE,SUMIFS(TotalGMContribution[August],TotalGMContribution[Status],GMConSpreadTable[[#This Row],[STATUS]],TotalGMContribution[Opps Status],"Risk"),0) -> 0 | E58: =IF(CompanyGoodToggle=TRUE,SUMIFS(TotalGMContribution[September],TotalGMContribution[Status],GMConSpreadTable[[#This Row],[STATUS]],TotalGMContribution[Opps Status],"Good"),0)+IF(CompanyFairToggle=TRUE,SUMIFS(TotalGMContribution[September],TotalGMContribution[Status],GMConSpreadTable[[#This Row],[STATUS]],TotalGMContribution[Opps Status],"Fair"),0)+IF(CompanyRiskToggle=TRUE,SUMIFS(TotalGMContribution[September],TotalGMContribution[Status],GMConSpreadTable[[#This Row],[STATUS]],TotalGMContribution[Opps Status],"Risk"),0) -> 0 | F58: =IF(CompanyGoodToggle=TRUE,SUMIFS(TotalGMContribution[October],TotalGMContribution[Status],GMConSpreadTable[[#This Row],[STATUS]],TotalGMContribution[Opps Status],"Good"),0)+IF(CompanyFairToggle=TRUE,SUMIFS(TotalGMContribution[October],TotalGMContribution[Status],GMConSpreadTable[[#This Row],[STATUS]],TotalGMContribution[Opps Status],"Fair"),0)+IF(CompanyRiskToggle=TRUE,SUMIFS(TotalGMContribution[October],TotalGMContribution[Status],GMConSpreadTable[[#This Row],[STATUS]],TotalGMContribution[Opps Status],"Risk"),0) -> 0 | G58: =IF(CompanyGoodToggle=TRUE,SUMIFS(TotalGMContribution[November],TotalGMContribution[Status],GMConSpreadTable[[#This Row],[STATUS]],TotalGMContribution[Opps Status],"Good"),0)+IF(CompanyFairToggle=TRUE,SUMIFS(TotalGMContribution[November],TotalGMContribution[Status],GMConSpreadTable[[#This Row],[STATUS]],TotalGMContribution[Opps Status],"Fair"),0)+IF(CompanyRiskToggle=TRUE,SUMIFS(TotalGMContribution[November],TotalGMContribution[Status],GMConSpreadTable[[#This Row],[STATUS]],TotalGMContribution[Opps Status],"Risk"),0) -> 0 | H58: =IF(CompanyGoodToggle=TRUE,SUMIFS(TotalGMContribution[December],TotalGMContribution[Status],GMConSpreadTable[[#This Row],[STATUS]],TotalGMContribution[Opps Status],"Good"),0)+IF(CompanyFairToggle=TRUE,SUMIFS(TotalGMContribution[December],TotalGMContribution[Status],GMConSpreadTable[[#This Row],[STATUS]],TotalGMContribution[Opps Status],"Fair"),0)+IF(CompanyRiskToggle=TRUE,SUMIFS(TotalGMContribution[December],TotalGMContribution[Status],GMConSpreadTable[[#This Row],[STATUS]],TotalGMContribution[Opps Status],"Risk"),0) -> 0 | I58: =IF(CompanyGoodToggle=TRUE,SUMIFS(TotalGMContribution[January],TotalGMContribution[Status],GMConSpreadTable[[#This Row],[STATUS]],TotalGMContribution[Opps Status],"Good"),0)+IF(CompanyFairToggle=TRUE,SUMIFS(TotalGMContribution[January],TotalGMContribution[Status],GMConSpreadTable[[#This Row],[STATUS]],TotalGMContribution[Opps Status],"Fair"),0)+IF(CompanyRiskToggle=TRUE,SUMIFS(TotalGMContribution[January],TotalGMContribution[Status],GMConSpreadTable[[#This Row],[STATUS]],TotalGMContribution[Opps Status],"Risk"),0) -> 0 | J58: =IF(CompanyGoodToggle=TRUE,SUMIFS(TotalGMContribution[February],TotalGMContribution[Status],GMConSpreadTable[[#This Row],[STATUS]],TotalGMContribution[Opps Status],"Good"),0)+IF(CompanyFairToggle=TRUE,SUMIFS(TotalGMContribution[February],TotalGMContribution[Status],GMConSpreadTable[[#This Row],[STATUS]],TotalGMContribution[Opps Status],"Fair"),0)+IF(CompanyRiskToggle=TRUE,SUMIFS(TotalGMContribution[February],TotalGMContribution[Status],GMConSpreadTable[[#This Row],[STATUS]],TotalGMContribution[Opps Status],"Risk"),0) -> 0 | K58: =IF(CompanyGoodToggle=TRUE,SUMIFS(TotalGMContribution[March],TotalGMContribution[Status],GMConSpreadTable[[#This Row],[STATUS]],TotalGMContribution[Opps Status],"Good"),0)+IF(CompanyFairToggle=TRUE,SUMIFS(TotalGMContribution[March],TotalGMContribution[Status],GMConSpreadTable[[#This Row],[STATUS]],TotalGMContribution[Opps Status],"Fair"),0)+IF(CompanyRiskToggle=TRUE,SUMIFS(TotalGMContribution[March],TotalGMContribution[Status],GMConSpreadTable[[#This Row],[STATUS]],TotalGMContribution[Opps Status],"Risk"),0) -> 0 | L58: =IF(CompanyGoodToggle=TRUE,SUMIFS(TotalGMContribution[April],TotalGMContribution[Status],GMConSpreadTable[[#This Row],[STATUS]],TotalGMContribution[Opps Status],"Good"),0)+IF(CompanyFairToggle=TRUE,SUMIFS(TotalGMContribution[April],TotalGMContribution[Status],GMConSpreadTable[[#This Row],[STATUS]],TotalGMContribution[Opps Status],"Fair"),0)+IF(CompanyRiskToggle=TRUE,SUMIFS(TotalGMContribution[April],TotalGMContribution[Status],GMConSpreadTable[[#This Row],[STATUS]],TotalGMContribution[Opps Status],"Risk"),0) -> 0 | M58: =IF(CompanyGoodToggle=TRUE,SUMIFS(TotalGMContribution[May],TotalGMContribution[Status],GMConSpreadTable[[#This Row],[STATUS]],TotalGMContribution[Opps Status],"Good"),0)+IF(CompanyFairToggle=TRUE,SUMIFS(TotalGMContribution[May],TotalGMContribution[Status],GMConSpreadTable[[#This Row],[STATUS]],TotalGMContribution[Opps Status],"Fair"),0)+IF(CompanyRiskToggle=TRUE,SUMIFS(TotalGMContribution[May],TotalGMContribution[Status],GMConSpreadTable[[#This Row],[STATUS]],TotalGMContribution[Opps Status],"Risk"),0) -> 0 | N58: =IF(CompanyGoodToggle=TRUE,SUMIFS(TotalGMContribution[June],TotalGMContribution[Status],GMConSpreadTable[[#This Row],[STATUS]],TotalGMContribution[Opps Status],"Good"),0)+IF(CompanyFairToggle=TRUE,SUMIFS(TotalGMContribution[June],TotalGMContribution[Status],GMConSpreadTable[[#This Row],[STATUS]],TotalGMContribution[Opps Status],"Fair"),0)+IF(CompanyRiskToggle=TRUE,SUMIFS(TotalGMContribution[June],TotalGMContribution[Status],GMConSpreadTable[[#This Row],[STATUS]],TotalGMContribution[Opps Status],"Risk"),0) -> 0 | P58: Q | Q58: {=IF(CompanyGoodToggle=TRUE, SUM( _xlfn._xlws.FILTER( _xlfn.DROP(_xlfn.CHOOSECOLS(QBlockRev,5),1), _xlfn.DROP(_xlfn.CHOOSECOLS(QBlockRev,4),1)="Good" ) ),0 ) + IF(CompanyFairToggle=TRUE, SUM( _xlfn._xlws.FILTER( _xlfn.DROP(_xlfn.CHOOSECOLS(QBlockRev,5),1), _xlfn.DROP(_xlfn.CHOOSECOLS(QBlockRev,4),1)="Fair" ) ),0 ) + IF(CompanyRiskToggle=TRUE, SUM( _xlfn._xlws.FILTER( _xlfn.DROP(_xlfn.CHOOSECOLS(QBlockRev,5),1), _xlfn.DROP(_xlfn.CHOOSECOLS(QBlockRev,4),1)="Risk" ) ),0 )} -> 0 | R58: {=IF(CompanyGoodToggle=TRUE, SUM( _xlfn._xlws.FILTER( _xlfn.DROP(_xlfn.CHOOSECOLS(QBlockRev,6),1), _xlfn.DROP(_xlfn.CHOOSECOLS(QBlockRev,4),1)="Good" ) ),0 ) + IF(CompanyFairToggle=TRUE, SUM( _xlfn._xlws.FILTER( _xlfn.DROP(_xlfn.CHOOSECOLS(QBlockRev,6),1), _xlfn.DROP(_xlfn.CHOOSECOLS(QBlockRev,4),1)="Fair" ) ),0 ) + IF(CompanyRiskToggle=TRUE, SUM( _xlfn._xlws.FILTER( _xlfn.DROP(_xlfn.CHOOSECOLS(QBlockRev,6),1), _xlfn.DROP(_xlfn.CHOOSECOLS(QBlockRev,4),1)="Risk" ) ),0 )} -> 0 | S58: {=IF(CompanyGoodToggle=TRUE, SUM( _xlfn._xlws.FILTER( _xlfn.DROP(_xlfn.CHOOSECOLS(QBlockRev,7),1), _xlfn.DROP(_xlfn.CHOOSECOLS(QBlockRev,4),1)="Good" ) ),0 ) + IF(CompanyFairToggle=TRUE, SUM( _xlfn._xlws.FILTER( _xlfn.DROP(_xlfn.CHOOSECOLS(QBlockRev,7),1), _xlfn.DROP(_xlfn.CHOOSECOLS(QBlockRev,4),1)="Fair" ) ),0 ) + IF(CompanyRiskToggle=TRUE, SUM( _xlfn._xlws.FILTER( _xlfn.DROP(_xlfn.CHOOSECOLS(QBlockRev,7),1), _xlfn.DROP(_xlfn.CHOOSECOLS(QBlockRev,4),1)="Risk" ) ),0 )} -> 0 | T58: {=IF(CompanyGoodToggle=TRUE, SUM( _xlfn._xlws.FILTER( _xlfn.DROP(_xlfn.CHOOSECOLS(QBlockRev,8),1), _xlfn.DROP(_xlfn.CHOOSECOLS(QBlockRev,4),1)="Good" ) ),0 ) + IF(CompanyFairToggle=TRUE, SUM( _xlfn._xlws.FILTER( _xlfn.DROP(_xlfn.CHOOSECOLS(QBlockRev,8),1), _xlfn.DROP(_xlfn.CHOOSECOLS(QBlockRev,4),1)="Fair" ) ),0 ) + IF(CompanyRiskToggle=TRUE, SUM( _xlfn._xlws.FILTER( _xlfn.DROP(_xlfn.CHOOSECOLS(QBlockRev,8),1), _xlfn.DROP(_xlfn.CHOOSECOLS(QBlockRev,4),1)="Risk" ) ),0 )} -> 0 | U58: {=IF(CompanyGoodToggle=TRUE, SUM( _xlfn._xlws.FILTER( _xlfn.DROP(_xlfn.CHOOSECOLS(QBlockRev,9),1), _xlfn.DROP(_xlfn.CHOOSECOLS(QBlockRev,4),1)="Good" ) ),0 ) + IF(CompanyFairToggle=TRUE, SUM( _xlfn._xlws.FILTER( _xlfn.DROP(_xlfn.CHOOSECOLS(QBlockRev,9),1), _xlfn.DROP(_xlfn.CHOOSECOLS(QBlockRev,4),1)="Fair" ) ),0 ) + IF(CompanyRiskToggle=TRUE, SUM( _xlfn._xlws.FILTER( _xlfn.DROP(_xlfn.CHOOSECOLS(QBlockRev,9),1), _xlfn.DROP(_xlfn.CHOOSECOLS(QBlockRev,4),1)="Risk" ) ),0 )} -> 0 | V58: {=IF(CompanyGoodToggle=TRUE, SUM( _xlfn._xlws.FILTER( _xlfn.DROP(_xlfn.CHOOSECOLS(QBlockRev,10),1), _xlfn.DROP(_xlfn.CHOOSECOLS(QBlockRev,4),1)="Good" ) ),0 ) + IF(CompanyFairToggle=TRUE, SUM( _xlfn._xlws.FILTER( _xlfn.DROP(_xlfn.CHOOSECOLS(QBlockRev,10),1), _xlfn.DROP(_xlfn.CHOOSECOLS(QBlockRev,4),1)="Fair" ) ),0 ) + IF(CompanyRiskToggle=TRUE, SUM( _xlfn._xlws.FILTER( _xlfn.DROP(_xlfn.CHOOSECOLS(QBlockRev,10),1), _xlfn.DROP(_xlfn.CHOOSECOLS(QBlockRev,4),1)="Risk" ) ),0 )} -> 0 | W58: {=IF(CompanyGoodToggle=TRUE, SUM( _xlfn._xlws.FILTER( _xlfn.DROP(_xlfn.CHOOSECOLS(QBlockRev,11),1), _xlfn.DROP(_xlfn.CHOOSECOLS(QBlockRev,4),1)="Good" ) ),0 ) + IF(CompanyFairToggle=TRUE, SUM( _xlfn._xlws.FILTER( _xlfn.DROP(_xlfn.CHOOSECOLS(QBlockRev,11),1), _xlfn.DROP(_xlfn.CHOOSECOLS(QBlockRev,4),1)="Fair" ) ),0 ) + IF(CompanyRiskToggle=TRUE, SUM( _xlfn._xlws.FILTER( _xlfn.DROP(_xlfn.CHOOSECOLS(QBlockRev,11),1), _xlfn.DROP(_xlfn.CHOOSECOLS(QBlockRev,4),1)="Risk" ) ),0 )} -> 0 | X58: {=IF(CompanyGoodToggle=TRUE, SUM( _xlfn._xlws.FILTER( _xlfn.DROP(_xlfn.CHOOSECOLS(QBlockRev,12),1), _xlfn.DROP(_xlfn.CHOOSECOLS(QBlockRev,4),1)="Good" ) ),0 ) + IF(CompanyFairToggle=TRUE, SUM( _xlfn._xlws.FILTER( _xlfn.DROP(_xlfn.CHOOSECOLS(QBlockRev,12),1), _xlfn.DROP(_xlfn.CHOOSECOLS(QBlockRev,4),1)="Fair" ) ),0 ) + IF(CompanyRiskToggle=TRUE, SUM( _xlfn._xlws.FILTER( _xlfn.DROP(_xlfn.CHOOSECOLS(QBlockRev,12),1), _xlfn.DROP(_xlfn.CHOOSECOLS(QBlockRev,4),1)="Risk" ) ),0 )} -> 120000 | Y58: {=IF(CompanyGoodToggle=TRUE, SUM( _xlfn._xlws.FILTER( _xlfn.DROP(_xlfn.CHOOSECOLS(QBlockRev,13),1), _xlfn.DROP(_xlfn.CHOOSECOLS(QBlockRev,4),1)="Good" ) ),0 ) + IF(CompanyFairToggle=TRUE, SUM( _xlfn._xlws.FILTER( _xlfn.DROP(_xlfn.CHOOSECOLS(QBlockRev,13),1), _xlfn.DROP(_xlfn.CHOOSECOLS(QBlockRev,4),1)="Fair" ) ),0 ) + IF(CompanyRiskToggle=TRUE, SUM( _xlfn._xlws.FILTER( _xlfn.DROP(_xlfn.CHOOSECOLS(QBlockRev,13),1), _xlfn.DROP(_xlfn.CHOOSECOLS(QBlockRev,4),1)="Risk" ) ),0 )} -> 120000 | Z58: {=IF(CompanyGoodToggle=TRUE, SUM( _xlfn._xlws.FILTER( _xlfn.DROP(_xlfn.CHOOSECOLS(QBlockRev,14),1), _xlfn.DROP(_xlfn.CHOOSECOLS(QBlockRev,4),1)="Good" ) ),0 ) + IF(CompanyFairToggle=TRUE, SUM( _xlfn._xlws.FILTER( _xlfn.DROP(_xlfn.CHOOSECOLS(QBlockRev,14),1), _xlfn.DROP(_xlfn.CHOOSECOLS(QBlockRev,4),1)="Fair" ) ),0 ) + IF(CompanyRiskToggle=TRUE, SUM( _xlfn._xlws.FILTER( _xlfn.DROP(_xlfn.CHOOSECOLS(QBlockRev,14),1), _xlfn.DROP(_xlfn.CHOOSECOLS(QBlockRev,4),1)="Risk" ) ),0 )} -> 120000 | AA58: {=IF(CompanyGoodToggle=TRUE, SUM( _xlfn._xlws.FILTER( _xlfn.DROP(_xlfn.CHOOSECOLS(QBlockRev,15),1), _xlfn.DROP(_xlfn.CHOOSECOLS(QBlockRev,4),1)="Good" ) ),0 ) + IF(CompanyFairToggle=TRUE, SUM( _xlfn._xlws.FILTER( _xlfn.DROP(_xlfn.CHOOSECOLS(QBlockRev,15),1), _xlfn.DROP(_xlfn.CHOOSECOLS(QBlockRev,4),1)="Fair" ) ),0 ) + IF(CompanyRiskToggle=TRUE, SUM( _xlfn._xlws.FILTER( _xlfn.DROP(_xlfn.CHOOSECOLS(QBlockRev,15),1), _xlfn.DROP(_xlfn.CHOOSECOLS(QBlockRev,4),1)="Risk" ) ),0 )} -> 312857.14 | AB58: {=IF(CompanyGoodToggle=TRUE, SUM( _xlfn._xlws.FILTER( _xlfn.DROP(_xlfn.CHOOSECOLS(QBlockRev,16),1), _xlfn.DROP(_xlfn.CHOOSECOLS(QBlockRev,4),1)="Good" ) ),0 ) + IF(CompanyFairToggle=TRUE, SUM( _xlfn._xlws.FILTER( _xlfn.DROP(_xlfn.CHOOSECOLS(QBlockRev,16),1), _xlfn.DROP(_xlfn.CHOOSECOLS(QBlockRev,4),1)="Fair" ) ),0 ) + IF(CompanyRiskToggle=TRUE, SUM( _xlfn._xlws.FILTER( _xlfn.DROP(_xlfn.CHOOSECOLS(QBlockRev,16),1), _xlfn.DROP(_xlfn.CHOOSECOLS(QBlockRev,4),1)="Risk" ) ),0 )} -> 262857.14
B59: GREAT | C59: ='DAFF VAT Summary'!U21+'SAU VAT Summary'!U21+'VIC VAT Summary'!U21+'DISR VAT Summary'!U21+'EMERGING VAT Summary'!U21+'GROWTH VAT Summary'!U22 -> 971166.67 | D59: ='DAFF VAT Summary'!V21+'SAU VAT Summary'!V21+'VIC VAT Summary'!V21+'DISR VAT Summary'!V21+'EMERGING VAT Summary'!V21+'GROWTH VAT Summary'!V22 -> 975666.67 | E59: ='DAFF VAT Summary'!W21+'SAU VAT Summary'!W21+'VIC VAT Summary'!W21+'DISR VAT Summary'!W21+'EMERGING VAT Summary'!W21+'GROWTH VAT Summary'!W22 -> 990666.67 | F59: ='DAFF VAT Summary'!X21+'SAU VAT Summary'!X21+'VIC VAT Summary'!X21+'DISR VAT Summary'!X21+'EMERGING VAT Summary'!X21+'GROWTH VAT Summary'!X22 -> 954166.67 | G59: ='DAFF VAT Summary'!Y21+'SAU VAT Summary'!Y21+'VIC VAT Summary'!Y21+'DISR VAT Summary'!Y21+'EMERGING VAT Summary'!Y21+'GROWTH VAT Summary'!Y22 -> 954166.67 | H59: ='DAFF VAT Summary'!Z21+'SAU VAT Summary'!Z21+'VIC VAT Summary'!Z21+'DISR VAT Summary'!Z21+'EMERGING VAT Summary'!Z21+'GROWTH VAT Summary'!Z22 -> 954166.67 | I59: ='DAFF VAT Summary'!AA21+'SAU VAT Summary'!AA21+'VIC VAT Summary'!AA21+'DISR VAT Summary'!AA21+'EMERGING VAT Summary'!AA21+'GROWTH VAT Summary'!AA22 -> 1216666.7 | J59: ='DAFF VAT Summary'!AB21+'SAU VAT Summary'!AB21+'VIC VAT Summary'!AB21+'DISR VAT Summary'!AB21+'EMERGING VAT Summary'!AB21+'GROWTH VAT Summary'!AB22 -> 1216666.7 | ... N59: ='DAFF VAT Summary'!AF21+'SAU VAT Summary'!AF21+'VIC VAT Summary'!AF21+'DISR VAT Summary'!AF21+'EMERGING VAT Summary'!AF21+'GROWTH VAT Summary'!AF22 -> 1216666.7 | P59: GREAT | Q59: ='DAFF VAT Summary'!U43+'SAU VAT Summary'!U43+'VIC VAT Summary'!U43+'DISR VAT Summary'!U43+'EMERGING VAT Summary'!U43+'GROWTH VAT Summary'!U44 -> 3179953.1 | R59: ='DAFF VAT Summary'!V43+'SAU VAT Summary'!V43+'VIC VAT Summary'!V43+'DISR VAT Summary'!V43+'EMERGING VAT Summary'!V43+'GROWTH VAT Summary'!V44 -> 3194953.1 | S59: ='DAFF VAT Summary'!W43+'SAU VAT Summary'!W43+'VIC VAT Summary'!W43+'DISR VAT Summary'!W43+'EMERGING VAT Summary'!W43+'GROWTH VAT Summary'!W44 -> 3244953.1 | T59: ='DAFF VAT Summary'!X43+'SAU VAT Summary'!X43+'VIC VAT Summary'!X43+'DISR VAT Summary'!X43+'EMERGING VAT Summary'!X43+'GROWTH VAT Summary'!X44 -> 2812680.4 | U59: ='DAFF VAT Summary'!Y43+'SAU VAT Summary'!Y43+'VIC VAT Summary'!Y43+'DISR VAT Summary'!Y43+'EMERGING VAT Summary'!Y43+'GROWTH VAT Summary'!Y44 -> 2812680.4 | V59: ='DAFF VAT Summary'!Z43+'SAU VAT Summary'!Z43+'VIC VAT Summary'!Z43+'DISR VAT Summary'!Z43+'EMERGING VAT Summary'!Z43+'GROWTH VAT Summary'!Z44 -> 2812680.4 | W59: ='DAFF VAT Summary'!AA43+'SAU VAT Summary'!AA43+'VIC VAT Summary'!AA43+'DISR VAT Summary'!AA43+'EMERGING VAT Summary'!AA43+'GROWTH VAT Summary'!AA44 -> 4153589.5 | X59: ='DAFF VAT Summary'!AB43+'SAU VAT Summary'!AB43+'VIC VAT Summary'!AB43+'DISR VAT Summary'!AB43+'EMERGING VAT Summary'!AB43+'GROWTH VAT Summary'!AB44 -> 4153589.5 | ... AB59: ='DAFF VAT Summary'!AF43+'SAU VAT Summary'!AF43+'VIC VAT Summary'!AF43+'DISR VAT Summary'!AF43+'EMERGING VAT Summary'!AF43+'GROWTH VAT Summary'!AF44 -> 4153589.5
B60: GOOD | C60: ='DAFF VAT Summary'!U22+'SAU VAT Summary'!U22+'VIC VAT Summary'!U22+'DISR VAT Summary'!U22+'EMERGING VAT Summary'!U22+'GROWTH VAT Summary'!U23 -> 748666.67 | D60: ='DAFF VAT Summary'!V22+'SAU VAT Summary'!V22+'VIC VAT Summary'!V22+'DISR VAT Summary'!V22+'EMERGING VAT Summary'!V22+'GROWTH VAT Summary'!V23 -> 753166.67 | E60: ='DAFF VAT Summary'!W22+'SAU VAT Summary'!W22+'VIC VAT Summary'!W22+'DISR VAT Summary'!W22+'EMERGING VAT Summary'!W22+'GROWTH VAT Summary'!W23 -> 768166.67 | F60: ='DAFF VAT Summary'!X22+'SAU VAT Summary'!X22+'VIC VAT Summary'!X22+'DISR VAT Summary'!X22+'EMERGING VAT Summary'!X22+'GROWTH VAT Summary'!X23 -> 773333.33 | G60: ='DAFF VAT Summary'!Y22+'SAU VAT Summary'!Y22+'VIC VAT Summary'!Y22+'DISR VAT Summary'!Y22+'EMERGING VAT Summary'!Y22+'GROWTH VAT Summary'!Y23 -> 773333.33 | H60: ='DAFF VAT Summary'!Z22+'SAU VAT Summary'!Z22+'VIC VAT Summary'!Z22+'DISR VAT Summary'!Z22+'EMERGING VAT Summary'!Z22+'GROWTH VAT Summary'!Z23 -> 773333.33 | I60: ='DAFF VAT Summary'!AA22+'SAU VAT Summary'!AA22+'VIC VAT Summary'!AA22+'DISR VAT Summary'!AA22+'EMERGING VAT Summary'!AA22+'GROWTH VAT Summary'!AA23 -> 923333.33 | J60: ='DAFF VAT Summary'!AB22+'SAU VAT Summary'!AB22+'VIC VAT Summary'!AB22+'DISR VAT Summary'!AB22+'EMERGING VAT Summary'!AB22+'GROWTH VAT Summary'!AB23 -> 923333.33 | ... N60: ='DAFF VAT Summary'!AF22+'SAU VAT Summary'!AF22+'VIC VAT Summary'!AF22+'DISR VAT Summary'!AF22+'EMERGING VAT Summary'!AF22+'GROWTH VAT Summary'!AF23 -> 923333.33 | P60: GOOD | Q60: ='DAFF VAT Summary'!U44+'SAU VAT Summary'!U44+'VIC VAT Summary'!U44+'DISR VAT Summary'!U44+'EMERGING VAT Summary'!U44+'GROWTH VAT Summary'!U45 -> 2510562.8 | R60: ='DAFF VAT Summary'!V44+'SAU VAT Summary'!V44+'VIC VAT Summary'!V44+'DISR VAT Summary'!V44+'EMERGING VAT Summary'!V44+'GROWTH VAT Summary'!V45 -> 2525562.8 | S60: ='DAFF VAT Summary'!W44+'SAU VAT Summary'!W44+'VIC VAT Summary'!W44+'DISR VAT Summary'!W44+'EMERGING VAT Summary'!W44+'GROWTH VAT Summary'!W45 -> 2575562.8 | T60: ='DAFF VAT Summary'!X44+'SAU VAT Summary'!X44+'VIC VAT Summary'!X44+'DISR VAT Summary'!X44+'EMERGING VAT Summary'!X44+'GROWTH VAT Summary'!X45 -> 2395815.3 | U60: ='DAFF VAT Summary'!Y44+'SAU VAT Summary'!Y44+'VIC VAT Summary'!Y44+'DISR VAT Summary'!Y44+'EMERGING VAT Summary'!Y44+'GROWTH VAT Summary'!Y45 -> 2395815.3 | V60: ='DAFF VAT Summary'!Z44+'SAU VAT Summary'!Z44+'VIC VAT Summary'!Z44+'DISR VAT Summary'!Z44+'EMERGING VAT Summary'!Z44+'GROWTH VAT Summary'!Z45 -> 2395815.3 | W60: ='DAFF VAT Summary'!AA44+'SAU VAT Summary'!AA44+'VIC VAT Summary'!AA44+'DISR VAT Summary'!AA44+'EMERGING VAT Summary'!AA44+'GROWTH VAT Summary'!AA45 -> 3191269.8 | X60: ='DAFF VAT Summary'!AB44+'SAU VAT Summary'!AB44+'VIC VAT Summary'!AB44+'DISR VAT Summary'!AB44+'EMERGING VAT Summary'!AB44+'GROWTH VAT Summary'!AB45 -> 3191269.8 | ... AB60: ='DAFF VAT Summary'!AF44+'SAU VAT Summary'!AF44+'VIC VAT Summary'!AF44+'DISR VAT Summary'!AF44+'EMERGING VAT Summary'!AF44+'GROWTH VAT Summary'!AF45 -> 3191269.8
B61: OK | C61: ='DAFF VAT Summary'!U23+'SAU VAT Summary'!U23+'VIC VAT Summary'!U23+'DISR VAT Summary'!U23+'EMERGING VAT Summary'!U23+'GROWTH VAT Summary'!U24 -> 537000 | D61: ='DAFF VAT Summary'!V23+'SAU VAT Summary'!V23+'VIC VAT Summary'!V23+'DISR VAT Summary'!V23+'EMERGING VAT Summary'!V23+'GROWTH VAT Summary'!V24 -> 541500 | E61: ='DAFF VAT Summary'!W23+'SAU VAT Summary'!W23+'VIC VAT Summary'!W23+'DISR VAT Summary'!W23+'EMERGING VAT Summary'!W23+'GROWTH VAT Summary'!W24 -> 556500 | F61: ='DAFF VAT Summary'!X23+'SAU VAT Summary'!X23+'VIC VAT Summary'!X23+'DISR VAT Summary'!X23+'EMERGING VAT Summary'!X23+'GROWTH VAT Summary'!X24 -> 580000 | G61: ='DAFF VAT Summary'!Y23+'SAU VAT Summary'!Y23+'VIC VAT Summary'!Y23+'DISR VAT Summary'!Y23+'EMERGING VAT Summary'!Y23+'GROWTH VAT Summary'!Y24 -> 580000 | H61: ='DAFF VAT Summary'!Z23+'SAU VAT Summary'!Z23+'VIC VAT Summary'!Z23+'DISR VAT Summary'!Z23+'EMERGING VAT Summary'!Z23+'GROWTH VAT Summary'!Z24 -> 580000 | I61: ='DAFF VAT Summary'!AA23+'SAU VAT Summary'!AA23+'VIC VAT Summary'!AA23+'DISR VAT Summary'!AA23+'EMERGING VAT Summary'!AA23+'GROWTH VAT Summary'!AA24 -> 617500 | J61: ='DAFF VAT Summary'!AB23+'SAU VAT Summary'!AB23+'VIC VAT Summary'!AB23+'DISR VAT Summary'!AB23+'EMERGING VAT Summary'!AB23+'GROWTH VAT Summary'!AB24 -> 617500 | ... N61: ='DAFF VAT Summary'!AF23+'SAU VAT Summary'!AF23+'VIC VAT Summary'!AF23+'DISR VAT Summary'!AF23+'EMERGING VAT Summary'!AF23+'GROWTH VAT Summary'!AF24 -> 617500 | P61: OK | Q61: ='DAFF VAT Summary'!U45+'SAU VAT Summary'!U45+'VIC VAT Summary'!U45+'DISR VAT Summary'!U45+'EMERGING VAT Summary'!U45+'GROWTH VAT Summary'!U46 -> 1877366.9 | R61: ='DAFF VAT Summary'!V45+'SAU VAT Summary'!V45+'VIC VAT Summary'!V45+'DISR VAT Summary'!V45+'EMERGING VAT Summary'!V45+'GROWTH VAT Summary'!V46 -> 1892366.9 | S61: ='DAFF VAT Summary'!W45+'SAU VAT Summary'!W45+'VIC VAT Summary'!W45+'DISR VAT Summary'!W45+'EMERGING VAT Summary'!W45+'GROWTH VAT Summary'!W46 -> 1942366.9 | T61: ='DAFF VAT Summary'!X45+'SAU VAT Summary'!X45+'VIC VAT Summary'!X45+'DISR VAT Summary'!X45+'EMERGING VAT Summary'!X45+'GROWTH VAT Summary'!X46 -> 1931619.7 | U61: ='DAFF VAT Summary'!Y45+'SAU VAT Summary'!Y45+'VIC VAT Summary'!Y45+'DISR VAT Summary'!Y45+'EMERGING VAT Summary'!Y45+'GROWTH VAT Summary'!Y46 -> 1931619.7 | V61: ='DAFF VAT Summary'!Z45+'SAU VAT Summary'!Z45+'VIC VAT Summary'!Z45+'DISR VAT Summary'!Z45+'EMERGING VAT Summary'!Z45+'GROWTH VAT Summary'!Z46 -> 1931619.7 | W61: ='DAFF VAT Summary'!AA45+'SAU VAT Summary'!AA45+'VIC VAT Summary'!AA45+'DISR VAT Summary'!AA45+'EMERGING VAT Summary'!AA45+'GROWTH VAT Summary'!AA46 -> 2190240.4 | X61: ='DAFF VAT Summary'!AB45+'SAU VAT Summary'!AB45+'VIC VAT Summary'!AB45+'DISR VAT Summary'!AB45+'EMERGING VAT Summary'!AB45+'GROWTH VAT Summary'!AB46 -> 2190240.4 | ... AB61: ='DAFF VAT Summary'!AF45+'SAU VAT Summary'!AF45+'VIC VAT Summary'!AF45+'DISR VAT Summary'!AF45+'EMERGING VAT Summary'!AF45+'GROWTH VAT Summary'!AF46 -> 2190240.4
B65: Select VAT
B66: ALL

Sheet Open Opps Summary
A1: OPPS BY VAT & PHASE & STATUS | E1: GO TO DATA TAB -> REFRESH ALL to update dashboard
E2: $ IN TABLE BELOW IS FOR THE WHOLE DURATION OF THE OPPORTUNITY
A3: Path | B3: sites/RGSales/Shared Documents/General/1.Open Opportunities
A4: VAT | B4: (All)
A6: Value $ | G6: Status
A7: Phase | B7: Name | C7: Work Type | D7: Margin | E7: Start Date | F7: End Date | G7: Good | H7: Fair | I7: Risk | J7: Grand Total
A8: 4.DVF - Shortlisted | B8: PANEL People DOF Phase 3 - Professional Contractor Services | C8: Panel | D8: (blank) | E8: 46083 | F8: 47487
B9: PANEL Refresh DOF MAS Corp and Comm Servs 202502 | C9: Panel | D9: (blank) | E9: 46082 | F9: 47391
B10: SAU046-XX Delivery Manager (Alex) | C10: Labour Hire | D10: 0.28 | E10: 46113 | F10: 46477 | G10: 412500 | J10: 412500
B11: TECXXX DEWR DE RFQ ERP 202510 | C11: Delivery | D11: 0.32 | E11: 46113 | F11: 46844 | G11: 10812528 | J11: 10812528
B12: TECXXX INF RFQ TechOne - ERP Products, Implementation, Operational | C12: Delivery | D12: 0.4 | E12: 46113 | F12: 46600 | G12: 4188470 | J12: 4188470
B13: VICXXX DEECA RFQ Permissions System 202512 | C13: Delivery | D13: 0.12 | E13: 46069 | F13: 46630 | G13: 3000000 | J13: 3000000
B14: FWO001-XX Digital Transformation CPBC - Revision and Submission Support | C14: Delivery | D14: 0.615 | E14: 46160 | F14: 46290 | H14: 465220 | J14: 465220
B15: LAB001-01 DCC Program Plan (Extension) | C15: Delivery | D15: 0.43 | E15: 46069 | F15: 46203 | G15: 175220 | J15: 175220
B16: DPSXXX RFQ Cyber Security Assessor 202601 | C16: Delivery | D16: 0.164 | E16: 46069 | F16: 46108 | I16: 55200 | J16: 55200
B17: SAU045-XX Senior Technology Architect (Sidd) | C17: Labour Hire | D17: 0.14 | E17: 46113 | F17: 46203 | G17: 129600 | J17: 129600
B18: SAU052-XX Senior Solution Architect (Aniket) | C18: Labour Hire | D18: 0.11 | E18: 46112 | F18: 46203 | G18: 112108.24 | J18: 112108.24
B19: FWO001-XX Digital Transformation CPBC - PoC | C19: Delivery | D19: 0.3 | E19: 46097 | F19: 46203 | I19: 1000000 | J19: 1000000
A20: 3.DF - Submitted | B20: SAUXXX SPES Micro-Panel - RFQLH-02700 EL1 Senior Software Engineer | C20: Labour Hire | D20: 0.1 | E20: 46113 | F20: 46477 | I20: 2000000 | J20: 2000000
B21: DHAXXX LH-04634 One Senior Pega Developer 202509 | C21: Labour Hire | D21: 0.13 | E21: 46055 | F21: 46203 | I21: 367840 | J21: 367840
B22: DAFXXX TRACE ServiceNow | C22: Delivery | D22: 0.2 | E22: 46083 | F22: 46255 | I22: 533310.75 | J22: 533310.75
B23: PANEL Vic SRO ICT Supplier Panel 202510 | C23: Panel | D23: (blank) | E23: 46296 | F23: 47391
B24: DHAXXX RFQ On-demand services for mainframe Capability 202511 | C24: Resource Pool | D24: 0.212 | E24: 46055 | F24: 46371 | I24: 371616 | J24: 371616
B25: AFPXXX LH-05147 One (1) Lead Business Architect 202512 | C25: Labour Hire | D25: 0.154 | E25: 46204 | F25: 46568 | I25: 466560 | J25: 466560
B26: AGDXXX RFQ Review of ICT Services for AGS 202512 | C26: Delivery | D26: 0.36 | E26: 46069 | F26: 46250 | I26: 161000 | J26: 161000
B27: DHAXXX LH-04367 Two Senior Pega Analyst 202508 | C27: Labour Hire | D27: 0.17 | E27: 46048 | F27: 46203 | I27: 526240 | J27: 526240
B28: DODXXX RFQ Workforce Prioritisation Workshops 202512 | C28: Delivery | D28: 0.2 | E28: 46083 | F28: 46203 | I28: 311572 | J28: 311572
B29: PANEL RBA Consulting Panel 202511 | C29: Panel | D29: (blank) | E29: 46174 | F29: 48000
B30: TSYXXX ROI ESM Solution Replacement 202512 | C30: RFI/EOI | D30: (blank) | E30: (blank) | F30: (blank)
B31: AREXXX RFQ Design Future Data Platform 202601 | C31: Delivery | D31: 0.29 | E31: 46076 | F31: 46157 | I31: 298214 | J31: 298214
B32: DAFXXX RFQ Incident and Major Incident Management Review | C32: Delivery | D32: 0.29 | E32: 46083 | F32: 46266 | G32: 133000 | J32: 133000
B33: VICXXX CenITex Initial Strategy for One VPS | C33: Delivery | D33: 0.06 | E33: 46090 | F33: 46171 | G33: 135839 | J33: 135839
B34: IND004-01 Portfolio Management - IRM Implementation Extension) | C34: Delivery | D34: 0.3 | E34: 46076 | F34: 46203 | G34: 444574.24 | J34: 444574.24
A35: 2.Q - Qualified | B35: PANEL VIC DJSIR mini panel | C35: Panel | D35: (blank) | E35: 46083 | F35: 47149
B36: VICXXX DJSIR Opp 1 Technical T&M | C36: Resource Pool | D36: 0.15 | E36: 46069 | F36: 46203 | G36: 600000 | J36: 600000
B37: VICXXX DJSIR Opp 2 Regional Hub Case Mgt | C37: Delivery | D37: 0.2 | E37: 46097 | F37: 46276 | H37: 1200000 | J37: 1200000
B38: DAFXXX Trade and Imports Comeback | C38: Advisory | D38: 0.25 | E38: 46146 | F38: 46356 | G38: 1000000 | J38: 1000000
B39: BSSXXX BlueScope Steel SAP architects | C39: Resource Pool | D39: 0.28 | E39: 46083 | F39: 46171 | I39: 316800 | J39: 316800
B40: DTAXXX RFQ ERP 202602 | C40: Delivery | D40: (blank) | E40: (blank) | F40: (blank) | G40: 3000000 | J40: 3000000
B41: DOWXXX RFQ Downer Front Door Shared Services 202602 | C41: Delivery | D41: 0.3 | E41: 46125 | F41: 46157 | H41: 145440 | J41: 145440
B42: PANEL VIC HSV Asset Management Software 202602 | C42: Panel | D42: (blank) | E42: 46172 | F42: (blank)
B43: VICXXX RFI VIC Police Intelligence Mgt Application 202602 | C43: RFI/EOI | D43: (blank) | E43: (blank) | F43: (blank)
B44: DAFXXX STEPS Post-Gateway Response | C44: Delivery | D44: 0.25 | E44: 46146 | F44: 46192 | G44: 100000 | J44: 100000
A45: Grand Total | G45: 24243839 | H45: 1810660 | I45: 6408352.8 | J45: 32462852

Sheet DAFF VAT Summary
B2: DAFF VAT FY25-26 FINANCIAL SUMMARY | L2: Good | M2: Fair | N2: Risk
K3: For Inclusion | L3: =CompanyGoodToggle -> TRUE | M3: =CompanyFairToggle -> FALSE | N3: =CompanyRiskToggle -> FALSE | T3: Cumulative View - Gross Margin Contribution
T4: STATUS | U4: July | V4: August | W4: September | X4: October | Y4: November | Z4: December | AA4: January | AB4: February | AC4: March | AD4: April | AE4: May | AF4: June
K5: GROSS MARGIN CONTRIBUTION SUMMARY | L5: Q1 | M5: Q2 | N5: Q3 | O5: Q4 | P5: TOTAL | T5: C/S | U5: =U16 -> 211173.68 | V5: =SUM($U16:V16) -> 376948.07 | W5: =SUM($U16:W16) -> 562307.51 | X5: =SUM($U16:X16) -> 629192.1 | Y5: =SUM($U16:Y16) -> 681107.38 | Z5: =SUM($U16:Z16) -> 734289.42 | AA5: =SUM($U16:AA16) -> 789523.72 | AB5: =SUM($U16:AB16) -> 849218.3 | AC5: =SUM($U16:AC16) -> 914533.79 | ... AF5: =SUM($U16:AF16) -> 1021242.8
K6: GM Contribution 'Good' Target | L6: =SUM(U22:W22) -> 562500 | M6: =SUM(X22:Z22) -> 562500 | N6: =SUM(AA22:AC22) -> 562500 | O6: =SUM(AD22:AF22) -> 562500 | P6: =SUM(Table15[[#This Row],[Q1]:[Q4]]) -> 2250000 | T6: DVF+ | U6: =U17+U5 -> 211173.68 | V6: =SUM($U17:V17)+V5 -> 376948.07 | W6: =SUM($U17:W17)+W5 -> 562307.51 | X6: =SUM($U17:X17)+X5 -> 629192.1 | Y6: =SUM($U17:Y17)+Y5 -> 681107.38 | Z6: =SUM($U17:Z17)+Z5 -> 734289.42 | AA6: =SUM($U17:AA17)+AA5 -> 789523.72 | AB6: =SUM($U17:AB17)+AB5 -> 849218.3 | AC6: =SUM($U17:AC17)+AC5 -> 914533.79 | ... AF6: =SUM($U17:AF17)+AF5 -> 1021242.8
K7: YTD | L7: =SUMIFS(Job_Status[Gross Profit Q1],Job_Status[VAT],"DAFF") -> 562307.51 | M7: =SUMIFS(Job_Status[Gross Profit Q2],Job_Status[VAT],"DAFF") -> 171981.92 | N7: =SUMIFS(Job_Status[Gross Profit Q3],Job_Status[VAT],"DAFF") -> 65615.1 | O7: =SUMIFS(Job_Status[Gross Profit Q4],Job_Status[VAT],"DAFF") -> 0 | P7: =SUM(Table15[[#This Row],[Q1]:[Q4]]) -> 799904.52 | T7: DF+ | U7: =U18+U6 -> 211173.68 | V7: =SUM($U18:V18)+V6 -> 376948.07 | W7: =SUM($U18:W18)+W6 -> 562307.51 | X7: =SUM($U18:X18)+X6 -> 629192.1 | Y7: =SUM($U18:Y18)+Y6 -> 681107.38 | Z7: =SUM($U18:Z18)+Z6 -> 734289.42 | AA7: =SUM($U18:AA18)+AA6 -> 789523.72 | AB7: =SUM($U18:AB18)+AB6 -> 849218.3 | AC7: =SUM($U18:AC18)+AC6 -> 914533.79 | ... AF7: =SUM($U18:AF18)+AF6 -> 1021242.8
K8: Forecast (C/S) | L8: =SUM(U16:W16) -> 562307.51 | M8: =SUM(X16:Z16) -> 171981.91 | N8: =SUM(AA16:AC16) -> 180244.37 | O8: =SUM(AD16:AF16) -> 106708.97 | P8: =SUM(Table15[[#This Row],[Q1]:[Q4]]) -> 1021242.8 | T8: Q+ | U8: =U19+U7 -> 211173.68 | V8: =SUM($U19:V19)+V7 -> 376948.07 | W8: =SUM($U19:W19)+W7 -> 562307.51 | X8: =SUM($U19:X19)+X7 -> 629192.1 | Y8: =SUM($U19:Y19)+Y7 -> 681107.38 | Z8: =SUM($U19:Z19)+Z7 -> 734289.42 | AA8: =SUM($U19:AA19)+AA7 -> 789523.72 | AB8: =SUM($U19:AB19)+AB7 -> 849218.3 | AC8: =SUM($U19:AC19)+AC7 -> 914533.79 | ... AF8: =SUM($U19:AF19)+AF7 -> 1021242.8
K9: Variance | L9: =L8-L$6 -> -192.4925 | M9: =M8-M$6 -> -390518.09 | N9: =N8-N$6 -> -382255.63 | O9: =O8-O$6 -> -455791.03 | P9: =P8-P$6 -> -1228757.2 | T9: VAT Lead | U9: =U20 -> 0 | V9: =SUM($U20:V20) -> 0 | W9: =SUM($U20:W20) -> 0 | X9: =SUM($U20:X20) -> 0 | Y9: =SUM($U20:Y20) -> 0 | Z9: =SUM($U20:Z20) -> 0 | AA9: =SUM($U20:AA20) -> 0 | AB9: =SUM($U20:AB20) -> 0 | AC9: =SUM($U20:AC20) -> 0 | ... AF9: =SUM($U20:AF20) -> 0
K10: GM Contribution Forecast (DVF+) | L10: =SUM(U$16:W17) -> 562307.51 | M10: =SUM(X$16:Z17) -> 171981.91 | N10: =SUM(AA$16:AC17) -> 180244.37 | O10: =SUM(AD$16:AF17) -> 106708.97 | P10: =SUM(Table15[[#This Row],[Q1]:[Q4]]) -> 1021242.8 | T10: GREAT | U10: =U21 -> 225000 | V10: =SUM($U21:V21) -> 450000 | W10: =SUM($U21:W21) -> 675000 | X10: =SUM($U21:X21) -> 900000 | Y10: =SUM($U21:Y21) -> 1125000 | Z10: =SUM($U21:Z21) -> 1350000 | AA10: =SUM($U21:AA21) -> 1575000 | AB10: =SUM($U21:AB21) -> 1800000 | AC10: =SUM($U21:AC21) -> 2025000 | ... AF10: =SUM($U21:AF21) -> 2700000
K11: Delta to 'Good' Target | L11: =L10-L$6 -> -192.4925 | M11: =M10-M$6 -> -390518.09 | N11: =N10-N$6 -> -382255.63 | O11: =O10-O$6 -> -455791.03 | P11: =P10-P$6 -> -1228757.2 | T11: GOOD | U11: =U22 -> 187500 | V11: =SUM($U22:V22) -> 375000 | W11: =SUM($U22:W22) -> 562500 | X11: =SUM($U22:X22) -> 750000 | Y11: =SUM($U22:Y22) -> 937500 | Z11: =SUM($U22:Z22) -> 1125000 | AA11: =SUM($U22:AA22) -> 1312500 | AB11: =SUM($U22:AB22) -> 1500000 | AC11: =SUM($U22:AC22) -> 1687500 | ... AF11: =SUM($U22:AF22) -> 2250000
K12: GM Contribution Forecast (DF+) | L12: =SUM(U$16:W18) -> 562307.51 | M12: =SUM(X$16:Z18) -> 171981.91 | N12: =SUM(AA$16:AC18) -> 180244.37 | O12: =SUM(AD$16:AF18) -> 106708.97 | P12: =SUM(Table15[[#This Row],[Q1]:[Q4]]) -> 1021242.8 | T12: OK | U12: =U23 -> 150000 | V12: =SUM($U23:V23) -> 300000 | W12: =SUM($U23:W23) -> 450000 | X12: =SUM($U23:X23) -> 600000 | Y12: =SUM($U23:Y23) -> 750000 | Z12: =SUM($U23:Z23) -> 900000 | AA12: =SUM($U23:AA23) -> 1050000 | AB12: =SUM($U23:AB23) -> 1200000 | AC12: =SUM($U23:AC23) -> 1350000 | ... AF12: =SUM($U23:AF23) -> 1800000
K13: Delta to 'Good' Target | L13: =L12-L$6 -> -192.4925 | M13: =M12-M$6 -> -390518.09 | N13: =N12-N$6 -> -382255.63 | O13: =O12-O$6 -> -455791.03 | P13: =P12-P$6 -> -1228757.2
K14: GM Contribution Forecast (Q+) | L14: =SUM(U$16:W20) -> 562307.51 | M14: =SUM(X$16:Z20) -> 171981.91 | N14: =SUM(AA$16:AC20) -> 180244.37 | O14: =SUM(AD$16:AF20) -> 106708.97 | P14: =SUM(Table15[[#This Row],[Q1]:[Q4]]) -> 1021242.8 | T14: Monthly View - Gross Margin Contribution
K15: Delta to 'Good' Target | L15: =L14-L$6 -> -192.4925 | M15: =M14-M$6 -> -390518.09 | N15: =N14-N$6 -> -382255.63 | O15: =O14-O$6 -> -455791.03 | P15: =P14-P$6 -> -1228757.2 | T15: STATUS | U15: July | V15: August | W15: September | X15: October | Y15: November | Z15: December | AA15: January | AB15: February | AC15: March | AD15: April | AE15: May | AF15: June
T16: C/S | U16: =SUMIF(Job_Status[VAT],"DAFF",Job_Status[P1]) -> 211173.68 | V16: =SUMIF(Job_Status[VAT],"DAFF",Job_Status[P2]) -> 165774.39 | W16: =SUMIF(Job_Status[VAT],"DAFF",Job_Status[P3]) -> 185359.44 | X16: =SUMIF(Job_Status[VAT],"DAFF",Job_Status[P4]) -> 66884.595 | Y16: =SUMIF(Job_Status[VAT],"DAFF",Job_Status[P5]) -> 51915.28 | Z16: =SUMIF(Job_Status[VAT],"DAFF",Job_Status[P6]) -> 53182.04 | AA16: =SUMIF(Job_Status[VAT],"DAFF",Job_Status[P7]) -> 55234.3 | AB16: =SUMIF(Job_Status[VAT],"DAFF",Job_Status[P8]) -> 59694.575 | AC16: =SUMIF(Job_Status[VAT],"DAFF",Job_Status[P9]) -> 65315.495 | AD16: =SUMIF(Job_Status[VAT],"DAFF",Job_Status[P10]) -> 40877.33 | AE16: =SUMIF(Job_Status[VAT],"DAFF",Job_Status[P11]) -> 32823.7 | AF16: =SUMIF(Job_Status[VAT],"DAFF",Job_Status[P12]) -> 33007.94
K17: REVENUE SUMMARY | L17: Q1 | M17: Q2 | N17: Q3 | O17: Q4 | P17: TOTAL | T17: DVF | U17: =_xlfn.LET( _xlpm.s, GMConSpreadTable8[[#This Row],[STATUS]], _xlpm.vatCrit, "DAFF", _xlpm.sumcol, TotalGMContribution[July], _xlpm.statuscol, TotalGMContribution[Status], _xlpm.vatcol, TotalGMContribution[VAT], _xlpm.oppcol, TotalGMContribution[Opps Status], IF(DAFFGoodToggle=TRUE, SUMIFS(_xlpm.sumcol, _xlpm.statuscol, _xlpm.s, _xlpm.vatcol, _xlpm.vatCrit, _xlpm.oppcol, "Good"), 0) + IF(DAFFFairToggle=TRUE, SUMIFS(_xlpm.sumcol, _xlpm.statuscol, _xlpm.s, _xlpm.vatcol, _xlpm.vatCrit, _xlpm.oppcol, "Fair"), 0) + IF(DAFFRiskToggle=TRUE, SUMIFS(_xlpm.sumcol, _xlpm.statuscol, _xlpm.s, _xlpm.vatcol, _xlpm.vatCrit, _xlpm.oppcol, "Risk"), 0) ) -> 0 | V17: =_xlfn.LET( _xlpm.s, GMConSpreadTable8[[#This Row],[STATUS]], _xlpm.vatCrit, "DAFF", _xlpm.sumcol, TotalGMContribution[August], _xlpm.statuscol, TotalGMContribution[Status], _xlpm.vatcol, TotalGMContribution[VAT], _xlpm.oppcol, TotalGMContribution[Opps Status], IF(DAFFGoodToggle=TRUE, SUMIFS(_xlpm.sumcol, _xlpm.statuscol, _xlpm.s, _xlpm.vatcol, _xlpm.vatCrit, _xlpm.oppcol, "Good"), 0) + IF(DAFFFairToggle=TRUE, SUMIFS(_xlpm.sumcol, _xlpm.statuscol, _xlpm.s, _xlpm.vatcol, _xlpm.vatCrit, _xlpm.oppcol, "Fair"), 0) + IF(DAFFRiskToggle=TRUE, SUMIFS(_xlpm.sumcol, _xlpm.statuscol, _xlpm.s, _xlpm.vatcol, _xlpm.vatCrit, _xlpm.oppcol, "Risk"), 0) ) -> 0 | W17: =_xlfn.LET( _xlpm.s, GMConSpreadTable8[[#This Row],[STATUS]], _xlpm.vatCrit, "DAFF", _xlpm.sumcol, TotalGMContribution[September], _xlpm.statuscol, TotalGMContribution[Status], _xlpm.vatcol, TotalGMContribution[VAT], _xlpm.oppcol, TotalGMContribution[Opps Status], IF(DAFFGoodToggle=TRUE, SUMIFS(_xlpm.sumcol, _xlpm.statuscol, _xlpm.s, _xlpm.vatcol, _xlpm.vatCrit, _xlpm.oppcol, "Good"), 0) + IF(DAFFFairToggle=TRUE, SUMIFS(_xlpm.sumcol, _xlpm.statuscol, _xlpm.s, _xlpm.vatcol, _xlpm.vatCrit, _xlpm.oppcol, "Fair"), 0) + IF(DAFFRiskToggle=TRUE, SUMIFS(_xlpm.sumcol, _xlpm.statuscol, _xlpm.s, _xlpm.vatcol, _xlpm.vatCrit, _xlpm.oppcol, "Risk"), 0) ) -> 0 | X17: =_xlfn.LET( _xlpm.s, GMConSpreadTable8[[#This Row],[STATUS]], _xlpm.vatCrit, "DAFF", _xlpm.sumcol, TotalGMContribution[October], _xlpm.statuscol, TotalGMContribution[Status], _xlpm.vatcol, TotalGMContribution[VAT], _xlpm.oppcol, TotalGMContribution[Opps Status], IF(DAFFGoodToggle=TRUE, SUMIFS(_xlpm.sumcol, _xlpm.statuscol, _xlpm.s, _xlpm.vatcol, _xlpm.vatCrit, _xlpm.oppcol, "Good"), 0) + IF(DAFFFairToggle=TRUE, SUMIFS(_xlpm.sumcol, _xlpm.statuscol, _xlpm.s, _xlpm.vatcol, _xlpm.vatCrit, _xlpm.oppcol, "Fair"), 0) + IF(DAFFRiskToggle=TRUE, SUMIFS(_xlpm.sumcol, _xlpm.statuscol, _xlpm.s, _xlpm.vatcol, _xlpm.vatCrit, _xlpm.oppcol, "Risk"), 0) ) -> 0 | Y17: =_xlfn.LET( _xlpm.s, GMConSpreadTable8[[#This Row],[STATUS]], _xlpm.vatCrit, "DAFF", _xlpm.sumcol, TotalGMContribution[November], _xlpm.statuscol, TotalGMContribution[Status], _xlpm.vatcol, TotalGMContribution[VAT], _xlpm.oppcol, TotalGMContribution[Opps Status], IF(DAFFGoodToggle=TRUE, SUMIFS(_xlpm.sumcol, _xlpm.statuscol, _xlpm.s, _xlpm.vatcol, _xlpm.vatCrit, _xlpm.oppcol, "Good"), 0) + IF(DAFFFairToggle=TRUE, SUMIFS(_xlpm.sumcol, _xlpm.statuscol, _xlpm.s, _xlpm.vatcol, _xlpm.vatCrit, _xlpm.oppcol, "Fair"), 0) + IF(DAFFRiskToggle=TRUE, SUMIFS(_xlpm.sumcol, _xlpm.statuscol, _xlpm.s, _xlpm.vatcol, _xlpm.vatCrit, _xlpm.oppcol, "Risk"), 0) ) -> 0 | Z17: =_xlfn.LET( _xlpm.s, GMConSpreadTable8[[#This Row],[STATUS]], _xlpm.vatCrit, "DAFF", _xlpm.sumcol, TotalGMContribution[December], _xlpm.statuscol, TotalGMContribution[Status], _xlpm.vatcol, TotalGMContribution[VAT], _xlpm.oppcol, TotalGMContribution[Opps Status], IF(DAFFGoodToggle=TRUE, SUMIFS(_xlpm.sumcol, _xlpm.statuscol, _xlpm.s, _xlpm.vatcol, _xlpm.vatCrit, _xlpm.oppcol, "Good"), 0) + IF(DAFFFairToggle=TRUE, SUMIFS(_xlpm.sumcol, _xlpm.statuscol, _xlpm.s, _xlpm.vatcol, _xlpm.vatCrit, _xlpm.oppcol, "Fair"), 0) + IF(DAFFRiskToggle=TRUE, SUMIFS(_xlpm.sumcol, _xlpm.statuscol, _xlpm.s, _xlpm.vatcol, _xlpm.vatCrit, _xlpm.oppcol, "Risk"), 0) ) -> 0 | AA17: =_xlfn.LET( _xlpm.s, GMConSpreadTable8[[#This Row],[STATUS]], _xlpm.vatCrit, "DAFF", _xlpm.sumcol, TotalGMContribution[January], _xlpm.statuscol, TotalGMContribution[Status], _xlpm.vatcol, TotalGMContribution[VAT], _xlpm.oppcol, TotalGMContribution[Opps Status], IF(DAFFGoodToggle=TRUE, SUMIFS(_xlpm.sumcol, _xlpm.statuscol, _xlpm.s, _xlpm.vatcol, _xlpm.vatCrit, _xlpm.oppcol, "Good"), 0) + IF(DAFFFairToggle=TRUE, SUMIFS(_xlpm.sumcol, _xlpm.statuscol, _xlpm.s, _xlpm.vatcol, _xlpm.vatCrit, _xlpm.oppcol, "Fair"), 0) + IF(DAFFRiskToggle=TRUE, SUMIFS(_xlpm.sumcol, _xlpm.statuscol, _xlpm.s, _xlpm.vatcol, _xlpm.vatCrit, _xlpm.oppcol, "Risk"), 0) ) -> 0 | AB17: =_xlfn.LET( _xlpm.s, GMConSpreadTable8[[#This Row],[STATUS]], _xlpm.vatCrit, "DAFF", _xlpm.sumcol, TotalGMContribution[February], _xlpm.statuscol, TotalGMContribution[Status], _xlpm.vatcol, TotalGMContribution[VAT], _xlpm.oppcol, TotalGMContribution[Opps Status], IF(DAFFGoodToggle=TRUE, SUMIFS(_xlpm.sumcol, _xlpm.statuscol, _xlpm.s, _xlpm.vatcol, _xlpm.vatCrit, _xlpm.oppcol, "Good"), 0) + IF(DAFFFairToggle=TRUE, SUMIFS(_xlpm.sumcol, _xlpm.statuscol, _xlpm.s, _xlpm.vatcol, _xlpm.vatCrit, _xlpm.oppcol, "Fair"), 0) + IF(DAFFRiskToggle=TRUE, SUMIFS(_xlpm.sumcol, _xlpm.statuscol, _xlpm.s, _xlpm.vatcol, _xlpm.vatCrit, _xlpm.oppcol, "Risk"), 0) ) -> 0 | AC17: =_xlfn.LET( _xlpm.s, GMConSpreadTable8[[#This Row],[STATUS]], _xlpm.vatCrit, "DAFF", _xlpm.sumcol, TotalGMContribution[March], _xlpm.statuscol, TotalGMContribution[Status], _xlpm.vatcol, TotalGMContribution[VAT], _xlpm.oppcol, TotalGMContribution[Opps Status], IF(DAFFGoodToggle=TRUE, SUMIFS(_xlpm.sumcol, _xlpm.statuscol, _xlpm.s, _xlpm.vatcol, _xlpm.vatCrit, _xlpm.oppcol, "Good"), 0) + IF(DAFFFairToggle=TRUE, SUMIFS(_xlpm.sumcol, _xlpm.statuscol, _xlpm.s, _xlpm.vatcol, _xlpm.vatCrit, _xlpm.oppcol, "Fair"), 0) + IF(DAFFRiskToggle=TRUE, SUMIFS(_xlpm.sumcol, _xlpm.statuscol, _xlpm.s, _xlpm.vatcol, _xlpm.vatCrit, _xlpm.oppcol, "Risk"), 0) ) -> 0 | AD17: =_xlfn.LET( _xlpm.s, GMConSpreadTable8[[#This Row],[STATUS]], _xlpm.vatCrit, "DAFF", _xlpm.sumcol, TotalGMContribution[April], _xlpm.statuscol, TotalGMContribution[Status], _xlpm.vatcol, TotalGMContribution[VAT], _xlpm.oppcol, TotalGMContribution[Opps Status], IF(DAFFGoodToggle=TRUE, SUMIFS(_xlpm.sumcol, _xlpm.statuscol, _xlpm.s, _xlpm.vatcol, _xlpm.vatCrit, _xlpm.oppcol, "Good"), 0) + IF(DAFFFairToggle=TRUE, SUMIFS(_xlpm.sumcol, _xlpm.statuscol, _xlpm.s, _xlpm.vatcol, _xlpm.vatCrit, _xlpm.oppcol, "Fair"), 0) + IF(DAFFRiskToggle=TRUE, SUMIFS(_xlpm.sumcol, _xlpm.statuscol, _xlpm.s, _xlpm.vatcol, _xlpm.vatCrit, _xlpm.oppcol, "Risk"), 0) ) -> 0 | AE17: =_xlfn.LET( _xlpm.s, GMConSpreadTable8[[#This Row],[STATUS]], _xlpm.vatCrit, "DAFF", _xlpm.sumcol, TotalGMContribution[May], _xlpm.statuscol, TotalGMContribution[Status], _xlpm.vatcol, TotalGMContribution[VAT], _xlpm.oppcol, TotalGMContribution[Opps Status], IF(DAFFGoodToggle=TRUE, SUMIFS(_xlpm.sumcol, _xlpm.statuscol, _xlpm.s, _xlpm.vatcol, _xlpm.vatCrit, _xlpm.oppcol, "Good"), 0) + IF(DAFFFairToggle=TRUE, SUMIFS(_xlpm.sumcol, _xlpm.statuscol, _xlpm.s, _xlpm.vatcol, _xlpm.vatCrit, _xlpm.oppcol, "Fair"), 0) + IF(DAFFRiskToggle=TRUE, SUMIFS(_xlpm.sumcol, _xlpm.statuscol, _xlpm.s, _xlpm.vatcol, _xlpm.vatCrit, _xlpm.oppcol, "Risk"), 0) ) -> 0 | AF17: =_xlfn.LET( _xlpm.s, GMConSpreadTable8[[#This Row],[STATUS]], _xlpm.vatCrit, "DAFF", _xlpm.sumcol, TotalGMContribution[June], _xlpm.statuscol, TotalGMContribution[Status], _xlpm.vatcol, TotalGMContribution[VAT], _xlpm.oppcol, TotalGMContribution[Opps Status], IF(DAFFGoodToggle=TRUE, SUMIFS(_xlpm.sumcol, _xlpm.statuscol, _xlpm.s, _xlpm.vatcol, _xlpm.vatCrit, _xlpm.oppcol, "Good"), 0) + IF(DAFFFairToggle=TRUE, SUMIFS(_xlpm.sumcol, _xlpm.statuscol, _xlpm.s, _xlpm.vatcol, _xlpm.vatCrit, _xlpm.oppcol, "Fair"), 0) + IF(DAFFRiskToggle=TRUE, SUMIFS(_xlpm.sumcol, _xlpm.statuscol, _xlpm.s, _xlpm.vatcol, _xlpm.vatCrit, _xlpm.oppcol, "Risk"), 0) ) -> 0
K18: Revenue 'Good' Target | L18: =SUM(U44:W44) -> 1607142.9 | M18: =SUM(X44:Z44) -> 1607142.9 | N18: =SUM(AA44:AC44) -> 1607142.9 | O18: =SUM(AD44:AF44) -> 1607142.9 | P18: =SUM(Table34[[#This Row],[Q1]:[Q4]]) -> 6428571.4 | T18: DF | U18: =_xlfn.LET( _xlpm.s, GMConSpreadTable8[[#This Row],[STATUS]], _xlpm.vatCrit, "DAFF", _xlpm.sumcol, TotalGMContribution[July], _xlpm.statuscol, TotalGMContribution[Status], _xlpm.vatcol, TotalGMContribution[VAT], _xlpm.oppcol, TotalGMContribution[Opps Status], IF(DAFFGoodToggle=TRUE, SUMIFS(_xlpm.sumcol, _xlpm.statuscol, _xlpm.s, _xlpm.vatcol, _xlpm.vatCrit, _xlpm.oppcol, "Good"), 0) + IF(DAFFFairToggle=TRUE, SUMIFS(_xlpm.sumcol, _xlpm.statuscol, _xlpm.s, _xlpm.vatcol, _xlpm.vatCrit, _xlpm.oppcol, "Fair"), 0) + IF(DAFFRiskToggle=TRUE, SUMIFS(_xlpm.sumcol, _xlpm.statuscol, _xlpm.s, _xlpm.vatcol, _xlpm.vatCrit, _xlpm.oppcol, "Risk"), 0) ) -> 0 | V18: =_xlfn.LET( _xlpm.s, GMConSpreadTable8[[#This Row],[STATUS]], _xlpm.vatCrit, "DAFF", _xlpm.sumcol, TotalGMContribution[August], _xlpm.statuscol, TotalGMContribution[Status], _xlpm.vatcol, TotalGMContribution[VAT], _xlpm.oppcol, TotalGMContribution[Opps Status], IF(DAFFGoodToggle=TRUE, SUMIFS(_xlpm.sumcol, _xlpm.statuscol, _xlpm.s, _xlpm.vatcol, _xlpm.vatCrit, _xlpm.oppcol, "Good"), 0) + IF(DAFFFairToggle=TRUE, SUMIFS(_xlpm.sumcol, _xlpm.statuscol, _xlpm.s, _xlpm.vatcol, _xlpm.vatCrit, _xlpm.oppcol, "Fair"), 0) + IF(DAFFRiskToggle=TRUE, SUMIFS(_xlpm.sumcol, _xlpm.statuscol, _xlpm.s, _xlpm.vatcol, _xlpm.vatCrit, _xlpm.oppcol, "Risk"), 0) ) -> 0 | W18: =_xlfn.LET( _xlpm.s, GMConSpreadTable8[[#This Row],[STATUS]], _xlpm.vatCrit, "DAFF", _xlpm.sumcol, TotalGMContribution[September], _xlpm.statuscol, TotalGMContribution[Status], _xlpm.vatcol, TotalGMContribution[VAT], _xlpm.oppcol, TotalGMContribution[Opps Status], IF(DAFFGoodToggle=TRUE, SUMIFS(_xlpm.sumcol, _xlpm.statuscol, _xlpm.s, _xlpm.vatcol, _xlpm.vatCrit, _xlpm.oppcol, "Good"), 0) + IF(DAFFFairToggle=TRUE, SUMIFS(_xlpm.sumcol, _xlpm.statuscol, _xlpm.s, _xlpm.vatcol, _xlpm.vatCrit, _xlpm.oppcol, "Fair"), 0) + IF(DAFFRiskToggle=TRUE, SUMIFS(_xlpm.sumcol, _xlpm.statuscol, _xlpm.s, _xlpm.vatcol, _xlpm.vatCrit, _xlpm.oppcol, "Risk"), 0) ) -> 0 | X18: =_xlfn.LET( _xlpm.s, GMConSpreadTable8[[#This Row],[STATUS]], _xlpm.vatCrit, "DAFF", _xlpm.sumcol, TotalGMContribution[October], _xlpm.statuscol, TotalGMContribution[Status], _xlpm.vatcol, TotalGMContribution[VAT], _xlpm.oppcol, TotalGMContribution[Opps Status], IF(DAFFGoodToggle=TRUE, SUMIFS(_xlpm.sumcol, _xlpm.statuscol, _xlpm.s, _xlpm.vatcol, _xlpm.vatCrit, _xlpm.oppcol, "Good"), 0) + IF(DAFFFairToggle=TRUE, SUMIFS(_xlpm.sumcol, _xlpm.statuscol, _xlpm.s, _xlpm.vatcol, _xlpm.vatCrit, _xlpm.oppcol, "Fair"), 0) + IF(DAFFRiskToggle=TRUE, SUMIFS(_xlpm.sumcol, _xlpm.statuscol, _xlpm.s, _xlpm.vatcol, _xlpm.vatCrit, _xlpm.oppcol, "Risk"), 0) ) -> 0 | Y18: =_xlfn.LET( _xlpm.s, GMConSpreadTable8[[#This Row],[STATUS]], _xlpm.vatCrit, "DAFF", _xlpm.sumcol, TotalGMContribution[November], _xlpm.statuscol, TotalGMContribution[Status], _xlpm.vatcol, TotalGMContribution[VAT], _xlpm.oppcol, TotalGMContribution[Opps Status], IF(DAFFGoodToggle=TRUE, SUMIFS(_xlpm.sumcol, _xlpm.statuscol, _xlpm.s, _xlpm.vatcol, _xlpm.vatCrit, _xlpm.oppcol, "Good"), 0) + IF(DAFFFairToggle=TRUE, SUMIFS(_xlpm.sumcol, _xlpm.statuscol, _xlpm.s, _xlpm.vatcol, _xlpm.vatCrit, _xlpm.oppcol, "Fair"), 0) + IF(DAFFRiskToggle=TRUE, SUMIFS(_xlpm.sumcol, _xlpm.statuscol, _xlpm.s, _xlpm.vatcol, _xlpm.vatCrit, _xlpm.oppcol, "Risk"), 0) ) -> 0 | Z18: =_xlfn.LET( _xlpm.s, GMConSpreadTable8[[#This Row],[STATUS]], _xlpm.vatCrit, "DAFF", _xlpm.sumcol, TotalGMContribution[December], _xlpm.statuscol, TotalGMContribution[Status], _xlpm.vatcol, TotalGMContribution[VAT], _xlpm.oppcol, TotalGMContribution[Opps Status], IF(DAFFGoodToggle=TRUE, SUMIFS(_xlpm.sumcol, _xlpm.statuscol, _xlpm.s, _xlpm.vatcol, _xlpm.vatCrit, _xlpm.oppcol, "Good"), 0) + IF(DAFFFairToggle=TRUE, SUMIFS(_xlpm.sumcol, _xlpm.statuscol, _xlpm.s, _xlpm.vatcol, _xlpm.vatCrit, _xlpm.oppcol, "Fair"), 0) + IF(DAFFRiskToggle=TRUE, SUMIFS(_xlpm.sumcol, _xlpm.statuscol, _xlpm.s, _xlpm.vatcol, _xlpm.vatCrit, _xlpm.oppcol, "Risk"), 0) ) -> 0 | AA18: =_xlfn.LET( _xlpm.s, GMConSpreadTable8[[#This Row],[STATUS]], _xlpm.vatCrit, "DAFF", _xlpm.sumcol, TotalGMContribution[January], _xlpm.statuscol, TotalGMContribution[Status], _xlpm.vatcol, TotalGMContribution[VAT], _xlpm.oppcol, TotalGMContribution[Opps Status], IF(DAFFGoodToggle=TRUE, SUMIFS(_xlpm.sumcol, _xlpm.statuscol, _xlpm.s, _xlpm.vatcol, _xlpm.vatCrit, _xlpm.oppcol, "Good"), 0) + IF(DAFFFairToggle=TRUE, SUMIFS(_xlpm.sumcol, _xlpm.statuscol, _xlpm.s, _xlpm.vatcol, _xlpm.vatCrit, _xlpm.oppcol, "Fair"), 0) + IF(DAFFRiskToggle=TRUE, SUMIFS(_xlpm.sumcol, _xlpm.statuscol, _xlpm.s, _xlpm.vatcol, _xlpm.vatCrit, _xlpm.oppcol, "Risk"), 0) ) -> 0 | AB18: =_xlfn.LET( _xlpm.s, GMConSpreadTable8[[#This Row],[STATUS]], _xlpm.vatCrit, "DAFF", _xlpm.sumcol, TotalGMContribution[February], _xlpm.statuscol, TotalGMContribution[Status], _xlpm.vatcol, TotalGMContribution[VAT], _xlpm.oppcol, TotalGMContribution[Opps Status], IF(DAFFGoodToggle=TRUE, SUMIFS(_xlpm.sumcol, _xlpm.statuscol, _xlpm.s, _xlpm.vatcol, _xlpm.vatCrit, _xlpm.oppcol, "Good"), 0) + IF(DAFFFairToggle=TRUE, SUMIFS(_xlpm.sumcol, _xlpm.statuscol, _xlpm.s, _xlpm.vatcol, _xlpm.vatCrit, _xlpm.oppcol, "Fair"), 0) + IF(DAFFRiskToggle=TRUE, SUMIFS(_xlpm.sumcol, _xlpm.statuscol, _xlpm.s, _xlpm.vatcol, _xlpm.vatCrit, _xlpm.oppcol, "Risk"), 0) ) -> 0 | AC18: =_xlfn.LET( _xlpm.s, GMConSpreadTable8[[#This Row],[STATUS]], _xlpm.vatCrit, "DAFF", _xlpm.sumcol, TotalGMContribution[March], _xlpm.statuscol, TotalGMContribution[Status], _xlpm.vatcol, TotalGMContribution[VAT], _xlpm.oppcol, TotalGMContribution[Opps Status], IF(DAFFGoodToggle=TRUE, SUMIFS(_xlpm.sumcol, _xlpm.statuscol, _xlpm.s, _xlpm.vatcol, _xlpm.vatCrit, _xlpm.oppcol, "Good"), 0) + IF(DAFFFairToggle=TRUE, SUMIFS(_xlpm.sumcol, _xlpm.statuscol, _xlpm.s, _xlpm.vatcol, _xlpm.vatCrit, _xlpm.oppcol, "Fair"), 0) + IF(DAFFRiskToggle=TRUE, SUMIFS(_xlpm.sumcol, _xlpm.statuscol, _xlpm.s, _xlpm.vatcol, _xlpm.vatCrit, _xlpm.oppcol, "Risk"), 0) ) -> 0 | AD18: =_xlfn.LET( _xlpm.s, GMConSpreadTable8[[#This Row],[STATUS]], _xlpm.vatCrit, "DAFF", _xlpm.sumcol, TotalGMContribution[April], _xlpm.statuscol, TotalGMContribution[Status], _xlpm.vatcol, TotalGMContribution[VAT], _xlpm.oppcol, TotalGMContribution[Opps Status], IF(DAFFGoodToggle=TRUE, SUMIFS(_xlpm.sumcol, _xlpm.statuscol, _xlpm.s, _xlpm.vatcol, _xlpm.vatCrit, _xlpm.oppcol, "Good"), 0) + IF(DAFFFairToggle=TRUE, SUMIFS(_xlpm.sumcol, _xlpm.statuscol, _xlpm.s, _xlpm.vatcol, _xlpm.vatCrit, _xlpm.oppcol, "Fair"), 0) + IF(DAFFRiskToggle=TRUE, SUMIFS(_xlpm.sumcol, _xlpm.statuscol, _xlpm.s, _xlpm.vatcol, _xlpm.vatCrit, _xlpm.oppcol, "Risk"), 0) ) -> 0 | AE18: =_xlfn.LET( _xlpm.s, GMConSpreadTable8[[#This Row],[STATUS]], _xlpm.vatCrit, "DAFF", _xlpm.sumcol, TotalGMContribution[May], _xlpm.statuscol, TotalGMContribution[Status], _xlpm.vatcol, TotalGMContribution[VAT], _xlpm.oppcol, TotalGMContribution[Opps Status], IF(DAFFGoodToggle=TRUE, SUMIFS(_xlpm.sumcol, _xlpm.statuscol, _xlpm.s, _xlpm.vatcol, _xlpm.vatCrit, _xlpm.oppcol, "Good"), 0) + IF(DAFFFairToggle=TRUE, SUMIFS(_xlpm.sumcol, _xlpm.statuscol, _xlpm.s, _xlpm.vatcol, _xlpm.vatCrit, _xlpm.oppcol, "Fair"), 0) + IF(DAFFRiskToggle=TRUE, SUMIFS(_xlpm.sumcol, _xlpm.statuscol, _xlpm.s, _xlpm.vatcol, _xlpm.vatCrit, _xlpm.oppcol, "Risk"), 0) ) -> 0 | AF18: =_xlfn.LET( _xlpm.s, GMConSpreadTable8[[#This Row],[STATUS]], _xlpm.vatCrit, "DAFF", _xlpm.sumcol, TotalGMContribution[June], _xlpm.statuscol, TotalGMContribution[Status], _xlpm.vatcol, TotalGMContribution[VAT], _xlpm.oppcol, TotalGMContribution[Opps Status], IF(DAFFGoodToggle=TRUE, SUMIFS(_xlpm.sumcol, _xlpm.statuscol, _xlpm.s, _xlpm.vatcol, _xlpm.vatCrit, _xlpm.oppcol, "Good"), 0) + IF(DAFFFairToggle=TRUE, SUMIFS(_xlpm.sumcol, _xlpm.statuscol, _xlpm.s, _xlpm.vatcol, _xlpm.vatCrit, _xlpm.oppcol, "Fair"), 0) + IF(DAFFRiskToggle=TRUE, SUMIFS(_xlpm.sumcol, _xlpm.statuscol, _xlpm.s, _xlpm.vatcol, _xlpm.vatCrit, _xlpm.oppcol, "Risk"), 0) ) -> 0
K19: YTD | L19: =SUMIFS(Job_Status[Revenue Q1],Job_Status[VAT],"DAFF") -> 1806921.6 | M19: =SUMIFS(Job_Status[Revenue Q2],Job_Status[VAT],"DAFF") -> 970384.69 | N19: =SUMIFS(Job_Status[Revenue Q3],Job_Status[VAT],"DAFF") -> 380218.51 | O19: =SUMIFS(Job_Status[Revenue Q4],Job_Status[VAT],"DAFF") -> 0 | P19: =SUM(Table34[[#This Row],[Q1]:[Q4]]) -> 3157524.8 | T19: Q | U19: =_xlfn.LET( _xlpm.s, GMConSpreadTable8[[#This Row],[STATUS]], _xlpm.vatCrit, "DAFF", _xlpm.sumcol, TotalGMContribution[July], _xlpm.statuscol, TotalGMContribution[Status], _xlpm.vatcol, TotalGMContribution[VAT], _xlpm.oppcol, TotalGMContribution[Opps Status], IF(DAFFGoodToggle=TRUE, SUMIFS(_xlpm.sumcol, _xlpm.statuscol, _xlpm.s, _xlpm.vatcol, _xlpm.vatCrit, _xlpm.oppcol, "Good"), 0) + IF(DAFFFairToggle=TRUE, SUMIFS(_xlpm.sumcol, _xlpm.statuscol, _xlpm.s, _xlpm.vatcol, _xlpm.vatCrit, _xlpm.oppcol, "Fair"), 0) + IF(DAFFRiskToggle=TRUE, SUMIFS(_xlpm.sumcol, _xlpm.statuscol, _xlpm.s, _xlpm.vatcol, _xlpm.vatCrit, _xlpm.oppcol, "Risk"), 0) ) -> 0 | V19: =_xlfn.LET( _xlpm.s, GMConSpreadTable8[[#This Row],[STATUS]], _xlpm.vatCrit, "DAFF", _xlpm.sumcol, TotalGMContribution[August], _xlpm.statuscol, TotalGMContribution[Status], _xlpm.vatcol, TotalGMContribution[VAT], _xlpm.oppcol, TotalGMContribution[Opps Status], IF(DAFFGoodToggle=TRUE, SUMIFS(_xlpm.sumcol, _xlpm.statuscol, _xlpm.s, _xlpm.vatcol, _xlpm.vatCrit, _xlpm.oppcol, "Good"), 0) + IF(DAFFFairToggle=TRUE, SUMIFS(_xlpm.sumcol, _xlpm.statuscol, _xlpm.s, _xlpm.vatcol, _xlpm.vatCrit, _xlpm.oppcol, "Fair"), 0) + IF(DAFFRiskToggle=TRUE, SUMIFS(_xlpm.sumcol, _xlpm.statuscol, _xlpm.s, _xlpm.vatcol, _xlpm.vatCrit, _xlpm.oppcol, "Risk"), 0) ) -> 0 | W19: =_xlfn.LET( _xlpm.s, GMConSpreadTable8[[#This Row],[STATUS]], _xlpm.vatCrit, "DAFF", _xlpm.sumcol, TotalGMContribution[September], _xlpm.statuscol, TotalGMContribution[Status], _xlpm.vatcol, TotalGMContribution[VAT], _xlpm.oppcol, TotalGMContribution[Opps Status], IF(DAFFGoodToggle=TRUE, SUMIFS(_xlpm.sumcol, _xlpm.statuscol, _xlpm.s, _xlpm.vatcol, _xlpm.vatCrit, _xlpm.oppcol, "Good"), 0) + IF(DAFFFairToggle=TRUE, SUMIFS(_xlpm.sumcol, _xlpm.statuscol, _xlpm.s, _xlpm.vatcol, _xlpm.vatCrit, _xlpm.oppcol, "Fair"), 0) + IF(DAFFRiskToggle=TRUE, SUMIFS(_xlpm.sumcol, _xlpm.statuscol, _xlpm.s, _xlpm.vatcol, _xlpm.vatCrit, _xlpm.oppcol, "Risk"), 0) ) -> 0 | X19: =_xlfn.LET( _xlpm.s, GMConSpreadTable8[[#This Row],[STATUS]], _xlpm.vatCrit, "DAFF", _xlpm.sumcol, TotalGMContribution[October], _xlpm.statuscol, TotalGMContribution[Status], _xlpm.vatcol, TotalGMContribution[VAT], _xlpm.oppcol, TotalGMContribution[Opps Status], IF(DAFFGoodToggle=TRUE, SUMIFS(_xlpm.sumcol, _xlpm.statuscol, _xlpm.s, _xlpm.vatcol, _xlpm.vatCrit, _xlpm.oppcol, "Good"), 0) + IF(DAFFFairToggle=TRUE, SUMIFS(_xlpm.sumcol, _xlpm.statuscol, _xlpm.s, _xlpm.vatcol, _xlpm.vatCrit, _xlpm.oppcol, "Fair"), 0) + IF(DAFFRiskToggle=TRUE, SUMIFS(_xlpm.sumcol, _xlpm.statuscol, _xlpm.s, _xlpm.vatcol, _xlpm.vatCrit, _xlpm.oppcol, "Risk"), 0) ) -> 0 | Y19: =_xlfn.LET( _xlpm.s, GMConSpreadTable8[[#This Row],[STATUS]], _xlpm.vatCrit, "DAFF", _xlpm.sumcol, TotalGMContribution[November], _xlpm.statuscol, TotalGMContribution[Status], _xlpm.vatcol, TotalGMContribution[VAT], _xlpm.oppcol, TotalGMContribution[Opps Status], IF(DAFFGoodToggle=TRUE, SUMIFS(_xlpm.sumcol, _xlpm.statuscol, _xlpm.s, _xlpm.vatcol, _xlpm.vatCrit, _xlpm.oppcol, "Good"), 0) + IF(DAFFFairToggle=TRUE, SUMIFS(_xlpm.sumcol, _xlpm.statuscol, _xlpm.s, _xlpm.vatcol, _xlpm.vatCrit, _xlpm.oppcol, "Fair"), 0) + IF(DAFFRiskToggle=TRUE, SUMIFS(_xlpm.sumcol, _xlpm.statuscol, _xlpm.s, _xlpm.vatcol, _xlpm.vatCrit, _xlpm.oppcol, "Risk"), 0) ) -> 0 | Z19: =_xlfn.LET( _xlpm.s, GMConSpreadTable8[[#This Row],[STATUS]], _xlpm.vatCrit, "DAFF", _xlpm.sumcol, TotalGMContribution[December], _xlpm.statuscol, TotalGMContribution[Status], _xlpm.vatcol, TotalGMContribution[VAT], _xlpm.oppcol, TotalGMContribution[Opps Status], IF(DAFFGoodToggle=TRUE, SUMIFS(_xlpm.sumcol, _xlpm.statuscol, _xlpm.s, _xlpm.vatcol, _xlpm.vatCrit, _xlpm.oppcol, "Good"), 0) + IF(DAFFFairToggle=TRUE, SUMIFS(_xlpm.sumcol, _xlpm.statuscol, _xlpm.s, _xlpm.vatcol, _xlpm.vatCrit, _xlpm.oppcol, "Fair"), 0) + IF(DAFFRiskToggle=TRUE, SUMIFS(_xlpm.sumcol, _xlpm.statuscol, _xlpm.s, _xlpm.vatcol, _xlpm.vatCrit, _xlpm.oppcol, "Risk"), 0) ) -> 0 | AA19: =_xlfn.LET( _xlpm.s, GMConSpreadTable8[[#This Row],[STATUS]], _xlpm.vatCrit, "DAFF", _xlpm.sumcol, TotalGMContribution[January], _xlpm.statuscol, TotalGMContribution[Status], _xlpm.vatcol, TotalGMContribution[VAT], _xlpm.oppcol, TotalGMContribution[Opps Status], IF(DAFFGoodToggle=TRUE, SUMIFS(_xlpm.sumcol, _xlpm.statuscol, _xlpm.s, _xlpm.vatcol, _xlpm.vatCrit, _xlpm.oppcol, "Good"), 0) + IF(DAFFFairToggle=TRUE, SUMIFS(_xlpm.sumcol, _xlpm.statuscol, _xlpm.s, _xlpm.vatcol, _xlpm.vatCrit, _xlpm.oppcol, "Fair"), 0) + IF(DAFFRiskToggle=TRUE, SUMIFS(_xlpm.sumcol, _xlpm.statuscol, _xlpm.s, _xlpm.vatcol, _xlpm.vatCrit, _xlpm.oppcol, "Risk"), 0) ) -> 0 | AB19: =_xlfn.LET( _xlpm.s, GMConSpreadTable8[[#This Row],[STATUS]], _xlpm.vatCrit, "DAFF", _xlpm.sumcol, TotalGMContribution[February], _xlpm.statuscol, TotalGMContribution[Status], _xlpm.vatcol, TotalGMContribution[VAT], _xlpm.oppcol, TotalGMContribution[Opps Status], IF(DAFFGoodToggle=TRUE, SUMIFS(_xlpm.sumcol, _xlpm.statuscol, _xlpm.s, _xlpm.vatcol, _xlpm.vatCrit, _xlpm.oppcol, "Good"), 0) + IF(DAFFFairToggle=TRUE, SUMIFS(_xlpm.sumcol, _xlpm.statuscol, _xlpm.s, _xlpm.vatcol, _xlpm.vatCrit, _xlpm.oppcol, "Fair"), 0) + IF(DAFFRiskToggle=TRUE, SUMIFS(_xlpm.sumcol, _xlpm.statuscol, _xlpm.s, _xlpm.vatcol, _xlpm.vatCrit, _xlpm.oppcol, "Risk"), 0) ) -> 0 | AC19: =_xlfn.LET( _xlpm.s, GMConSpreadTable8[[#This Row],[STATUS]], _xlpm.vatCrit, "DAFF", _xlpm.sumcol, TotalGMContribution[March], _xlpm.statuscol, TotalGMContribution[Status], _xlpm.vatcol, TotalGMContribution[VAT], _xlpm.oppcol, TotalGMContribution[Opps Status], IF(DAFFGoodToggle=TRUE, SUMIFS(_xlpm.sumcol, _xlpm.statuscol, _xlpm.s, _xlpm.vatcol, _xlpm.vatCrit, _xlpm.oppcol, "Good"), 0) + IF(DAFFFairToggle=TRUE, SUMIFS(_xlpm.sumcol, _xlpm.statuscol, _xlpm.s, _xlpm.vatcol, _xlpm.vatCrit, _xlpm.oppcol, "Fair"), 0) + IF(DAFFRiskToggle=TRUE, SUMIFS(_xlpm.sumcol, _xlpm.statuscol, _xlpm.s, _xlpm.vatcol, _xlpm.vatCrit, _xlpm.oppcol, "Risk"), 0) ) -> 0 | AD19: =_xlfn.LET( _xlpm.s, GMConSpreadTable8[[#This Row],[STATUS]], _xlpm.vatCrit, "DAFF", _xlpm.sumcol, TotalGMContribution[April], _xlpm.statuscol, TotalGMContribution[Status], _xlpm.vatcol, TotalGMContribution[VAT], _xlpm.oppcol, TotalGMContribution[Opps Status], IF(DAFFGoodToggle=TRUE, SUMIFS(_xlpm.sumcol, _xlpm.statuscol, _xlpm.s, _xlpm.vatcol, _xlpm.vatCrit, _xlpm.oppcol, "Good"), 0) + IF(DAFFFairToggle=TRUE, SUMIFS(_xlpm.sumcol, _xlpm.statuscol, _xlpm.s, _xlpm.vatcol, _xlpm.vatCrit, _xlpm.oppcol, "Fair"), 0) + IF(DAFFRiskToggle=TRUE, SUMIFS(_xlpm.sumcol, _xlpm.statuscol, _xlpm.s, _xlpm.vatcol, _xlpm.vatCrit, _xlpm.oppcol, "Risk"), 0) ) -> 0 | AE19: =_xlfn.LET( _xlpm.s, GMConSpreadTable8[[#This Row],[STATUS]], _xlpm.vatCrit, "DAFF", _xlpm.sumcol, TotalGMContribution[May], _xlpm.statuscol, TotalGMContribution[Status], _xlpm.vatcol, TotalGMContribution[VAT], _xlpm.oppcol, TotalGMContribution[Opps Status], IF(DAFFGoodToggle=TRUE, SUMIFS(_xlpm.sumcol, _xlpm.statuscol, _xlpm.s, _xlpm.vatcol, _xlpm.vatCrit, _xlpm.oppcol, "Good"), 0) + IF(DAFFFairToggle=TRUE, SUMIFS(_xlpm.sumcol, _xlpm.statuscol, _xlpm.s, _xlpm.vatcol, _xlpm.vatCrit, _xlpm.oppcol, "Fair"), 0) + IF(DAFFRiskToggle=TRUE, SUMIFS(_xlpm.sumcol, _xlpm.statuscol, _xlpm.s, _xlpm.vatcol, _xlpm.vatCrit, _xlpm.oppcol, "Risk"), 0) ) -> 0 | AF19: =_xlfn.LET( _xlpm.s, GMConSpreadTable8[[#This Row],[STATUS]], _xlpm.vatCrit, "DAFF", _xlpm.sumcol, TotalGMContribution[June], _xlpm.statuscol, TotalGMContribution[Status], _xlpm.vatcol, TotalGMContribution[VAT], _xlpm.oppcol, TotalGMContribution[Opps Status], IF(DAFFGoodToggle=TRUE, SUMIFS(_xlpm.sumcol, _xlpm.statuscol, _xlpm.s, _xlpm.vatcol, _xlpm.vatCrit, _xlpm.oppcol, "Good"), 0) + IF(DAFFFairToggle=TRUE, SUMIFS(_xlpm.sumcol, _xlpm.statuscol, _xlpm.s, _xlpm.vatcol, _xlpm.vatCrit, _xlpm.oppcol, "Fair"), 0) + IF(DAFFRiskToggle=TRUE, SUMIFS(_xlpm.sumcol, _xlpm.statuscol, _xlpm.s, _xlpm.vatcol, _xlpm.vatCrit, _xlpm.oppcol, "Risk"), 0) ) -> 0
K20: Forecast (C/S) | L20: =SUM(U38:W38) -> 1806921.6 | M20: =SUM(X38:Z38) -> 970384.69 | N20: =SUM(AA38:AC38) -> 1019225.9 | O20: =SUM(AD38:AF38) -> 685781.76 | P20: =SUM(Table34[[#This Row],[Q1]:[Q4]]) -> 4482313.9 | T20: VAT Lead
K21: Variance | L21: =L20-L$18 -> 199778.75 | M21: =M20-M$18 -> -636758.17 | N21: =N20-N$18 -> -587916.99 | O21: =O20-O$18 -> -921361.1 | P21: =SUM(Table34[[#This Row],[Q1]:[Q4]]) -> -1946257.5 | T21: GREAT | U21: {=INDEX('FY2526 VAT Financial KPIs'!$G:$G, MATCH(1, ('FY2526 VAT Financial KPIs'!$A:$A="DAFF")*('FY2526 VAT Financial KPIs'!$D:$D="Gross Margin Contribution"), 0))/12} -> 225000 | V21: {=INDEX('FY2526 VAT Financial KPIs'!$G:$G, MATCH(1, ('FY2526 VAT Financial KPIs'!$A:$A="DAFF")*('FY2526 VAT Financial KPIs'!$D:$D="Gross Margin Contribution"), 0))/12} -> 225000 | W21: {=INDEX('FY2526 VAT Financial KPIs'!$G:$G, MATCH(1, ('FY2526 VAT Financial KPIs'!$A:$A="DAFF")*('FY2526 VAT Financial KPIs'!$D:$D="Gross Margin Contribution"), 0))/12} -> 225000 | X21: {=INDEX('FY2526 VAT Financial KPIs'!$G:$G, MATCH(1, ('FY2526 VAT Financial KPIs'!$A:$A="DAFF")*('FY2526 VAT Financial KPIs'!$D:$D="Gross Margin Contribution"), 0))/12} -> 225000 | Y21: {=INDEX('FY2526 VAT Financial KPIs'!$G:$G, MATCH(1, ('FY2526 VAT Financial KPIs'!$A:$A="DAFF")*('FY2526 VAT Financial KPIs'!$D:$D="Gross Margin Contribution"), 0))/12} -> 225000 | Z21: {=INDEX('FY2526 VAT Financial KPIs'!$G:$G, MATCH(1, ('FY2526 VAT Financial KPIs'!$A:$A="DAFF")*('FY2526 VAT Financial KPIs'!$D:$D="Gross Margin Contribution"), 0))/12} -> 225000 | AA21: {=INDEX('FY2526 VAT Financial KPIs'!$G:$G, MATCH(1, ('FY2526 VAT Financial KPIs'!$A:$A="DAFF")*('FY2526 VAT Financial KPIs'!$D:$D="Gross Margin Contribution"), 0))/12} -> 225000 | AB21: {=INDEX('FY2526 VAT Financial KPIs'!$G:$G, MATCH(1, ('FY2526 VAT Financial KPIs'!$A:$A="DAFF")*('FY2526 VAT Financial KPIs'!$D:$D="Gross Margin Contribution"), 0))/12} -> 225000 | ... AF21: {=INDEX('FY2526 VAT Financial KPIs'!$G:$G, MATCH(1, ('FY2526 VAT Financial KPIs'!$A:$A="DAFF")*('FY2526 VAT Financial KPIs'!$D:$D="Gross Margin Contribution"), 0))/12} -> 225000
K22: Revenue Forecast (DVF+) | L22: =SUM(U$38:W39) -> 1806921.6 | M22: =SUM(X$38:Z39) -> 970384.69 | N22: =SUM(AA$38:AC39) -> 1019225.9 | O22: =SUM(AD$38:AF39) -> 685781.76 | P22: =SUM(Table34[[#This Row],[Q1]:[Q4]]) -> 4482313.9 | T22: GOOD | U22: {=INDEX('FY2526 VAT Financial KPIs'!$F:$F, MATCH(1, ('FY2526 VAT Financial KPIs'!$A:$A="DAFF")*('FY2526 VAT Financial KPIs'!$D:$D="Gross Margin Contribution"), 0))/12} -> 187500 | V22: {=INDEX('FY2526 VAT Financial KPIs'!$F:$F, MATCH(1, ('FY2526 VAT Financial KPIs'!$A:$A="DAFF")*('FY2526 VAT Financial KPIs'!$D:$D="Gross Margin Contribution"), 0))/12} -> 187500 | W22: {=INDEX('FY2526 VAT Financial KPIs'!$F:$F, MATCH(1, ('FY2526 VAT Financial KPIs'!$A:$A="DAFF")*('FY2526 VAT Financial KPIs'!$D:$D="Gross Margin Contribution"), 0))/12} -> 187500 | X22: {=INDEX('FY2526 VAT Financial KPIs'!$F:$F, MATCH(1, ('FY2526 VAT Financial KPIs'!$A:$A="DAFF")*('FY2526 VAT Financial KPIs'!$D:$D="Gross Margin Contribution"), 0))/12} -> 187500 | Y22: {=INDEX('FY2526 VAT Financial KPIs'!$F:$F, MATCH(1, ('FY2526 VAT Financial KPIs'!$A:$A="DAFF")*('FY2526 VAT Financial KPIs'!$D:$D="Gross Margin Contribution"), 0))/12} -> 187500 | Z22: {=INDEX('FY2526 VAT Financial KPIs'!$F:$F, MATCH(1, ('FY2526 VAT Financial KPIs'!$A:$A="DAFF")*('FY2526 VAT Financial KPIs'!$D:$D="Gross Margin Contribution"), 0))/12} -> 187500 | AA22: {=INDEX('FY2526 VAT Financial KPIs'!$F:$F, MATCH(1, ('FY2526 VAT Financial KPIs'!$A:$A="DAFF")*('FY2526 VAT Financial KPIs'!$D:$D="Gross Margin Contribution"), 0))/12} -> 187500 | AB22: {=INDEX('FY2526 VAT Financial KPIs'!$F:$F, MATCH(1, ('FY2526 VAT Financial KPIs'!$A:$A="DAFF")*('FY2526 VAT Financial KPIs'!$D:$D="Gross Margin Contribution"), 0))/12} -> 187500 | ... AF22: {=INDEX('FY2526 VAT Financial KPIs'!$F:$F, MATCH(1, ('FY2526 VAT Financial KPIs'!$A:$A="DAFF")*('FY2526 VAT Financial KPIs'!$D:$D="Gross Margin Contribution"), 0))/12} -> 187500
K23: Delta to 'Good' Target | L23: =L22-L$18 -> 199778.75 | M23: =M22-M$18 -> -636758.17 | N23: =N22-N$18 -> -587916.99 | O23: =O22-O$18 -> -921361.1 | P23: =SUM(Table34[[#This Row],[Q1]:[Q4]]) -> -1946257.5 | T23: OK | U23: {=INDEX('FY2526 VAT Financial KPIs'!$E:$E, MATCH(1, ('FY2526 VAT Financial KPIs'!$A:$A="DAFF")*('FY2526 VAT Financial KPIs'!$D:$D="Gross Margin Contribution"), 0))/12} -> 150000 | V23: {=INDEX('FY2526 VAT Financial KPIs'!$E:$E, MATCH(1, ('FY2526 VAT Financial KPIs'!$A:$A="DAFF")*('FY2526 VAT Financial KPIs'!$D:$D="Gross Margin Contribution"), 0))/12} -> 150000 | W23: {=INDEX('FY2526 VAT Financial KPIs'!$E:$E, MATCH(1, ('FY2526 VAT Financial KPIs'!$A:$A="DAFF")*('FY2526 VAT Financial KPIs'!$D:$D="Gross Margin Contribution"), 0))/12} -> 150000 | X23: {=INDEX('FY2526 VAT Financial KPIs'!$E:$E, MATCH(1, ('FY2526 VAT Financial KPIs'!$A:$A="DAFF")*('FY2526 VAT Financial KPIs'!$D:$D="Gross Margin Contribution"), 0))/12} -> 150000 | Y23: {=INDEX('FY2526 VAT Financial KPIs'!$E:$E, MATCH(1, ('FY2526 VAT Financial KPIs'!$A:$A="DAFF")*('FY2526 VAT Financial KPIs'!$D:$D="Gross Margin Contribution"), 0))/12} -> 150000 | Z23: {=INDEX('FY2526 VAT Financial KPIs'!$E:$E, MATCH(1, ('FY2526 VAT Financial KPIs'!$A:$A="DAFF")*('FY2526 VAT Financial KPIs'!$D:$D="Gross Margin Contribution"), 0))/12} -> 150000 | AA23: {=INDEX('FY2526 VAT Financial KPIs'!$E:$E, MATCH(1, ('FY2526 VAT Financial KPIs'!$A:$A="DAFF")*('FY2526 VAT Financial KPIs'!$D:$D="Gross Margin Contribution"), 0))/12} -> 150000 | AB23: {=INDEX('FY2526 VAT Financial KPIs'!$E:$E, MATCH(1, ('FY2526 VAT Financial KPIs'!$A:$A="DAFF")*('FY2526 VAT Financial KPIs'!$D:$D="Gross Margin Contribution"), 0))/12} -> 150000 | ... AF23: {=INDEX('FY2526 VAT Financial KPIs'!$E:$E, MATCH(1, ('FY2526 VAT Financial KPIs'!$A:$A="DAFF")*('FY2526 VAT Financial KPIs'!$D:$D="Gross Margin Contribution"), 0))/12} -> 150000
K24: Revenue Forecast (DF+) | L24: =SUM(U$38:W40) -> 1806921.6 | M24: =SUM(X$38:Z40) -> 970384.69 | N24: =SUM(AA$38:AC40) -> 1352635.9 | O24: =SUM(AD$38:AF40) -> 1176871.8 | P24: =SUM(Table34[[#This Row],[Q1]:[Q4]]) -> 5306813.9
K25: Delta to 'Good' Target | L25: =L24-L$18 -> 199778.75 | M25: =M24-M$18 -> -636758.17 | N25: =N24-N$18 -> -254506.99 | O25: =O24-O$18 -> -430271.1 | P25: =SUM(Table34[[#This Row],[Q1]:[Q4]]) -> -1121757.5 | T25: Cumulative View - Revenue
K26: Revenue Forecast (Q+) | L26: =SUM(U$38:W41) -> 1806921.6 | M26: =SUM(X$38:Z41) -> 970384.69 | N26: =SUM(AA$38:AC41) -> 1352635.9 | O26: =SUM(AD$38:AF41) -> 1369728.9 | P26: =SUM(Table34[[#This Row],[Q1]:[Q4]]) -> 5499671.1 | T26: STATUS | U26: July | V26: August | W26: September | X26: October | Y26: November | Z26: December | AA26: January | AB26: February | AC26: March | AD26: April | AE26: May | AF26: June
K27: Delta to 'Good' Target | L27: =L26-L$18 -> 199778.75 | M27: =M26-M$18 -> -636758.17 | N27: =N26-N$18 -> -254506.99 | O27: =O26-O$18 -> -237413.95 | P27: =SUM(Table34[[#This Row],[Q1]:[Q4]]) -> -928900.36 | T27: C/S | U27: =U38 -> 655397.71 | V27: =SUM($U38:V38) -> 1219575 | W27: =SUM($U38:W38) -> 1806921.6 | X27: =SUM($U38:X38) -> 2167050.7 | Y27: =SUM($U38:Y38) -> 2480800.7 | Z27: =SUM($U38:Z38) -> 2777306.3 | AA27: =SUM($U38:AA38) -> 3092301.2 | AB27: =SUM($U38:AB38) -> 3417215.6 | AC27: =SUM($U38:AC38) -> 3796532.2 | ... AF27: =SUM($U38:AF38) -> 4482313.9
T28: DVF+ | U28: =U39+U27 -> 655397.71 | V28: =SUM($U39:V39)+V27 -> 1219575 | W28: =SUM($U39:W39)+W27 -> 1806921.6 | X28: =SUM($U39:X39)+X27 -> 2167050.7 | Y28: =SUM($U39:Y39)+Y27 -> 2480800.7 | Z28: =SUM($U39:Z39)+Z27 -> 2777306.3 | AA28: =SUM($U39:AA39)+AA27 -> 3092301.2 | AB28: =SUM($U39:AB39)+AB27 -> 3417215.6 | AC28: =SUM($U39:AC39)+AC27 -> 3796532.2 | ... AF28: =SUM($U39:AF39)+AF27 -> 4482313.9
K29: GROSS MARGIN % SUMMARY | L29: Q1 | M29: Q2 | N29: Q3 | O29: Q4 | P29: TOTAL | T29: DF+ | U29: =U40+U28 -> 655397.71 | V29: =SUM($U40:V40)+V28 -> 1219575 | W29: =SUM($U40:W40)+W28 -> 1806921.6 | X29: =SUM($U40:X40)+X28 -> 2167050.7 | Y29: =SUM($U40:Y40)+Y28 -> 2480800.7 | Z29: =SUM($U40:Z40)+Z28 -> 2777306.3 | AA29: =SUM($U40:AA40)+AA28 -> 3092301.2 | AB29: =SUM($U40:AB40)+AB28 -> 3488335.6 | AC29: =SUM($U40:AC40)+AC28 -> 4129942.2 | ... AF29: =SUM($U40:AF40)+AF28 -> 5306813.9
K30: Gross Margin % 'Good' Target | L30: =L6/L18 -> 0.35 | M30: =M6/M18 -> 0.35 | N30: =N6/N18 -> 0.35 | O30: =O6/O18 -> 0.35 | P30: =P6/P18 -> 0.35 | T30: Q+ | U30: =U41+U29 -> 655397.71 | V30: =SUM($U41:V41)+V29 -> 1219575 | W30: =SUM($U41:W41)+W29 -> 1806921.6 | X30: =SUM($U41:X41)+X29 -> 2167050.7 | Y30: =SUM($U41:Y41)+Y29 -> 2480800.7 | Z30: =SUM($U41:Z41)+Z29 -> 2777306.3 | AA30: =SUM($U41:AA41)+AA29 -> 3092301.2 | AB30: =SUM($U41:AB41)+AB29 -> 3488335.6 | AC30: =SUM($U41:AC41)+AC29 -> 4129942.2 | ... AF30: =SUM($U41:AF41)+AF29 -> 5499671.1
K31: YTD | L31: =L7/L19 -> 0.3111964 | M31: =M7/M19 -> 0.17723066 | N31: =N7/N19 -> 0.17257208 | O31: =O7/O19 -> #DIV/0! | P31: =P7/P19 -> 0.25333278 | T31: VAT Lead | U31: =U42 -> 0 | V31: =SUM($U42:V42) -> 0 | W31: =SUM($U42:W42) -> 0 | X31: =SUM($U42:X42) -> 0 | Y31: =SUM($U42:Y42) -> 0 | Z31: =SUM($U42:Z42) -> 0 | AA31: =SUM($U42:AA42) -> 0 | AB31: =SUM($U42:AB42) -> 0 | AC31: =SUM($U42:AC42) -> 0 | ... AF31: =SUM($U42:AF42) -> 0
K32: Forecast (C/S) | L32: =L8/L20 -> 0.3111964 | M32: =M8/M20 -> 0.17723066 | N32: =N8/N20 -> 0.17684438 | O32: =O8/O20 -> 0.15560194 | P32: =P8/P20 -> 0.2278383 | T32: GREAT | U32: =U43 -> 642857.14 | V32: =SUM($U43:V43) -> 1285714.3 | W32: =SUM($U43:W43) -> 1928571.4 | X32: =SUM($U43:X43) -> 2571428.6 | Y32: =SUM($U43:Y43) -> 3214285.7 | Z32: =SUM($U43:Z43) -> 3857142.9 | AA32: =SUM($U43:AA43) -> 4500000 | AB32: =SUM($U43:AB43) -> 5142857.1 | AC32: =SUM($U43:AC43) -> 5785714.3 | ... AF32: =SUM($U43:AF43) -> 7714285.7
K33: Variance | L33: =L32-L$30 -> -0.038803595 | M33: =M32-M$30 -> -0.17276934 | N33: =N32-N$30 -> -0.17315562 | O33: =O32-O$30 -> -0.19439806 | P33: =P32-P$30 -> -0.1221617 | T33: GOOD | U33: =U44 -> 535714.29 | V33: =SUM($U44:V44) -> 1071428.6 | W33: =SUM($U44:W44) -> 1607142.9 | X33: =SUM($U44:X44) -> 2142857.1 | Y33: =SUM($U44:Y44) -> 2678571.4 | Z33: =SUM($U44:Z44) -> 3214285.7 | AA33: =SUM($U44:AA44) -> 3750000 | AB33: =SUM($U44:AB44) -> 4285714.3 | AC33: =SUM($U44:AC44) -> 4821428.6 | ... AF33: =SUM($U44:AF44) -> 6428571.4
K34: Gross Margin % Forecast (DVF+) | L34: =L10/L22 -> 0.3111964 | M34: =M10/M22 -> 0.17723066 | N34: =N10/N22 -> 0.17684438 | O34: =O10/O22 -> 0.15560194 | P34: =P10/P22 -> 0.2278383 | T34: OK | U34: =U45 -> 428571.43 | V34: =SUM($U45:V45) -> 857142.86 | W34: =SUM($U45:W45) -> 1285714.3 | X34: =SUM($U45:X45) -> 1714285.7 | Y34: =SUM($U45:Y45) -> 2142857.1 | Z34: =SUM($U45:Z45) -> 2571428.6 | AA34: =SUM($U45:AA45) -> 3000000 | AB34: =SUM($U45:AB45) -> 3428571.4 | AC34: =SUM($U45:AC45) -> 3857142.9 | ... AF34: =SUM($U45:AF45) -> 5142857.1
K35: Delta to 'Good' Target | L35: =L34-L$30 -> -0.038803595 | M35: =M34-M$30 -> -0.17276934 | N35: =N34-N$30 -> -0.17315562 | O35: =O34-O$30 -> -0.19439806 | P35: =P34-P$30 -> -0.1221617
K36: Gross Margin % Forecast (DF+) | L36: =L12/L24 -> 0.3111964 | M36: =M12/M24 -> 0.17723066 | N36: =N12/N24 -> 0.13325417 | O36: =O12/O24 -> 0.090671706 | P36: =P12/P24 -> 0.1924399 | T36: Monthly View - Revenue
K37: Delta to 'Good' Target | L37: =L36-L$30 -> -0.038803595 | M37: =M36-M$30 -> -0.17276934 | N37: =N36-N$30 -> -0.21674583 | O37: =O36-O$30 -> -0.25932829 | P37: =P36-P$30 -> -0.1575601 | T37: STATUS | U37: July | V37: August | W37: September | X37: October | Y37: November | Z37: December | AA37: January | AB37: February | AC37: March | AD37: April | AE37: May | AF37: June
K38: Gross Margin % Forecast (Q+) | L38: =L14/L26 -> 0.3111964 | M38: =M14/M26 -> 0.17723066 | N38: =N14/N26 -> 0.13325417 | O38: =O14/O26 -> 0.077905175 | P38: =P14/P26 -> 0.18569161 | T38: C/S | U38: =SUMIF(Job_Status[VAT],"DAFF",Job_Status[R1]) -> 655397.71 | V38: =SUMIF(Job_Status[VAT],"DAFF",Job_Status[R2]) -> 564177.27 | W38: =SUMIF(Job_Status[VAT],"DAFF",Job_Status[R3]) -> 587346.63 | X38: =SUMIF(Job_Status[VAT],"DAFF",Job_Status[R4]) -> 360129.06 | Y38: =SUMIF(Job_Status[VAT],"DAFF",Job_Status[R5]) -> 313750 | Z38: =SUMIF(Job_Status[VAT],"DAFF",Job_Status[R6]) -> 296505.62 | AA38: =SUMIF(Job_Status[VAT],"DAFF",Job_Status[R7]) -> 314994.91 | AB38: =SUMIF(Job_Status[VAT],"DAFF",Job_Status[R8]) -> 324914.4 | AC38: =SUMIF(Job_Status[VAT],"DAFF",Job_Status[R9]) -> 379316.56 | AD38: =SUMIF(Job_Status[VAT],"DAFF",Job_Status[R10]) -> 250812.96 | AE38: =SUMIF(Job_Status[VAT],"DAFF",Job_Status[R11]) -> 216814.4 | AF38: =SUMIF(Job_Status[VAT],"DAFF",Job_Status[R12]) -> 218154.4
K39: Delta to 'Good' Target | L39: =L38-L$30 -> -0.038803595 | M39: =M38-M$30 -> -0.17276934 | N39: =N38-N$30 -> -0.21674583 | O39: =O38-O$30 -> -0.27209482 | P39: =P38-P$30 -> -0.16430839 | T39: DVF | U39: =SUMIFS(OppSpreadData[July],OppSpreadData[VAT],"DAFF",OppSpreadData[Phase],RevSpreadTable5[[#This Row],[STATUS]]) -> 0 | V39: =SUMIFS(OppSpreadData[August],OppSpreadData[VAT],"DAFF",OppSpreadData[Phase],RevSpreadTable5[[#This Row],[STATUS]]) -> 0 | W39: =SUMIFS(OppSpreadData[September],OppSpreadData[VAT],"DAFF",OppSpreadData[Phase],RevSpreadTable5[[#This Row],[STATUS]]) -> 0 | X39: =SUMIFS(OppSpreadData[October],OppSpreadData[VAT],"DAFF",OppSpreadData[Phase],RevSpreadTable5[[#This Row],[STATUS]]) -> 0 | Y39: =SUMIFS(OppSpreadData[November],OppSpreadData[VAT],"DAFF",OppSpreadData[Phase],RevSpreadTable5[[#This Row],[STATUS]]) -> 0 | Z39: =SUMIFS(OppSpreadData[December],OppSpreadData[VAT],"DAFF",OppSpreadData[Phase],RevSpreadTable5[[#This Row],[STATUS]]) -> 0 | AA39: =SUMIFS(OppSpreadData[January],OppSpreadData[VAT],"DAFF",OppSpreadData[Phase],RevSpreadTable5[[#This Row],[STATUS]]) -> 0 | AB39: =SUMIFS(OppSpreadData[February],OppSpreadData[VAT],"DAFF",OppSpreadData[Phase],RevSpreadTable5[[#This Row],[STATUS]]) -> 0 | AC39: =SUMIFS(OppSpreadData[March],OppSpreadData[VAT],"DAFF",OppSpreadData[Phase],RevSpreadTable5[[#This Row],[STATUS]]) -> 0 | AD39: =SUMIFS(OppSpreadData[April],OppSpreadData[VAT],"DAFF",OppSpreadData[Phase],RevSpreadTable5[[#This Row],[STATUS]]) -> 0 | AE39: =SUMIFS(OppSpreadData[May],OppSpreadData[VAT],"DAFF",OppSpreadData[Phase],RevSpreadTable5[[#This Row],[STATUS]]) -> 0 | AF39: =SUMIFS(OppSpreadData[June],OppSpreadData[VAT],"DAFF",OppSpreadData[Phase],RevSpreadTable5[[#This Row],[STATUS]]) -> 0
T40: DF | U40: =SUMIFS(OppSpreadData[July],OppSpreadData[VAT],"DAFF",OppSpreadData[Phase],RevSpreadTable5[[#This Row],[STATUS]]) -> 0 | V40: =SUMIFS(OppSpreadData[August],OppSpreadData[VAT],"DAFF",OppSpreadData[Phase],RevSpreadTable5[[#This Row],[STATUS]]) -> 0 | W40: =SUMIFS(OppSpreadData[September],OppSpreadData[VAT],"DAFF",OppSpreadData[Phase],RevSpreadTable5[[#This Row],[STATUS]]) -> 0 | X40: =SUMIFS(OppSpreadData[October],OppSpreadData[VAT],"DAFF",OppSpreadData[Phase],RevSpreadTable5[[#This Row],[STATUS]]) -> 0 | Y40: =SUMIFS(OppSpreadData[November],OppSpreadData[VAT],"DAFF",OppSpreadData[Phase],RevSpreadTable5[[#This Row],[STATUS]]) -> 0 | Z40: =SUMIFS(OppSpreadData[December],OppSpreadData[VAT],"DAFF",OppSpreadData[Phase],RevSpreadTable5[[#This Row],[STATUS]]) -> 0 | AA40: =SUMIFS(OppSpreadData[January],OppSpreadData[VAT],"DAFF",OppSpreadData[Phase],RevSpreadTable5[[#This Row],[STATUS]]) -> 0 | AB40: =SUMIFS(OppSpreadData[February],OppSpreadData[VAT],"DAFF",OppSpreadData[Phase],RevSpreadTable5[[#This Row],[STATUS]]) -> 71120 | AC40: =SUMIFS(OppSpreadData[March],OppSpreadData[VAT],"DAFF",OppSpreadData[Phase],RevSpreadTable5[[#This Row],[STATUS]]) -> 262290 | AD40: =SUMIFS(OppSpreadData[April],OppSpreadData[VAT],"DAFF",OppSpreadData[Phase],RevSpreadTable5[[#This Row],[STATUS]]) -> 174330 | AE40: =SUMIFS(OppSpreadData[May],OppSpreadData[VAT],"DAFF",OppSpreadData[Phase],RevSpreadTable5[[#This Row],[STATUS]]) -> 156490 | AF40: =SUMIFS(OppSpreadData[June],OppSpreadData[VAT],"DAFF",OppSpreadData[Phase],RevSpreadTable5[[#This Row],[STATUS]]) -> 160270
T41: Q | U41: {=SUM( _xlfn._xlws.FILTER( _xlfn.DROP(_xlfn.CHOOSECOLS(QBlockRev,4),1), _xlfn.DROP(_xlfn.CHOOSECOLS(QBlockRev,3),1)="DAFF", 0 ))} -> 0 | V41: {=SUM( _xlfn._xlws.FILTER( _xlfn.DROP(_xlfn.CHOOSECOLS(QBlockRev,5),1), _xlfn.DROP(_xlfn.CHOOSECOLS(QBlockRev,3),1)="DAFF", 0 ) )} -> 0 | W41: {=SUM( _xlfn._xlws.FILTER( _xlfn.DROP(_xlfn.CHOOSECOLS(QBlockRev,6),1), _xlfn.DROP(_xlfn.CHOOSECOLS(QBlockRev,3),1)="DAFF", 0 ) )} -> 0 | X41: {=SUM( _xlfn._xlws.FILTER( _xlfn.DROP(_xlfn.CHOOSECOLS(QBlockRev,7),1), _xlfn.DROP(_xlfn.CHOOSECOLS(QBlockRev,3),1)="DAFF", 0 ) )} -> 0 | Y41: {=SUM( _xlfn._xlws.FILTER( _xlfn.DROP(_xlfn.CHOOSECOLS(QBlockRev,8),1), _xlfn.DROP(_xlfn.CHOOSECOLS(QBlockRev,3),1)="DAFF", 0 ) )} -> 0 | Z41: {=SUM( _xlfn._xlws.FILTER( _xlfn.DROP(_xlfn.CHOOSECOLS(QBlockRev,9),1), _xlfn.DROP(_xlfn.CHOOSECOLS(QBlockRev,3),1)="DAFF", 0 ) )} -> 0 | AA41: {=SUM( _xlfn._xlws.FILTER( _xlfn.DROP(_xlfn.CHOOSECOLS(QBlockRev,10),1), _xlfn.DROP(_xlfn.CHOOSECOLS(QBlockRev,3),1)="DAFF", 0 ) )} -> 0 | AB41: {=SUM( _xlfn._xlws.FILTER( _xlfn.DROP(_xlfn.CHOOSECOLS(QBlockRev,11),1), _xlfn.DROP(_xlfn.CHOOSECOLS(QBlockRev,3),1)="DAFF", 0 ) )} -> 0 | AC41: {=SUM( _xlfn._xlws.FILTER( _xlfn.DROP(_xlfn.CHOOSECOLS(QBlockRev,12),1), _xlfn.DROP(_xlfn.CHOOSECOLS(QBlockRev,3),1)="DAFF", 0 ) )} -> 0 | AD41: {=SUM( _xlfn._xlws.FILTER( _xlfn.DROP(_xlfn.CHOOSECOLS(QBlockRev,13),1), _xlfn.DROP(_xlfn.CHOOSECOLS(QBlockRev,3),1)="DAFF", 0 ) )} -> 0 | AE41: {=SUM( _xlfn._xlws.FILTER( _xlfn.DROP(_xlfn.CHOOSECOLS(QBlockRev,14),1), _xlfn.DROP(_xlfn.CHOOSECOLS(QBlockRev,3),1)="DAFF", 0 ) )} -> 0 | AF41: {=SUM( _xlfn._xlws.FILTER( _xlfn.DROP(_xlfn.CHOOSECOLS(QBlockRev,15),1), _xlfn.DROP(_xlfn.CHOOSECOLS(QBlockRev,3),1)="DAFF", 0 ) )} -> 192857.14
L42: GM Contribution | N42: Gross Margin % | P42: Revenue | T42: VAT Lead
K43: WORK | L43: Earned to Date | M43: @Completion | N43: Earned to Date | O43: @ Completion | P43: Earned to Date | Q43: @ Completion | T43: GREAT | U43: {=INDEX('FY2526 VAT Financial KPIs'!$G:$G, MATCH(1, ('FY2526 VAT Financial KPIs'!$A:$A="DAFF")*('FY2526 VAT Financial KPIs'!$D:$D="Revenue"), 0))/12} -> 642857.14 | V43: {=INDEX('FY2526 VAT Financial KPIs'!$G:$G, MATCH(1, ('FY2526 VAT Financial KPIs'!$A:$A="DAFF")*('FY2526 VAT Financial KPIs'!$D:$D="Revenue"), 0))/12} -> 642857.14 | W43: {=INDEX('FY2526 VAT Financial KPIs'!$G:$G, MATCH(1, ('FY2526 VAT Financial KPIs'!$A:$A="DAFF")*('FY2526 VAT Financial KPIs'!$D:$D="Revenue"), 0))/12} -> 642857.14 | X43: {=INDEX('FY2526 VAT Financial KPIs'!$G:$G, MATCH(1, ('FY2526 VAT Financial KPIs'!$A:$A="DAFF")*('FY2526 VAT Financial KPIs'!$D:$D="Revenue"), 0))/12} -> 642857.14 | Y43: {=INDEX('FY2526 VAT Financial KPIs'!$G:$G, MATCH(1, ('FY2526 VAT Financial KPIs'!$A:$A="DAFF")*('FY2526 VAT Financial KPIs'!$D:$D="Revenue"), 0))/12} -> 642857.14 | Z43: {=INDEX('FY2526 VAT Financial KPIs'!$G:$G, MATCH(1, ('FY2526 VAT Financial KPIs'!$A:$A="DAFF")*('FY2526 VAT Financial KPIs'!$D:$D="Revenue"), 0))/12} -> 642857.14 | AA43: {=INDEX('FY2526 VAT Financial KPIs'!$G:$G, MATCH(1, ('FY2526 VAT Financial KPIs'!$A:$A="DAFF")*('FY2526 VAT Financial KPIs'!$D:$D="Revenue"), 0))/12} -> 642857.14 | AB43: {=INDEX('FY2526 VAT Financial KPIs'!$G:$G, MATCH(1, ('FY2526 VAT Financial KPIs'!$A:$A="DAFF")*('FY2526 VAT Financial KPIs'!$D:$D="Revenue"), 0))/12} -> 642857.14 | ... AF43: {=INDEX('FY2526 VAT Financial KPIs'!$G:$G, MATCH(1, ('FY2526 VAT Financial KPIs'!$A:$A="DAFF")*('FY2526 VAT Financial KPIs'!$D:$D="Revenue"), 0))/12} -> 642857.14
K44: Advisory | L44: =SUMIFS(Job_Status[To Date Gross Profit],Job_Status[Work Type],K44,Job_Status[VAT],"DAFF") -> 0 | M44: =SUMIFS(Job_Status[GP at completion],Job_Status[Work Type],K44,Job_Status[VAT],"DAFF") -> 0 | N44: =IFERROR(L44/P44,"") | O44: =IFERROR(M44/Q44,"") | P44: =SUMIFS(Job_Status[Actual], Job_Status[Work Type],K44,Job_Status[VAT],"DAFF") -> 0 | Q44: =SUMIFS(Job_Status[Forecasted Revenue], Job_Status[Work Type],K44,Job_Status[VAT],"DAFF") -> 0 | T44: GOOD | U44: {=INDEX('FY2526 VAT Financial KPIs'!$F:$F, MATCH(1, ('FY2526 VAT Financial KPIs'!$A:$A="DAFF")*('FY2526 VAT Financial KPIs'!$D:$D="Revenue"), 0))/12} -> 535714.29 | V44: {=INDEX('FY2526 VAT Financial KPIs'!$F:$F, MATCH(1, ('FY2526 VAT Financial KPIs'!$A:$A="DAFF")*('FY2526 VAT Financial KPIs'!$D:$D="Revenue"), 0))/12} -> 535714.29 | W44: {=INDEX('FY2526 VAT Financial KPIs'!$F:$F, MATCH(1, ('FY2526 VAT Financial KPIs'!$A:$A="DAFF")*('FY2526 VAT Financial KPIs'!$D:$D="Revenue"), 0))/12} -> 535714.29 | X44: {=INDEX('FY2526 VAT Financial KPIs'!$F:$F, MATCH(1, ('FY2526 VAT Financial KPIs'!$A:$A="DAFF")*('FY2526 VAT Financial KPIs'!$D:$D="Revenue"), 0))/12} -> 535714.29 | Y44: {=INDEX('FY2526 VAT Financial KPIs'!$F:$F, MATCH(1, ('FY2526 VAT Financial KPIs'!$A:$A="DAFF")*('FY2526 VAT Financial KPIs'!$D:$D="Revenue"), 0))/12} -> 535714.29 | Z44: {=INDEX('FY2526 VAT Financial KPIs'!$F:$F, MATCH(1, ('FY2526 VAT Financial KPIs'!$A:$A="DAFF")*('FY2526 VAT Financial KPIs'!$D:$D="Revenue"), 0))/12} -> 535714.29 | AA44: {=INDEX('FY2526 VAT Financial KPIs'!$F:$F, MATCH(1, ('FY2526 VAT Financial KPIs'!$A:$A="DAFF")*('FY2526 VAT Financial KPIs'!$D:$D="Revenue"), 0))/12} -> 535714.29 | AB44: {=INDEX('FY2526 VAT Financial KPIs'!$F:$F, MATCH(1, ('FY2526 VAT Financial KPIs'!$A:$A="DAFF")*('FY2526 VAT Financial KPIs'!$D:$D="Revenue"), 0))/12} -> 535714.29 | ... AF44: {=INDEX('FY2526 VAT Financial KPIs'!$F:$F, MATCH(1, ('FY2526 VAT Financial KPIs'!$A:$A="DAFF")*('FY2526 VAT Financial KPIs'!$D:$D="Revenue"), 0))/12} -> 535714.29
K45: Delivery | L45: =SUMIFS(Job_Status[To Date Gross Profit],Job_Status[Work Type],K45,Job_Status[VAT],"DAFF") -> 389195.42 | M45: =SUMIFS(Job_Status[GP at completion],Job_Status[Work Type],K45,Job_Status[VAT],"DAFF") -> 524047.42 | N45: =IFERROR(L45/P45,"") -> 0.26273244 | O45: =IFERROR(M45/Q45,"") -> 0.23008175 | P45: =SUMIFS(Job_Status[Actual], Job_Status[Work Type],K45,Job_Status[VAT],"DAFF") -> 1481337.5 | Q45: =SUMIFS(Job_Status[Forecasted Revenue], Job_Status[Work Type],K45,Job_Status[VAT],"DAFF") -> 2277657.5 | T45: OK | U45: {=INDEX('FY2526 VAT Financial KPIs'!$E:$E, MATCH(1, ('FY2526 VAT Financial KPIs'!$A:$A="DAFF")*('FY2526 VAT Financial KPIs'!$D:$D="Revenue"), 0))/12} -> 428571.43 | V45: {=INDEX('FY2526 VAT Financial KPIs'!$E:$E, MATCH(1, ('FY2526 VAT Financial KPIs'!$A:$A="DAFF")*('FY2526 VAT Financial KPIs'!$D:$D="Revenue"), 0))/12} -> 428571.43 | W45: {=INDEX('FY2526 VAT Financial KPIs'!$E:$E, MATCH(1, ('FY2526 VAT Financial KPIs'!$A:$A="DAFF")*('FY2526 VAT Financial KPIs'!$D:$D="Revenue"), 0))/12} -> 428571.43 | X45: {=INDEX('FY2526 VAT Financial KPIs'!$E:$E, MATCH(1, ('FY2526 VAT Financial KPIs'!$A:$A="DAFF")*('FY2526 VAT Financial KPIs'!$D:$D="Revenue"), 0))/12} -> 428571.43 | Y45: {=INDEX('FY2526 VAT Financial KPIs'!$E:$E, MATCH(1, ('FY2526 VAT Financial KPIs'!$A:$A="DAFF")*('FY2526 VAT Financial KPIs'!$D:$D="Revenue"), 0))/12} -> 428571.43 | Z45: {=INDEX('FY2526 VAT Financial KPIs'!$E:$E, MATCH(1, ('FY2526 VAT Financial KPIs'!$A:$A="DAFF")*('FY2526 VAT Financial KPIs'!$D:$D="Revenue"), 0))/12} -> 428571.43 | AA45: {=INDEX('FY2526 VAT Financial KPIs'!$E:$E, MATCH(1, ('FY2526 VAT Financial KPIs'!$A:$A="DAFF")*('FY2526 VAT Financial KPIs'!$D:$D="Revenue"), 0))/12} -> 428571.43 | AB45: {=INDEX('FY2526 VAT Financial KPIs'!$E:$E, MATCH(1, ('FY2526 VAT Financial KPIs'!$A:$A="DAFF")*('FY2526 VAT Financial KPIs'!$D:$D="Revenue"), 0))/12} -> 428571.43 | ... AF45: {=INDEX('FY2526 VAT Financial KPIs'!$E:$E, MATCH(1, ('FY2526 VAT Financial KPIs'!$A:$A="DAFF")*('FY2526 VAT Financial KPIs'!$D:$D="Revenue"), 0))/12} -> 428571.43
K46: Resource Pool | L46: =SUMIFS(Job_Status[To Date Gross Profit],Job_Status[Work Type],K46,Job_Status[VAT],"DAFF") -> 332766.98 | M46: =SUMIFS(Job_Status[GP at completion],Job_Status[Work Type],K46,Job_Status[VAT],"DAFF") -> 392169.53 | N46: =IFERROR(L46/P46,"") -> 0.23156783 | O46: =IFERROR(M46/Q46,"") -> 0.21582186 | P46: =SUMIFS(Job_Status[Actual], Job_Status[Work Type],K46,Job_Status[VAT],"DAFF") -> 1437017.3 | Q46: =SUMIFS(Job_Status[Forecasted Revenue], Job_Status[Work Type],K46,Job_Status[VAT],"DAFF") -> 1817098.3
K47: Labour Hire | L47: =SUMIFS(Job_Status[To Date Gross Profit],Job_Status[Work Type],K47,Job_Status[VAT],"DAFF") -> 77942.12 | M47: =SUMIFS(Job_Status[GP at completion],Job_Status[Work Type],K47,Job_Status[VAT],"DAFF") -> 102957.64 | N47: =IFERROR(L47/P47,"") -> 0.32588586 | O47: =IFERROR(M47/Q47,"") -> 0.26708252 | P47: =SUMIFS(Job_Status[Actual], Job_Status[Work Type],K47,Job_Status[VAT],"DAFF") -> 239170 | Q47: =SUMIFS(Job_Status[Forecasted Revenue], Job_Status[Work Type],K47,Job_Status[VAT],"DAFF") -> 385490
K48: Total | L48: =SUBTOTAL(109,Table14[Earned to Date]) -> 799904.52 | M48: =SUBTOTAL(109,Table14[@Completion]) -> 1019174.6 | N48: =Table14[[#Totals],[Earned to Date]]/Table14[[#Totals],[Earned to Date ]] -> 0.25333278 | O48: =Table14[[#Totals],[@Completion]]/Table14[[#Totals],[@ Completion ]] -> 0.22748185 | P48: =SUBTOTAL(109,Table14[[Earned to Date ]]) -> 3157524.8 | Q48: =SUBTOTAL(109,Table14[@ Completion ]) -> 4480245.8 | T48: STATUS | U48: Jul'25 | V48: Aug'25 | W48: Sep'25 | X48: Oct'25 | Y48: Nov'25 | Z48: Dec'25 | AA48: Jan'25 | AB48: Feb'25 | AC48: Mar'25 | AD48: Apr'25 | AE48: May'25 | AF48: June'26
K49: Target | M49: {=INDEX('FY2526 VAT Financial KPIs'!$F:$F, MATCH(1, ('FY2526 VAT Financial KPIs'!$A:$A="DAFF")*('FY2526 VAT Financial KPIs'!$D:$D="Gross Margin Contribution"), 0))} -> 2250000 | N49: {=INDEX('FY2526 VAT Financial KPIs'!$F:$F, MATCH(1, ('FY2526 VAT Financial KPIs'!$A:$A="DAFF")*('FY2526 VAT Financial KPIs'!$D:$D="Gross Margin Contribution %"), 0))} -> 0.35 | O49: {=INDEX('FY2526 VAT Financial KPIs'!$F:$F, MATCH(1, ('FY2526 VAT Financial KPIs'!$A:$A="DAFF")*('FY2526 VAT Financial KPIs'!$D:$D="Gross Margin Contribution %"), 0))} -> 0.35 | Q49: {=INDEX('FY2526 VAT Financial KPIs'!$F:$F, MATCH(1, ('FY2526 VAT Financial KPIs'!$A:$A="DAFF")*('FY2526 VAT Financial KPIs'!$D:$D="Revenue"), 0))} -> 6428571.4
Q50: =Q49-Table14[[#Totals],[@ Completion ]] -> 1948325.7 | T50: YTD Aug'25 | Y50: Year End
T51: STATUS | U51: GREAT | V51: GOOD | W51: OK | Y51: STATUS | Z51: GREAT | AA51: GOOD | AB51: OK
J52: Path | K52: sites/RGSales/Shared Documents/General/1.Open Opportunities | T52: C/S | U52: =V5/V$10-1 -> -0.16233763 | V52: =V5/V$11-1 -> 0.00519484 | W52: =V5/V$12-1 -> 0.25649355 | Y52: C/S | Z52: =AF5/AF$10-1 -> -0.62176194 | AA52: =AF5/AF$10-1 -> -0.62176194 | AB52: =AF5/AF$12-1 -> -0.43264291
J53: VAT | K53: DAFF | M53: REVENUE IN TABLE BELOW IS FOR THE WHOLE OF CONTRACT | T53: DVF | U53: =V6/V$10-1 -> -0.16233763 | V53: =V6/V$11-1 -> 0.00519484 | W53: =V6/V$12-1 -> 0.25649355 | Y53: DVF | Z53: =AF6/AF$10-1 -> -0.62176194 | AA53: =AF6/AF$10-1 -> -0.62176194 | AB53: =AF6/AF$12-1 -> -0.43264291
T54: DF | U54: =V7/V$10-1 -> -0.16233763 | V54: =V7/V$11-1 -> 0.00519484 | W54: =V7/V$12-1 -> 0.25649355 | Y54: DF | Z54: =AF7/AF$10-1 -> -0.62176194 | AA54: =AF7/AF$10-1 -> -0.62176194 | AB54: =AF7/AF$12-1 -> -0.43264291
J55: Phase | K55: Name | L55: Work Type | M55: Margin | N55: Status | O55: Start Date | P55: Expiry Date | Q55: Revenue | R55: GM Contribution | T55: Q | U55: =V8/V$10-1 -> -0.16233763 | V55: =V8/V$11-1 -> 0.00519484 | W55: =V8/V$12-1 -> 0.25649355 | Y55: Q | Z55: =AA8/AA$10-1 -> -0.4987151 | AA55: =AA8/AA$11-1 -> -0.39845812 | AB55: =AA8/AA$12-1 -> -0.24807265
J56: 4.DVF - Shortlisted | K56: LAB001-01 DCC Program Plan (Extension) | L56: Delivery | M56: 0.43 | N56: Good | O56: 46069 | P56: 46203 | Q56: 175220 | R56: 75344.6
J57: 3.DF - Submitted | K57: DAFXXX TRACE ServiceNow | L57: Delivery | M57: 0.2 | N57: Risk | O57: 46083 | P57: 46255 | Q57: 533310.75 | R57: 106662.15
K58: DAFXXX RFQ Incident and Major Incident Management Review | L58: Delivery | M58: 0.29 | N58: Good | O58: 46083 | P58: 46266 | Q58: 133000 | R58: 38570
J59: 2.Q - Qualified | K59: DAFXXX Trade and Imports Comeback | L59: Advisory | M59: 0.25 | N59: Good | O59: 46146 | P59: 46356 | Q59: 1000000 | R59: 250000
K60: DAFXXX STEPS Post-Gateway Response | L60: Delivery | M60: 0.25 | N60: Good | O60: 46146 | P60: 46192 | Q60: 100000 | R60: 25000
